Workbook

Sheet Deck Tie-Out (LW)
A1: LITTLE WING — DECK TIE-OUT
A2: Every financial claim in LW_Vessel_Plan_of_Action → its live model source. Model values recalculate; if a Status turns ⚠, deck and model have diverged.
A4: Slide | B4: Claim in deck | C4: Deck value | D4: Model source | E4: Model value (live) | F4: Status / note
A5: 2 | B5: 2026 revenue (Act/For) | C5: $288.7K | D5: LW 2026 P&L AB16 | E5: ='LW 2026 P&L'!$AB$16 -> 288692 | F5: ✓
A6: 2 | B6: 2026 net operating loss | C6: ($164.0K) | D6: LW 2026 P&L AB55 | E6: ='LW 2026 P&L'!$AB$55 -> -164007 | F6: ✓
A7: 2 | B7: Labor as % of revenue | C7: 59% | D7: AB33 / AB16 | E7: ='LW 2026 P&L'!$AB$33/'LW 2026 P&L'!$AB$16 -> 0.58979812 | F7: ✓
A8: 2 | B8: Prime cost % | C8: 95.2% | D8: (AB24+AB33)/AB16 | E8: =('LW 2026 P&L'!$AB$24+'LW 2026 P&L'!$AB$33)/'LW 2026 P&L'!$AB$16 -> 0.9522259 | F8: ✓
A9: 2 | B9: Flat mgmt fee + rent today | C9: $65.4K | D9: AB50 + AB48 | E9: ='LW 2026 P&L'!$AB$50+'LW 2026 P&L'!$AB$48 -> 65381 | F9: ✓
A10: 2 | B10: Discounts & comps | C10: ($18.6K) | D10: LW 2026 P&L AB15 | E10: ='LW 2026 P&L'!$AB$15 -> -18574 | F10: ✓
A11: 4 | B11: Product mix by group (8 categories) | C11: $250.5K total | D11: TTM PMIX export (external workbook) | F11: ≈ ties within mapping of $10.6K uncategorized rings — rebuild from TTM export for exact figures
A12: 5 | B12: Self-serve window share of sales | C12: 17% | D12: Daypart Analysis — TTM post-4pm % | E12: ='LW Daypart Analysis'!$D$59 -> 0.173 | F12: ✓ (17.3%)
A13: 5 | B13: "Three biggest hours ~39% of the day" | C13: ~39% | D13: TTM: 8–10am = $87.2K of $254.9K | E13: =87226/254946 -> 0.3421352 | F13: ⚠ TTM says 34.2% — fix deck copy
A14: 6 | B14: Labor lever (chip) | C14: +$39K/yr | D14: Weekly Compare D29 (annualized savings) | E14: =-'LW Weekly Compare'!$D$29 -> 39027.04 | F14: ✓ · plan-year P&L now ties exactly: December true-up in LW Budget Y37 reconciles to the Weekly Compare basis
A15: 6 | B15: Pricing lever (chip) | C15: +$9K/yr | D15: Menu Pricing C53 (net @90% capture) | E15: ='LW Menu Pricing'!$C$53 -> 9160.92 | F15: ✓
A16: 6 | B16: Retail lever (chip) | C16: +$24K GP/yr | D16: base uplift + programming × margin | E16: ='LW Assumptions'!$C$47+'LW Assumptions'!$C$36*(1-'LW Assumptions'!$C$37) -> 27283.908 | F16: ✓ ($23.9K)
A17: 6 | B17: Owner charges today → plan | C17: $65.4K → $14.8K | D17: LW 2026 P&L AB50+AB48 → LW Budget AB56 | E17: ='LW Budget'!$AB$56 -> 14834.232 | F17: ✓ (plan side; today side row above)
A18: 6 | B18: Owner charges saving (chip) | C18: −$51K/yr | D18: difference of the two | E18: =('LW 2026 P&L'!$AB$50+'LW 2026 P&L'!$AB$48)-'LW Budget'!$AB$56 -> 50546.768 | F18: ✓ ($50.9K)
A19: 6 | B19: Owner charges % of revenue | C19: 22.6% → 4.0% | D19: fee+rent ÷ revenue, both years | E19: ='LW Budget'!$AB$56/'LW Budget'!$AB$20 -> 0.04 | F19: ✓ (plan side 4.0%)
A20: 6 | B20: Programming lever | C20: +$500/wk | D20: assumption — baked into the revenue base | F20: ✓ by convention: 2x/month activations assumed to sustain ~$500/wk of traffic already counted in the Act/For-based revenue; no separate lever, no double-count
A21: 7 | B21: Post-4pm share of sales (TTM) | C21: 17.3% | D21: Daypart Analysis TTM block | E21: ='LW Daypart Analysis'!$D$59 -> 0.173 | F21: ✓
A22: 7 | B22: Barista-required share of post-4pm | C22: 21.5% | D22: Daypart Analysis TTM block | E22: ='LW Daypart Analysis'!$D$60 -> 0.215 | F22: ✓
A23: 7 | B23: Net sales at risk | C23: ~3.7% | D23: barista-required ÷ TTM total | E23: ='LW Daypart Analysis'!$C$60/244323 -> 0.03731945 | F23: ✓
A24: 8 | B24: Proposed loaded labor / week | C24: $2,441 | D24: Weekly Compare C20 | E24: ='LW Weekly Compare'!$C$20 -> 2440.2831 | F24: ✓ whole table = Weekly Compare tab, cols B (current) & C (proposed)
A25: 8 | B25: Weekly savings → annualized | C25: −$750 / ~$39.0K | D25: Weekly Compare C29 / D29 | E25: ='LW Weekly Compare'!$C$29 -> 750.52 | F25: ✓
A26: 9 | B26: Item prices, units & bumps (10 rows) | C26: per deck | D26: LW Menu Pricing rows 6–15 | F26: ✓ tab rebuilt FROM the deck (TTM units, list prices) — deck is source of truth
A27: 11 | B27: Today shelf run-rate | C27: $1,346/wk | D27: Retail Plan B15 ÷ 52 | E27: ='LW Retail Plan'!$B$15/52 -> 1346.0769 | F27: ✓
A28: 11 | B28: Plan-year shelf revenue | C28: $114.9K | D28: Retail Plan E15 | E28: ='LW Retail Plan'!$E$15 -> 114920 | F28: ✓
A29: 11 | B29: Shelf % of go-forward top line | C29: 31.7% | D29: Retail Plan E15 ÷ LW Budget AB20 | E29: ='LW Retail Plan'!$E$15/'LW Budget'!$AB$20 -> 0.30987786 | F29: ✓
A30: 11 | B30: Incremental gross profit | C30: $23.9K/yr | D30: base uplift (0% COGS) + programming margin | E30: ='LW Assumptions'!$C$47+'LW Assumptions'!$C$36*(1-'LW Assumptions'!$C$37) -> 27283.908 | F30: ✓ note: Retail Plan F15 shows $22.5K because it applies blended COGS to the base uplift too — model is the truth
A31: 14 | B31: Total income (Act/For → Mod → 2027) | C31: $288.7/311.2/362.1K | D31: Scenario Summary row 6 (C/D/E) | E31: ='Scenario Summary'!$E$6 -> 370855.8 | F31: ✓ (2027 shown; whole table = Scenario Summary LW block)
A32: 14 | B32: NOP (Act/For → Mod → 2027) | C32: (164.0)/(97.4)/+1.0K | D32: Scenario Summary row 14 | E32: ='Scenario Summary'!$E$14 -> 1034.3316 | F32: ✓
A33: 14 | B33: Loss cut vs Act/For | C33: loss eliminated | D33: 1 − E14/C14 | E33: =1-'Scenario Summary'!$E$14/'Scenario Summary'!$C$14 -> 1.0063066 | F33: ✓
A34: 14 | B34: Combined 2027 (with Vessel) | C34: +$88.1K | D34: Scenario Summary E40 | E34: ='Scenario Summary'!$E$40 -> 88148.101 | F34: ✓
A35: 14 | B35: Immediate impact note: Aug–Dec with vs without changes | C35: +$66.6K | D35: 2026 Bridge D19 | E35: ='2026 Bridge'!$D$19 -> 66646.471 | F35: ✓
A36: 18 | B36: Vessel go-forward: Aug–Dec immediate impact | C36: +$29.6K (9/1 go-live) | D36: 2026 Bridge D20 | E36: ='2026 Bridge'!$D$20 -> 36552.702 | F36: ✓ (Vessel slide)
A37: 7 | B37: Point 3: 4pm-close trade — labor saved vs worst-case margin lost | C37: +$27.5K worst case | D37: Daypart Analysis C68–C70 | E37: ='LW Daypart Analysis'!$C$70 -> 27533.37 | F37: ✓

Sheet Scenario Summary
A1: Method Terrapin
A2: Scenario Summary — T12 · 2026 Forecast · 2026 Modified (changes from effective dates) · 2027 Plan
A4: LITTLE WING
B5: T12 (GL actual) | C5: 2026 Act/For (unmodified) | D5: 2026 Act/For MODIFIED | E5: 2027 Plan
A6: Total Income | B6: 258287 | C6: ='LW 2026 P&L'!$AB$16 -> 288692 | D6: ='LW 2026 Modified'!$AB$20 -> 314870.25 | E6: ='LW Budget'!$AB$20 -> 370855.8
A7: Total COGS | B7: 81599 | C7: ='LW 2026 P&L'!$AB$24 -> 104630 | D7: ='LW 2026 Modified'!$AB$29 -> 103761.04 | E7: ='LW Budget'!$AB$29 -> 112332.09
A8: Gross Profit | B8: =B6-B7 -> 176688 | C8: =C6-C7 -> 184062 | D8: =D6-D7 -> 211109.21 | E8: =E6-E7 -> 258523.7
A9: Total Labor Cost | B9: 164857 | C9: ='LW 2026 P&L'!$AB$33 -> 170270 | D9: ='LW 2026 Modified'!$AB$38 -> 155478.07 | E9: ='LW Budget'!$AB$38 -> 131242.96
A10: Operating Expenses (excl fees & occupancy) | B10: 105344 | C10: ='LW 2026 P&L'!$AB$44+'LW 2026 P&L'!$AB$53-'LW 2026 P&L'!$AB$50-'LW 2026 P&L'!$AB$48 -> 112418 | D10: ='LW 2026 Modified'!$AB$50+'LW 2026 Modified'!$AB$60-'LW 2026 Modified'!$AB$54-'LW 2026 Modified'!$AB$56-'LW 2026 Modified'!$AB$57 -> 109129.74 | E10: ='LW Budget'!$AB$50+'LW Budget'!$AB$60-'LW Budget'!$AB$54-'LW Budget'!$AB$56-'LW Budget'!$AB$57 -> 111412.18
A11: Management Fee | B11: 48000 | C11: ='LW 2026 P&L'!$AB$50 -> 48000 | D11: ='LW 2026 Modified'!$AB$56 -> 34180.93 | E11: ='LW Budget'!$AB$56 -> 14834.232
A12: Admin Fee (Vessel — billed to clients, in income) | B12: 0 | C12: 0 | D12: ='LW 2026 Modified'!$AB$57 -> 0 | E12: =0 -> 0
A13: Occupancy / Rent | B13: 15642 | C13: ='LW 2026 P&L'!$AB$48 -> 17381 | D13: ='LW 2026 Modified'!$AB$54 -> 9681 | E13: ='LW Budget'!$AB$54 -> 0
A14: Net Operating Profit | B14: =B6-B7-B9-B10-B11-B12-B13 -> -157155 | C14: =C6-C7-C9-C10-C11-C12-C13 -> -164007 | D14: =D6-D7-D9-D10-D11-D12-D13 -> -97360.529 | E14: =E6-E7-E9-E10-E11-E12-E13 -> 1034.3316
A15: NOP margin | B15: =B14/B6 -> -0.60845106 | C15: =C14/C6 -> -0.56810372 | D15: =D14/D6 -> -0.30920841 | E15: =E14/E6 -> 0.0027890398
A17: VESSEL
B18: T12 (GL actual) | C18: 2026 Act/For (unmodified) | D18: 2026 Act/For MODIFIED | E18: 2027 Plan
A19: Total Income | B19: ='Vessel 2026 P&L'!$AB$16 -> 351975 | C19: ='Vessel 2026 P&L'!$AB$16 -> 351975 | D19: ='Vessel 2026 Modified'!$AB$20 -> 354765.8 | E19: ='Vessel Budget'!$AB$20 -> 350111.52
A20: Total COGS | B20: ='Vessel 2026 P&L'!$AB$24 -> 122932 | C20: ='Vessel 2026 P&L'!$AB$24 -> 122932 | D20: ='Vessel 2026 Modified'!$AB$29 -> 122932 | E20: ='Vessel Budget'!$AB$29 -> 136279.97
A21: Gross Profit | B21: =B19-B20 -> 229043 | C21: =C19-C20 -> 229043 | D21: =D19-D20 -> 231833.8 | E21: =E19-E20 -> 213831.55
A22: Total Labor Cost | B22: ='Vessel 2026 P&L'!$AB$33 -> 80034 | C22: ='Vessel 2026 P&L'!$AB$33 -> 80034 | D22: ='Vessel 2026 Modified'!$AB$38 -> 80034 | E22: ='Vessel Budget'!$AB$38 -> 60685.997
A23: Operating Expenses (excl fees & occupancy) | B23: ='Vessel 2026 P&L'!$AB$44+'Vessel 2026 P&L'!$AB$53-'Vessel 2026 P&L'!$AB$50-'Vessel 2026 P&L'!$AB$48 -> 93169 | C23: ='Vessel 2026 P&L'!$AB$44+'Vessel 2026 P&L'!$AB$53-'Vessel 2026 P&L'!$AB$50-'Vessel 2026 P&L'!$AB$48 -> 93169 | D23: ='Vessel 2026 Modified'!$AB$50+'Vessel 2026 Modified'!$AB$60-'Vessel 2026 Modified'!$AB$54-'Vessel 2026 Modified'!$AB$56-'Vessel 2026 Modified'!$AB$57 -> 81795.426 | E23: ='Vessel Budget'!$AB$50+'Vessel Budget'!$AB$60-'Vessel Budget'!$AB$54-'Vessel Budget'!$AB$56-'Vessel Budget'!$AB$57 -> 52027.325
A24: Management Fee | B24: ='Vessel 2026 P&L'!$AB$50 -> 48000 | C24: ='Vessel 2026 P&L'!$AB$50 -> 48000 | D24: ='Vessel 2026 Modified'!$AB$56 -> 33111.672 | E24: ='Vessel Budget'!$AB$56 -> 14004.461
A25: Admin Fee (Vessel — billed to clients, in income) | B25: 0 | C25: 0 | D25: ='Vessel 2026 Modified'!$AB$57 -> 0 | E25: ='Vessel Budget'!$AB$57 -> 0
A26: Occupancy / Rent | B26: ='Vessel 2026 P&L'!$AB$48 -> 21341 | C26: ='Vessel 2026 P&L'!$AB$48 -> 21341 | D26: ='Vessel 2026 Modified'!$AB$54 -> 13841 | E26: ='Vessel Budget'!$AB$54 -> 0
A27: Net Operating Profit | B27: =B19-B20-B22-B23-B24-B25-B26 -> -13501 | C27: =C19-C20-C22-C23-C24-C25-C26 -> -13501 | D27: =D19-D20-D22-D23-D24-D25-D26 -> 23051.702 | E27: =E19-E20-E22-E23-E24-E25-E26 -> 87113.77
A28: NOP margin | B28: =B27/B19 -> -0.038357838 | C28: =C27/C19 -> -0.038357838 | D28: =D27/D19 -> 0.064977239 | E28: =E27/E19 -> 0.2488172
A30: COMBINED
B31: T12 (GL actual) | C31: 2026 Act/For (unmodified) | D31: 2026 Act/For MODIFIED | E31: 2027 Plan
A32: Total Income | B32: =B6+B19 -> 610262 | C32: =C6+C19 -> 640667 | D32: =D6+D19 -> 669636.05 | E32: =E6+E19 -> 720967.32
A33: Total COGS | B33: =B7+B20 -> 204531 | C33: =C7+C20 -> 227562 | D33: =D7+D20 -> 226693.04 | E33: =E7+E20 -> 248612.06
A34: Gross Profit | B34: =B32-B33 -> 405731 | C34: =C32-C33 -> 413105 | D34: =D32-D33 -> 442943.01 | E34: =E32-E33 -> 472355.26
A35: Total Labor Cost | B35: =B9+B22 -> 244891 | C35: =C9+C22 -> 250304 | D35: =D9+D22 -> 235512.07 | E35: =E9+E22 -> 191928.96
A36: Operating Expenses (excl fees & occupancy) | B36: =B10+B23 -> 198513 | C36: =C10+C23 -> 205587 | D36: =D10+D23 -> 190925.17 | E36: =E10+E23 -> 163439.51
A37: Management Fee | B37: =B11+B24 -> 96000 | C37: =C11+C24 -> 96000 | D37: =D11+D24 -> 67292.602 | E37: =E11+E24 -> 28838.693
A38: Admin Fee (Vessel — billed to clients, in income) | B38: =B12+B25 -> 0 | C38: =C12+C25 -> 0 | D38: =D12+D25 -> 0 | E38: =E12+E25 -> 0
A39: Occupancy / Rent | B39: =B13+B26 -> 36983 | C39: =C13+C26 -> 38722 | D39: =D13+D26 -> 23522 | E39: =E13+E26 -> 0
A40: Net Operating Profit | B40: =B32-B33-B35-B36-B37-B38-B39 -> -170656 | C40: =C32-C33-C35-C36-C37-C38-C39 -> -177508 | D40: =D32-D33-D35-D36-D37-D38-D39 -> -74308.827 | E40: =E32-E33-E35-E36-E37-E38-E39 -> 88148.101
A41: NOP margin | B41: =B40/B32 -> -0.27964383 | C41: =C40/C32 -> -0.27706749 | D41: =D40/D32 -> -0.11096898 | E41: =E40/E32 -> 0.12226366
A43: Vessel T12 seeded with 2026 Act/For. Unmodified = accountant Act/For statements (Jan–Jun actual). MODIFIED = monthly build on the 2026 Modified tabs — levers live from the go-live date input (default 2026-08-01, editable on each Modified tab). 2027 Plan: LW = annualized modified run-rate; Vessel = event-driven plan ($4K F&B min × 80% volume).

Sheet 2026 Bridge
A1: 2026 CHANGE RECONCILIATION
A2: Unmodified Act/For → Modified 2026 · driven by the monthly Modified tabs (levers gated by each tab's go-live date input)
B4: Unmodified 2026 NOP | C4: Δ from changes | D4: MODIFIED 2026 NOP | E4: Go-live
A5: Little Wing | B5: ='LW 2026 P&L'!$AB$55 -> -164007 | C5: ='LW 2026 Modified'!$AB$62-'LW 2026 P&L'!$AB$55 -> 66646.471 | D5: ='LW 2026 Modified'!$AB$62 -> -97360.529 | E5: ='LW 2026 Modified'!$C$4 -> 46235
A6: Vessel | B6: ='Vessel 2026 P&L'!$AB$55 -> -13501 | C6: ='Vessel 2026 Modified'!$AB$62-'Vessel 2026 P&L'!$AB$55 -> 36552.702 | D6: ='Vessel 2026 Modified'!$AB$62 -> 23051.702 | E6: ='Vessel 2026 Modified'!$C$4 -> 46235
A7: COMBINED | B7: =B5+B6 -> -177508 | C7: =C5+C6 -> 103199.17 | D7: =D5+D6 -> -74308.827
A9: LEVERS IN THE MODIFIED MONTHS (edit on LW Assumptions / LW Menu Pricing / Vessel Assumptions):
A10: LW — Single-shift staffing: FOH 6:30am–4pm (C20) + wknd 2nd barista (C21) @ $20/hr (C23) + BOH cook $296/wk (C26) + GL mgmt labor kept
A11: LW — Menu pricing uplift (item-level, LW Menu Pricing) × capture % → Food/NA lines, pure margin
A12: LW — Retail: existing-base uplift (C46) + new programming $ (C36) with programming COGS % (C37)
A13: LW — Management fee: $4,000/mo → 4% of revenue (C40) · rent WAIVED (C41=0%) · CC 2.5% on added revenue (C31)
A14: Vessel — Management fee: $4,000/mo → 4% of revenue (C30) · rent waived (C31=0%) · NEW 5% admin fee on F&B billed to clients → Other Operating Income (C32)
A15: LW — Programming: 2x/month activations assumed to sustain ~$500/wk of traffic ALREADY included in the revenue base (no incremental revenue modeled)
A16: LW — Cleanup levers (v23): food COGS → 40% of food sales · G&A-unc → 4.5% of revenue · discounts & comps → 2.5% of gross · retail COGS → 42% (LW Assumptions C51–C53, Retail Plan col D)
A18: AUG–DEC 2026 — IMMEDIATE IMPACT OF THE CHANGES (8/1 go-live → year-end) | B18: Without changes | C18: With changes | D18: Impact
A19: Little Wing | B19: ='LW 2026 P&L'!Q55+'LW 2026 P&L'!S55+'LW 2026 P&L'!U55+'LW 2026 P&L'!W55+'LW 2026 P&L'!Y55 -> -67807 | C19: ='LW 2026 Modified'!Q62+'LW 2026 Modified'!S62+'LW 2026 Modified'!U62+'LW 2026 Modified'!W62+'LW 2026 Modified'!Y62 -> -1160.5285 | D19: =C19-B19 -> 66646.471
A20: Vessel | B20: ='Vessel 2026 P&L'!Q55+'Vessel 2026 P&L'!S55+'Vessel 2026 P&L'!U55+'Vessel 2026 P&L'!W55+'Vessel 2026 P&L'!Y55 -> 8977 | C20: ='Vessel 2026 Modified'!Q62+'Vessel 2026 Modified'!S62+'Vessel 2026 Modified'!U62+'Vessel 2026 Modified'!W62+'Vessel 2026 Modified'!Y62 -> 45529.702 | D20: =C20-B20 -> 36552.702 | E20: 8/1 fees · 9/1 revenue
A21: COMBINED | B21: =B19+B20 -> -58830 | C21: =C19+C20 -> 44369.173 | D21: =C21-B21 -> 103199.17

Sheet Consolidated P&L
A1: Method Terrapin
A2: Consolidated Profit & Loss — FY 2027
A3: 2027
C5: Vessel | F5: Little Wing | I5: Consolidated
C6: FY 2027 | F6: FY 2027 | I6: FY 2027
C7: Amount $ | D7: % | F7: Amount $ | G7: % | I7: Amount $ | J7: %
A11: Income
A12: Food Sales | C12: ='Vessel Budget'!$AB$12 -> 216843.26 | D12: =IFERROR(C12/C$20,0) -> 0.61935484 | F12: ='LW Budget'!$AB$12 -> 135366.3 | G12: =IFERROR(F12/F$20,0) -> 0.36501061 | I12: =C12+F12 -> 352209.56 | J12: =IFERROR(I12/I$20,0) -> 0.48852362
A13: Non-Alcoholic Beverage Sales | C13: ='Vessel Budget'!$AB$13 -> 21224.734 | D13: =IFERROR(C13/C$20,0) -> 0.060622781 | F13: ='LW Budget'!$AB$13 -> 168766.62 | G13: =IFERROR(F13/F$20,0) -> 0.45507343 | I13: =C13+F13 -> 189991.35 | J13: =IFERROR(I13/I$20,0) -> 0.26352284
A14: Liquor Sales | C14: ='Vessel Budget'!$AB$14 -> 35697.462 | D14: =IFERROR(C14/C$20,0) -> 0.10196026 | F14: ='LW Budget'!$AB$14 -> 7308 | G14: =IFERROR(F14/F$20,0) -> 0.019705773 | I14: =C14+F14 -> 43005.462 | J14: =IFERROR(I14/I$20,0) -> 0.05964967
A15: Beer Sales | C15: ='Vessel Budget'!$AB$15 -> 1316.0495 | D15: =IFERROR(C15/C$20,0) -> 0.0037589439 | F15: ='LW Budget'!$AB$15 -> 7380 | G15: =IFERROR(F15/F$20,0) -> 0.019899918 | I15: =C15+F15 -> 8696.0495 | J15: =IFERROR(I15/I$20,0) -> 0.012061642
A16: Wine Sales | C16: ='Vessel Budget'!$AB$16 -> 5007.7059 | D16: =IFERROR(C16/C$20,0) -> 0.014303174 | F16: ='LW Budget'!$AB$16 -> 12540 | G16: =IFERROR(F16/F$20,0) -> 0.033813682 | I16: =C16+F16 -> 17547.706 | J16: =IFERROR(I16/I$20,0) -> 0.024339114
A17: Retail / Merch Sales | C17: ='Vessel Budget'!$AB$17 -> 0 | D17: =IFERROR(C17/C$20,0) -> 0 | F17: ='LW Budget'!$AB$17 -> 44924 | G17: =IFERROR(F17/F$20,0) -> 0.12113603 | I17: =C17+F17 -> 44924 | J17: =IFERROR(I17/I$20,0) -> 0.06231073
A18: Other Operating Income | C18: ='Vessel Budget'!$AB$18 -> 70022.304 | D18: =IFERROR(C18/C$20,0) -> 0.2 | F18: ='LW Budget'!$AB$18 -> 4080 | G18: =IFERROR(F18/F$20,0) -> 0.011001581 | I18: =C18+F18 -> 74102.304 | J18: =IFERROR(I18/I$20,0) -> 0.10278178
A19: Discounts & Comps | C19: ='Vessel Budget'!$AB$19 -> 0 | D19: =IFERROR(C19/C$20,0) -> 0 | F19: ='LW Budget'!$AB$19 -> -9509.123 | G19: =IFERROR(F19/F$20,0) -> -0.025641026 | I19: =C19+F19 -> -9509.123 | J19: =IFERROR(I19/I$20,0) -> -0.013189395
A20: Total Income | C20: ='Vessel Budget'!$AB$20 -> 350111.52 | D20: =IFERROR(C20/C$20,0) -> 1 | F20: ='LW Budget'!$AB$20 -> 370855.8 | G20: =IFERROR(F20/F$20,0) -> 1 | I20: =C20+F20 -> 720967.32 | J20: =IFERROR(I20/I$20,0) -> 1
A22: Cost of Goods Sold
A23: Food Cost | C23: ='Vessel Budget'!$AB$23 -> 120468.48 | D23: =IFERROR(C23/C$12,0) -> 0.55555556 | F23: ='LW Budget'!$AB$23 -> 53208 | G23: =IFERROR(F23/F$12,0) -> 0.39306681 | I23: =C23+F23 -> 173676.48 | J23: =IFERROR(I23/I$12,0) -> 0.49310552
A24: Non-Alcoholic Beverage Cost | C24: ='Vessel Budget'!$AB$24 -> 5306.1835 | D24: =IFERROR(C24/C$13,0) -> 0.25 | F24: ='LW Budget'!$AB$24 -> 33996 | G24: =IFERROR(F24/F$13,0) -> 0.20143794 | I24: =C24+F24 -> 39302.184 | J24: =IFERROR(I24/I$13,0) -> 0.20686301
A25: Liquor Cost | C25: ='Vessel Budget'!$AB$25 -> 8924.3656 | D25: =IFERROR(C25/C$14,0) -> 0.25 | F25: ='LW Budget'!$AB$25 -> 948 | G25: =IFERROR(F25/F$14,0) -> 0.12972085 | I25: =C25+F25 -> 9872.3656 | J25: =IFERROR(I25/I$14,0) -> 0.22956074
A26: Beer Cost | C26: ='Vessel Budget'!$AB$26 -> 329.01239 | D26: =IFERROR(C26/C$15,0) -> 0.25 | F26: ='LW Budget'!$AB$26 -> 2064 | G26: =IFERROR(F26/F$15,0) -> 0.2796748 | I26: =C26+F26 -> 2393.0124 | J26: =IFERROR(I26/I$15,0) -> 0.27518385
A27: Wine/Sake Cost | C27: ='Vessel Budget'!$AB$27 -> 1251.9265 | D27: =IFERROR(C27/C$16,0) -> 0.25 | F27: ='LW Budget'!$AB$27 -> 4476 | G27: =IFERROR(F27/F$16,0) -> 0.3569378 | I27: =C27+F27 -> 5727.9265 | J27: =IFERROR(I27/I$16,0) -> 0.32642025
A28: Retail Cost | C28: ='Vessel Budget'!$AB$28 -> 0 | D28: =IFERROR(C28/C$17,0) -> 0 | F28: ='LW Budget'!$AB$28 -> 17640.092 | G28: =IFERROR(F28/F$17,0) -> 0.39266522 | I28: =C28+F28 -> 17640.092 | J28: =IFERROR(I28/I$17,0) -> 0.39266522
A29: Total COGS | C29: ='Vessel Budget'!$AB$29 -> 136279.97 | D29: =IFERROR(C29/C$20,0) -> 0.38924731 | F29: ='LW Budget'!$AB$29 -> 112332.09 | G29: =IFERROR(F29/F$20,0) -> 0.30289965 | I29: =C29+F29 -> 248612.06 | J29: =IFERROR(I29/I$20,0) -> 0.34483125
A30: Gross Profit | C30: ='Vessel Budget'!$AB$30 -> 213831.55 | D30: =IFERROR(C30/C$20,0) -> 0.61075269 | F30: ='LW Budget'!$AB$30 -> 258523.7 | G30: =IFERROR(F30/F$20,0) -> 0.69710035 | I30: =C30+F30 -> 472355.26 | J30: =IFERROR(I30/I$20,0) -> 0.65516875
A32: Labor Cost
A33: Management Labor | C33: ='Vessel Budget'!$AB$33 -> 4141.104 | D33: =IFERROR(C33/C$20,0) -> 0.011827957 | F33: ='LW Budget'!$AB$33 -> 19884 | G33: =IFERROR(F33/F$20,0) -> 0.053616527 | I33: =C33+F33 -> 24025.104 | J33: =IFERROR(I33/I$20,0) -> 0.03332343
A34: Back of House Hourly Labor | C34: ='Vessel Budget'!$AB$34 -> 0 | D34: =IFERROR(C34/C$20,0) -> 0 | F34: ='LW Budget'!$AB$34 -> 15392 | G34: =IFERROR(F34/F$20,0) -> 0.041504003 | I34: =C34+F34 -> 15392 | J34: =IFERROR(I34/I$20,0) -> 0.021349095
A35: Front of House Hourly Labor | C35: ='Vessel Budget'!$AB$35 -> 39528.72 | D35: =IFERROR(C35/C$20,0) -> 0.11290323 | F35: ='LW Budget'!$AB$35 -> 81120 | G35: =IFERROR(F35/F$20,0) -> 0.21873731 | I35: =C35+F35 -> 120648.72 | J35: =IFERROR(I35/I$20,0) -> 0.16734284
A36: Payroll Taxes & Benefits | C36: ='Vessel Budget'!$AB$36 -> 8583.3792 | D36: =IFERROR(C36/C$20,0) -> 0.024516129 | F36: ='LW Budget'!$AB$36 -> 18623.36 | G36: =IFERROR(F36/F$20,0) -> 0.050217255 | I36: =C36+F36 -> 27206.739 | J36: =IFERROR(I36/I$20,0) -> 0.037736439
A37: Bonus | C37: ='Vessel Budget'!$AB$37 -> 8432.7936 | D37: =IFERROR(C37/C$20,0) -> 0.024086022 | F37: ='LW Budget'!$AB$37 -> -3776.4 | G37: =IFERROR(F37/F$20,0) -> -0.010182934 | I37: =C37+F37 -> 4656.3936 | J37: =IFERROR(I37/I$20,0) -> 0.0064585363
A38: Total Labor Cost | C38: ='Vessel Budget'!$AB$38 -> 60685.997 | D38: =IFERROR(C38/C$20,0) -> 0.17333333 | F38: ='LW Budget'!$AB$38 -> 131242.96 | G38: =IFERROR(F38/F$20,0) -> 0.35389216 | I38: =C38+F38 -> 191928.96 | J38: =IFERROR(I38/I$20,0) -> 0.26621034
A40: Prime Costs | C40: ='Vessel Budget'!$AB$40 -> 196965.96 | D40: =IFERROR(C40/C$20,0) -> 0.56258065 | F40: ='LW Budget'!$AB$40 -> 243575.05 | G40: =IFERROR(F40/F$20,0) -> 0.65679182 | I40: =C40+F40 -> 440541.02 | J40: =IFERROR(I40/I$20,0) -> 0.61104159
A41: Operating Profit | C41: ='Vessel Budget'!$AB$41 -> 153145.56 | D41: =IFERROR(C41/C$20,0) -> 0.43741935 | F41: ='LW Budget'!$AB$41 -> 127280.74 | G41: =IFERROR(F41/F$20,0) -> 0.34320818 | I41: =C41+F41 -> 280426.3 | J41: =IFERROR(I41/I$20,0) -> 0.38895841
A43: Controllable Expenses
A44: Operating Expenses | C44: ='Vessel Budget'!$AB$44 -> 43293.36 | D44: =IFERROR(C44/C$20,0) -> 0.12365591 | F44: ='LW Budget'!$AB$44 -> 46356.975 | G44: =IFERROR(F44/F$20,0) -> 0.125 | I44: =C44+F44 -> 89650.335 | J44: =IFERROR(I44/I$20,0) -> 0.12434729
A45: Music & Entertainment | C45: ='Vessel Budget'!$AB$45 -> 0 | D45: =IFERROR(C45/C$20,0) -> 0 | F45: ='LW Budget'!$AB$45 -> 0 | G45: =IFERROR(F45/F$20,0) -> 0 | I45: =C45+F45 -> 0 | J45: =IFERROR(I45/I$20,0) -> 0
A46: Marketing & Advertising | C46: ='Vessel Budget'!$AB$46 -> 0 | D46: =IFERROR(C46/C$20,0) -> 0 | F46: ='LW Budget'!$AB$46 -> 12979.953 | G46: =IFERROR(F46/F$20,0) -> 0.035 | I46: =C46+F46 -> 12979.953 | J46: =IFERROR(I46/I$20,0) -> 0.018003525
A47: General & Administrative - Controllable | C47: ='Vessel Budget'!$AB$47 -> 0 | D47: =IFERROR(C47/C$20,0) -> 0 | F47: ='LW Budget'!$AB$47 -> 31522.743 | G47: =IFERROR(F47/F$20,0) -> 0.085 | I47: =C47+F47 -> 31522.743 | J47: =IFERROR(I47/I$20,0) -> 0.043722846
A48: Repairs & Maintenance | C48: ='Vessel Budget'!$AB$48 -> 0 | D48: =IFERROR(C48/C$20,0) -> 0 | F48: ='LW Budget'!$AB$48 -> 876 | G48: =IFERROR(F48/F$20,0) -> 0.0023621041 | I48: =C48+F48 -> 876 | J48: =IFERROR(I48/I$20,0) -> 0.0012150343
A49: Credit Card Fees | C49: ='Vessel Budget'!$AB$49 -> 0 | D49: =IFERROR(C49/C$20,0) -> 0 | F49: ='LW Budget'!$AB$49 -> 0 | G49: =IFERROR(F49/F$20,0) -> 0 | I49: =C49+F49 -> 0 | J49: =IFERROR(I49/I$20,0) -> 0
A50: Total Controllable Expenses | C50: ='Vessel Budget'!$AB$50 -> 43293.36 | D50: =IFERROR(C50/C$20,0) -> 0.12365591 | F50: ='LW Budget'!$AB$50 -> 91735.67 | G50: =IFERROR(F50/F$20,0) -> 0.2473621 | I50: =C50+F50 -> 135029.03 | J50: =IFERROR(I50/I$20,0) -> 0.1872887
A52: Uncontrollable Expenses
A53: Utilities | C53: ='Vessel Budget'!$AB$53 -> 0 | D53: =IFERROR(C53/C$20,0) -> 0 | F53: ='LW Budget'!$AB$53 -> 2988 | G53: =IFERROR(F53/F$20,0) -> 0.00805704 | I53: =C53+F53 -> 2988 | J53: =IFERROR(I53/I$20,0) -> 0.004144432
A54: Occupancy Cost | C54: ='Vessel Budget'!$AB$54 -> 0 | D54: =IFERROR(C54/C$20,0) -> 0 | F54: ='LW Budget'!$AB$54 -> 0 | G54: =IFERROR(F54/F$20,0) -> 0 | I54: =C54+F54 -> 0 | J54: =IFERROR(I54/I$20,0) -> 0
A55: General & Administrative - Uncon | C55: ='Vessel Budget'!$AB$55 -> 8733.9648 | D55: =IFERROR(C55/C$20,0) -> 0.024946237 | F55: ='LW Budget'!$AB$55 -> 16688.511 | G55: =IFERROR(F55/F$20,0) -> 0.045 | I55: =C55+F55 -> 25422.476 | J55: =IFERROR(I55/I$20,0) -> 0.03526162
A56: Management Fee | C56: ='Vessel Budget'!$AB$56 -> 14004.461 | D56: =IFERROR(C56/C$20,0) -> 0.04 | F56: ='LW Budget'!$AB$56 -> 14834.232 | G56: =IFERROR(F56/F$20,0) -> 0.04 | I56: =C56+F56 -> 28838.693 | J56: =IFERROR(I56/I$20,0) -> 0.04
A57: Admin Fee (5% of F&B) | C57: ='Vessel Budget'!$AB$57 -> 0 | D57: =IFERROR(C57/C$20,0) -> 0 | F57: ='LW Budget'!$AB$57 -> 0 | G57: =IFERROR(F57/F$20,0) -> 0 | I57: =C57+F57 -> 0 | J57: =IFERROR(I57/I$20,0) -> 0
A58: Owner Fee | C58: ='Vessel Budget'!$AB$58 -> 0 | D58: =IFERROR(C58/C$20,0) -> 0 | F58: ='LW Budget'!$AB$58 -> 0 | G58: =IFERROR(F58/F$20,0) -> 0 | I58: =C58+F58 -> 0 | J58: =IFERROR(I58/I$20,0) -> 0
A59: Business Taxes | C59: ='Vessel Budget'!$AB$59 -> 0 | D59: =IFERROR(C59/C$20,0) -> 0 | F59: ='LW Budget'!$AB$59 -> 0 | G59: =IFERROR(F59/F$20,0) -> 0 | I59: =C59+F59 -> 0 | J59: =IFERROR(I59/I$20,0) -> 0
A60: Total Uncontrollable Expenses | C60: ='Vessel Budget'!$AB$60 -> 22738.426 | D60: =IFERROR(C60/C$20,0) -> 0.064946237 | F60: ='LW Budget'!$AB$60 -> 34510.743 | G60: =IFERROR(F60/F$20,0) -> 0.09305704 | I60: =C60+F60 -> 57249.168 | J60: =IFERROR(I60/I$20,0) -> 0.079406052
A62: Net Operating Profit Before Debt Service | C62: ='Vessel Budget'!$AB$62 -> 87113.77 | D62: =IFERROR(C62/C$20,0) -> 0.2488172 | F62: ='LW Budget'!$AB$62 -> 1034.3316 | G62: =IFERROR(F62/F$20,0) -> 0.0027890398 | I62: =C62+F62 -> 88148.101 | J62: =IFERROR(I62/I$20,0) -> 0.12226366
A64: Debt Service | C64: ='Vessel Budget'!$AB$64 -> 0 | D64: =IFERROR(C64/C$20,0) -> 0 | F64: ='LW Budget'!$AB$64 -> 0 | G64: =IFERROR(F64/F$20,0) -> 0 | I64: =C64+F64 -> 0 | J64: =IFERROR(I64/I$20,0) -> 0
A66: Net Operating Profit After Debt Service | C66: ='Vessel Budget'!$AB$66 -> 87113.77 | D66: =IFERROR(C66/C$20,0) -> 0.2488172 | F66: ='LW Budget'!$AB$66 -> 1034.3316 | G66: =IFERROR(F66/F$20,0) -> 0.0027890398 | I66: =C66+F66 -> 88148.101 | J66: =IFERROR(I66/I$20,0) -> 0.12226366
A68: Other (Income) Expense | C68: ='Vessel Budget'!$AB$68 -> 0 | D68: =IFERROR(C68/C$20,0) -> 0 | F68: ='LW Budget'!$AB$68 -> 0 | G68: =IFERROR(F68/F$20,0) -> 0 | I68: =C68+F68 -> 0 | J68: =IFERROR(I68/I$20,0) -> 0
A69: Reserve / CapEx | C69: ='Vessel Budget'!$AB$69 -> 0 | D69: =IFERROR(C69/C$20,0) -> 0 | F69: ='LW Budget'!$AB$69 -> 2988 | G69: =IFERROR(F69/F$20,0) -> 0.00805704 | I69: =C69+F69 -> 2988 | J69: =IFERROR(I69/I$20,0) -> 0.004144432
A70: Net Cash Flow | C70: ='Vessel Budget'!$AB$70 -> 87113.77 | D70: =IFERROR(C70/C$20,0) -> 0.2488172 | F70: ='LW Budget'!$AB$70 -> -1953.6684 | G70: =IFERROR(F70/F$20,0) -> -0.0052680002 | I70: =C70+F70 -> 85160.101 | J70: =IFERROR(I70/I$20,0) -> 0.11811923
A74: NET OPERATING PROFIT BY MONTH
A75: Month | B75: Vessel | C75: Little Wing | D75: Consolidated | E75: Cumulative
A76: Jan | B76: ='Vessel Budget'!C62 -> 10724.233 | C76: ='LW Budget'!C62 -> -228.5057 | D76: =B76+C76 -> 10495.727 | E76: =SUM($D$76:D76) -> 10495.727
A77: Feb | B77: ='Vessel Budget'!E62 -> 3299.764 | C77: ='LW Budget'!E62 -> -228.5057 | D77: =B77+C77 -> 3071.2583 | E77: =SUM($D$76:D77) -> 13566.986
A78: Mar | B78: ='Vessel Budget'!G62 -> 10724.233 | C78: ='LW Budget'!G62 -> -228.5057 | D78: =B78+C78 -> 10495.727 | E78: =SUM($D$76:D78) -> 24062.713
A79: Apr | B79: ='Vessel Budget'!I62 -> 3299.764 | C79: ='LW Budget'!I62 -> -228.5057 | D79: =B79+C79 -> 3071.2583 | E79: =SUM($D$76:D79) -> 27133.971
A80: May | B80: ='Vessel Budget'!K62 -> 8249.41 | C80: ='LW Budget'!K62 -> -228.5057 | D80: =B80+C80 -> 8020.9043 | E80: =SUM($D$76:D80) -> 35154.875
A81: Jun | B81: ='Vessel Budget'!M62 -> 7259.4808 | C81: ='LW Budget'!M62 -> -228.5057 | D81: =B81+C81 -> 7030.9751 | E81: =SUM($D$76:D81) -> 42185.851
A82: Jul | B82: ='Vessel Budget'!O62 -> 7259.4808 | C82: ='LW Budget'!O62 -> -228.5057 | D82: =B82+C82 -> 7030.9751 | E82: =SUM($D$76:D82) -> 49216.826
A83: Aug | B83: ='Vessel Budget'!Q62 -> 7259.4808 | C83: ='LW Budget'!Q62 -> -228.5057 | D83: =B83+C83 -> 7030.9751 | E83: =SUM($D$76:D83) -> 56247.801
A84: Sep | B84: ='Vessel Budget'!S62 -> 7259.4808 | C84: ='LW Budget'!S62 -> -228.5057 | D84: =B84+C84 -> 7030.9751 | E84: =SUM($D$76:D84) -> 63278.776
A85: Oct | B85: ='Vessel Budget'!U62 -> 7259.4808 | C85: ='LW Budget'!U62 -> -228.5057 | D85: =B85+C85 -> 7030.9751 | E85: =SUM($D$76:D85) -> 70309.751
A86: Nov | B86: ='Vessel Budget'!W62 -> 7259.4808 | C86: ='LW Budget'!W62 -> -228.5057 | D86: =B86+C86 -> 7030.9751 | E86: =SUM($D$76:D86) -> 77340.726
A87: Dec | B87: ='Vessel Budget'!Y62 -> 7259.4808 | C87: ='LW Budget'!Y62 -> 3547.8943 | D87: =B87+C87 -> 10807.375 | E87: =SUM($D$76:D87) -> 88148.101
A88: FY 2027 | B88: =SUM(B76:B87) -> 87113.77 | C88: =SUM(C76:C87) -> 1034.3316 | D88: =SUM(D76:D87) -> 88148.101

Sheet Combined 12-Mo P&L
A1: Method Terrapin — Combined
A2: Profit & Loss Budget — Vessel + Little Wing
A3: 2027
C5: January | E5: February | G5: March | I5: April | K5: May | M5: June | O5: July | Q5: August | S5: September | U5: October | W5: November | Y5: December | AB5: 2027
C6: Budget | E6: Budget | G6: Budget | I6: Budget | K6: Budget | M6: Budget | O6: Budget | Q6: Budget | S6: Budget | U6: Budget | W6: Budget | Y6: Budget | AB6: FY 2027
C7: Amount $ | D7: % | E7: Amount $ | F7: % | G7: Amount $ | H7: % | I7: Amount $ | J7: % | K7: Amount $ | L7: % | M7: Amount $ | N7: % | O7: Amount $ | P7: % | Q7: Amount $ | R7: % | S7: Amount $ | T7: % | U7: Amount $ | V7: % | W7: Amount $ | X7: % | Y7: Amount $ | Z7: % | AB7: Amount $ | AC7: %
A8: Events (Vessel, budgeted) | C8: ='Vessel Budget'!C9 -> 9.269 | E8: ='Vessel Budget'!E9 -> 2.852 | G8: ='Vessel Budget'!G9 -> 9.269 | I8: ='Vessel Budget'!I9 -> 2.852 | K8: ='Vessel Budget'!K9 -> 7.13 | M8: ='Vessel Budget'!M9 -> 6.2744 | O8: ='Vessel Budget'!O9 -> 6.2744 | Q8: ='Vessel Budget'!Q9 -> 6.2744 | S8: ='Vessel Budget'!S9 -> 6.2744 | U8: ='Vessel Budget'!U9 -> 6.2744 | W8: ='Vessel Budget'!W9 -> 6.2744 | Y8: ='Vessel Budget'!Y9 -> 6.2744
A11: Income
A12: Food Sales | C12: ='Vessel Budget'!C12+'LW Budget'!C12 -> 37975.245 | D12: =IFERROR(C12/C$20,0) -> 0.51314085 | E12: ='Vessel Budget'!E12+'LW Budget'!E12 -> 19494.285 | F12: =IFERROR(E12/E$20,0) -> 0.44138221 | G12: ='Vessel Budget'!G12+'LW Budget'!G12 -> 37975.245 | H12: =IFERROR(G12/G$20,0) -> 0.51314085 | I12: ='Vessel Budget'!I12+'LW Budget'!I12 -> 19494.285 | J12: =IFERROR(I12/I$20,0) -> 0.44138221 | K12: ='Vessel Budget'!K12+'LW Budget'!K12 -> 31814.925 | L12: =IFERROR(K12/K$20,0) -> 0.49664919 | M12: ='Vessel Budget'!M12+'LW Budget'!M12 -> 29350.797 | N12: =IFERROR(M12/M$20,0) -> 0.48852362 | O12: ='Vessel Budget'!O12+'LW Budget'!O12 -> 29350.797 | P12: =IFERROR(O12/O$20,0) -> 0.48852362 | Q12: ='Vessel Budget'!Q12+'LW Budget'!Q12 -> 29350.797 | R12: =IFERROR(Q12/Q$20,0) -> 0.48852362 | S12: ='Vessel Budget'!S12+'LW Budget'!S12 -> 29350.797 | T12: =IFERROR(S12/S$20,0) -> 0.48852362 | U12: ='Vessel Budget'!U12+'LW Budget'!U12 -> 29350.797 | V12: =IFERROR(U12/U$20,0) -> 0.48852362 | W12: ='Vessel Budget'!W12+'LW Budget'!W12 -> 29350.797 | X12: =IFERROR(W12/W$20,0) -> 0.48852362 | Y12: ='Vessel Budget'!Y12+'LW Budget'!Y12 -> 29350.797 | Z12: =IFERROR(Y12/Y$20,0) -> 0.48852362 | AB12: =SUM(C12,E12,G12,I12,K12,M12,O12,Q12,S12,U12,W12,Y12) -> 352209.56 | AC12: =IFERROR(AB12/AB$20,0) -> 0.48852362
A13: Non-Alcoholic Beverage Sales | C13: ='Vessel Budget'!C13+'LW Budget'!C13 -> 16676.778 | D13: =IFERROR(C13/C$20,0) -> 0.22534512 | E13: ='Vessel Budget'!E13+'LW Budget'!E13 -> 14867.852 | F13: =IFERROR(E13/E$20,0) -> 0.33663227 | G13: ='Vessel Budget'!G13+'LW Budget'!G13 -> 16676.778 | H13: =IFERROR(G13/G$20,0) -> 0.22534512 | I13: ='Vessel Budget'!I13+'LW Budget'!I13 -> 14867.852 | J13: =IFERROR(I13/I$20,0) -> 0.33663227 | K13: ='Vessel Budget'!K13+'LW Budget'!K13 -> 16073.803 | L13: =IFERROR(K13/K$20,0) -> 0.25092127 | M13: ='Vessel Budget'!M13+'LW Budget'!M13 -> 15832.613 | N13: =IFERROR(M13/M$20,0) -> 0.26352284 | O13: ='Vessel Budget'!O13+'LW Budget'!O13 -> 15832.613 | P13: =IFERROR(O13/O$20,0) -> 0.26352284 | Q13: ='Vessel Budget'!Q13+'LW Budget'!Q13 -> 15832.613 | R13: =IFERROR(Q13/Q$20,0) -> 0.26352284 | S13: ='Vessel Budget'!S13+'LW Budget'!S13 -> 15832.613 | T13: =IFERROR(S13/S$20,0) -> 0.26352284 | U13: ='Vessel Budget'!U13+'LW Budget'!U13 -> 15832.613 | V13: =IFERROR(U13/U$20,0) -> 0.26352284 | W13: ='Vessel Budget'!W13+'LW Budget'!W13 -> 15832.613 | X13: =IFERROR(W13/W$20,0) -> 0.26352284 | Y13: ='Vessel Budget'!Y13+'LW Budget'!Y13 -> 15832.613 | Z13: =IFERROR(Y13/Y$20,0) -> 0.26352284 | AB13: =SUM(C13,E13,G13,I13,K13,M13,O13,Q13,S13,U13,W13,Y13) -> 189991.35 | AC13: =IFERROR(AB13/AB$20,0) -> 0.26352284
A14: Liquor Sales | C14: ='Vessel Budget'!C14+'LW Budget'!C14 -> 5003.574 | D14: =IFERROR(C14/C$20,0) -> 0.067610839 | E14: ='Vessel Budget'!E14+'LW Budget'!E14 -> 1961.1766 | F14: =IFERROR(E14/E$20,0) -> 0.044404217 | G14: ='Vessel Budget'!G14+'LW Budget'!G14 -> 5003.574 | H14: =IFERROR(G14/G$20,0) -> 0.067610839 | I14: ='Vessel Budget'!I14+'LW Budget'!I14 -> 1961.1766 | J14: =IFERROR(I14/I$20,0) -> 0.044404217 | K14: ='Vessel Budget'!K14+'LW Budget'!K14 -> 3989.4415 | L14: =IFERROR(K14/K$20,0) -> 0.062277466 | M14: ='Vessel Budget'!M14+'LW Budget'!M14 -> 3583.7885 | N14: =IFERROR(M14/M$20,0) -> 0.05964967 | O14: ='Vessel Budget'!O14+'LW Budget'!O14 -> 3583.7885 | P14: =IFERROR(O14/O$20,0) -> 0.05964967 | Q14: ='Vessel Budget'!Q14+'LW Budget'!Q14 -> 3583.7885 | R14: =IFERROR(Q14/Q$20,0) -> 0.05964967 | S14: ='Vessel Budget'!S14+'LW Budget'!S14 -> 3583.7885 | T14: =IFERROR(S14/S$20,0) -> 0.05964967 | U14: ='Vessel Budget'!U14+'LW Budget'!U14 -> 3583.7885 | V14: =IFERROR(U14/U$20,0) -> 0.05964967 | W14: ='Vessel Budget'!W14+'LW Budget'!W14 -> 3583.7885 | X14: =IFERROR(W14/W$20,0) -> 0.05964967 | Y14: ='Vessel Budget'!Y14+'LW Budget'!Y14 -> 3583.7885 | Z14: =IFERROR(Y14/Y$20,0) -> 0.05964967 | AB14: =SUM(C14,E14,G14,I14,K14,M14,O14,Q14,S14,U14,W14,Y14) -> 43005.462 | AC14: =IFERROR(AB14/AB$20,0) -> 0.05964967
A15: Beer Sales | C15: ='Vessel Budget'!C15+'LW Budget'!C15 -> 777.01368 | D15: =IFERROR(C15/C$20,0) -> 0.010499404 | E15: ='Vessel Budget'!E15+'LW Budget'!E15 -> 664.85036 | F15: =IFERROR(E15/E$20,0) -> 0.01505329 | G15: ='Vessel Budget'!G15+'LW Budget'!G15 -> 777.01368 | H15: =IFERROR(G15/G$20,0) -> 0.010499404 | I15: ='Vessel Budget'!I15+'LW Budget'!I15 -> 664.85036 | J15: =IFERROR(I15/I$20,0) -> 0.01505329 | K15: ='Vessel Budget'!K15+'LW Budget'!K15 -> 739.6259 | L15: =IFERROR(K15/K$20,0) -> 0.011545984 | M15: ='Vessel Budget'!M15+'LW Budget'!M15 -> 724.6708 | N15: =IFERROR(M15/M$20,0) -> 0.012061642 | O15: ='Vessel Budget'!O15+'LW Budget'!O15 -> 724.6708 | P15: =IFERROR(O15/O$20,0) -> 0.012061642 | Q15: ='Vessel Budget'!Q15+'LW Budget'!Q15 -> 724.6708 | R15: =IFERROR(Q15/Q$20,0) -> 0.012061642 | S15: ='Vessel Budget'!S15+'LW Budget'!S15 -> 724.6708 | T15: =IFERROR(S15/S$20,0) -> 0.012061642 | U15: ='Vessel Budget'!U15+'LW Budget'!U15 -> 724.6708 | V15: =IFERROR(U15/U$20,0) -> 0.012061642 | W15: ='Vessel Budget'!W15+'LW Budget'!W15 -> 724.6708 | X15: =IFERROR(W15/W$20,0) -> 0.012061642 | Y15: ='Vessel Budget'!Y15+'LW Budget'!Y15 -> 724.6708 | Z15: =IFERROR(Y15/Y$20,0) -> 0.012061642 | AB15: =SUM(C15,E15,G15,I15,K15,M15,O15,Q15,S15,U15,W15,Y15) -> 8696.0495 | AC15: =IFERROR(AB15/AB$20,0) -> 0.012061642
A16: Wine Sales | C16: ='Vessel Budget'!C16+'LW Budget'!C16 -> 1661.479 | D16: =IFERROR(C16/C$20,0) -> 0.02245075 | E16: ='Vessel Budget'!E16+'LW Budget'!E16 -> 1234.6858 | F16: =IFERROR(E16/E$20,0) -> 0.027955288 | G16: ='Vessel Budget'!G16+'LW Budget'!G16 -> 1661.479 | H16: =IFERROR(G16/G$20,0) -> 0.02245075 | I16: ='Vessel Budget'!I16+'LW Budget'!I16 -> 1234.6858 | J16: =IFERROR(I16/I$20,0) -> 0.027955288 | K16: ='Vessel Budget'!K16+'LW Budget'!K16 -> 1519.2146 | L16: =IFERROR(K16/K$20,0) -> 0.023715809 | M16: ='Vessel Budget'!M16+'LW Budget'!M16 -> 1462.3088 | N16: =IFERROR(M16/M$20,0) -> 0.024339114 | O16: ='Vessel Budget'!O16+'LW Budget'!O16 -> 1462.3088 | P16: =IFERROR(O16/O$20,0) -> 0.024339114 | Q16: ='Vessel Budget'!Q16+'LW Budget'!Q16 -> 1462.3088 | R16: =IFERROR(Q16/Q$20,0) -> 0.024339114 | S16: ='Vessel Budget'!S16+'LW Budget'!S16 -> 1462.3088 | T16: =IFERROR(S16/S$20,0) -> 0.024339114 | U16: ='Vessel Budget'!U16+'LW Budget'!U16 -> 1462.3088 | V16: =IFERROR(U16/U$20,0) -> 0.024339114 | W16: ='Vessel Budget'!W16+'LW Budget'!W16 -> 1462.3088 | X16: =IFERROR(W16/W$20,0) -> 0.024339114 | Y16: ='Vessel Budget'!Y16+'LW Budget'!Y16 -> 1462.3088 | Z16: =IFERROR(Y16/Y$20,0) -> 0.024339114 | AB16: =SUM(C16,E16,G16,I16,K16,M16,O16,Q16,S16,U16,W16,Y16) -> 17547.706 | AC16: =IFERROR(AB16/AB$20,0) -> 0.024339114
A17: Retail / Merch Sales | C17: ='Vessel Budget'!C17+'LW Budget'!C17 -> 3743.6667 | D17: =IFERROR(C17/C$20,0) -> 0.05058633 | E17: ='Vessel Budget'!E17+'LW Budget'!E17 -> 3743.6667 | F17: =IFERROR(E17/E$20,0) -> 0.08476268 | G17: ='Vessel Budget'!G17+'LW Budget'!G17 -> 3743.6667 | H17: =IFERROR(G17/G$20,0) -> 0.05058633 | I17: ='Vessel Budget'!I17+'LW Budget'!I17 -> 3743.6667 | J17: =IFERROR(I17/I$20,0) -> 0.08476268 | K17: ='Vessel Budget'!K17+'LW Budget'!K17 -> 3743.6667 | L17: =IFERROR(K17/K$20,0) -> 0.05844078 | M17: ='Vessel Budget'!M17+'LW Budget'!M17 -> 3743.6667 | N17: =IFERROR(M17/M$20,0) -> 0.06231073 | O17: ='Vessel Budget'!O17+'LW Budget'!O17 -> 3743.6667 | P17: =IFERROR(O17/O$20,0) -> 0.06231073 | Q17: ='Vessel Budget'!Q17+'LW Budget'!Q17 -> 3743.6667 | R17: =IFERROR(Q17/Q$20,0) -> 0.06231073 | S17: ='Vessel Budget'!S17+'LW Budget'!S17 -> 3743.6667 | T17: =IFERROR(S17/S$20,0) -> 0.06231073 | U17: ='Vessel Budget'!U17+'LW Budget'!U17 -> 3743.6667 | V17: =IFERROR(U17/U$20,0) -> 0.06231073 | W17: ='Vessel Budget'!W17+'LW Budget'!W17 -> 3743.6667 | X17: =IFERROR(W17/W$20,0) -> 0.06231073 | Y17: ='Vessel Budget'!Y17+'LW Budget'!Y17 -> 3743.6667 | Z17: =IFERROR(Y17/Y$20,0) -> 0.06231073 | AB17: =SUM(C17,E17,G17,I17,K17,M17,O17,Q17,S17,U17,W17,Y17) -> 44924 | AC17: =IFERROR(AB17/AB$20,0) -> 0.06231073
A18: Other Operating Income | C18: ='Vessel Budget'!C18+'LW Budget'!C18 -> 8960.17 | D18: =IFERROR(C18/C$20,0) -> 0.12107438 | E18: ='Vessel Budget'!E18+'LW Budget'!E18 -> 2992.36 | F18: =IFERROR(E18/E$20,0) -> 0.06775188 | G18: ='Vessel Budget'!G18+'LW Budget'!G18 -> 8960.17 | H18: =IFERROR(G18/G$20,0) -> 0.12107438 | I18: ='Vessel Budget'!I18+'LW Budget'!I18 -> 2992.36 | J18: =IFERROR(I18/I$20,0) -> 0.06775188 | K18: ='Vessel Budget'!K18+'LW Budget'!K18 -> 6970.9 | L18: =IFERROR(K18/K$20,0) -> 0.10881974 | M18: ='Vessel Budget'!M18+'LW Budget'!M18 -> 6175.192 | N18: =IFERROR(M18/M$20,0) -> 0.10278178 | O18: ='Vessel Budget'!O18+'LW Budget'!O18 -> 6175.192 | P18: =IFERROR(O18/O$20,0) -> 0.10278178 | Q18: ='Vessel Budget'!Q18+'LW Budget'!Q18 -> 6175.192 | R18: =IFERROR(Q18/Q$20,0) -> 0.10278178 | S18: ='Vessel Budget'!S18+'LW Budget'!S18 -> 6175.192 | T18: =IFERROR(S18/S$20,0) -> 0.10278178 | U18: ='Vessel Budget'!U18+'LW Budget'!U18 -> 6175.192 | V18: =IFERROR(U18/U$20,0) -> 0.10278178 | W18: ='Vessel Budget'!W18+'LW Budget'!W18 -> 6175.192 | X18: =IFERROR(W18/W$20,0) -> 0.10278178 | Y18: ='Vessel Budget'!Y18+'LW Budget'!Y18 -> 6175.192 | Z18: =IFERROR(Y18/Y$20,0) -> 0.10278178 | AB18: =SUM(C18,E18,G18,I18,K18,M18,O18,Q18,S18,U18,W18,Y18) -> 74102.304 | AC18: =IFERROR(AB18/AB$20,0) -> 0.10278178
A19: Discounts & Comps | C19: ='Vessel Budget'!C19+'LW Budget'!C19 -> -792.42692 | D19: =IFERROR(C19/C$20,0) -> -0.010707676 | E19: ='Vessel Budget'!E19+'LW Budget'!E19 -> -792.42692 | F19: =IFERROR(E19/E$20,0) -> -0.01794183 | G19: ='Vessel Budget'!G19+'LW Budget'!G19 -> -792.42692 | H19: =IFERROR(G19/G$20,0) -> -0.010707676 | I19: ='Vessel Budget'!I19+'LW Budget'!I19 -> -792.42692 | J19: =IFERROR(I19/I$20,0) -> -0.01794183 | K19: ='Vessel Budget'!K19+'LW Budget'!K19 -> -792.42692 | L19: =IFERROR(K19/K$20,0) -> -0.012370238 | M19: ='Vessel Budget'!M19+'LW Budget'!M19 -> -792.42692 | N19: =IFERROR(M19/M$20,0) -> -0.013189395 | O19: ='Vessel Budget'!O19+'LW Budget'!O19 -> -792.42692 | P19: =IFERROR(O19/O$20,0) -> -0.013189395 | Q19: ='Vessel Budget'!Q19+'LW Budget'!Q19 -> -792.42692 | R19: =IFERROR(Q19/Q$20,0) -> -0.013189395 | S19: ='Vessel Budget'!S19+'LW Budget'!S19 -> -792.42692 | T19: =IFERROR(S19/S$20,0) -> -0.013189395 | U19: ='Vessel Budget'!U19+'LW Budget'!U19 -> -792.42692 | V19: =IFERROR(U19/U$20,0) -> -0.013189395 | W19: ='Vessel Budget'!W19+'LW Budget'!W19 -> -792.42692 | X19: =IFERROR(W19/W$20,0) -> -0.013189395 | Y19: ='Vessel Budget'!Y19+'LW Budget'!Y19 -> -792.42692 | Z19: =IFERROR(Y19/Y$20,0) -> -0.013189395 | AB19: =SUM(C19,E19,G19,I19,K19,M19,O19,Q19,S19,U19,W19,Y19) -> -9509.123 | AC19: =IFERROR(AB19/AB$20,0) -> -0.013189395
A20: Total Income | C20: =SUM(C12:C19) -> 74005.5 | D20: =IFERROR(C20/C$20,0) -> 1 | E20: =SUM(E12:E19) -> 44166.45 | F20: =IFERROR(E20/E$20,0) -> 1 | G20: =SUM(G12:G19) -> 74005.5 | H20: =IFERROR(G20/G$20,0) -> 1 | I20: =SUM(I12:I19) -> 44166.45 | J20: =IFERROR(I20/I$20,0) -> 1 | K20: =SUM(K12:K19) -> 64059.15 | L20: =IFERROR(K20/K$20,0) -> 1 | M20: =SUM(M12:M19) -> 60080.61 | N20: =IFERROR(M20/M$20,0) -> 1 | O20: =SUM(O12:O19) -> 60080.61 | P20: =IFERROR(O20/O$20,0) -> 1 | Q20: =SUM(Q12:Q19) -> 60080.61 | R20: =IFERROR(Q20/Q$20,0) -> 1 | S20: =SUM(S12:S19) -> 60080.61 | T20: =IFERROR(S20/S$20,0) -> 1 | U20: =SUM(U12:U19) -> 60080.61 | V20: =IFERROR(U20/U$20,0) -> 1 | W20: =SUM(W12:W19) -> 60080.61 | X20: =IFERROR(W20/W$20,0) -> 1 | Y20: =SUM(Y12:Y19) -> 60080.61 | Z20: =IFERROR(Y20/Y$20,0) -> 1 | AB20: =SUM(AB12:AB19) -> 720967.32 | AC20: =IFERROR(AB20/AB$20,0) -> 1
A22: Cost of Goods Sold
A23: Food Cost | C23: ='Vessel Budget'!C23+'LW Budget'!C23 -> 19264.4 | D23: =IFERROR(C23/C$12,0) -> 0.50728837 | E23: ='Vessel Budget'!E23+'LW Budget'!E23 -> 8997.2 | F23: =IFERROR(E23/E$12,0) -> 0.46153014 | G23: ='Vessel Budget'!G23+'LW Budget'!G23 -> 19264.4 | H23: =IFERROR(G23/G$12,0) -> 0.50728837 | I23: ='Vessel Budget'!I23+'LW Budget'!I23 -> 8997.2 | J23: =IFERROR(I23/I$12,0) -> 0.46153014 | K23: ='Vessel Budget'!K23+'LW Budget'!K23 -> 15842 | L23: =IFERROR(K23/K$12,0) -> 0.4979424 | M23: ='Vessel Budget'!M23+'LW Budget'!M23 -> 14473.04 | N23: =IFERROR(M23/M$12,0) -> 0.49310552 | O23: ='Vessel Budget'!O23+'LW Budget'!O23 -> 14473.04 | P23: =IFERROR(O23/O$12,0) -> 0.49310552 | Q23: ='Vessel Budget'!Q23+'LW Budget'!Q23 -> 14473.04 | R23: =IFERROR(Q23/Q$12,0) -> 0.49310552 | S23: ='Vessel Budget'!S23+'LW Budget'!S23 -> 14473.04 | T23: =IFERROR(S23/S$12,0) -> 0.49310552 | U23: ='Vessel Budget'!U23+'LW Budget'!U23 -> 14473.04 | V23: =IFERROR(U23/U$12,0) -> 0.49310552 | W23: ='Vessel Budget'!W23+'LW Budget'!W23 -> 14473.04 | X23: =IFERROR(W23/W$12,0) -> 0.49310552 | Y23: ='Vessel Budget'!Y23+'LW Budget'!Y23 -> 14473.04 | Z23: =IFERROR(Y23/Y$12,0) -> 0.49310552 | AB23: =SUM(C23,E23,G23,I23,K23,M23,O23,Q23,S23,U23,W23,Y23) -> 173676.48 | AC23: =IFERROR(AB23/AB$12,0) -> 0.49310552
A24: Non-Alcoholic Beverage Cost | C24: ='Vessel Budget'!C24+'LW Budget'!C24 -> 3486.2234 | D24: =IFERROR(C24/C$13,0) -> 0.20904657 | E24: ='Vessel Budget'!E24+'LW Budget'!E24 -> 3033.9918 | F24: =IFERROR(E24/E$13,0) -> 0.20406389 | G24: ='Vessel Budget'!G24+'LW Budget'!G24 -> 3486.2234 | H24: =IFERROR(G24/G$13,0) -> 0.20904657 | I24: ='Vessel Budget'!I24+'LW Budget'!I24 -> 3033.9918 | J24: =IFERROR(I24/I$13,0) -> 0.20406389 | K24: ='Vessel Budget'!K24+'LW Budget'!K24 -> 3335.4795 | L24: =IFERROR(K24/K$13,0) -> 0.20751029 | M24: ='Vessel Budget'!M24+'LW Budget'!M24 -> 3275.182 | N24: =IFERROR(M24/M$13,0) -> 0.20686301 | O24: ='Vessel Budget'!O24+'LW Budget'!O24 -> 3275.182 | P24: =IFERROR(O24/O$13,0) -> 0.20686301 | Q24: ='Vessel Budget'!Q24+'LW Budget'!Q24 -> 3275.182 | R24: =IFERROR(Q24/Q$13,0) -> 0.20686301 | S24: ='Vessel Budget'!S24+'LW Budget'!S24 -> 3275.182 | T24: =IFERROR(S24/S$13,0) -> 0.20686301 | U24: ='Vessel Budget'!U24+'LW Budget'!U24 -> 3275.182 | V24: =IFERROR(U24/U$13,0) -> 0.20686301 | W24: ='Vessel Budget'!W24+'LW Budget'!W24 -> 3275.182 | X24: =IFERROR(W24/W$13,0) -> 0.20686301 | Y24: ='Vessel Budget'!Y24+'LW Budget'!Y24 -> 3275.182 | Z24: =IFERROR(Y24/Y$13,0) -> 0.20686301 | AB24: =SUM(C24,E24,G24,I24,K24,M24,O24,Q24,S24,U24,W24,Y24) -> 39302.184 | AC24: =IFERROR(AB24/AB$13,0) -> 0.20686301
A25: Liquor Cost | C25: ='Vessel Budget'!C25+'LW Budget'!C25 -> 1177.6435 | D25: =IFERROR(C25/C$14,0) -> 0.23536046 | E25: ='Vessel Budget'!E25+'LW Budget'!E25 -> 417.04415 | F25: =IFERROR(E25/E$14,0) -> 0.21264997 | G25: ='Vessel Budget'!G25+'LW Budget'!G25 -> 1177.6435 | H25: =IFERROR(G25/G$14,0) -> 0.23536046 | I25: ='Vessel Budget'!I25+'LW Budget'!I25 -> 417.04415 | J25: =IFERROR(I25/I$14,0) -> 0.21264997 | K25: ='Vessel Budget'!K25+'LW Budget'!K25 -> 924.11038 | L25: =IFERROR(K25/K$14,0) -> 0.23163903 | M25: ='Vessel Budget'!M25+'LW Budget'!M25 -> 822.69713 | N25: =IFERROR(M25/M$14,0) -> 0.22956074 | O25: ='Vessel Budget'!O25+'LW Budget'!O25 -> 822.69713 | P25: =IFERROR(O25/O$14,0) -> 0.22956074 | Q25: ='Vessel Budget'!Q25+'LW Budget'!Q25 -> 822.69713 | R25: =IFERROR(Q25/Q$14,0) -> 0.22956074 | S25: ='Vessel Budget'!S25+'LW Budget'!S25 -> 822.69713 | T25: =IFERROR(S25/S$14,0) -> 0.22956074 | U25: ='Vessel Budget'!U25+'LW Budget'!U25 -> 822.69713 | V25: =IFERROR(U25/U$14,0) -> 0.22956074 | W25: ='Vessel Budget'!W25+'LW Budget'!W25 -> 822.69713 | X25: =IFERROR(W25/W$14,0) -> 0.22956074 | Y25: ='Vessel Budget'!Y25+'LW Budget'!Y25 -> 822.69713 | Z25: =IFERROR(Y25/Y$14,0) -> 0.22956074 | AB25: =SUM(C25,E25,G25,I25,K25,M25,O25,Q25,S25,U25,W25,Y25) -> 9872.3656 | AC25: =IFERROR(AB25/AB$14,0) -> 0.22956074
A26: Beer Cost | C26: ='Vessel Budget'!C26+'LW Budget'!C26 -> 212.50342 | D26: =IFERROR(C26/C$15,0) -> 0.27348736 | E26: ='Vessel Budget'!E26+'LW Budget'!E26 -> 184.46259 | F26: =IFERROR(E26/E$15,0) -> 0.27744979 | G26: ='Vessel Budget'!G26+'LW Budget'!G26 -> 212.50342 | H26: =IFERROR(G26/G$15,0) -> 0.27348736 | I26: ='Vessel Budget'!I26+'LW Budget'!I26 -> 184.46259 | J26: =IFERROR(I26/I$15,0) -> 0.27744979 | K26: ='Vessel Budget'!K26+'LW Budget'!K26 -> 203.15648 | L26: =IFERROR(K26/K$15,0) -> 0.27467464 | M26: ='Vessel Budget'!M26+'LW Budget'!M26 -> 199.4177 | N26: =IFERROR(M26/M$15,0) -> 0.27518385 | O26: ='Vessel Budget'!O26+'LW Budget'!O26 -> 199.4177 | P26: =IFERROR(O26/O$15,0) -> 0.27518385 | Q26: ='Vessel Budget'!Q26+'LW Budget'!Q26 -> 199.4177 | R26: =IFERROR(Q26/Q$15,0) -> 0.27518385 | S26: ='Vessel Budget'!S26+'LW Budget'!S26 -> 199.4177 | T26: =IFERROR(S26/S$15,0) -> 0.27518385 | U26: ='Vessel Budget'!U26+'LW Budget'!U26 -> 199.4177 | V26: =IFERROR(U26/U$15,0) -> 0.27518385 | W26: ='Vessel Budget'!W26+'LW Budget'!W26 -> 199.4177 | X26: =IFERROR(W26/W$15,0) -> 0.27518385 | Y26: ='Vessel Budget'!Y26+'LW Budget'!Y26 -> 199.4177 | Z26: =IFERROR(Y26/Y$15,0) -> 0.27518385 | AB26: =SUM(C26,E26,G26,I26,K26,M26,O26,Q26,S26,U26,W26,Y26) -> 2393.0124 | AC26: =IFERROR(AB26/AB$15,0) -> 0.27518385
A27: Wine/Sake Cost | C27: ='Vessel Budget'!C27+'LW Budget'!C27 -> 527.11974 | D27: =IFERROR(C27/C$16,0) -> 0.31725935 | E27: ='Vessel Budget'!E27+'LW Budget'!E27 -> 420.42146 | F27: =IFERROR(E27/E$16,0) -> 0.34050885 | G27: ='Vessel Budget'!G27+'LW Budget'!G27 -> 527.11974 | H27: =IFERROR(G27/G$16,0) -> 0.31725935 | I27: ='Vessel Budget'!I27+'LW Budget'!I27 -> 420.42146 | J27: =IFERROR(I27/I$16,0) -> 0.34050885 | K27: ='Vessel Budget'!K27+'LW Budget'!K27 -> 491.55364 | L27: =IFERROR(K27/K$16,0) -> 0.32355775 | M27: ='Vessel Budget'!M27+'LW Budget'!M27 -> 477.32721 | N27: =IFERROR(M27/M$16,0) -> 0.32642025 | O27: ='Vessel Budget'!O27+'LW Budget'!O27 -> 477.32721 | P27: =IFERROR(O27/O$16,0) -> 0.32642025 | Q27: ='Vessel Budget'!Q27+'LW Budget'!Q27 -> 477.32721 | R27: =IFERROR(Q27/Q$16,0) -> 0.32642025 | S27: ='Vessel Budget'!S27+'LW Budget'!S27 -> 477.32721 | T27: =IFERROR(S27/S$16,0) -> 0.32642025 | U27: ='Vessel Budget'!U27+'LW Budget'!U27 -> 477.32721 | V27: =IFERROR(U27/U$16,0) -> 0.32642025 | W27: ='Vessel Budget'!W27+'LW Budget'!W27 -> 477.32721 | X27: =IFERROR(W27/W$16,0) -> 0.32642025 | Y27: ='Vessel Budget'!Y27+'LW Budget'!Y27 -> 477.32721 | Z27: =IFERROR(Y27/Y$16,0) -> 0.32642025 | AB27: =SUM(C27,E27,G27,I27,K27,M27,O27,Q27,S27,U27,W27,Y27) -> 5727.9265 | AC27: =IFERROR(AB27/AB$16,0) -> 0.32642025
A28: Retail Cost | C28: ='Vessel Budget'!C28+'LW Budget'!C28 -> 1470.0077 | D28: =IFERROR(C28/C$17,0) -> 0.39266522 | E28: ='Vessel Budget'!E28+'LW Budget'!E28 -> 1470.0077 | F28: =IFERROR(E28/E$17,0) -> 0.39266522 | G28: ='Vessel Budget'!G28+'LW Budget'!G28 -> 1470.0077 | H28: =IFERROR(G28/G$17,0) -> 0.39266522 | I28: ='Vessel Budget'!I28+'LW Budget'!I28 -> 1470.0077 | J28: =IFERROR(I28/I$17,0) -> 0.39266522 | K28: ='Vessel Budget'!K28+'LW Budget'!K28 -> 1470.0077 | L28: =IFERROR(K28/K$17,0) -> 0.39266522 | M28: ='Vessel Budget'!M28+'LW Budget'!M28 -> 1470.0077 | N28: =IFERROR(M28/M$17,0) -> 0.39266522 | O28: ='Vessel Budget'!O28+'LW Budget'!O28 -> 1470.0077 | P28: =IFERROR(O28/O$17,0) -> 0.39266522 | Q28: ='Vessel Budget'!Q28+'LW Budget'!Q28 -> 1470.0077 | R28: =IFERROR(Q28/Q$17,0) -> 0.39266522 | S28: ='Vessel Budget'!S28+'LW Budget'!S28 -> 1470.0077 | T28: =IFERROR(S28/S$17,0) -> 0.39266522 | U28: ='Vessel Budget'!U28+'LW Budget'!U28 -> 1470.0077 | V28: =IFERROR(U28/U$17,0) -> 0.39266522 | W28: ='Vessel Budget'!W28+'LW Budget'!W28 -> 1470.0077 | X28: =IFERROR(W28/W$17,0) -> 0.39266522 | Y28: ='Vessel Budget'!Y28+'LW Budget'!Y28 -> 1470.0077 | Z28: =IFERROR(Y28/Y$17,0) -> 0.39266522 | AB28: =SUM(C28,E28,G28,I28,K28,M28,O28,Q28,S28,U28,W28,Y28) -> 17640.092 | AC28: =IFERROR(AB28/AB$17,0) -> 0.39266522
A29: Total COGS | C29: =SUM(C23:C28) -> 26137.898 | D29: =IFERROR(C29/C$20,0) -> 0.35318858 | E29: =SUM(E23:E28) -> 14523.128 | F29: =IFERROR(E29/E$20,0) -> 0.32882715 | G29: =SUM(G23:G28) -> 26137.898 | H29: =IFERROR(G29/G$20,0) -> 0.35318858 | I29: =SUM(I23:I28) -> 14523.128 | J29: =IFERROR(I29/I$20,0) -> 0.32882715 | K29: =SUM(K23:K28) -> 22266.308 | L29: =IFERROR(K29/K$20,0) -> 0.34758981 | M29: =SUM(M23:M28) -> 20717.672 | N29: =IFERROR(M29/M$20,0) -> 0.34483125 | O29: =SUM(O23:O28) -> 20717.672 | P29: =IFERROR(O29/O$20,0) -> 0.34483125 | Q29: =SUM(Q23:Q28) -> 20717.672 | R29: =IFERROR(Q29/Q$20,0) -> 0.34483125 | S29: =SUM(S23:S28) -> 20717.672 | T29: =IFERROR(S29/S$20,0) -> 0.34483125 | U29: =SUM(U23:U28) -> 20717.672 | V29: =IFERROR(U29/U$20,0) -> 0.34483125 | W29: =SUM(W23:W28) -> 20717.672 | X29: =IFERROR(W29/W$20,0) -> 0.34483125 | Y29: =SUM(Y23:Y28) -> 20717.672 | Z29: =IFERROR(Y29/Y$20,0) -> 0.34483125 | AB29: =SUM(AB23:AB28) -> 248612.06 | AC29: =IFERROR(AB29/AB$20,0) -> 0.34483125
A30: Gross Profit | C30: =C20-C29 -> 47867.602 | D30: =IFERROR(C30/C$20,0) -> 0.64681142 | E30: =E20-E29 -> 29643.322 | F30: =IFERROR(E30/E$20,0) -> 0.67117285 | G30: =G20-G29 -> 47867.602 | H30: =IFERROR(G30/G$20,0) -> 0.64681142 | I30: =I20-I29 -> 29643.322 | J30: =IFERROR(I30/I$20,0) -> 0.67117285 | K30: =K20-K29 -> 41792.842 | L30: =IFERROR(K30/K$20,0) -> 0.65241019 | M30: =M20-M29 -> 39362.938 | N30: =IFERROR(M30/M$20,0) -> 0.65516875 | O30: =O20-O29 -> 39362.938 | P30: =IFERROR(O30/O$20,0) -> 0.65516875 | Q30: =Q20-Q29 -> 39362.938 | R30: =IFERROR(Q30/Q$20,0) -> 0.65516875 | S30: =S20-S29 -> 39362.938 | T30: =IFERROR(S30/S$20,0) -> 0.65516875 | U30: =U20-U29 -> 39362.938 | V30: =IFERROR(U30/U$20,0) -> 0.65516875 | W30: =W20-W29 -> 39362.938 | X30: =IFERROR(W30/W$20,0) -> 0.65516875 | Y30: =Y20-Y29 -> 39362.938 | Z30: =IFERROR(Y30/Y$20,0) -> 0.65516875 | AB30: =AB20-AB29 -> 472355.26 | AC30: =IFERROR(AB30/AB$20,0) -> 0.65516875
A32: Labor Cost
A33: Management Labor | C33: ='Vessel Budget'!C33+'LW Budget'!C33 -> 2166.795 | D33: =IFERROR(C33/C$20,0) -> 0.029278837 | E33: ='Vessel Budget'!E33+'LW Budget'!E33 -> 1813.86 | F33: =IFERROR(E33/E$20,0) -> 0.04106873 | G33: ='Vessel Budget'!G33+'LW Budget'!G33 -> 2166.795 | H33: =IFERROR(G33/G$20,0) -> 0.029278837 | I33: ='Vessel Budget'!I33+'LW Budget'!I33 -> 1813.86 | J33: =IFERROR(I33/I$20,0) -> 0.04106873 | K33: ='Vessel Budget'!K33+'LW Budget'!K33 -> 2049.15 | L33: =IFERROR(K33/K$20,0) -> 0.031988405 | M33: ='Vessel Budget'!M33+'LW Budget'!M33 -> 2002.092 | N33: =IFERROR(M33/M$20,0) -> 0.03332343 | O33: ='Vessel Budget'!O33+'LW Budget'!O33 -> 2002.092 | P33: =IFERROR(O33/O$20,0) -> 0.03332343 | Q33: ='Vessel Budget'!Q33+'LW Budget'!Q33 -> 2002.092 | R33: =IFERROR(Q33/Q$20,0) -> 0.03332343 | S33: ='Vessel Budget'!S33+'LW Budget'!S33 -> 2002.092 | T33: =IFERROR(S33/S$20,0) -> 0.03332343 | U33: ='Vessel Budget'!U33+'LW Budget'!U33 -> 2002.092 | V33: =IFERROR(U33/U$20,0) -> 0.03332343 | W33: ='Vessel Budget'!W33+'LW Budget'!W33 -> 2002.092 | X33: =IFERROR(W33/W$20,0) -> 0.03332343 | Y33: ='Vessel Budget'!Y33+'LW Budget'!Y33 -> 2002.092 | Z33: =IFERROR(Y33/Y$20,0) -> 0.03332343 | AB33: =SUM(C33,E33,G33,I33,K33,M33,O33,Q33,S33,U33,W33,Y33) -> 24025.104 | AC33: =IFERROR(AB33/AB$20,0) -> 0.03332343
A34: Back of House Hourly Labor | C34: ='Vessel Budget'!C34+'LW Budget'!C34 -> 1282.6667 | D34: =IFERROR(C34/C$20,0) -> 0.017332045 | E34: ='Vessel Budget'!E34+'LW Budget'!E34 -> 1282.6667 | F34: =IFERROR(E34/E$20,0) -> 0.029041652 | G34: ='Vessel Budget'!G34+'LW Budget'!G34 -> 1282.6667 | H34: =IFERROR(G34/G$20,0) -> 0.017332045 | I34: ='Vessel Budget'!I34+'LW Budget'!I34 -> 1282.6667 | J34: =IFERROR(I34/I$20,0) -> 0.029041652 | K34: ='Vessel Budget'!K34+'LW Budget'!K34 -> 1282.6667 | L34: =IFERROR(K34/K$20,0) -> 0.020023161 | M34: ='Vessel Budget'!M34+'LW Budget'!M34 -> 1282.6667 | N34: =IFERROR(M34/M$20,0) -> 0.021349095 | O34: ='Vessel Budget'!O34+'LW Budget'!O34 -> 1282.6667 | P34: =IFERROR(O34/O$20,0) -> 0.021349095 | Q34: ='Vessel Budget'!Q34+'LW Budget'!Q34 -> 1282.6667 | R34: =IFERROR(Q34/Q$20,0) -> 0.021349095 | S34: ='Vessel Budget'!S34+'LW Budget'!S34 -> 1282.6667 | T34: =IFERROR(S34/S$20,0) -> 0.021349095 | U34: ='Vessel Budget'!U34+'LW Budget'!U34 -> 1282.6667 | V34: =IFERROR(U34/U$20,0) -> 0.021349095 | W34: ='Vessel Budget'!W34+'LW Budget'!W34 -> 1282.6667 | X34: =IFERROR(W34/W$20,0) -> 0.021349095 | Y34: ='Vessel Budget'!Y34+'LW Budget'!Y34 -> 1282.6667 | Z34: =IFERROR(Y34/Y$20,0) -> 0.021349095 | AB34: =SUM(C34,E34,G34,I34,K34,M34,O34,Q34,S34,U34,W34,Y34) -> 15392 | AC34: =IFERROR(AB34/AB$20,0) -> 0.021349095
A35: Front of House Hourly Labor | C35: ='Vessel Budget'!C35+'LW Budget'!C35 -> 11626.225 | D35: =IFERROR(C35/C$20,0) -> 0.15709947 | E35: ='Vessel Budget'!E35+'LW Budget'!E35 -> 8257.3 | F35: =IFERROR(E35/E$20,0) -> 0.18695865 | G35: ='Vessel Budget'!G35+'LW Budget'!G35 -> 11626.225 | H35: =IFERROR(G35/G$20,0) -> 0.15709947 | I35: ='Vessel Budget'!I35+'LW Budget'!I35 -> 8257.3 | J35: =IFERROR(I35/I$20,0) -> 0.18695865 | K35: ='Vessel Budget'!K35+'LW Budget'!K35 -> 10503.25 | L35: =IFERROR(K35/K$20,0) -> 0.16396175 | M35: ='Vessel Budget'!M35+'LW Budget'!M35 -> 10054.06 | N35: =IFERROR(M35/M$20,0) -> 0.16734284 | O35: ='Vessel Budget'!O35+'LW Budget'!O35 -> 10054.06 | P35: =IFERROR(O35/O$20,0) -> 0.16734284 | Q35: ='Vessel Budget'!Q35+'LW Budget'!Q35 -> 10054.06 | R35: =IFERROR(Q35/Q$20,0) -> 0.16734284 | S35: ='Vessel Budget'!S35+'LW Budget'!S35 -> 10054.06 | T35: =IFERROR(S35/S$20,0) -> 0.16734284 | U35: ='Vessel Budget'!U35+'LW Budget'!U35 -> 10054.06 | V35: =IFERROR(U35/U$20,0) -> 0.16734284 | W35: ='Vessel Budget'!W35+'LW Budget'!W35 -> 10054.06 | X35: =IFERROR(W35/W$20,0) -> 0.16734284 | Y35: ='Vessel Budget'!Y35+'LW Budget'!Y35 -> 10054.06 | Z35: =IFERROR(Y35/Y$20,0) -> 0.16734284 | AB35: =SUM(C35,E35,G35,I35,K35,M35,O35,Q35,S35,U35,W35,Y35) -> 120648.72 | AC35: =IFERROR(AB35/AB$20,0) -> 0.16734284
A36: Payroll Taxes & Benefits | C36: ='Vessel Budget'!C36+'LW Budget'!C36 -> 2608.6127 | D36: =IFERROR(C36/C$20,0) -> 0.035248903 | E36: ='Vessel Budget'!E36+'LW Budget'!E36 -> 1877.0747 | F36: =IFERROR(E36/E$20,0) -> 0.042500013 | G36: ='Vessel Budget'!G36+'LW Budget'!G36 -> 2608.6127 | H36: =IFERROR(G36/G$20,0) -> 0.035248903 | I36: ='Vessel Budget'!I36+'LW Budget'!I36 -> 1877.0747 | J36: =IFERROR(I36/I$20,0) -> 0.042500013 | K36: ='Vessel Budget'!K36+'LW Budget'!K36 -> 2364.7667 | L36: =IFERROR(K36/K$20,0) -> 0.036915361 | M36: ='Vessel Budget'!M36+'LW Budget'!M36 -> 2267.2283 | N36: =IFERROR(M36/M$20,0) -> 0.037736439 | O36: ='Vessel Budget'!O36+'LW Budget'!O36 -> 2267.2283 | P36: =IFERROR(O36/O$20,0) -> 0.037736439 | Q36: ='Vessel Budget'!Q36+'LW Budget'!Q36 -> 2267.2283 | R36: =IFERROR(Q36/Q$20,0) -> 0.037736439 | S36: ='Vessel Budget'!S36+'LW Budget'!S36 -> 2267.2283 | T36: =IFERROR(S36/S$20,0) -> 0.037736439 | U36: ='Vessel Budget'!U36+'LW Budget'!U36 -> 2267.2283 | V36: =IFERROR(U36/U$20,0) -> 0.037736439 | W36: ='Vessel Budget'!W36+'LW Budget'!W36 -> 2267.2283 | X36: =IFERROR(W36/W$20,0) -> 0.037736439 | Y36: ='Vessel Budget'!Y36+'LW Budget'!Y36 -> 2267.2283 | Z36: =IFERROR(Y36/Y$20,0) -> 0.037736439 | AB36: =SUM(C36,E36,G36,I36,K36,M36,O36,Q36,S36,U36,W36,Y36) -> 27206.739 | AC36: =IFERROR(AB36/AB$20,0) -> 0.037736439
A37: Bonus | C37: ='Vessel Budget'!C37+'LW Budget'!C37 -> 1038.128 | D37: =IFERROR(C37/C$20,0) -> 0.014027714 | E37: ='Vessel Budget'!E37+'LW Budget'!E37 -> 319.424 | F37: =IFERROR(E37/E$20,0) -> 0.007232277 | G37: ='Vessel Budget'!G37+'LW Budget'!G37 -> 1038.128 | H37: =IFERROR(G37/G$20,0) -> 0.014027714 | I37: ='Vessel Budget'!I37+'LW Budget'!I37 -> 319.424 | J37: =IFERROR(I37/I$20,0) -> 0.007232277 | K37: ='Vessel Budget'!K37+'LW Budget'!K37 -> 798.56 | L37: =IFERROR(K37/K$20,0) -> 0.012465979 | M37: ='Vessel Budget'!M37+'LW Budget'!M37 -> 702.7328 | N37: =IFERROR(M37/M$20,0) -> 0.011696499 | O37: ='Vessel Budget'!O37+'LW Budget'!O37 -> 702.7328 | P37: =IFERROR(O37/O$20,0) -> 0.011696499 | Q37: ='Vessel Budget'!Q37+'LW Budget'!Q37 -> 702.7328 | R37: =IFERROR(Q37/Q$20,0) -> 0.011696499 | S37: ='Vessel Budget'!S37+'LW Budget'!S37 -> 702.7328 | T37: =IFERROR(S37/S$20,0) -> 0.011696499 | U37: ='Vessel Budget'!U37+'LW Budget'!U37 -> 702.7328 | V37: =IFERROR(U37/U$20,0) -> 0.011696499 | W37: ='Vessel Budget'!W37+'LW Budget'!W37 -> 702.7328 | X37: =IFERROR(W37/W$20,0) -> 0.011696499 | Y37: ='Vessel Budget'!Y37+'LW Budget'!Y37 -> -3073.6672 | Z37: =IFERROR(Y37/Y$20,0) -> -0.051159055 | AB37: =SUM(C37,E37,G37,I37,K37,M37,O37,Q37,S37,U37,W37,Y37) -> 4656.3936 | AC37: =IFERROR(AB37/AB$20,0) -> 0.0064585363
A38: Total Labor Cost | C38: =SUM(C33:C37) -> 18722.427 | D38: =IFERROR(C38/C$20,0) -> 0.25298697 | E38: =SUM(E33:E37) -> 13550.325 | F38: =IFERROR(E38/E$20,0) -> 0.30680133 | G38: =SUM(G33:G37) -> 18722.427 | H38: =IFERROR(G38/G$20,0) -> 0.25298697 | I38: =SUM(I33:I37) -> 13550.325 | J38: =IFERROR(I38/I$20,0) -> 0.30680133 | K38: =SUM(K33:K37) -> 16998.393 | L38: =IFERROR(K38/K$20,0) -> 0.26535465 | M38: =SUM(M33:M37) -> 16308.78 | N38: =IFERROR(M38/M$20,0) -> 0.27144831 | O38: =SUM(O33:O37) -> 16308.78 | P38: =IFERROR(O38/O$20,0) -> 0.27144831 | Q38: =SUM(Q33:Q37) -> 16308.78 | R38: =IFERROR(Q38/Q$20,0) -> 0.27144831 | S38: =SUM(S33:S37) -> 16308.78 | T38: =IFERROR(S38/S$20,0) -> 0.27144831 | U38: =SUM(U33:U37) -> 16308.78 | V38: =IFERROR(U38/U$20,0) -> 0.27144831 | W38: =SUM(W33:W37) -> 16308.78 | X38: =IFERROR(W38/W$20,0) -> 0.27144831 | Y38: =SUM(Y33:Y37) -> 12532.38 | Z38: =IFERROR(Y38/Y$20,0) -> 0.20859275 | AB38: =SUM(AB33:AB37) -> 191928.96 | AC38: =IFERROR(AB38/AB$20,0) -> 0.26621034
A40: Prime Costs | C40: =C29+C38 -> 44860.325 | D40: =IFERROR(C40/C$20,0) -> 0.60617556 | E40: =E29+E38 -> 28073.453 | F40: =IFERROR(E40/E$20,0) -> 0.63562847 | G40: =G29+G38 -> 44860.325 | H40: =IFERROR(G40/G$20,0) -> 0.60617556 | I40: =I29+I38 -> 28073.453 | J40: =IFERROR(I40/I$20,0) -> 0.63562847 | K40: =K29+K38 -> 39264.701 | L40: =IFERROR(K40/K$20,0) -> 0.61294446 | M40: =M29+M38 -> 37026.451 | N40: =IFERROR(M40/M$20,0) -> 0.61627955 | O40: =O29+O38 -> 37026.451 | P40: =IFERROR(O40/O$20,0) -> 0.61627955 | Q40: =Q29+Q38 -> 37026.451 | R40: =IFERROR(Q40/Q$20,0) -> 0.61627955 | S40: =S29+S38 -> 37026.451 | T40: =IFERROR(S40/S$20,0) -> 0.61627955 | U40: =U29+U38 -> 37026.451 | V40: =IFERROR(U40/U$20,0) -> 0.61627955 | W40: =W29+W38 -> 37026.451 | X40: =IFERROR(W40/W$20,0) -> 0.61627955 | Y40: =Y29+Y38 -> 33250.051 | Z40: =IFERROR(Y40/Y$20,0) -> 0.553424 | AB40: =AB29+AB38 -> 440541.02 | AC40: =IFERROR(AB40/AB$20,0) -> 0.61104159
A41: Operating Profit | C41: =C30-C38 -> 29145.175 | D41: =IFERROR(C41/C$20,0) -> 0.39382444 | E41: =E30-E38 -> 16092.997 | F41: =IFERROR(E41/E$20,0) -> 0.36437153 | G41: =G30-G38 -> 29145.175 | H41: =IFERROR(G41/G$20,0) -> 0.39382444 | I41: =I30-I38 -> 16092.997 | J41: =IFERROR(I41/I$20,0) -> 0.36437153 | K41: =K30-K38 -> 24794.449 | L41: =IFERROR(K41/K$20,0) -> 0.38705554 | M41: =M30-M38 -> 23054.158 | N41: =IFERROR(M41/M$20,0) -> 0.38372045 | O41: =O30-O38 -> 23054.158 | P41: =IFERROR(O41/O$20,0) -> 0.38372045 | Q41: =Q30-Q38 -> 23054.158 | R41: =IFERROR(Q41/Q$20,0) -> 0.38372045 | S41: =S30-S38 -> 23054.158 | T41: =IFERROR(S41/S$20,0) -> 0.38372045 | U41: =U30-U38 -> 23054.158 | V41: =IFERROR(U41/U$20,0) -> 0.38372045 | W41: =W30-W38 -> 23054.158 | X41: =IFERROR(W41/W$20,0) -> 0.38372045 | Y41: =Y30-Y38 -> 26830.558 | Z41: =IFERROR(Y41/Y$20,0) -> 0.446576 | AB41: =AB30-AB38 -> 280426.3 | AC41: =IFERROR(AB41/AB$20,0) -> 0.38895841
A43: Controllable Expenses
A44: Operating Expenses | C44: ='Vessel Budget'!C44+'LW Budget'!C44 -> 9192.7562 | D44: =IFERROR(C44/C$20,0) -> 0.1242172 | E44: ='Vessel Budget'!E44+'LW Budget'!E44 -> 5502.9812 | F44: =IFERROR(E44/E$20,0) -> 0.12459641 | G44: ='Vessel Budget'!G44+'LW Budget'!G44 -> 9192.7562 | H44: =IFERROR(G44/G$20,0) -> 0.1242172 | I44: ='Vessel Budget'!I44+'LW Budget'!I44 -> 5502.9812 | J44: =IFERROR(I44/I$20,0) -> 0.12459641 | K44: ='Vessel Budget'!K44+'LW Budget'!K44 -> 7962.8312 | L44: =IFERROR(K44/K$20,0) -> 0.12430435 | M44: ='Vessel Budget'!M44+'LW Budget'!M44 -> 7470.8612 | N44: =IFERROR(M44/M$20,0) -> 0.12434729 | O44: ='Vessel Budget'!O44+'LW Budget'!O44 -> 7470.8612 | P44: =IFERROR(O44/O$20,0) -> 0.12434729 | Q44: ='Vessel Budget'!Q44+'LW Budget'!Q44 -> 7470.8612 | R44: =IFERROR(Q44/Q$20,0) -> 0.12434729 | S44: ='Vessel Budget'!S44+'LW Budget'!S44 -> 7470.8612 | T44: =IFERROR(S44/S$20,0) -> 0.12434729 | U44: ='Vessel Budget'!U44+'LW Budget'!U44 -> 7470.8612 | V44: =IFERROR(U44/U$20,0) -> 0.12434729 | W44: ='Vessel Budget'!W44+'LW Budget'!W44 -> 7470.8612 | X44: =IFERROR(W44/W$20,0) -> 0.12434729 | Y44: ='Vessel Budget'!Y44+'LW Budget'!Y44 -> 7470.8612 | Z44: =IFERROR(Y44/Y$20,0) -> 0.12434729 | AB44: =SUM(C44,E44,G44,I44,K44,M44,O44,Q44,S44,U44,W44,Y44) -> 89650.335 | AC44: =IFERROR(AB44/AB$20,0) -> 0.12434729
A45: Music & Entertainment | C45: ='Vessel Budget'!C45+'LW Budget'!C45 -> 0 | D45: =IFERROR(C45/C$20,0) -> 0 | E45: ='Vessel Budget'!E45+'LW Budget'!E45 -> 0 | F45: =IFERROR(E45/E$20,0) -> 0 | G45: ='Vessel Budget'!G45+'LW Budget'!G45 -> 0 | H45: =IFERROR(G45/G$20,0) -> 0 | I45: ='Vessel Budget'!I45+'LW Budget'!I45 -> 0 | J45: =IFERROR(I45/I$20,0) -> 0 | K45: ='Vessel Budget'!K45+'LW Budget'!K45 -> 0 | L45: =IFERROR(K45/K$20,0) -> 0 | M45: ='Vessel Budget'!M45+'LW Budget'!M45 -> 0 | N45: =IFERROR(M45/M$20,0) -> 0 | O45: ='Vessel Budget'!O45+'LW Budget'!O45 -> 0 | P45: =IFERROR(O45/O$20,0) -> 0 | Q45: ='Vessel Budget'!Q45+'LW Budget'!Q45 -> 0 | R45: =IFERROR(Q45/Q$20,0) -> 0 | S45: ='Vessel Budget'!S45+'LW Budget'!S45 -> 0 | T45: =IFERROR(S45/S$20,0) -> 0 | U45: ='Vessel Budget'!U45+'LW Budget'!U45 -> 0 | V45: =IFERROR(U45/U$20,0) -> 0 | W45: ='Vessel Budget'!W45+'LW Budget'!W45 -> 0 | X45: =IFERROR(W45/W$20,0) -> 0 | Y45: ='Vessel Budget'!Y45+'LW Budget'!Y45 -> 0 | Z45: =IFERROR(Y45/Y$20,0) -> 0 | AB45: =SUM(C45,E45,G45,I45,K45,M45,O45,Q45,S45,U45,W45,Y45) -> 0 | AC45: =IFERROR(AB45/AB$20,0) -> 0
A46: Marketing & Advertising | C46: ='Vessel Budget'!C46+'LW Budget'!C46 -> 1081.6627 | D46: =IFERROR(C46/C$20,0) -> 0.014615978 | E46: ='Vessel Budget'!E46+'LW Budget'!E46 -> 1081.6627 | F46: =IFERROR(E46/E$20,0) -> 0.024490597 | G46: ='Vessel Budget'!G46+'LW Budget'!G46 -> 1081.6627 | H46: =IFERROR(G46/G$20,0) -> 0.014615978 | I46: ='Vessel Budget'!I46+'LW Budget'!I46 -> 1081.6627 | J46: =IFERROR(I46/I$20,0) -> 0.024490597 | K46: ='Vessel Budget'!K46+'LW Budget'!K46 -> 1081.6627 | L46: =IFERROR(K46/K$20,0) -> 0.016885375 | M46: ='Vessel Budget'!M46+'LW Budget'!M46 -> 1081.6627 | N46: =IFERROR(M46/M$20,0) -> 0.018003525 | O46: ='Vessel Budget'!O46+'LW Budget'!O46 -> 1081.6627 | P46: =IFERROR(O46/O$20,0) -> 0.018003525 | Q46: ='Vessel Budget'!Q46+'LW Budget'!Q46 -> 1081.6627 | R46: =IFERROR(Q46/Q$20,0) -> 0.018003525 | S46: ='Vessel Budget'!S46+'LW Budget'!S46 -> 1081.6627 | T46: =IFERROR(S46/S$20,0) -> 0.018003525 | U46: ='Vessel Budget'!U46+'LW Budget'!U46 -> 1081.6627 | V46: =IFERROR(U46/U$20,0) -> 0.018003525 | W46: ='Vessel Budget'!W46+'LW Budget'!W46 -> 1081.6627 | X46: =IFERROR(W46/W$20,0) -> 0.018003525 | Y46: ='Vessel Budget'!Y46+'LW Budget'!Y46 -> 1081.6627 | Z46: =IFERROR(Y46/Y$20,0) -> 0.018003525 | AB46: =SUM(C46,E46,G46,I46,K46,M46,O46,Q46,S46,U46,W46,Y46) -> 12979.953 | AC46: =IFERROR(AB46/AB$20,0) -> 0.018003525
A47: General & Administrative - Controllable | C47: ='Vessel Budget'!C47+'LW Budget'!C47 -> 2626.8952 | D47: =IFERROR(C47/C$20,0) -> 0.035495946 | E47: ='Vessel Budget'!E47+'LW Budget'!E47 -> 2626.8952 | F47: =IFERROR(E47/E$20,0) -> 0.059477165 | G47: ='Vessel Budget'!G47+'LW Budget'!G47 -> 2626.8952 | H47: =IFERROR(G47/G$20,0) -> 0.035495946 | I47: ='Vessel Budget'!I47+'LW Budget'!I47 -> 2626.8952 | J47: =IFERROR(I47/I$20,0) -> 0.059477165 | K47: ='Vessel Budget'!K47+'LW Budget'!K47 -> 2626.8952 | L47: =IFERROR(K47/K$20,0) -> 0.041007338 | M47: ='Vessel Budget'!M47+'LW Budget'!M47 -> 2626.8952 | N47: =IFERROR(M47/M$20,0) -> 0.043722846 | O47: ='Vessel Budget'!O47+'LW Budget'!O47 -> 2626.8952 | P47: =IFERROR(O47/O$20,0) -> 0.043722846 | Q47: ='Vessel Budget'!Q47+'LW Budget'!Q47 -> 2626.8952 | R47: =IFERROR(Q47/Q$20,0) -> 0.043722846 | S47: ='Vessel Budget'!S47+'LW Budget'!S47 -> 2626.8952 | T47: =IFERROR(S47/S$20,0) -> 0.043722846 | U47: ='Vessel Budget'!U47+'LW Budget'!U47 -> 2626.8952 | V47: =IFERROR(U47/U$20,0) -> 0.043722846 | W47: ='Vessel Budget'!W47+'LW Budget'!W47 -> 2626.8952 | X47: =IFERROR(W47/W$20,0) -> 0.043722846 | Y47: ='Vessel Budget'!Y47+'LW Budget'!Y47 -> 2626.8952 | Z47: =IFERROR(Y47/Y$20,0) -> 0.043722846 | AB47: =SUM(C47,E47,G47,I47,K47,M47,O47,Q47,S47,U47,W47,Y47) -> 31522.743 | AC47: =IFERROR(AB47/AB$20,0) -> 0.043722846
A48: Repairs & Maintenance | C48: ='Vessel Budget'!C48+'LW Budget'!C48 -> 73 | D48: =IFERROR(C48/C$20,0) -> 0.00098641318 | E48: ='Vessel Budget'!E48+'LW Budget'!E48 -> 73 | F48: =IFERROR(E48/E$20,0) -> 0.0016528383 | G48: ='Vessel Budget'!G48+'LW Budget'!G48 -> 73 | H48: =IFERROR(G48/G$20,0) -> 0.00098641318 | I48: ='Vessel Budget'!I48+'LW Budget'!I48 -> 73 | J48: =IFERROR(I48/I$20,0) -> 0.0016528383 | K48: ='Vessel Budget'!K48+'LW Budget'!K48 -> 73 | L48: =IFERROR(K48/K$20,0) -> 0.0011395718 | M48: ='Vessel Budget'!M48+'LW Budget'!M48 -> 73 | N48: =IFERROR(M48/M$20,0) -> 0.0012150343 | O48: ='Vessel Budget'!O48+'LW Budget'!O48 -> 73 | P48: =IFERROR(O48/O$20,0) -> 0.0012150343 | Q48: ='Vessel Budget'!Q48+'LW Budget'!Q48 -> 73 | R48: =IFERROR(Q48/Q$20,0) -> 0.0012150343 | S48: ='Vessel Budget'!S48+'LW Budget'!S48 -> 73 | T48: =IFERROR(S48/S$20,0) -> 0.0012150343 | U48: ='Vessel Budget'!U48+'LW Budget'!U48 -> 73 | V48: =IFERROR(U48/U$20,0) -> 0.0012150343 | W48: ='Vessel Budget'!W48+'LW Budget'!W48 -> 73 | X48: =IFERROR(W48/W$20,0) -> 0.0012150343 | Y48: ='Vessel Budget'!Y48+'LW Budget'!Y48 -> 73 | Z48: =IFERROR(Y48/Y$20,0) -> 0.0012150343 | AB48: =SUM(C48,E48,G48,I48,K48,M48,O48,Q48,S48,U48,W48,Y48) -> 876 | AC48: =IFERROR(AB48/AB$20,0) -> 0.0012150343
A49: Credit Card Fees | C49: ='Vessel Budget'!C49+'LW Budget'!C49 -> 0 | D49: =IFERROR(C49/C$20,0) -> 0 | E49: ='Vessel Budget'!E49+'LW Budget'!E49 -> 0 | F49: =IFERROR(E49/E$20,0) -> 0 | G49: ='Vessel Budget'!G49+'LW Budget'!G49 -> 0 | H49: =IFERROR(G49/G$20,0) -> 0 | I49: ='Vessel Budget'!I49+'LW Budget'!I49 -> 0 | J49: =IFERROR(I49/I$20,0) -> 0 | K49: ='Vessel Budget'!K49+'LW Budget'!K49 -> 0 | L49: =IFERROR(K49/K$20,0) -> 0 | M49: ='Vessel Budget'!M49+'LW Budget'!M49 -> 0 | N49: =IFERROR(M49/M$20,0) -> 0 | O49: ='Vessel Budget'!O49+'LW Budget'!O49 -> 0 | P49: =IFERROR(O49/O$20,0) -> 0 | Q49: ='Vessel Budget'!Q49+'LW Budget'!Q49 -> 0 | R49: =IFERROR(Q49/Q$20,0) -> 0 | S49: ='Vessel Budget'!S49+'LW Budget'!S49 -> 0 | T49: =IFERROR(S49/S$20,0) -> 0 | U49: ='Vessel Budget'!U49+'LW Budget'!U49 -> 0 | V49: =IFERROR(U49/U$20,0) -> 0 | W49: ='Vessel Budget'!W49+'LW Budget'!W49 -> 0 | X49: =IFERROR(W49/W$20,0) -> 0 | Y49: ='Vessel Budget'!Y49+'LW Budget'!Y49 -> 0 | Z49: =IFERROR(Y49/Y$20,0) -> 0 | AB49: =SUM(C49,E49,G49,I49,K49,M49,O49,Q49,S49,U49,W49,Y49) -> 0 | AC49: =IFERROR(AB49/AB$20,0) -> 0
A50: Total Controllable Expenses | C50: =SUM(C44:C49) -> 12974.314 | D50: =IFERROR(C50/C$20,0) -> 0.17531554 | E50: =SUM(E44:E49) -> 9284.5392 | F50: =IFERROR(E50/E$20,0) -> 0.21021701 | G50: =SUM(G44:G49) -> 12974.314 | H50: =IFERROR(G50/G$20,0) -> 0.17531554 | I50: =SUM(I44:I49) -> 9284.5392 | J50: =IFERROR(I50/I$20,0) -> 0.21021701 | K50: =SUM(K44:K49) -> 11744.389 | L50: =IFERROR(K50/K$20,0) -> 0.18333664 | M50: =SUM(M44:M49) -> 11252.419 | N50: =IFERROR(M50/M$20,0) -> 0.1872887 | O50: =SUM(O44:O49) -> 11252.419 | P50: =IFERROR(O50/O$20,0) -> 0.1872887 | Q50: =SUM(Q44:Q49) -> 11252.419 | R50: =IFERROR(Q50/Q$20,0) -> 0.1872887 | S50: =SUM(S44:S49) -> 11252.419 | T50: =IFERROR(S50/S$20,0) -> 0.1872887 | U50: =SUM(U44:U49) -> 11252.419 | V50: =IFERROR(U50/U$20,0) -> 0.1872887 | W50: =SUM(W44:W49) -> 11252.419 | X50: =IFERROR(W50/W$20,0) -> 0.1872887 | Y50: =SUM(Y44:Y49) -> 11252.419 | Z50: =IFERROR(Y50/Y$20,0) -> 0.1872887 | AB50: =SUM(AB44:AB49) -> 135029.03 | AC50: =IFERROR(AB50/AB$20,0) -> 0.1872887
A52: Uncontrollable Expenses
A53: Utilities | C53: ='Vessel Budget'!C53+'LW Budget'!C53 -> 249 | D53: =IFERROR(C53/C$20,0) -> 0.0033646148 | E53: ='Vessel Budget'!E53+'LW Budget'!E53 -> 249 | F53: =IFERROR(E53/E$20,0) -> 0.0056377635 | G53: ='Vessel Budget'!G53+'LW Budget'!G53 -> 249 | H53: =IFERROR(G53/G$20,0) -> 0.0033646148 | I53: ='Vessel Budget'!I53+'LW Budget'!I53 -> 249 | J53: =IFERROR(I53/I$20,0) -> 0.0056377635 | K53: ='Vessel Budget'!K53+'LW Budget'!K53 -> 249 | L53: =IFERROR(K53/K$20,0) -> 0.0038870325 | M53: ='Vessel Budget'!M53+'LW Budget'!M53 -> 249 | N53: =IFERROR(M53/M$20,0) -> 0.004144432 | O53: ='Vessel Budget'!O53+'LW Budget'!O53 -> 249 | P53: =IFERROR(O53/O$20,0) -> 0.004144432 | Q53: ='Vessel Budget'!Q53+'LW Budget'!Q53 -> 249 | R53: =IFERROR(Q53/Q$20,0) -> 0.004144432 | S53: ='Vessel Budget'!S53+'LW Budget'!S53 -> 249 | T53: =IFERROR(S53/S$20,0) -> 0.004144432 | U53: ='Vessel Budget'!U53+'LW Budget'!U53 -> 249 | V53: =IFERROR(U53/U$20,0) -> 0.004144432 | W53: ='Vessel Budget'!W53+'LW Budget'!W53 -> 249 | X53: =IFERROR(W53/W$20,0) -> 0.004144432 | Y53: ='Vessel Budget'!Y53+'LW Budget'!Y53 -> 249 | Z53: =IFERROR(Y53/Y$20,0) -> 0.004144432 | AB53: =SUM(C53,E53,G53,I53,K53,M53,O53,Q53,S53,U53,W53,Y53) -> 2988 | AC53: =IFERROR(AB53/AB$20,0) -> 0.004144432
A54: Occupancy Cost | C54: ='Vessel Budget'!C54+'LW Budget'!C54 -> 0 | D54: =IFERROR(C54/C$20,0) -> 0 | E54: ='Vessel Budget'!E54+'LW Budget'!E54 -> 0 | F54: =IFERROR(E54/E$20,0) -> 0 | G54: ='Vessel Budget'!G54+'LW Budget'!G54 -> 0 | H54: =IFERROR(G54/G$20,0) -> 0 | I54: ='Vessel Budget'!I54+'LW Budget'!I54 -> 0 | J54: =IFERROR(I54/I$20,0) -> 0 | K54: ='Vessel Budget'!K54+'LW Budget'!K54 -> 0 | L54: =IFERROR(K54/K$20,0) -> 0 | M54: ='Vessel Budget'!M54+'LW Budget'!M54 -> 0 | N54: =IFERROR(M54/M$20,0) -> 0 | O54: ='Vessel Budget'!O54+'LW Budget'!O54 -> 0 | P54: =IFERROR(O54/O$20,0) -> 0 | Q54: ='Vessel Budget'!Q54+'LW Budget'!Q54 -> 0 | R54: =IFERROR(Q54/Q$20,0) -> 0 | S54: ='Vessel Budget'!S54+'LW Budget'!S54 -> 0 | T54: =IFERROR(S54/S$20,0) -> 0 | U54: ='Vessel Budget'!U54+'LW Budget'!U54 -> 0 | V54: =IFERROR(U54/U$20,0) -> 0 | W54: ='Vessel Budget'!W54+'LW Budget'!W54 -> 0 | X54: =IFERROR(W54/W$20,0) -> 0 | Y54: ='Vessel Budget'!Y54+'LW Budget'!Y54 -> 0 | Z54: =IFERROR(Y54/Y$20,0) -> 0 | AB54: =SUM(C54,E54,G54,I54,K54,M54,O54,Q54,S54,U54,W54,Y54) -> 0 | AC54: =IFERROR(AB54/AB$20,0) -> 0
A55: General & Administrative - Uncon | C55: ='Vessel Budget'!C55+'LW Budget'!C55 -> 2465.9132 | D55: =IFERROR(C55/C$20,0) -> 0.033320675 | E55: ='Vessel Budget'!E55+'LW Budget'!E55 -> 1721.5412 | F55: =IFERROR(E55/E$20,0) -> 0.038978484 | G55: ='Vessel Budget'!G55+'LW Budget'!G55 -> 2465.9132 | H55: =IFERROR(G55/G$20,0) -> 0.033320675 | I55: ='Vessel Budget'!I55+'LW Budget'!I55 -> 1721.5412 | J55: =IFERROR(I55/I$20,0) -> 0.038978484 | K55: ='Vessel Budget'!K55+'LW Budget'!K55 -> 2217.7892 | L55: =IFERROR(K55/K$20,0) -> 0.03462096 | M55: ='Vessel Budget'!M55+'LW Budget'!M55 -> 2118.5396 | N55: =IFERROR(M55/M$20,0) -> 0.03526162 | O55: ='Vessel Budget'!O55+'LW Budget'!O55 -> 2118.5396 | P55: =IFERROR(O55/O$20,0) -> 0.03526162 | Q55: ='Vessel Budget'!Q55+'LW Budget'!Q55 -> 2118.5396 | R55: =IFERROR(Q55/Q$20,0) -> 0.03526162 | S55: ='Vessel Budget'!S55+'LW Budget'!S55 -> 2118.5396 | T55: =IFERROR(S55/S$20,0) -> 0.03526162 | U55: ='Vessel Budget'!U55+'LW Budget'!U55 -> 2118.5396 | V55: =IFERROR(U55/U$20,0) -> 0.03526162 | W55: ='Vessel Budget'!W55+'LW Budget'!W55 -> 2118.5396 | X55: =IFERROR(W55/W$20,0) -> 0.03526162 | Y55: ='Vessel Budget'!Y55+'LW Budget'!Y55 -> 2118.5396 | Z55: =IFERROR(Y55/Y$20,0) -> 0.03526162 | AB55: =SUM(C55,E55,G55,I55,K55,M55,O55,Q55,S55,U55,W55,Y55) -> 25422.476 | AC55: =IFERROR(AB55/AB$20,0) -> 0.03526162
A56: Management Fee | C56: ='Vessel Budget'!C56+'LW Budget'!C56 -> 2960.22 | D56: =IFERROR(C56/C$20,0) -> 0.04 | E56: ='Vessel Budget'!E56+'LW Budget'!E56 -> 1766.658 | F56: =IFERROR(E56/E$20,0) -> 0.04 | G56: ='Vessel Budget'!G56+'LW Budget'!G56 -> 2960.22 | H56: =IFERROR(G56/G$20,0) -> 0.04 | I56: ='Vessel Budget'!I56+'LW Budget'!I56 -> 1766.658 | J56: =IFERROR(I56/I$20,0) -> 0.04 | K56: ='Vessel Budget'!K56+'LW Budget'!K56 -> 2562.366 | L56: =IFERROR(K56/K$20,0) -> 0.04 | M56: ='Vessel Budget'!M56+'LW Budget'!M56 -> 2403.2244 | N56: =IFERROR(M56/M$20,0) -> 0.04 | O56: ='Vessel Budget'!O56+'LW Budget'!O56 -> 2403.2244 | P56: =IFERROR(O56/O$20,0) -> 0.04 | Q56: ='Vessel Budget'!Q56+'LW Budget'!Q56 -> 2403.2244 | R56: =IFERROR(Q56/Q$20,0) -> 0.04 | S56: ='Vessel Budget'!S56+'LW Budget'!S56 -> 2403.2244 | T56: =IFERROR(S56/S$20,0) -> 0.04 | U56: ='Vessel Budget'!U56+'LW Budget'!U56 -> 2403.2244 | V56: =IFERROR(U56/U$20,0) -> 0.04 | W56: ='Vessel Budget'!W56+'LW Budget'!W56 -> 2403.2244 | X56: =IFERROR(W56/W$20,0) -> 0.04 | Y56: ='Vessel Budget'!Y56+'LW Budget'!Y56 -> 2403.2244 | Z56: =IFERROR(Y56/Y$20,0) -> 0.04 | AB56: =SUM(C56,E56,G56,I56,K56,M56,O56,Q56,S56,U56,W56,Y56) -> 28838.693 | AC56: =IFERROR(AB56/AB$20,0) -> 0.04
A57: Admin Fee (5% of F&B) | C57: ='Vessel Budget'!C57+'LW Budget'!C57 -> 0 | D57: =IFERROR(C57/C$20,0) -> 0 | E57: ='Vessel Budget'!E57+'LW Budget'!E57 -> 0 | F57: =IFERROR(E57/E$20,0) -> 0 | G57: ='Vessel Budget'!G57+'LW Budget'!G57 -> 0 | H57: =IFERROR(G57/G$20,0) -> 0 | I57: ='Vessel Budget'!I57+'LW Budget'!I57 -> 0 | J57: =IFERROR(I57/I$20,0) -> 0 | K57: ='Vessel Budget'!K57+'LW Budget'!K57 -> 0 | L57: =IFERROR(K57/K$20,0) -> 0 | M57: ='Vessel Budget'!M57+'LW Budget'!M57 -> 0 | N57: =IFERROR(M57/M$20,0) -> 0 | O57: ='Vessel Budget'!O57+'LW Budget'!O57 -> 0 | P57: =IFERROR(O57/O$20,0) -> 0 | Q57: ='Vessel Budget'!Q57+'LW Budget'!Q57 -> 0 | R57: =IFERROR(Q57/Q$20,0) -> 0 | S57: ='Vessel Budget'!S57+'LW Budget'!S57 -> 0 | T57: =IFERROR(S57/S$20,0) -> 0 | U57: ='Vessel Budget'!U57+'LW Budget'!U57 -> 0 | V57: =IFERROR(U57/U$20,0) -> 0 | W57: ='Vessel Budget'!W57+'LW Budget'!W57 -> 0 | X57: =IFERROR(W57/W$20,0) -> 0 | Y57: ='Vessel Budget'!Y57+'LW Budget'!Y57 -> 0 | Z57: =IFERROR(Y57/Y$20,0) -> 0 | AB57: =SUM(C57,E57,G57,I57,K57,M57,O57,Q57,S57,U57,W57,Y57) -> 0 | AC57: =IFERROR(AB57/AB$20,0) -> 0
A58: Owner Fee | C58: ='Vessel Budget'!C58+'LW Budget'!C58 -> 0 | D58: =IFERROR(C58/C$20,0) -> 0 | E58: ='Vessel Budget'!E58+'LW Budget'!E58 -> 0 | F58: =IFERROR(E58/E$20,0) -> 0 | G58: ='Vessel Budget'!G58+'LW Budget'!G58 -> 0 | H58: =IFERROR(G58/G$20,0) -> 0 | I58: ='Vessel Budget'!I58+'LW Budget'!I58 -> 0 | J58: =IFERROR(I58/I$20,0) -> 0 | K58: ='Vessel Budget'!K58+'LW Budget'!K58 -> 0 | L58: =IFERROR(K58/K$20,0) -> 0 | M58: ='Vessel Budget'!M58+'LW Budget'!M58 -> 0 | N58: =IFERROR(M58/M$20,0) -> 0 | O58: ='Vessel Budget'!O58+'LW Budget'!O58 -> 0 | P58: =IFERROR(O58/O$20,0) -> 0 | Q58: ='Vessel Budget'!Q58+'LW Budget'!Q58 -> 0 | R58: =IFERROR(Q58/Q$20,0) -> 0 | S58: ='Vessel Budget'!S58+'LW Budget'!S58 -> 0 | T58: =IFERROR(S58/S$20,0) -> 0 | U58: ='Vessel Budget'!U58+'LW Budget'!U58 -> 0 | V58: =IFERROR(U58/U$20,0) -> 0 | W58: ='Vessel Budget'!W58+'LW Budget'!W58 -> 0 | X58: =IFERROR(W58/W$20,0) -> 0 | Y58: ='Vessel Budget'!Y58+'LW Budget'!Y58 -> 0 | Z58: =IFERROR(Y58/Y$20,0) -> 0 | AB58: =SUM(C58,E58,G58,I58,K58,M58,O58,Q58,S58,U58,W58,Y58) -> 0 | AC58: =IFERROR(AB58/AB$20,0) -> 0
A59: Business Taxes | C59: ='Vessel Budget'!C59+'LW Budget'!C59 -> 0 | D59: =IFERROR(C59/C$20,0) -> 0 | E59: ='Vessel Budget'!E59+'LW Budget'!E59 -> 0 | F59: =IFERROR(E59/E$20,0) -> 0 | G59: ='Vessel Budget'!G59+'LW Budget'!G59 -> 0 | H59: =IFERROR(G59/G$20,0) -> 0 | I59: ='Vessel Budget'!I59+'LW Budget'!I59 -> 0 | J59: =IFERROR(I59/I$20,0) -> 0 | K59: ='Vessel Budget'!K59+'LW Budget'!K59 -> 0 | L59: =IFERROR(K59/K$20,0) -> 0 | M59: ='Vessel Budget'!M59+'LW Budget'!M59 -> 0 | N59: =IFERROR(M59/M$20,0) -> 0 | O59: ='Vessel Budget'!O59+'LW Budget'!O59 -> 0 | P59: =IFERROR(O59/O$20,0) -> 0 | Q59: ='Vessel Budget'!Q59+'LW Budget'!Q59 -> 0 | R59: =IFERROR(Q59/Q$20,0) -> 0 | S59: ='Vessel Budget'!S59+'LW Budget'!S59 -> 0 | T59: =IFERROR(S59/S$20,0) -> 0 | U59: ='Vessel Budget'!U59+'LW Budget'!U59 -> 0 | V59: =IFERROR(U59/U$20,0) -> 0 | W59: ='Vessel Budget'!W59+'LW Budget'!W59 -> 0 | X59: =IFERROR(W59/W$20,0) -> 0 | Y59: ='Vessel Budget'!Y59+'LW Budget'!Y59 -> 0 | Z59: =IFERROR(Y59/Y$20,0) -> 0 | AB59: =SUM(C59,E59,G59,I59,K59,M59,O59,Q59,S59,U59,W59,Y59) -> 0 | AC59: =IFERROR(AB59/AB$20,0) -> 0
A60: Total Uncontrollable Expenses | C60: =SUM(C53:C59) -> 5675.1332 | D60: =IFERROR(C60/C$20,0) -> 0.07668529 | E60: =SUM(E53:E59) -> 3737.1992 | F60: =IFERROR(E60/E$20,0) -> 0.084616247 | G60: =SUM(G53:G59) -> 5675.1332 | H60: =IFERROR(G60/G$20,0) -> 0.07668529 | I60: =SUM(I53:I59) -> 3737.1992 | J60: =IFERROR(I60/I$20,0) -> 0.084616247 | K60: =SUM(K53:K59) -> 5029.1552 | L60: =IFERROR(K60/K$20,0) -> 0.078507992 | M60: =SUM(M53:M59) -> 4770.764 | N60: =IFERROR(M60/M$20,0) -> 0.079406052 | O60: =SUM(O53:O59) -> 4770.764 | P60: =IFERROR(O60/O$20,0) -> 0.079406052 | Q60: =SUM(Q53:Q59) -> 4770.764 | R60: =IFERROR(Q60/Q$20,0) -> 0.079406052 | S60: =SUM(S53:S59) -> 4770.764 | T60: =IFERROR(S60/S$20,0) -> 0.079406052 | U60: =SUM(U53:U59) -> 4770.764 | V60: =IFERROR(U60/U$20,0) -> 0.079406052 | W60: =SUM(W53:W59) -> 4770.764 | X60: =IFERROR(W60/W$20,0) -> 0.079406052 | Y60: =SUM(Y53:Y59) -> 4770.764 | Z60: =IFERROR(Y60/Y$20,0) -> 0.079406052 | AB60: =SUM(AB53:AB59) -> 57249.168 | AC60: =IFERROR(AB60/AB$20,0) -> 0.079406052
A62: Net Operating Profit Before Debt Service | C62: =C41-C50-C60 -> 10495.727 | D62: =IFERROR(C62/C$20,0) -> 0.14182361 | E62: =E41-E50-E60 -> 3071.2583 | F62: =IFERROR(E62/E$20,0) -> 0.069538265 | G62: =G41-G50-G60 -> 10495.727 | H62: =IFERROR(G62/G$20,0) -> 0.14182361 | I62: =I41-I50-I60 -> 3071.2583 | J62: =IFERROR(I62/I$20,0) -> 0.069538265 | K62: =K41-K50-K60 -> 8020.9043 | L62: =IFERROR(K62/K$20,0) -> 0.12521091 | M62: =M41-M50-M60 -> 7030.9751 | N62: =IFERROR(M62/M$20,0) -> 0.11702569 | O62: =O41-O50-O60 -> 7030.9751 | P62: =IFERROR(O62/O$20,0) -> 0.11702569 | Q62: =Q41-Q50-Q60 -> 7030.9751 | R62: =IFERROR(Q62/Q$20,0) -> 0.11702569 | S62: =S41-S50-S60 -> 7030.9751 | T62: =IFERROR(S62/S$20,0) -> 0.11702569 | U62: =U41-U50-U60 -> 7030.9751 | V62: =IFERROR(U62/U$20,0) -> 0.11702569 | W62: =W41-W50-W60 -> 7030.9751 | X62: =IFERROR(W62/W$20,0) -> 0.11702569 | Y62: =Y41-Y50-Y60 -> 10807.375 | Z62: =IFERROR(Y62/Y$20,0) -> 0.17988125 | AB62: =AB41-AB50-AB60 -> 88148.101 | AC62: =IFERROR(AB62/AB$20,0) -> 0.12226366
A64: Debt Service | C64: ='Vessel Budget'!C64+'LW Budget'!C64 -> 0 | D64: =IFERROR(C64/C$20,0) -> 0 | E64: ='Vessel Budget'!E64+'LW Budget'!E64 -> 0 | F64: =IFERROR(E64/E$20,0) -> 0 | G64: ='Vessel Budget'!G64+'LW Budget'!G64 -> 0 | H64: =IFERROR(G64/G$20,0) -> 0 | I64: ='Vessel Budget'!I64+'LW Budget'!I64 -> 0 | J64: =IFERROR(I64/I$20,0) -> 0 | K64: ='Vessel Budget'!K64+'LW Budget'!K64 -> 0 | L64: =IFERROR(K64/K$20,0) -> 0 | M64: ='Vessel Budget'!M64+'LW Budget'!M64 -> 0 | N64: =IFERROR(M64/M$20,0) -> 0 | O64: ='Vessel Budget'!O64+'LW Budget'!O64 -> 0 | P64: =IFERROR(O64/O$20,0) -> 0 | Q64: ='Vessel Budget'!Q64+'LW Budget'!Q64 -> 0 | R64: =IFERROR(Q64/Q$20,0) -> 0 | S64: ='Vessel Budget'!S64+'LW Budget'!S64 -> 0 | T64: =IFERROR(S64/S$20,0) -> 0 | U64: ='Vessel Budget'!U64+'LW Budget'!U64 -> 0 | V64: =IFERROR(U64/U$20,0) -> 0 | W64: ='Vessel Budget'!W64+'LW Budget'!W64 -> 0 | X64: =IFERROR(W64/W$20,0) -> 0 | Y64: ='Vessel Budget'!Y64+'LW Budget'!Y64 -> 0 | Z64: =IFERROR(Y64/Y$20,0) -> 0 | AB64: =SUM(C64,E64,G64,I64,K64,M64,O64,Q64,S64,U64,W64,Y64) -> 0 | AC64: =IFERROR(AB64/AB$20,0) -> 0
A66: Net Operating Profit After Debt Service | C66: =C62-C64 -> 10495.727 | D66: =IFERROR(C66/C$20,0) -> 0.14182361 | E66: =E62-E64 -> 3071.2583 | F66: =IFERROR(E66/E$20,0) -> 0.069538265 | G66: =G62-G64 -> 10495.727 | H66: =IFERROR(G66/G$20,0) -> 0.14182361 | I66: =I62-I64 -> 3071.2583 | J66: =IFERROR(I66/I$20,0) -> 0.069538265 | K66: =K62-K64 -> 8020.9043 | L66: =IFERROR(K66/K$20,0) -> 0.12521091 | M66: =M62-M64 -> 7030.9751 | N66: =IFERROR(M66/M$20,0) -> 0.11702569 | O66: =O62-O64 -> 7030.9751 | P66: =IFERROR(O66/O$20,0) -> 0.11702569 | Q66: =Q62-Q64 -> 7030.9751 | R66: =IFERROR(Q66/Q$20,0) -> 0.11702569 | S66: =S62-S64 -> 7030.9751 | T66: =IFERROR(S66/S$20,0) -> 0.11702569 | U66: =U62-U64 -> 7030.9751 | V66: =IFERROR(U66/U$20,0) -> 0.11702569 | W66: =W62-W64 -> 7030.9751 | X66: =IFERROR(W66/W$20,0) -> 0.11702569 | Y66: =Y62-Y64 -> 10807.375 | Z66: =IFERROR(Y66/Y$20,0) -> 0.17988125 | AB66: =AB62-AB64 -> 88148.101 | AC66: =IFERROR(AB66/AB$20,0) -> 0.12226366
A68: Other (Income) Expense | C68: ='Vessel Budget'!C68+'LW Budget'!C68 -> 0 | D68: =IFERROR(C68/C$20,0) -> 0 | E68: ='Vessel Budget'!E68+'LW Budget'!E68 -> 0 | F68: =IFERROR(E68/E$20,0) -> 0 | G68: ='Vessel Budget'!G68+'LW Budget'!G68 -> 0 | H68: =IFERROR(G68/G$20,0) -> 0 | I68: ='Vessel Budget'!I68+'LW Budget'!I68 -> 0 | J68: =IFERROR(I68/I$20,0) -> 0 | K68: ='Vessel Budget'!K68+'LW Budget'!K68 -> 0 | L68: =IFERROR(K68/K$20,0) -> 0 | M68: ='Vessel Budget'!M68+'LW Budget'!M68 -> 0 | N68: =IFERROR(M68/M$20,0) -> 0 | O68: ='Vessel Budget'!O68+'LW Budget'!O68 -> 0 | P68: =IFERROR(O68/O$20,0) -> 0 | Q68: ='Vessel Budget'!Q68+'LW Budget'!Q68 -> 0 | R68: =IFERROR(Q68/Q$20,0) -> 0 | S68: ='Vessel Budget'!S68+'LW Budget'!S68 -> 0 | T68: =IFERROR(S68/S$20,0) -> 0 | U68: ='Vessel Budget'!U68+'LW Budget'!U68 -> 0 | V68: =IFERROR(U68/U$20,0) -> 0 | W68: ='Vessel Budget'!W68+'LW Budget'!W68 -> 0 | X68: =IFERROR(W68/W$20,0) -> 0 | Y68: ='Vessel Budget'!Y68+'LW Budget'!Y68 -> 0 | Z68: =IFERROR(Y68/Y$20,0) -> 0 | AB68: =SUM(C68,E68,G68,I68,K68,M68,O68,Q68,S68,U68,W68,Y68) -> 0 | AC68: =IFERROR(AB68/AB$20,0) -> 0
A69: Reserve / CapEx | C69: ='Vessel Budget'!C69+'LW Budget'!C69 -> 249 | D69: =IFERROR(C69/C$20,0) -> 0.0033646148 | E69: ='Vessel Budget'!E69+'LW Budget'!E69 -> 249 | F69: =IFERROR(E69/E$20,0) -> 0.0056377635 | G69: ='Vessel Budget'!G69+'LW Budget'!G69 -> 249 | H69: =IFERROR(G69/G$20,0) -> 0.0033646148 | I69: ='Vessel Budget'!I69+'LW Budget'!I69 -> 249 | J69: =IFERROR(I69/I$20,0) -> 0.0056377635 | K69: ='Vessel Budget'!K69+'LW Budget'!K69 -> 249 | L69: =IFERROR(K69/K$20,0) -> 0.0038870325 | M69: ='Vessel Budget'!M69+'LW Budget'!M69 -> 249 | N69: =IFERROR(M69/M$20,0) -> 0.004144432 | O69: ='Vessel Budget'!O69+'LW Budget'!O69 -> 249 | P69: =IFERROR(O69/O$20,0) -> 0.004144432 | Q69: ='Vessel Budget'!Q69+'LW Budget'!Q69 -> 249 | R69: =IFERROR(Q69/Q$20,0) -> 0.004144432 | S69: ='Vessel Budget'!S69+'LW Budget'!S69 -> 249 | T69: =IFERROR(S69/S$20,0) -> 0.004144432 | U69: ='Vessel Budget'!U69+'LW Budget'!U69 -> 249 | V69: =IFERROR(U69/U$20,0) -> 0.004144432 | W69: ='Vessel Budget'!W69+'LW Budget'!W69 -> 249 | X69: =IFERROR(W69/W$20,0) -> 0.004144432 | Y69: ='Vessel Budget'!Y69+'LW Budget'!Y69 -> 249 | Z69: =IFERROR(Y69/Y$20,0) -> 0.004144432 | AB69: =SUM(C69,E69,G69,I69,K69,M69,O69,Q69,S69,U69,W69,Y69) -> 2988 | AC69: =IFERROR(AB69/AB$20,0) -> 0.004144432
A70: Net Cash Flow | C70: =C66-C68-C69 -> 10246.727 | D70: =IFERROR(C70/C$20,0) -> 0.138459 | E70: =E66-E68-E69 -> 2822.2583 | F70: =IFERROR(E70/E$20,0) -> 0.063900502 | G70: =G66-G68-G69 -> 10246.727 | H70: =IFERROR(G70/G$20,0) -> 0.138459 | I70: =I66-I68-I69 -> 2822.2583 | J70: =IFERROR(I70/I$20,0) -> 0.063900502 | K70: =K66-K68-K69 -> 7771.9043 | L70: =IFERROR(K70/K$20,0) -> 0.12132388 | M70: =M66-M68-M69 -> 6781.9751 | N70: =IFERROR(M70/M$20,0) -> 0.11288126 | O70: =O66-O68-O69 -> 6781.9751 | P70: =IFERROR(O70/O$20,0) -> 0.11288126 | Q70: =Q66-Q68-Q69 -> 6781.9751 | R70: =IFERROR(Q70/Q$20,0) -> 0.11288126 | S70: =S66-S68-S69 -> 6781.9751 | T70: =IFERROR(S70/S$20,0) -> 0.11288126 | U70: =U66-U68-U69 -> 6781.9751 | V70: =IFERROR(U70/U$20,0) -> 0.11288126 | W70: =W66-W68-W69 -> 6781.9751 | X70: =IFERROR(W70/W$20,0) -> 0.11288126 | Y70: =Y66-Y68-Y69 -> 10558.375 | Z70: =IFERROR(Y70/Y$20,0) -> 0.17573682 | AB70: =AB66-AB68-AB69 -> 85160.101 | AC70: =IFERROR(AB70/AB$20,0) -> 0.11811923

Sheet Vessel Summary
B2: VESSEL EVENTS — 2027 OPERATING SUMMARY
B3: ="$"&TEXT('Vessel Assumptions'!$C$6,"#,##0")&" F&B min · "&TEXT('Vessel Assumptions'!$C$7,"0%")&" volume · "&TEXT('Vessel Assumptions'!$C$30,"0%")&" mgmt fee" -> $3,720 F&B min · 71% volume · 4% mgmt fee
B5: ANNUAL P&L | C5: $ | D5: % rev | F5: KEY METRICS
B6: Total revenue | C6: ='Vessel Budget'!$AB$20 -> 350111.52 | D6: =C6/C6 -> 1 | F6: Net operating margin | G6: ='Vessel Budget'!$AB$62/'Vessel Budget'!$AB$20 -> 0.2488172
B7: Total COGS | C7: ='Vessel Budget'!$AB$29 -> 136279.97 | D7: =C7/C6 -> 0.38924731 | F7: Prime cost % | G7: ='Vessel Budget'!$AB$40/'Vessel Budget'!$AB$20 -> 0.56258065
B8: Gross profit | C8: ='Vessel Budget'!$AB$30 -> 213831.55 | D8: =C8/C6 -> 0.61075269 | F8: COGS % | G8: ='Vessel Budget'!$AB$29/'Vessel Budget'!$AB$20 -> 0.38924731
B9: Total labor (incl. mgmt) | C9: ='Vessel Budget'!$AB$38 -> 60685.997 | D9: =C9/C6 -> 0.17333333 | F9: Total events / year | G9: ='Vessel Budget'!$AB$9 -> 75.2928
B10: Prime cost | C10: ='Vessel Budget'!$AB$40 -> 196965.96 | D10: =C10/C6 -> 0.56258065 | F10: Avg F&B / event | G10: =SUM('Vessel Budget'!$AB$12:$AB$16)/'Vessel Budget'!$AB$9 -> 3720
B11: Controllable (excl CC) | C11: ='Vessel Budget'!$AB$50-'Vessel Budget'!$AB$49 -> 43293.36 | D11: =C11/C6 -> 0.12365591 | F11: Revenue / event | G11: ='Vessel Budget'!$AB$20/'Vessel Budget'!$AB$9 -> 4650
B12: Credit card fees (2.5%) | C12: ='Vessel Budget'!$AB$49 -> 0 | D12: =C12/C6 -> 0
B13: Non-controllable | C13: ='Vessel Budget'!$AB$60-'Vessel Budget'!$AB$54-'Vessel Budget'!$AB$56-'Vessel Budget'!$AB$57 -> 8733.9648 | D13: =C13/C6 -> 0.024946237
B14: Management fee (4% of revenue) | C14: ='Vessel Budget'!$AB$56 -> 14004.461 | D14: =C14/C6 -> 0.04
B15: Admin fee income (5% of F&B, billed to clients) | C15: =SUM('Vessel Budget'!$AB$12:$AB$16)*'Vessel Assumptions'!$C$32 -> 14004.461 | D15: =C15/C6 -> 0.04
B16: Rent / occupancy (none) | C16: ='Vessel Budget'!$AB$54 -> 0 | D16: =C16/C6 -> 0
B17: NET OPERATING PROFIT | C17: ='Vessel Budget'!$AB$62 -> 87113.77 | D17: =C17/C6 -> 0.2488172
B20: Adjust inputs on the Vessel Assumptions tab — every figure recalculates. Management fee = 4% of revenue; no separate rent.

Sheet Vessel Assumptions
B2: VESSEL · EVENT OPERATING MODEL
B3: Model drivers — adjust any input and the 2027 budget recalculates
B5: REVENUE DRIVERS
B6: F&B minimum per event | C6: 3720 | D6: per-event F&B realized (card: food $2,880 + bev $840; $4,000 contract minimum)
B7: Event volume (% of run-rate) | C7: 0.713 | D7: scaled to ~$350K 2027 revenue — fewer, better events (~75/yr vs 105 run-rate)
B8: Food share of F&B | C8: =2880/3720 -> 0.77419355 | D8: food share per the 2027 unit-economics card
B9: Service charge (% of F&B) | C9: 0.2 | D9: revenue, not billed labor
B11: COST OF SALES (% of that category's sales)
B12: Food cost % (of food sales) | C12: =1600/2880 -> 0.55555556 | D12: food cost per card: $1,600 on $2,880 (55.6%)
B13: Beverage cost % (of bev sales) | C13: 0.25 | D13: =TEXT(1-$C$13,"0%")&" margin" -> 75% margin
B15: LABOR
B16: Bartenders per event | C16: 1
B17: Servers per event | C17: 2
B18: Hourly rate | C18: 35
B19: Shift hours | C19: 5
B20: Hourly labor per event (calc) | C20: =(C16+C17)*C18*C19 -> 525
B21: Management labor / month | C21: ='Vessel GL Basis'!D8 -> 1435.8333 | D21: linked ← Vessel GL Basis
B22: Payroll taxes & benefits % | C22: =114/692 -> 0.16473988 | D22: PT&B per card: $114 on $692 of wages (hourly+manager+bonus)
B24: OVERHEAD & VARIABLE
B25: Controllable exp / month (excl CC) | C25: ='Vessel GL Basis'!D18 -> 6718.6667 | D25: linked ← Vessel GL Basis
B26: Non-controllable / month | C26: ='Vessel GL Basis'!D24 -> 1045.4167 | D26: linked ← Vessel GL Basis
B27: Credit card fee (% of revenue) | C27: 0.025 | D27: variable — own line
B29: OWNER CHARGES (above NOI) & ADMIN FEE INCOME
B30: Management fee (% of revenue) — EXPENSE | C30: 0.04 | D30: 4% of gross revenue → Method (replaces profit split)
B31: Rent (% of revenue) — EXPENSE (waived) | C31: 0 | D31: Vessel carries no separate rent (owner)
B32: Admin fee (% of F&B) — INCOME, billed to clients | C32: 0.05 | D32: 5% added to event client invoices → Vessel Other Operating Income (NOT an expense); 4% mgmt fee applies to it as revenue
B34: Operating expenses (% of revenue — modified/plan) | C34: 0.03 | D34: target ratio, replaces GL run-rate in modified months & 2027
B35: G&A controllable (% of revenue — modified/plan) | C35: 0.04 | D35: target ratio (GL runs ~11%) — the accounting/bank cleanup
B36: Manager labor $/event | C36: 55 | D36: 2027 unit-economics card
B37: Bonus $/event | C37: 112 | D37: 2027 unit-economics card
B38: Controllable expenses (% of revenue — 2027 card) | C38: =575/4650 -> 0.12365591 | D38: $575/event incl CC fees
B39: Uncontrollable (% of revenue — 2027 card) | C39: =116/4650 -> 0.024946237 | D39: $116/event

Sheet Vessel Budget
A1: Vessel
A2: Profit & Loss Budget
A3: 2027
C5: January | E5: February | G5: March | I5: April | K5: May | M5: June | O5: July | Q5: August | S5: September | U5: October | W5: November | Y5: December | AB5: 2027
C6: Budget | E6: Budget | G6: Budget | I6: Budget | K6: Budget | M6: Budget | O6: Budget | Q6: Budget | S6: Budget | U6: Budget | W6: Budget | Y6: Budget | AB6: FY 2027
C7: Amount $ | D7: % | E7: Amount $ | F7: % | G7: Amount $ | H7: % | I7: Amount $ | J7: % | K7: Amount $ | L7: % | M7: Amount $ | N7: % | O7: Amount $ | P7: % | Q7: Amount $ | R7: % | S7: Amount $ | T7: % | U7: Amount $ | V7: % | W7: Amount $ | X7: % | Y7: Amount $ | Z7: % | AB7: Amount $ | AC7: %
A8: Events (2026 run-rate) | C8: 13 | E8: 4 | G8: 13 | I8: 4 | K8: 10 | M8: =AVERAGE($C$8,$E$8,$G$8,$I$8,$K$8) -> 8.8 | O8: =AVERAGE($C$8,$E$8,$G$8,$I$8,$K$8) -> 8.8 | Q8: =AVERAGE($C$8,$E$8,$G$8,$I$8,$K$8) -> 8.8 | S8: =AVERAGE($C$8,$E$8,$G$8,$I$8,$K$8) -> 8.8 | U8: =AVERAGE($C$8,$E$8,$G$8,$I$8,$K$8) -> 8.8 | W8: =AVERAGE($C$8,$E$8,$G$8,$I$8,$K$8) -> 8.8 | Y8: =AVERAGE($C$8,$E$8,$G$8,$I$8,$K$8) -> 8.8 | AB8: =SUM(C8,E8,G8,I8,K8,M8,O8,Q8,S8,U8,W8,Y8) -> 105.6
A9: Events (budgeted · monthly average) | C9: =C8*'Vessel Assumptions'!$C$7 -> 9.269 | E9: =E8*'Vessel Assumptions'!$C$7 -> 2.852 | G9: =G8*'Vessel Assumptions'!$C$7 -> 9.269 | I9: =I8*'Vessel Assumptions'!$C$7 -> 2.852 | K9: =K8*'Vessel Assumptions'!$C$7 -> 7.13 | M9: =M8*'Vessel Assumptions'!$C$7 -> 6.2744 | O9: =O8*'Vessel Assumptions'!$C$7 -> 6.2744 | Q9: =Q8*'Vessel Assumptions'!$C$7 -> 6.2744 | S9: =S8*'Vessel Assumptions'!$C$7 -> 6.2744 | U9: =U8*'Vessel Assumptions'!$C$7 -> 6.2744 | W9: =W8*'Vessel Assumptions'!$C$7 -> 6.2744 | Y9: =Y8*'Vessel Assumptions'!$C$7 -> 6.2744 | AB9: =SUM(C9,E9,G9,I9,K9,M9,O9,Q9,S9,U9,W9,Y9) -> 75.2928
A11: Income
A12: Food Sales | C12: =C9*'Vessel Assumptions'!$C$6*'Vessel Assumptions'!$C$8 -> 26694.72 | D12: =IFERROR(C12/C$20,0) -> 0.61935484 | E12: =E9*'Vessel Assumptions'!$C$6*'Vessel Assumptions'!$C$8 -> 8213.76 | F12: =IFERROR(E12/E$20,0) -> 0.61935484 | G12: =G9*'Vessel Assumptions'!$C$6*'Vessel Assumptions'!$C$8 -> 26694.72 | H12: =IFERROR(G12/G$20,0) -> 0.61935484 | I12: =I9*'Vessel Assumptions'!$C$6*'Vessel Assumptions'!$C$8 -> 8213.76 | J12: =IFERROR(I12/I$20,0) -> 0.61935484 | K12: =K9*'Vessel Assumptions'!$C$6*'Vessel Assumptions'!$C$8 -> 20534.4 | L12: =IFERROR(K12/K$20,0) -> 0.61935484 | M12: =M9*'Vessel Assumptions'!$C$6*'Vessel Assumptions'!$C$8 -> 18070.272 | N12: =IFERROR(M12/M$20,0) -> 0.61935484 | O12: =O9*'Vessel Assumptions'!$C$6*'Vessel Assumptions'!$C$8 -> 18070.272 | P12: =IFERROR(O12/O$20,0) -> 0.61935484 | Q12: =Q9*'Vessel Assumptions'!$C$6*'Vessel Assumptions'!$C$8 -> 18070.272 | R12: =IFERROR(Q12/Q$20,0) -> 0.61935484 | S12: =S9*'Vessel Assumptions'!$C$6*'Vessel Assumptions'!$C$8 -> 18070.272 | T12: =IFERROR(S12/S$20,0) -> 0.61935484 | U12: =U9*'Vessel Assumptions'!$C$6*'Vessel Assumptions'!$C$8 -> 18070.272 | V12: =IFERROR(U12/U$20,0) -> 0.61935484 | W12: =W9*'Vessel Assumptions'!$C$6*'Vessel Assumptions'!$C$8 -> 18070.272 | X12: =IFERROR(W12/W$20,0) -> 0.61935484 | Y12: =Y9*'Vessel Assumptions'!$C$6*'Vessel Assumptions'!$C$8 -> 18070.272 | Z12: =IFERROR(Y12/Y$20,0) -> 0.61935484 | AB12: =SUM(C12,E12,G12,I12,K12,M12,O12,Q12,S12,U12,W12,Y12) -> 216843.26 | AC12: =IFERROR(AB12/AB$20,0) -> 0.61935484
A13: Non-Alcoholic Beverage Sales | C13: =(C9*'Vessel Assumptions'!$C$6*(1-'Vessel Assumptions'!$C$8))*'Vessel 2026 P&L'!$AB$10/SUM('Vessel 2026 P&L'!$AB$10:$AB$13) -> 2612.8934 | D13: =IFERROR(C13/C$20,0) -> 0.060622781 | E13: =(E9*'Vessel Assumptions'!$C$6*(1-'Vessel Assumptions'!$C$8))*'Vessel 2026 P&L'!$AB$10/SUM('Vessel 2026 P&L'!$AB$10:$AB$13) -> 803.9672 | F13: =IFERROR(E13/E$20,0) -> 0.060622781 | G13: =(G9*'Vessel Assumptions'!$C$6*(1-'Vessel Assumptions'!$C$8))*'Vessel 2026 P&L'!$AB$10/SUM('Vessel 2026 P&L'!$AB$10:$AB$13) -> 2612.8934 | H13: =IFERROR(G13/G$20,0) -> 0.060622781 | I13: =(I9*'Vessel Assumptions'!$C$6*(1-'Vessel Assumptions'!$C$8))*'Vessel 2026 P&L'!$AB$10/SUM('Vessel 2026 P&L'!$AB$10:$AB$13) -> 803.9672 | J13: =IFERROR(I13/I$20,0) -> 0.060622781 | K13: =(K9*'Vessel Assumptions'!$C$6*(1-'Vessel Assumptions'!$C$8))*'Vessel 2026 P&L'!$AB$10/SUM('Vessel 2026 P&L'!$AB$10:$AB$13) -> 2009.918 | L13: =IFERROR(K13/K$20,0) -> 0.060622781 | M13: =(M9*'Vessel Assumptions'!$C$6*(1-'Vessel Assumptions'!$C$8))*'Vessel 2026 P&L'!$AB$10/SUM('Vessel 2026 P&L'!$AB$10:$AB$13) -> 1768.7278 | N13: =IFERROR(M13/M$20,0) -> 0.060622781 | O13: =(O9*'Vessel Assumptions'!$C$6*(1-'Vessel Assumptions'!$C$8))*'Vessel 2026 P&L'!$AB$10/SUM('Vessel 2026 P&L'!$AB$10:$AB$13) -> 1768.7278 | P13: =IFERROR(O13/O$20,0) -> 0.060622781 | Q13: =(Q9*'Vessel Assumptions'!$C$6*(1-'Vessel Assumptions'!$C$8))*'Vessel 2026 P&L'!$AB$10/SUM('Vessel 2026 P&L'!$AB$10:$AB$13) -> 1768.7278 | R13: =IFERROR(Q13/Q$20,0) -> 0.060622781 | S13: =(S9*'Vessel Assumptions'!$C$6*(1-'Vessel Assumptions'!$C$8))*'Vessel 2026 P&L'!$AB$10/SUM('Vessel 2026 P&L'!$AB$10:$AB$13) -> 1768.7278 | T13: =IFERROR(S13/S$20,0) -> 0.060622781 | U13: =(U9*'Vessel Assumptions'!$C$6*(1-'Vessel Assumptions'!$C$8))*'Vessel 2026 P&L'!$AB$10/SUM('Vessel 2026 P&L'!$AB$10:$AB$13) -> 1768.7278 | V13: =IFERROR(U13/U$20,0) -> 0.060622781 | W13: =(W9*'Vessel Assumptions'!$C$6*(1-'Vessel Assumptions'!$C$8))*'Vessel 2026 P&L'!$AB$10/SUM('Vessel 2026 P&L'!$AB$10:$AB$13) -> 1768.7278 | X13: =IFERROR(W13/W$20,0) -> 0.060622781 | Y13: =(Y9*'Vessel Assumptions'!$C$6*(1-'Vessel Assumptions'!$C$8))*'Vessel 2026 P&L'!$AB$10/SUM('Vessel 2026 P&L'!$AB$10:$AB$13) -> 1768.7278 | Z13: =IFERROR(Y13/Y$20,0) -> 0.060622781 | AB13: =SUM(C13,E13,G13,I13,K13,M13,O13,Q13,S13,U13,W13,Y13) -> 21224.734 | AC13: =IFERROR(AB13/AB$20,0) -> 0.060622781
A14: Liquor Sales | C14: =(C9*'Vessel Assumptions'!$C$6*(1-'Vessel Assumptions'!$C$8))*'Vessel 2026 P&L'!$AB$11/SUM('Vessel 2026 P&L'!$AB$10:$AB$13) -> 4394.574 | D14: =IFERROR(C14/C$20,0) -> 0.10196026 | E14: =(E9*'Vessel Assumptions'!$C$6*(1-'Vessel Assumptions'!$C$8))*'Vessel 2026 P&L'!$AB$11/SUM('Vessel 2026 P&L'!$AB$10:$AB$13) -> 1352.1766 | F14: =IFERROR(E14/E$20,0) -> 0.10196026 | G14: =(G9*'Vessel Assumptions'!$C$6*(1-'Vessel Assumptions'!$C$8))*'Vessel 2026 P&L'!$AB$11/SUM('Vessel 2026 P&L'!$AB$10:$AB$13) -> 4394.574 | H14: =IFERROR(G14/G$20,0) -> 0.10196026 | I14: =(I9*'Vessel Assumptions'!$C$6*(1-'Vessel Assumptions'!$C$8))*'Vessel 2026 P&L'!$AB$11/SUM('Vessel 2026 P&L'!$AB$10:$AB$13) -> 1352.1766 | J14: =IFERROR(I14/I$20,0) -> 0.10196026 | K14: =(K9*'Vessel Assumptions'!$C$6*(1-'Vessel Assumptions'!$C$8))*'Vessel 2026 P&L'!$AB$11/SUM('Vessel 2026 P&L'!$AB$10:$AB$13) -> 3380.4415 | L14: =IFERROR(K14/K$20,0) -> 0.10196026 | M14: =(M9*'Vessel Assumptions'!$C$6*(1-'Vessel Assumptions'!$C$8))*'Vessel 2026 P&L'!$AB$11/SUM('Vessel 2026 P&L'!$AB$10:$AB$13) -> 2974.7885 | N14: =IFERROR(M14/M$20,0) -> 0.10196026 | O14: =(O9*'Vessel Assumptions'!$C$6*(1-'Vessel Assumptions'!$C$8))*'Vessel 2026 P&L'!$AB$11/SUM('Vessel 2026 P&L'!$AB$10:$AB$13) -> 2974.7885 | P14: =IFERROR(O14/O$20,0) -> 0.10196026 | Q14: =(Q9*'Vessel Assumptions'!$C$6*(1-'Vessel Assumptions'!$C$8))*'Vessel 2026 P&L'!$AB$11/SUM('Vessel 2026 P&L'!$AB$10:$AB$13) -> 2974.7885 | R14: =IFERROR(Q14/Q$20,0) -> 0.10196026 | S14: =(S9*'Vessel Assumptions'!$C$6*(1-'Vessel Assumptions'!$C$8))*'Vessel 2026 P&L'!$AB$11/SUM('Vessel 2026 P&L'!$AB$10:$AB$13) -> 2974.7885 | T14: =IFERROR(S14/S$20,0) -> 0.10196026 | U14: =(U9*'Vessel Assumptions'!$C$6*(1-'Vessel Assumptions'!$C$8))*'Vessel 2026 P&L'!$AB$11/SUM('Vessel 2026 P&L'!$AB$10:$AB$13) -> 2974.7885 | V14: =IFERROR(U14/U$20,0) -> 0.10196026 | W14: =(W9*'Vessel Assumptions'!$C$6*(1-'Vessel Assumptions'!$C$8))*'Vessel 2026 P&L'!$AB$11/SUM('Vessel 2026 P&L'!$AB$10:$AB$13) -> 2974.7885 | X14: =IFERROR(W14/W$20,0) -> 0.10196026 | Y14: =(Y9*'Vessel Assumptions'!$C$6*(1-'Vessel Assumptions'!$C$8))*'Vessel 2026 P&L'!$AB$11/SUM('Vessel 2026 P&L'!$AB$10:$AB$13) -> 2974.7885 | Z14: =IFERROR(Y14/Y$20,0) -> 0.10196026 | AB14: =SUM(C14,E14,G14,I14,K14,M14,O14,Q14,S14,U14,W14,Y14) -> 35697.462 | AC14: =IFERROR(AB14/AB$20,0) -> 0.10196026
A15: Beer Sales | C15: =(C9*'Vessel Assumptions'!$C$6*(1-'Vessel Assumptions'!$C$8))*'Vessel 2026 P&L'!$AB$12/SUM('Vessel 2026 P&L'!$AB$10:$AB$13) -> 162.01368 | D15: =IFERROR(C15/C$20,0) -> 0.0037589439 | E15: =(E9*'Vessel Assumptions'!$C$6*(1-'Vessel Assumptions'!$C$8))*'Vessel 2026 P&L'!$AB$12/SUM('Vessel 2026 P&L'!$AB$10:$AB$13) -> 49.850362 | F15: =IFERROR(E15/E$20,0) -> 0.0037589439 | G15: =(G9*'Vessel Assumptions'!$C$6*(1-'Vessel Assumptions'!$C$8))*'Vessel 2026 P&L'!$AB$12/SUM('Vessel 2026 P&L'!$AB$10:$AB$13) -> 162.01368 | H15: =IFERROR(G15/G$20,0) -> 0.0037589439 | I15: =(I9*'Vessel Assumptions'!$C$6*(1-'Vessel Assumptions'!$C$8))*'Vessel 2026 P&L'!$AB$12/SUM('Vessel 2026 P&L'!$AB$10:$AB$13) -> 49.850362 | J15: =IFERROR(I15/I$20,0) -> 0.0037589439 | K15: =(K9*'Vessel Assumptions'!$C$6*(1-'Vessel Assumptions'!$C$8))*'Vessel 2026 P&L'!$AB$12/SUM('Vessel 2026 P&L'!$AB$10:$AB$13) -> 124.6259 | L15: =IFERROR(K15/K$20,0) -> 0.0037589439 | M15: =(M9*'Vessel Assumptions'!$C$6*(1-'Vessel Assumptions'!$C$8))*'Vessel 2026 P&L'!$AB$12/SUM('Vessel 2026 P&L'!$AB$10:$AB$13) -> 109.6708 | N15: =IFERROR(M15/M$20,0) -> 0.0037589439 | O15: =(O9*'Vessel Assumptions'!$C$6*(1-'Vessel Assumptions'!$C$8))*'Vessel 2026 P&L'!$AB$12/SUM('Vessel 2026 P&L'!$AB$10:$AB$13) -> 109.6708 | P15: =IFERROR(O15/O$20,0) -> 0.0037589439 | Q15: =(Q9*'Vessel Assumptions'!$C$6*(1-'Vessel Assumptions'!$C$8))*'Vessel 2026 P&L'!$AB$12/SUM('Vessel 2026 P&L'!$AB$10:$AB$13) -> 109.6708 | R15: =IFERROR(Q15/Q$20,0) -> 0.0037589439 | S15: =(S9*'Vessel Assumptions'!$C$6*(1-'Vessel Assumptions'!$C$8))*'Vessel 2026 P&L'!$AB$12/SUM('Vessel 2026 P&L'!$AB$10:$AB$13) -> 109.6708 | T15: =IFERROR(S15/S$20,0) -> 0.0037589439 | U15: =(U9*'Vessel Assumptions'!$C$6*(1-'Vessel Assumptions'!$C$8))*'Vessel 2026 P&L'!$AB$12/SUM('Vessel 2026 P&L'!$AB$10:$AB$13) -> 109.6708 | V15: =IFERROR(U15/U$20,0) -> 0.0037589439 | W15: =(W9*'Vessel Assumptions'!$C$6*(1-'Vessel Assumptions'!$C$8))*'Vessel 2026 P&L'!$AB$12/SUM('Vessel 2026 P&L'!$AB$10:$AB$13) -> 109.6708 | X15: =IFERROR(W15/W$20,0) -> 0.0037589439 | Y15: =(Y9*'Vessel Assumptions'!$C$6*(1-'Vessel Assumptions'!$C$8))*'Vessel 2026 P&L'!$AB$12/SUM('Vessel 2026 P&L'!$AB$10:$AB$13) -> 109.6708 | Z15: =IFERROR(Y15/Y$20,0) -> 0.0037589439 | AB15: =SUM(C15,E15,G15,I15,K15,M15,O15,Q15,S15,U15,W15,Y15) -> 1316.0495 | AC15: =IFERROR(AB15/AB$20,0) -> 0.0037589439
A16: Wine Sales | C16: =(C9*'Vessel Assumptions'!$C$6*(1-'Vessel Assumptions'!$C$8))*'Vessel 2026 P&L'!$AB$13/SUM('Vessel 2026 P&L'!$AB$10:$AB$13) -> 616.47895 | D16: =IFERROR(C16/C$20,0) -> 0.014303174 | E16: =(E9*'Vessel Assumptions'!$C$6*(1-'Vessel Assumptions'!$C$8))*'Vessel 2026 P&L'!$AB$13/SUM('Vessel 2026 P&L'!$AB$10:$AB$13) -> 189.68583 | F16: =IFERROR(E16/E$20,0) -> 0.014303174 | G16: =(G9*'Vessel Assumptions'!$C$6*(1-'Vessel Assumptions'!$C$8))*'Vessel 2026 P&L'!$AB$13/SUM('Vessel 2026 P&L'!$AB$10:$AB$13) -> 616.47895 | H16: =IFERROR(G16/G$20,0) -> 0.014303174 | I16: =(I9*'Vessel Assumptions'!$C$6*(1-'Vessel Assumptions'!$C$8))*'Vessel 2026 P&L'!$AB$13/SUM('Vessel 2026 P&L'!$AB$10:$AB$13) -> 189.68583 | J16: =IFERROR(I16/I$20,0) -> 0.014303174 | K16: =(K9*'Vessel Assumptions'!$C$6*(1-'Vessel Assumptions'!$C$8))*'Vessel 2026 P&L'!$AB$13/SUM('Vessel 2026 P&L'!$AB$10:$AB$13) -> 474.21458 | L16: =IFERROR(K16/K$20,0) -> 0.014303174 | M16: =(M9*'Vessel Assumptions'!$C$6*(1-'Vessel Assumptions'!$C$8))*'Vessel 2026 P&L'!$AB$13/SUM('Vessel 2026 P&L'!$AB$10:$AB$13) -> 417.30883 | N16: =IFERROR(M16/M$20,0) -> 0.014303174 | O16: =(O9*'Vessel Assumptions'!$C$6*(1-'Vessel Assumptions'!$C$8))*'Vessel 2026 P&L'!$AB$13/SUM('Vessel 2026 P&L'!$AB$10:$AB$13) -> 417.30883 | P16: =IFERROR(O16/O$20,0) -> 0.014303174 | Q16: =(Q9*'Vessel Assumptions'!$C$6*(1-'Vessel Assumptions'!$C$8))*'Vessel 2026 P&L'!$AB$13/SUM('Vessel 2026 P&L'!$AB$10:$AB$13) -> 417.30883 | R16: =IFERROR(Q16/Q$20,0) -> 0.014303174 | S16: =(S9*'Vessel Assumptions'!$C$6*(1-'Vessel Assumptions'!$C$8))*'Vessel 2026 P&L'!$AB$13/SUM('Vessel 2026 P&L'!$AB$10:$AB$13) -> 417.30883 | T16: =IFERROR(S16/S$20,0) -> 0.014303174 | U16: =(U9*'Vessel Assumptions'!$C$6*(1-'Vessel Assumptions'!$C$8))*'Vessel 2026 P&L'!$AB$13/SUM('Vessel 2026 P&L'!$AB$10:$AB$13) -> 417.30883 | V16: =IFERROR(U16/U$20,0) -> 0.014303174 | W16: =(W9*'Vessel Assumptions'!$C$6*(1-'Vessel Assumptions'!$C$8))*'Vessel 2026 P&L'!$AB$13/SUM('Vessel 2026 P&L'!$AB$10:$AB$13) -> 417.30883 | X16: =IFERROR(W16/W$20,0) -> 0.014303174 | Y16: =(Y9*'Vessel Assumptions'!$C$6*(1-'Vessel Assumptions'!$C$8))*'Vessel 2026 P&L'!$AB$13/SUM('Vessel 2026 P&L'!$AB$10:$AB$13) -> 417.30883 | Z16: =IFERROR(Y16/Y$20,0) -> 0.014303174 | AB16: =SUM(C16,E16,G16,I16,K16,M16,O16,Q16,S16,U16,W16,Y16) -> 5007.7059 | AC16: =IFERROR(AB16/AB$20,0) -> 0.014303174
A17: Retail / Merch Sales | C17: 0 | D17: =IFERROR(C17/C$20,0) -> 0 | E17: 0 | F17: =IFERROR(E17/E$20,0) -> 0 | G17: 0 | H17: =IFERROR(G17/G$20,0) -> 0 | I17: 0 | J17: =IFERROR(I17/I$20,0) -> 0 | K17: 0 | L17: =IFERROR(K17/K$20,0) -> 0 | M17: 0 | N17: =IFERROR(M17/M$20,0) -> 0 | O17: 0 | P17: =IFERROR(O17/O$20,0) -> 0 | Q17: 0 | R17: =IFERROR(Q17/Q$20,0) -> 0 | S17: 0 | T17: =IFERROR(S17/S$20,0) -> 0 | U17: 0 | V17: =IFERROR(U17/U$20,0) -> 0 | W17: 0 | X17: =IFERROR(W17/W$20,0) -> 0 | Y17: 0 | Z17: =IFERROR(Y17/Y$20,0) -> 0 | AB17: =SUM(C17,E17,G17,I17,K17,M17,O17,Q17,S17,U17,W17,Y17) -> 0 | AC17: =IFERROR(AB17/AB$20,0) -> 0
A18: Other Operating Income (svc charge + 5% admin fee) | C18: =C9*'Vessel Assumptions'!$C$6*'Vessel Assumptions'!$C$9+SUM(C12:C16)*'Vessel Assumptions'!$C$32 -> 8620.17 | D18: =IFERROR(C18/C$20,0) -> 0.2 | E18: =E9*'Vessel Assumptions'!$C$6*'Vessel Assumptions'!$C$9+SUM(E12:E16)*'Vessel Assumptions'!$C$32 -> 2652.36 | F18: =IFERROR(E18/E$20,0) -> 0.2 | G18: =G9*'Vessel Assumptions'!$C$6*'Vessel Assumptions'!$C$9+SUM(G12:G16)*'Vessel Assumptions'!$C$32 -> 8620.17 | H18: =IFERROR(G18/G$20,0) -> 0.2 | I18: =I9*'Vessel Assumptions'!$C$6*'Vessel Assumptions'!$C$9+SUM(I12:I16)*'Vessel Assumptions'!$C$32 -> 2652.36 | J18: =IFERROR(I18/I$20,0) -> 0.2 | K18: =K9*'Vessel Assumptions'!$C$6*'Vessel Assumptions'!$C$9+SUM(K12:K16)*'Vessel Assumptions'!$C$32 -> 6630.9 | L18: =IFERROR(K18/K$20,0) -> 0.2 | M18: =M9*'Vessel Assumptions'!$C$6*'Vessel Assumptions'!$C$9+SUM(M12:M16)*'Vessel Assumptions'!$C$32 -> 5835.192 | N18: =IFERROR(M18/M$20,0) -> 0.2 | O18: =O9*'Vessel Assumptions'!$C$6*'Vessel Assumptions'!$C$9+SUM(O12:O16)*'Vessel Assumptions'!$C$32 -> 5835.192 | P18: =IFERROR(O18/O$20,0) -> 0.2 | Q18: =Q9*'Vessel Assumptions'!$C$6*'Vessel Assumptions'!$C$9+SUM(Q12:Q16)*'Vessel Assumptions'!$C$32 -> 5835.192 | R18: =IFERROR(Q18/Q$20,0) -> 0.2 | S18: =S9*'Vessel Assumptions'!$C$6*'Vessel Assumptions'!$C$9+SUM(S12:S16)*'Vessel Assumptions'!$C$32 -> 5835.192 | T18: =IFERROR(S18/S$20,0) -> 0.2 | U18: =U9*'Vessel Assumptions'!$C$6*'Vessel Assumptions'!$C$9+SUM(U12:U16)*'Vessel Assumptions'!$C$32 -> 5835.192 | V18: =IFERROR(U18/U$20,0) -> 0.2 | W18: =W9*'Vessel Assumptions'!$C$6*'Vessel Assumptions'!$C$9+SUM(W12:W16)*'Vessel Assumptions'!$C$32 -> 5835.192 | X18: =IFERROR(W18/W$20,0) -> 0.2 | Y18: =Y9*'Vessel Assumptions'!$C$6*'Vessel Assumptions'!$C$9+SUM(Y12:Y16)*'Vessel Assumptions'!$C$32 -> 5835.192 | Z18: =IFERROR(Y18/Y$20,0) -> 0.2 | AB18: =SUM(C18,E18,G18,I18,K18,M18,O18,Q18,S18,U18,W18,Y18) -> 70022.304 | AC18: =IFERROR(AB18/AB$20,0) -> 0.2
A19: Discounts & Comps | C19: 0 | D19: =IFERROR(C19/C$20,0) -> 0 | E19: 0 | F19: =IFERROR(E19/E$20,0) -> 0 | G19: 0 | H19: =IFERROR(G19/G$20,0) -> 0 | I19: 0 | J19: =IFERROR(I19/I$20,0) -> 0 | K19: 0 | L19: =IFERROR(K19/K$20,0) -> 0 | M19: 0 | N19: =IFERROR(M19/M$20,0) -> 0 | O19: 0 | P19: =IFERROR(O19/O$20,0) -> 0 | Q19: 0 | R19: =IFERROR(Q19/Q$20,0) -> 0 | S19: 0 | T19: =IFERROR(S19/S$20,0) -> 0 | U19: 0 | V19: =IFERROR(U19/U$20,0) -> 0 | W19: 0 | X19: =IFERROR(W19/W$20,0) -> 0 | Y19: 0 | Z19: =IFERROR(Y19/Y$20,0) -> 0 | AB19: =SUM(C19,E19,G19,I19,K19,M19,O19,Q19,S19,U19,W19,Y19) -> 0 | AC19: =IFERROR(AB19/AB$20,0) -> 0
A20: Total Income | C20: =SUM(C12:C19) -> 43100.85 | D20: =IFERROR(C20/C$20,0) -> 1 | E20: =SUM(E12:E19) -> 13261.8 | F20: =IFERROR(E20/E$20,0) -> 1 | G20: =SUM(G12:G19) -> 43100.85 | H20: =IFERROR(G20/G$20,0) -> 1 | I20: =SUM(I12:I19) -> 13261.8 | J20: =IFERROR(I20/I$20,0) -> 1 | K20: =SUM(K12:K19) -> 33154.5 | L20: =IFERROR(K20/K$20,0) -> 1 | M20: =SUM(M12:M19) -> 29175.96 | N20: =IFERROR(M20/M$20,0) -> 1 | O20: =SUM(O12:O19) -> 29175.96 | P20: =IFERROR(O20/O$20,0) -> 1 | Q20: =SUM(Q12:Q19) -> 29175.96 | R20: =IFERROR(Q20/Q$20,0) -> 1 | S20: =SUM(S12:S19) -> 29175.96 | T20: =IFERROR(S20/S$20,0) -> 1 | U20: =SUM(U12:U19) -> 29175.96 | V20: =IFERROR(U20/U$20,0) -> 1 | W20: =SUM(W12:W19) -> 29175.96 | X20: =IFERROR(W20/W$20,0) -> 1 | Y20: =SUM(Y12:Y19) -> 29175.96 | Z20: =IFERROR(Y20/Y$20,0) -> 1 | AB20: =SUM(AB12:AB19) -> 350111.52 | AC20: =IFERROR(AB20/AB$20,0) -> 1
A22: Cost of Goods Sold
A23: Food Cost | C23: =C12*'Vessel Assumptions'!$C$12 -> 14830.4 | D23: =IFERROR(C23/C$12,0) -> 0.55555556 | E23: =E12*'Vessel Assumptions'!$C$12 -> 4563.2 | F23: =IFERROR(E23/E$12,0) -> 0.55555556 | G23: =G12*'Vessel Assumptions'!$C$12 -> 14830.4 | H23: =IFERROR(G23/G$12,0) -> 0.55555556 | I23: =I12*'Vessel Assumptions'!$C$12 -> 4563.2 | J23: =IFERROR(I23/I$12,0) -> 0.55555556 | K23: =K12*'Vessel Assumptions'!$C$12 -> 11408 | L23: =IFERROR(K23/K$12,0) -> 0.55555556 | M23: =M12*'Vessel Assumptions'!$C$12 -> 10039.04 | N23: =IFERROR(M23/M$12,0) -> 0.55555556 | O23: =O12*'Vessel Assumptions'!$C$12 -> 10039.04 | P23: =IFERROR(O23/O$12,0) -> 0.55555556 | Q23: =Q12*'Vessel Assumptions'!$C$12 -> 10039.04 | R23: =IFERROR(Q23/Q$12,0) -> 0.55555556 | S23: =S12*'Vessel Assumptions'!$C$12 -> 10039.04 | T23: =IFERROR(S23/S$12,0) -> 0.55555556 | U23: =U12*'Vessel Assumptions'!$C$12 -> 10039.04 | V23: =IFERROR(U23/U$12,0) -> 0.55555556 | W23: =W12*'Vessel Assumptions'!$C$12 -> 10039.04 | X23: =IFERROR(W23/W$12,0) -> 0.55555556 | Y23: =Y12*'Vessel Assumptions'!$C$12 -> 10039.04 | Z23: =IFERROR(Y23/Y$12,0) -> 0.55555556 | AB23: =SUM(C23,E23,G23,I23,K23,M23,O23,Q23,S23,U23,W23,Y23) -> 120468.48 | AC23: =IFERROR(AB23/AB$12,0) -> 0.55555556
A24: Non-Alcoholic Beverage Cost | C24: =C13*'Vessel Assumptions'!$C$13 -> 653.22335 | D24: =IFERROR(C24/C$13,0) -> 0.25 | E24: =E13*'Vessel Assumptions'!$C$13 -> 200.9918 | F24: =IFERROR(E24/E$13,0) -> 0.25 | G24: =G13*'Vessel Assumptions'!$C$13 -> 653.22335 | H24: =IFERROR(G24/G$13,0) -> 0.25 | I24: =I13*'Vessel Assumptions'!$C$13 -> 200.9918 | J24: =IFERROR(I24/I$13,0) -> 0.25 | K24: =K13*'Vessel Assumptions'!$C$13 -> 502.4795 | L24: =IFERROR(K24/K$13,0) -> 0.25 | M24: =M13*'Vessel Assumptions'!$C$13 -> 442.18196 | N24: =IFERROR(M24/M$13,0) -> 0.25 | O24: =O13*'Vessel Assumptions'!$C$13 -> 442.18196 | P24: =IFERROR(O24/O$13,0) -> 0.25 | Q24: =Q13*'Vessel Assumptions'!$C$13 -> 442.18196 | R24: =IFERROR(Q24/Q$13,0) -> 0.25 | S24: =S13*'Vessel Assumptions'!$C$13 -> 442.18196 | T24: =IFERROR(S24/S$13,0) -> 0.25 | U24: =U13*'Vessel Assumptions'!$C$13 -> 442.18196 | V24: =IFERROR(U24/U$13,0) -> 0.25 | W24: =W13*'Vessel Assumptions'!$C$13 -> 442.18196 | X24: =IFERROR(W24/W$13,0) -> 0.25 | Y24: =Y13*'Vessel Assumptions'!$C$13 -> 442.18196 | Z24: =IFERROR(Y24/Y$13,0) -> 0.25 | AB24: =SUM(C24,E24,G24,I24,K24,M24,O24,Q24,S24,U24,W24,Y24) -> 5306.1835 | AC24: =IFERROR(AB24/AB$13,0) -> 0.25
A25: Liquor Cost | C25: =C14*'Vessel Assumptions'!$C$13 -> 1098.6435 | D25: =IFERROR(C25/C$14,0) -> 0.25 | E25: =E14*'Vessel Assumptions'!$C$13 -> 338.04415 | F25: =IFERROR(E25/E$14,0) -> 0.25 | G25: =G14*'Vessel Assumptions'!$C$13 -> 1098.6435 | H25: =IFERROR(G25/G$14,0) -> 0.25 | I25: =I14*'Vessel Assumptions'!$C$13 -> 338.04415 | J25: =IFERROR(I25/I$14,0) -> 0.25 | K25: =K14*'Vessel Assumptions'!$C$13 -> 845.11038 | L25: =IFERROR(K25/K$14,0) -> 0.25 | M25: =M14*'Vessel Assumptions'!$C$13 -> 743.69713 | N25: =IFERROR(M25/M$14,0) -> 0.25 | O25: =O14*'Vessel Assumptions'!$C$13 -> 743.69713 | P25: =IFERROR(O25/O$14,0) -> 0.25 | Q25: =Q14*'Vessel Assumptions'!$C$13 -> 743.69713 | R25: =IFERROR(Q25/Q$14,0) -> 0.25 | S25: =S14*'Vessel Assumptions'!$C$13 -> 743.69713 | T25: =IFERROR(S25/S$14,0) -> 0.25 | U25: =U14*'Vessel Assumptions'!$C$13 -> 743.69713 | V25: =IFERROR(U25/U$14,0) -> 0.25 | W25: =W14*'Vessel Assumptions'!$C$13 -> 743.69713 | X25: =IFERROR(W25/W$14,0) -> 0.25 | Y25: =Y14*'Vessel Assumptions'!$C$13 -> 743.69713 | Z25: =IFERROR(Y25/Y$14,0) -> 0.25 | AB25: =SUM(C25,E25,G25,I25,K25,M25,O25,Q25,S25,U25,W25,Y25) -> 8924.3656 | AC25: =IFERROR(AB25/AB$14,0) -> 0.25
A26: Beer Cost | C26: =C15*'Vessel Assumptions'!$C$13 -> 40.503419 | D26: =IFERROR(C26/C$15,0) -> 0.25 | E26: =E15*'Vessel Assumptions'!$C$13 -> 12.46259 | F26: =IFERROR(E26/E$15,0) -> 0.25 | G26: =G15*'Vessel Assumptions'!$C$13 -> 40.503419 | H26: =IFERROR(G26/G$15,0) -> 0.25 | I26: =I15*'Vessel Assumptions'!$C$13 -> 12.46259 | J26: =IFERROR(I26/I$15,0) -> 0.25 | K26: =K15*'Vessel Assumptions'!$C$13 -> 31.156476 | L26: =IFERROR(K26/K$15,0) -> 0.25 | M26: =M15*'Vessel Assumptions'!$C$13 -> 27.417699 | N26: =IFERROR(M26/M$15,0) -> 0.25 | O26: =O15*'Vessel Assumptions'!$C$13 -> 27.417699 | P26: =IFERROR(O26/O$15,0) -> 0.25 | Q26: =Q15*'Vessel Assumptions'!$C$13 -> 27.417699 | R26: =IFERROR(Q26/Q$15,0) -> 0.25 | S26: =S15*'Vessel Assumptions'!$C$13 -> 27.417699 | T26: =IFERROR(S26/S$15,0) -> 0.25 | U26: =U15*'Vessel Assumptions'!$C$13 -> 27.417699 | V26: =IFERROR(U26/U$15,0) -> 0.25 | W26: =W15*'Vessel Assumptions'!$C$13 -> 27.417699 | X26: =IFERROR(W26/W$15,0) -> 0.25 | Y26: =Y15*'Vessel Assumptions'!$C$13 -> 27.417699 | Z26: =IFERROR(Y26/Y$15,0) -> 0.25 | AB26: =SUM(C26,E26,G26,I26,K26,M26,O26,Q26,S26,U26,W26,Y26) -> 329.01239 | AC26: =IFERROR(AB26/AB$15,0) -> 0.25
A27: Wine/Sake Cost | C27: =C16*'Vessel Assumptions'!$C$13 -> 154.11974 | D27: =IFERROR(C27/C$16,0) -> 0.25 | E27: =E16*'Vessel Assumptions'!$C$13 -> 47.421458 | F27: =IFERROR(E27/E$16,0) -> 0.25 | G27: =G16*'Vessel Assumptions'!$C$13 -> 154.11974 | H27: =IFERROR(G27/G$16,0) -> 0.25 | I27: =I16*'Vessel Assumptions'!$C$13 -> 47.421458 | J27: =IFERROR(I27/I$16,0) -> 0.25 | K27: =K16*'Vessel Assumptions'!$C$13 -> 118.55364 | L27: =IFERROR(K27/K$16,0) -> 0.25 | M27: =M16*'Vessel Assumptions'!$C$13 -> 104.32721 | N27: =IFERROR(M27/M$16,0) -> 0.25 | O27: =O16*'Vessel Assumptions'!$C$13 -> 104.32721 | P27: =IFERROR(O27/O$16,0) -> 0.25 | Q27: =Q16*'Vessel Assumptions'!$C$13 -> 104.32721 | R27: =IFERROR(Q27/Q$16,0) -> 0.25 | S27: =S16*'Vessel Assumptions'!$C$13 -> 104.32721 | T27: =IFERROR(S27/S$16,0) -> 0.25 | U27: =U16*'Vessel Assumptions'!$C$13 -> 104.32721 | V27: =IFERROR(U27/U$16,0) -> 0.25 | W27: =W16*'Vessel Assumptions'!$C$13 -> 104.32721 | X27: =IFERROR(W27/W$16,0) -> 0.25 | Y27: =Y16*'Vessel Assumptions'!$C$13 -> 104.32721 | Z27: =IFERROR(Y27/Y$16,0) -> 0.25 | AB27: =SUM(C27,E27,G27,I27,K27,M27,O27,Q27,S27,U27,W27,Y27) -> 1251.9265 | AC27: =IFERROR(AB27/AB$16,0) -> 0.25
A28: Retail Cost | C28: 0 | D28: =IFERROR(C28/C$17,0) -> 0 | E28: 0 | F28: =IFERROR(E28/E$17,0) -> 0 | G28: 0 | H28: =IFERROR(G28/G$17,0) -> 0 | I28: 0 | J28: =IFERROR(I28/I$17,0) -> 0 | K28: 0 | L28: =IFERROR(K28/K$17,0) -> 0 | M28: 0 | N28: =IFERROR(M28/M$17,0) -> 0 | O28: 0 | P28: =IFERROR(O28/O$17,0) -> 0 | Q28: 0 | R28: =IFERROR(Q28/Q$17,0) -> 0 | S28: 0 | T28: =IFERROR(S28/S$17,0) -> 0 | U28: 0 | V28: =IFERROR(U28/U$17,0) -> 0 | W28: 0 | X28: =IFERROR(W28/W$17,0) -> 0 | Y28: 0 | Z28: =IFERROR(Y28/Y$17,0) -> 0 | AB28: =SUM(C28,E28,G28,I28,K28,M28,O28,Q28,S28,U28,W28,Y28) -> 0 | AC28: =IFERROR(AB28/AB$17,0) -> 0
A29: Total COGS | C29: =SUM(C23:C28) -> 16776.89 | D29: =IFERROR(C29/C$20,0) -> 0.38924731 | E29: =SUM(E23:E28) -> 5162.12 | F29: =IFERROR(E29/E$20,0) -> 0.38924731 | G29: =SUM(G23:G28) -> 16776.89 | H29: =IFERROR(G29/G$20,0) -> 0.38924731 | I29: =SUM(I23:I28) -> 5162.12 | J29: =IFERROR(I29/I$20,0) -> 0.38924731 | K29: =SUM(K23:K28) -> 12905.3 | L29: =IFERROR(K29/K$20,0) -> 0.38924731 | M29: =SUM(M23:M28) -> 11356.664 | N29: =IFERROR(M29/M$20,0) -> 0.38924731 | O29: =SUM(O23:O28) -> 11356.664 | P29: =IFERROR(O29/O$20,0) -> 0.38924731 | Q29: =SUM(Q23:Q28) -> 11356.664 | R29: =IFERROR(Q29/Q$20,0) -> 0.38924731 | S29: =SUM(S23:S28) -> 11356.664 | T29: =IFERROR(S29/S$20,0) -> 0.38924731 | U29: =SUM(U23:U28) -> 11356.664 | V29: =IFERROR(U29/U$20,0) -> 0.38924731 | W29: =SUM(W23:W28) -> 11356.664 | X29: =IFERROR(W29/W$20,0) -> 0.38924731 | Y29: =SUM(Y23:Y28) -> 11356.664 | Z29: =IFERROR(Y29/Y$20,0) -> 0.38924731 | AB29: =SUM(AB23:AB28) -> 136279.97 | AC29: =IFERROR(AB29/AB$20,0) -> 0.38924731
A30: Gross Profit | C30: =C20-C29 -> 26323.96 | D30: =IFERROR(C30/C$20,0) -> 0.61075269 | E30: =E20-E29 -> 8099.68 | F30: =IFERROR(E30/E$20,0) -> 0.61075269 | G30: =G20-G29 -> 26323.96 | H30: =IFERROR(G30/G$20,0) -> 0.61075269 | I30: =I20-I29 -> 8099.68 | J30: =IFERROR(I30/I$20,0) -> 0.61075269 | K30: =K20-K29 -> 20249.2 | L30: =IFERROR(K30/K$20,0) -> 0.61075269 | M30: =M20-M29 -> 17819.296 | N30: =IFERROR(M30/M$20,0) -> 0.61075269 | O30: =O20-O29 -> 17819.296 | P30: =IFERROR(O30/O$20,0) -> 0.61075269 | Q30: =Q20-Q29 -> 17819.296 | R30: =IFERROR(Q30/Q$20,0) -> 0.61075269 | S30: =S20-S29 -> 17819.296 | T30: =IFERROR(S30/S$20,0) -> 0.61075269 | U30: =U20-U29 -> 17819.296 | V30: =IFERROR(U30/U$20,0) -> 0.61075269 | W30: =W20-W29 -> 17819.296 | X30: =IFERROR(W30/W$20,0) -> 0.61075269 | Y30: =Y20-Y29 -> 17819.296 | Z30: =IFERROR(Y30/Y$20,0) -> 0.61075269 | AB30: =AB20-AB29 -> 213831.55 | AC30: =IFERROR(AB30/AB$20,0) -> 0.61075269
A32: Labor Cost
A33: Management Labor (per event, card $55) | C33: =C9*'Vessel Assumptions'!$C$36 -> 509.795 | D33: =IFERROR(C33/C$20,0) -> 0.011827957 | E33: =E9*'Vessel Assumptions'!$C$36 -> 156.86 | F33: =IFERROR(E33/E$20,0) -> 0.011827957 | G33: =G9*'Vessel Assumptions'!$C$36 -> 509.795 | H33: =IFERROR(G33/G$20,0) -> 0.011827957 | I33: =I9*'Vessel Assumptions'!$C$36 -> 156.86 | J33: =IFERROR(I33/I$20,0) -> 0.011827957 | K33: =K9*'Vessel Assumptions'!$C$36 -> 392.15 | L33: =IFERROR(K33/K$20,0) -> 0.011827957 | M33: =M9*'Vessel Assumptions'!$C$36 -> 345.092 | N33: =IFERROR(M33/M$20,0) -> 0.011827957 | O33: =O9*'Vessel Assumptions'!$C$36 -> 345.092 | P33: =IFERROR(O33/O$20,0) -> 0.011827957 | Q33: =Q9*'Vessel Assumptions'!$C$36 -> 345.092 | R33: =IFERROR(Q33/Q$20,0) -> 0.011827957 | S33: =S9*'Vessel Assumptions'!$C$36 -> 345.092 | T33: =IFERROR(S33/S$20,0) -> 0.011827957 | U33: =U9*'Vessel Assumptions'!$C$36 -> 345.092 | V33: =IFERROR(U33/U$20,0) -> 0.011827957 | W33: =W9*'Vessel Assumptions'!$C$36 -> 345.092 | X33: =IFERROR(W33/W$20,0) -> 0.011827957 | Y33: =Y9*'Vessel Assumptions'!$C$36 -> 345.092 | Z33: =IFERROR(Y33/Y$20,0) -> 0.011827957 | AB33: =SUM(C33,E33,G33,I33,K33,M33,O33,Q33,S33,U33,W33,Y33) -> 4141.104 | AC33: =IFERROR(AB33/AB$20,0) -> 0.011827957
A34: Back of House Hourly Labor | C34: 0 | D34: =IFERROR(C34/C$20,0) -> 0 | E34: 0 | F34: =IFERROR(E34/E$20,0) -> 0 | G34: 0 | H34: =IFERROR(G34/G$20,0) -> 0 | I34: 0 | J34: =IFERROR(I34/I$20,0) -> 0 | K34: 0 | L34: =IFERROR(K34/K$20,0) -> 0 | M34: 0 | N34: =IFERROR(M34/M$20,0) -> 0 | O34: 0 | P34: =IFERROR(O34/O$20,0) -> 0 | Q34: 0 | R34: =IFERROR(Q34/Q$20,0) -> 0 | S34: 0 | T34: =IFERROR(S34/S$20,0) -> 0 | U34: 0 | V34: =IFERROR(U34/U$20,0) -> 0 | W34: 0 | X34: =IFERROR(W34/W$20,0) -> 0 | Y34: 0 | Z34: =IFERROR(Y34/Y$20,0) -> 0 | AB34: =SUM(C34,E34,G34,I34,K34,M34,O34,Q34,S34,U34,W34,Y34) -> 0 | AC34: =IFERROR(AB34/AB$20,0) -> 0
A35: Front of House Hourly Labor | C35: =C9*'Vessel Assumptions'!$C$20 -> 4866.225 | D35: =IFERROR(C35/C$20,0) -> 0.11290323 | E35: =E9*'Vessel Assumptions'!$C$20 -> 1497.3 | F35: =IFERROR(E35/E$20,0) -> 0.11290323 | G35: =G9*'Vessel Assumptions'!$C$20 -> 4866.225 | H35: =IFERROR(G35/G$20,0) -> 0.11290323 | I35: =I9*'Vessel Assumptions'!$C$20 -> 1497.3 | J35: =IFERROR(I35/I$20,0) -> 0.11290323 | K35: =K9*'Vessel Assumptions'!$C$20 -> 3743.25 | L35: =IFERROR(K35/K$20,0) -> 0.11290323 | M35: =M9*'Vessel Assumptions'!$C$20 -> 3294.06 | N35: =IFERROR(M35/M$20,0) -> 0.11290323 | O35: =O9*'Vessel Assumptions'!$C$20 -> 3294.06 | P35: =IFERROR(O35/O$20,0) -> 0.11290323 | Q35: =Q9*'Vessel Assumptions'!$C$20 -> 3294.06 | R35: =IFERROR(Q35/Q$20,0) -> 0.11290323 | S35: =S9*'Vessel Assumptions'!$C$20 -> 3294.06 | T35: =IFERROR(S35/S$20,0) -> 0.11290323 | U35: =U9*'Vessel Assumptions'!$C$20 -> 3294.06 | V35: =IFERROR(U35/U$20,0) -> 0.11290323 | W35: =W9*'Vessel Assumptions'!$C$20 -> 3294.06 | X35: =IFERROR(W35/W$20,0) -> 0.11290323 | Y35: =Y9*'Vessel Assumptions'!$C$20 -> 3294.06 | Z35: =IFERROR(Y35/Y$20,0) -> 0.11290323 | AB35: =SUM(C35,E35,G35,I35,K35,M35,O35,Q35,S35,U35,W35,Y35) -> 39528.72 | AC35: =IFERROR(AB35/AB$20,0) -> 0.11290323
A36: Payroll Taxes & Benefits | C36: =(C33+C35+C37)*'Vessel Assumptions'!$C$22 -> 1056.666 | D36: =IFERROR(C36/C$20,0) -> 0.024516129 | E36: =(E33+E35+E37)*'Vessel Assumptions'!$C$22 -> 325.128 | F36: =IFERROR(E36/E$20,0) -> 0.024516129 | G36: =(G33+G35+G37)*'Vessel Assumptions'!$C$22 -> 1056.666 | H36: =IFERROR(G36/G$20,0) -> 0.024516129 | I36: =(I33+I35+I37)*'Vessel Assumptions'!$C$22 -> 325.128 | J36: =IFERROR(I36/I$20,0) -> 0.024516129 | K36: =(K33+K35+K37)*'Vessel Assumptions'!$C$22 -> 812.82 | L36: =IFERROR(K36/K$20,0) -> 0.024516129 | M36: =(M33+M35+M37)*'Vessel Assumptions'!$C$22 -> 715.2816 | N36: =IFERROR(M36/M$20,0) -> 0.024516129 | O36: =(O33+O35+O37)*'Vessel Assumptions'!$C$22 -> 715.2816 | P36: =IFERROR(O36/O$20,0) -> 0.024516129 | Q36: =(Q33+Q35+Q37)*'Vessel Assumptions'!$C$22 -> 715.2816 | R36: =IFERROR(Q36/Q$20,0) -> 0.024516129 | S36: =(S33+S35+S37)*'Vessel Assumptions'!$C$22 -> 715.2816 | T36: =IFERROR(S36/S$20,0) -> 0.024516129 | U36: =(U33+U35+U37)*'Vessel Assumptions'!$C$22 -> 715.2816 | V36: =IFERROR(U36/U$20,0) -> 0.024516129 | W36: =(W33+W35+W37)*'Vessel Assumptions'!$C$22 -> 715.2816 | X36: =IFERROR(W36/W$20,0) -> 0.024516129 | Y36: =(Y33+Y35+Y37)*'Vessel Assumptions'!$C$22 -> 715.2816 | Z36: =IFERROR(Y36/Y$20,0) -> 0.024516129 | AB36: =SUM(C36,E36,G36,I36,K36,M36,O36,Q36,S36,U36,W36,Y36) -> 8583.3792 | AC36: =IFERROR(AB36/AB$20,0) -> 0.024516129
A37: Bonus (per event, card $112) | C37: =C9*'Vessel Assumptions'!$C$37 -> 1038.128 | D37: =IFERROR(C37/C$20,0) -> 0.024086022 | E37: =E9*'Vessel Assumptions'!$C$37 -> 319.424 | F37: =IFERROR(E37/E$20,0) -> 0.024086022 | G37: =G9*'Vessel Assumptions'!$C$37 -> 1038.128 | H37: =IFERROR(G37/G$20,0) -> 0.024086022 | I37: =I9*'Vessel Assumptions'!$C$37 -> 319.424 | J37: =IFERROR(I37/I$20,0) -> 0.024086022 | K37: =K9*'Vessel Assumptions'!$C$37 -> 798.56 | L37: =IFERROR(K37/K$20,0) -> 0.024086022 | M37: =M9*'Vessel Assumptions'!$C$37 -> 702.7328 | N37: =IFERROR(M37/M$20,0) -> 0.024086022 | O37: =O9*'Vessel Assumptions'!$C$37 -> 702.7328 | P37: =IFERROR(O37/O$20,0) -> 0.024086022 | Q37: =Q9*'Vessel Assumptions'!$C$37 -> 702.7328 | R37: =IFERROR(Q37/Q$20,0) -> 0.024086022 | S37: =S9*'Vessel Assumptions'!$C$37 -> 702.7328 | T37: =IFERROR(S37/S$20,0) -> 0.024086022 | U37: =U9*'Vessel Assumptions'!$C$37 -> 702.7328 | V37: =IFERROR(U37/U$20,0) -> 0.024086022 | W37: =W9*'Vessel Assumptions'!$C$37 -> 702.7328 | X37: =IFERROR(W37/W$20,0) -> 0.024086022 | Y37: =Y9*'Vessel Assumptions'!$C$37 -> 702.7328 | Z37: =IFERROR(Y37/Y$20,0) -> 0.024086022 | AB37: =SUM(C37,E37,G37,I37,K37,M37,O37,Q37,S37,U37,W37,Y37) -> 8432.7936 | AC37: =IFERROR(AB37/AB$20,0) -> 0.024086022
A38: Total Labor Cost | C38: =SUM(C33:C37) -> 7470.814 | D38: =IFERROR(C38/C$20,0) -> 0.17333333 | E38: =SUM(E33:E37) -> 2298.712 | F38: =IFERROR(E38/E$20,0) -> 0.17333333 | G38: =SUM(G33:G37) -> 7470.814 | H38: =IFERROR(G38/G$20,0) -> 0.17333333 | I38: =SUM(I33:I37) -> 2298.712 | J38: =IFERROR(I38/I$20,0) -> 0.17333333 | K38: =SUM(K33:K37) -> 5746.78 | L38: =IFERROR(K38/K$20,0) -> 0.17333333 | M38: =SUM(M33:M37) -> 5057.1664 | N38: =IFERROR(M38/M$20,0) -> 0.17333333 | O38: =SUM(O33:O37) -> 5057.1664 | P38: =IFERROR(O38/O$20,0) -> 0.17333333 | Q38: =SUM(Q33:Q37) -> 5057.1664 | R38: =IFERROR(Q38/Q$20,0) -> 0.17333333 | S38: =SUM(S33:S37) -> 5057.1664 | T38: =IFERROR(S38/S$20,0) -> 0.17333333 | U38: =SUM(U33:U37) -> 5057.1664 | V38: =IFERROR(U38/U$20,0) -> 0.17333333 | W38: =SUM(W33:W37) -> 5057.1664 | X38: =IFERROR(W38/W$20,0) -> 0.17333333 | Y38: =SUM(Y33:Y37) -> 5057.1664 | Z38: =IFERROR(Y38/Y$20,0) -> 0.17333333 | AB38: =SUM(AB33:AB37) -> 60685.997 | AC38: =IFERROR(AB38/AB$20,0) -> 0.17333333
A40: Prime Costs | C40: =C29+C38 -> 24247.704 | D40: =IFERROR(C40/C$20,0) -> 0.56258065 | E40: =E29+E38 -> 7460.832 | F40: =IFERROR(E40/E$20,0) -> 0.56258065 | G40: =G29+G38 -> 24247.704 | H40: =IFERROR(G40/G$20,0) -> 0.56258065 | I40: =I29+I38 -> 7460.832 | J40: =IFERROR(I40/I$20,0) -> 0.56258065 | K40: =K29+K38 -> 18652.08 | L40: =IFERROR(K40/K$20,0) -> 0.56258065 | M40: =M29+M38 -> 16413.83 | N40: =IFERROR(M40/M$20,0) -> 0.56258065 | O40: =O29+O38 -> 16413.83 | P40: =IFERROR(O40/O$20,0) -> 0.56258065 | Q40: =Q29+Q38 -> 16413.83 | R40: =IFERROR(Q40/Q$20,0) -> 0.56258065 | S40: =S29+S38 -> 16413.83 | T40: =IFERROR(S40/S$20,0) -> 0.56258065 | U40: =U29+U38 -> 16413.83 | V40: =IFERROR(U40/U$20,0) -> 0.56258065 | W40: =W29+W38 -> 16413.83 | X40: =IFERROR(W40/W$20,0) -> 0.56258065 | Y40: =Y29+Y38 -> 16413.83 | Z40: =IFERROR(Y40/Y$20,0) -> 0.56258065 | AB40: =AB29+AB38 -> 196965.96 | AC40: =IFERROR(AB40/AB$20,0) -> 0.56258065
A41: Operating Profit | C41: =C30-C38 -> 18853.146 | D41: =IFERROR(C41/C$20,0) -> 0.43741935 | E41: =E30-E38 -> 5800.968 | F41: =IFERROR(E41/E$20,0) -> 0.43741935 | G41: =G30-G38 -> 18853.146 | H41: =IFERROR(G41/G$20,0) -> 0.43741935 | I41: =I30-I38 -> 5800.968 | J41: =IFERROR(I41/I$20,0) -> 0.43741935 | K41: =K30-K38 -> 14502.42 | L41: =IFERROR(K41/K$20,0) -> 0.43741935 | M41: =M30-M38 -> 12762.13 | N41: =IFERROR(M41/M$20,0) -> 0.43741935 | O41: =O30-O38 -> 12762.13 | P41: =IFERROR(O41/O$20,0) -> 0.43741935 | Q41: =Q30-Q38 -> 12762.13 | R41: =IFERROR(Q41/Q$20,0) -> 0.43741935 | S41: =S30-S38 -> 12762.13 | T41: =IFERROR(S41/S$20,0) -> 0.43741935 | U41: =U30-U38 -> 12762.13 | V41: =IFERROR(U41/U$20,0) -> 0.43741935 | W41: =W30-W38 -> 12762.13 | X41: =IFERROR(W41/W$20,0) -> 0.43741935 | Y41: =Y30-Y38 -> 12762.13 | Z41: =IFERROR(Y41/Y$20,0) -> 0.43741935 | AB41: =AB30-AB38 -> 153145.56 | AC41: =IFERROR(AB41/AB$20,0) -> 0.43741935
A43: Controllable Expenses
A44: Operating Expenses (12.4% of revenue per card · incl CC) | C44: =C20*'Vessel Assumptions'!$C$38 -> 5329.675 | D44: =IFERROR(C44/C$20,0) -> 0.12365591 | E44: =E20*'Vessel Assumptions'!$C$38 -> 1639.9 | F44: =IFERROR(E44/E$20,0) -> 0.12365591 | G44: =G20*'Vessel Assumptions'!$C$38 -> 5329.675 | H44: =IFERROR(G44/G$20,0) -> 0.12365591 | I44: =I20*'Vessel Assumptions'!$C$38 -> 1639.9 | J44: =IFERROR(I44/I$20,0) -> 0.12365591 | K44: =K20*'Vessel Assumptions'!$C$38 -> 4099.75 | L44: =IFERROR(K44/K$20,0) -> 0.12365591 | M44: =M20*'Vessel Assumptions'!$C$38 -> 3607.78 | N44: =IFERROR(M44/M$20,0) -> 0.12365591 | O44: =O20*'Vessel Assumptions'!$C$38 -> 3607.78 | P44: =IFERROR(O44/O$20,0) -> 0.12365591 | Q44: =Q20*'Vessel Assumptions'!$C$38 -> 3607.78 | R44: =IFERROR(Q44/Q$20,0) -> 0.12365591 | S44: =S20*'Vessel Assumptions'!$C$38 -> 3607.78 | T44: =IFERROR(S44/S$20,0) -> 0.12365591 | U44: =U20*'Vessel Assumptions'!$C$38 -> 3607.78 | V44: =IFERROR(U44/U$20,0) -> 0.12365591 | W44: =W20*'Vessel Assumptions'!$C$38 -> 3607.78 | X44: =IFERROR(W44/W$20,0) -> 0.12365591 | Y44: =Y20*'Vessel Assumptions'!$C$38 -> 3607.78 | Z44: =IFERROR(Y44/Y$20,0) -> 0.12365591 | AB44: =SUM(C44,E44,G44,I44,K44,M44,O44,Q44,S44,U44,W44,Y44) -> 43293.36 | AC44: =IFERROR(AB44/AB$20,0) -> 0.12365591
A45: Music & Entertainment | C45: 0 | D45: =IFERROR(C45/C$20,0) -> 0 | E45: 0 | F45: =IFERROR(E45/E$20,0) -> 0 | G45: 0 | H45: =IFERROR(G45/G$20,0) -> 0 | I45: 0 | J45: =IFERROR(I45/I$20,0) -> 0 | K45: 0 | L45: =IFERROR(K45/K$20,0) -> 0 | M45: 0 | N45: =IFERROR(M45/M$20,0) -> 0 | O45: 0 | P45: =IFERROR(O45/O$20,0) -> 0 | Q45: 0 | R45: =IFERROR(Q45/Q$20,0) -> 0 | S45: 0 | T45: =IFERROR(S45/S$20,0) -> 0 | U45: 0 | V45: =IFERROR(U45/U$20,0) -> 0 | W45: 0 | X45: =IFERROR(W45/W$20,0) -> 0 | Y45: 0 | Z45: =IFERROR(Y45/Y$20,0) -> 0 | AB45: =SUM(C45,E45,G45,I45,K45,M45,O45,Q45,S45,U45,W45,Y45) -> 0 | AC45: =IFERROR(AB45/AB$20,0) -> 0
A46: Marketing & Advertising | C46: 0 | D46: =IFERROR(C46/C$20,0) -> 0 | E46: 0 | F46: =IFERROR(E46/E$20,0) -> 0 | G46: 0 | H46: =IFERROR(G46/G$20,0) -> 0 | I46: 0 | J46: =IFERROR(I46/I$20,0) -> 0 | K46: 0 | L46: =IFERROR(K46/K$20,0) -> 0 | M46: 0 | N46: =IFERROR(M46/M$20,0) -> 0 | O46: 0 | P46: =IFERROR(O46/O$20,0) -> 0 | Q46: 0 | R46: =IFERROR(Q46/Q$20,0) -> 0 | S46: 0 | T46: =IFERROR(S46/S$20,0) -> 0 | U46: 0 | V46: =IFERROR(U46/U$20,0) -> 0 | W46: 0 | X46: =IFERROR(W46/W$20,0) -> 0 | Y46: 0 | Z46: =IFERROR(Y46/Y$20,0) -> 0 | AB46: =SUM(C46,E46,G46,I46,K46,M46,O46,Q46,S46,U46,W46,Y46) -> 0 | AC46: =IFERROR(AB46/AB$20,0) -> 0
A47: General & Administrative - Controllable (4% target) | C47: 0 | D47: =IFERROR(C47/C$20,0) -> 0 | E47: 0 | F47: =IFERROR(E47/E$20,0) -> 0 | G47: 0 | H47: =IFERROR(G47/G$20,0) -> 0 | I47: 0 | J47: =IFERROR(I47/I$20,0) -> 0 | K47: 0 | L47: =IFERROR(K47/K$20,0) -> 0 | M47: 0 | N47: =IFERROR(M47/M$20,0) -> 0 | O47: 0 | P47: =IFERROR(O47/O$20,0) -> 0 | Q47: 0 | R47: =IFERROR(Q47/Q$20,0) -> 0 | S47: 0 | T47: =IFERROR(S47/S$20,0) -> 0 | U47: 0 | V47: =IFERROR(U47/U$20,0) -> 0 | W47: 0 | X47: =IFERROR(W47/W$20,0) -> 0 | Y47: 0 | Z47: =IFERROR(Y47/Y$20,0) -> 0 | AB47: =SUM(C47,E47,G47,I47,K47,M47,O47,Q47,S47,U47,W47,Y47) -> 0 | AC47: =IFERROR(AB47/AB$20,0) -> 0
A48: Repairs & Maintenance | C48: 0 | D48: =IFERROR(C48/C$20,0) -> 0 | E48: 0 | F48: =IFERROR(E48/E$20,0) -> 0 | G48: 0 | H48: =IFERROR(G48/G$20,0) -> 0 | I48: 0 | J48: =IFERROR(I48/I$20,0) -> 0 | K48: 0 | L48: =IFERROR(K48/K$20,0) -> 0 | M48: 0 | N48: =IFERROR(M48/M$20,0) -> 0 | O48: 0 | P48: =IFERROR(O48/O$20,0) -> 0 | Q48: 0 | R48: =IFERROR(Q48/Q$20,0) -> 0 | S48: 0 | T48: =IFERROR(S48/S$20,0) -> 0 | U48: 0 | V48: =IFERROR(U48/U$20,0) -> 0 | W48: 0 | X48: =IFERROR(W48/W$20,0) -> 0 | Y48: 0 | Z48: =IFERROR(Y48/Y$20,0) -> 0 | AB48: =SUM(C48,E48,G48,I48,K48,M48,O48,Q48,S48,U48,W48,Y48) -> 0 | AC48: =IFERROR(AB48/AB$20,0) -> 0
A49: Credit Card Fees | C49: 0 | D49: =IFERROR(C49/C$20,0) -> 0 | E49: 0 | F49: =IFERROR(E49/E$20,0) -> 0 | G49: 0 | H49: =IFERROR(G49/G$20,0) -> 0 | I49: 0 | J49: =IFERROR(I49/I$20,0) -> 0 | K49: 0 | L49: =IFERROR(K49/K$20,0) -> 0 | M49: 0 | N49: =IFERROR(M49/M$20,0) -> 0 | O49: 0 | P49: =IFERROR(O49/O$20,0) -> 0 | Q49: 0 | R49: =IFERROR(Q49/Q$20,0) -> 0 | S49: 0 | T49: =IFERROR(S49/S$20,0) -> 0 | U49: 0 | V49: =IFERROR(U49/U$20,0) -> 0 | W49: 0 | X49: =IFERROR(W49/W$20,0) -> 0 | Y49: 0 | Z49: =IFERROR(Y49/Y$20,0) -> 0 | AB49: =SUM(C49,E49,G49,I49,K49,M49,O49,Q49,S49,U49,W49,Y49) -> 0 | AC49: =IFERROR(AB49/AB$20,0) -> 0
A50: Total Controllable Expenses | C50: =SUM(C44:C49) -> 5329.675 | D50: =IFERROR(C50/C$20,0) -> 0.12365591 | E50: =SUM(E44:E49) -> 1639.9 | F50: =IFERROR(E50/E$20,0) -> 0.12365591 | G50: =SUM(G44:G49) -> 5329.675 | H50: =IFERROR(G50/G$20,0) -> 0.12365591 | I50: =SUM(I44:I49) -> 1639.9 | J50: =IFERROR(I50/I$20,0) -> 0.12365591 | K50: =SUM(K44:K49) -> 4099.75 | L50: =IFERROR(K50/K$20,0) -> 0.12365591 | M50: =SUM(M44:M49) -> 3607.78 | N50: =IFERROR(M50/M$20,0) -> 0.12365591 | O50: =SUM(O44:O49) -> 3607.78 | P50: =IFERROR(O50/O$20,0) -> 0.12365591 | Q50: =SUM(Q44:Q49) -> 3607.78 | R50: =IFERROR(Q50/Q$20,0) -> 0.12365591 | S50: =SUM(S44:S49) -> 3607.78 | T50: =IFERROR(S50/S$20,0) -> 0.12365591 | U50: =SUM(U44:U49) -> 3607.78 | V50: =IFERROR(U50/U$20,0) -> 0.12365591 | W50: =SUM(W44:W49) -> 3607.78 | X50: =IFERROR(W50/W$20,0) -> 0.12365591 | Y50: =SUM(Y44:Y49) -> 3607.78 | Z50: =IFERROR(Y50/Y$20,0) -> 0.12365591 | AB50: =SUM(AB44:AB49) -> 43293.36 | AC50: =IFERROR(AB50/AB$20,0) -> 0.12365591
A52: Uncontrollable Expenses
A53: Utilities | C53: 0 | D53: =IFERROR(C53/C$20,0) -> 0 | E53: 0 | F53: =IFERROR(E53/E$20,0) -> 0 | G53: 0 | H53: =IFERROR(G53/G$20,0) -> 0 | I53: 0 | J53: =IFERROR(I53/I$20,0) -> 0 | K53: 0 | L53: =IFERROR(K53/K$20,0) -> 0 | M53: 0 | N53: =IFERROR(M53/M$20,0) -> 0 | O53: 0 | P53: =IFERROR(O53/O$20,0) -> 0 | Q53: 0 | R53: =IFERROR(Q53/Q$20,0) -> 0 | S53: 0 | T53: =IFERROR(S53/S$20,0) -> 0 | U53: 0 | V53: =IFERROR(U53/U$20,0) -> 0 | W53: 0 | X53: =IFERROR(W53/W$20,0) -> 0 | Y53: 0 | Z53: =IFERROR(Y53/Y$20,0) -> 0 | AB53: =SUM(C53,E53,G53,I53,K53,M53,O53,Q53,S53,U53,W53,Y53) -> 0 | AC53: =IFERROR(AB53/AB$20,0) -> 0
A54: Occupancy Cost | C54: =C20*'Vessel Assumptions'!$C$31 -> 0 | D54: =IFERROR(C54/C$20,0) -> 0 | E54: =E20*'Vessel Assumptions'!$C$31 -> 0 | F54: =IFERROR(E54/E$20,0) -> 0 | G54: =G20*'Vessel Assumptions'!$C$31 -> 0 | H54: =IFERROR(G54/G$20,0) -> 0 | I54: =I20*'Vessel Assumptions'!$C$31 -> 0 | J54: =IFERROR(I54/I$20,0) -> 0 | K54: =K20*'Vessel Assumptions'!$C$31 -> 0 | L54: =IFERROR(K54/K$20,0) -> 0 | M54: =M20*'Vessel Assumptions'!$C$31 -> 0 | N54: =IFERROR(M54/M$20,0) -> 0 | O54: =O20*'Vessel Assumptions'!$C$31 -> 0 | P54: =IFERROR(O54/O$20,0) -> 0 | Q54: =Q20*'Vessel Assumptions'!$C$31 -> 0 | R54: =IFERROR(Q54/Q$20,0) -> 0 | S54: =S20*'Vessel Assumptions'!$C$31 -> 0 | T54: =IFERROR(S54/S$20,0) -> 0 | U54: =U20*'Vessel Assumptions'!$C$31 -> 0 | V54: =IFERROR(U54/U$20,0) -> 0 | W54: =W20*'Vessel Assumptions'!$C$31 -> 0 | X54: =IFERROR(W54/W$20,0) -> 0 | Y54: =Y20*'Vessel Assumptions'!$C$31 -> 0 | Z54: =IFERROR(Y54/Y$20,0) -> 0 | AB54: =SUM(C54,E54,G54,I54,K54,M54,O54,Q54,S54,U54,W54,Y54) -> 0 | AC54: =IFERROR(AB54/AB$20,0) -> 0
A55: General & Administrative - Uncon (2.5% of revenue per card) | C55: =C20*'Vessel Assumptions'!$C$39 -> 1075.204 | D55: =IFERROR(C55/C$20,0) -> 0.024946237 | E55: =E20*'Vessel Assumptions'!$C$39 -> 330.832 | F55: =IFERROR(E55/E$20,0) -> 0.024946237 | G55: =G20*'Vessel Assumptions'!$C$39 -> 1075.204 | H55: =IFERROR(G55/G$20,0) -> 0.024946237 | I55: =I20*'Vessel Assumptions'!$C$39 -> 330.832 | J55: =IFERROR(I55/I$20,0) -> 0.024946237 | K55: =K20*'Vessel Assumptions'!$C$39 -> 827.08 | L55: =IFERROR(K55/K$20,0) -> 0.024946237 | M55: =M20*'Vessel Assumptions'!$C$39 -> 727.8304 | N55: =IFERROR(M55/M$20,0) -> 0.024946237 | O55: =O20*'Vessel Assumptions'!$C$39 -> 727.8304 | P55: =IFERROR(O55/O$20,0) -> 0.024946237 | Q55: =Q20*'Vessel Assumptions'!$C$39 -> 727.8304 | R55: =IFERROR(Q55/Q$20,0) -> 0.024946237 | S55: =S20*'Vessel Assumptions'!$C$39 -> 727.8304 | T55: =IFERROR(S55/S$20,0) -> 0.024946237 | U55: =U20*'Vessel Assumptions'!$C$39 -> 727.8304 | V55: =IFERROR(U55/U$20,0) -> 0.024946237 | W55: =W20*'Vessel Assumptions'!$C$39 -> 727.8304 | X55: =IFERROR(W55/W$20,0) -> 0.024946237 | Y55: =Y20*'Vessel Assumptions'!$C$39 -> 727.8304 | Z55: =IFERROR(Y55/Y$20,0) -> 0.024946237 | AB55: =SUM(C55,E55,G55,I55,K55,M55,O55,Q55,S55,U55,W55,Y55) -> 8733.9648 | AC55: =IFERROR(AB55/AB$20,0) -> 0.024946237
A56: Management Fee | C56: =C20*'Vessel Assumptions'!$C$30 -> 1724.034 | D56: =IFERROR(C56/C$20,0) -> 0.04 | E56: =E20*'Vessel Assumptions'!$C$30 -> 530.472 | F56: =IFERROR(E56/E$20,0) -> 0.04 | G56: =G20*'Vessel Assumptions'!$C$30 -> 1724.034 | H56: =IFERROR(G56/G$20,0) -> 0.04 | I56: =I20*'Vessel Assumptions'!$C$30 -> 530.472 | J56: =IFERROR(I56/I$20,0) -> 0.04 | K56: =K20*'Vessel Assumptions'!$C$30 -> 1326.18 | L56: =IFERROR(K56/K$20,0) -> 0.04 | M56: =M20*'Vessel Assumptions'!$C$30 -> 1167.0384 | N56: =IFERROR(M56/M$20,0) -> 0.04 | O56: =O20*'Vessel Assumptions'!$C$30 -> 1167.0384 | P56: =IFERROR(O56/O$20,0) -> 0.04 | Q56: =Q20*'Vessel Assumptions'!$C$30 -> 1167.0384 | R56: =IFERROR(Q56/Q$20,0) -> 0.04 | S56: =S20*'Vessel Assumptions'!$C$30 -> 1167.0384 | T56: =IFERROR(S56/S$20,0) -> 0.04 | U56: =U20*'Vessel Assumptions'!$C$30 -> 1167.0384 | V56: =IFERROR(U56/U$20,0) -> 0.04 | W56: =W20*'Vessel Assumptions'!$C$30 -> 1167.0384 | X56: =IFERROR(W56/W$20,0) -> 0.04 | Y56: =Y20*'Vessel Assumptions'!$C$30 -> 1167.0384 | Z56: =IFERROR(Y56/Y$20,0) -> 0.04 | AB56: =SUM(C56,E56,G56,I56,K56,M56,O56,Q56,S56,U56,W56,Y56) -> 14004.461 | AC56: =IFERROR(AB56/AB$20,0) -> 0.04
A57: Admin Fee (5% of F&B — billed to clients, in income above) | C57: 0 | D57: =IFERROR(C57/C$20,0) -> 0 | E57: 0 | F57: =IFERROR(E57/E$20,0) -> 0 | G57: 0 | H57: =IFERROR(G57/G$20,0) -> 0 | I57: 0 | J57: =IFERROR(I57/I$20,0) -> 0 | K57: 0 | L57: =IFERROR(K57/K$20,0) -> 0 | M57: 0 | N57: =IFERROR(M57/M$20,0) -> 0 | O57: 0 | P57: =IFERROR(O57/O$20,0) -> 0 | Q57: 0 | R57: =IFERROR(Q57/Q$20,0) -> 0 | S57: 0 | T57: =IFERROR(S57/S$20,0) -> 0 | U57: 0 | V57: =IFERROR(U57/U$20,0) -> 0 | W57: 0 | X57: =IFERROR(W57/W$20,0) -> 0 | Y57: 0 | Z57: =IFERROR(Y57/Y$20,0) -> 0 | AB57: =SUM(C57,E57,G57,I57,K57,M57,O57,Q57,S57,U57,W57,Y57) -> 0 | AC57: =IFERROR(AB57/AB$20,0) -> 0
A58: Owner Fee | C58: 0 | D58: =IFERROR(C58/C$20,0) -> 0 | E58: 0 | F58: =IFERROR(E58/E$20,0) -> 0 | G58: 0 | H58: =IFERROR(G58/G$20,0) -> 0 | I58: 0 | J58: =IFERROR(I58/I$20,0) -> 0 | K58: 0 | L58: =IFERROR(K58/K$20,0) -> 0 | M58: 0 | N58: =IFERROR(M58/M$20,0) -> 0 | O58: 0 | P58: =IFERROR(O58/O$20,0) -> 0 | Q58: 0 | R58: =IFERROR(Q58/Q$20,0) -> 0 | S58: 0 | T58: =IFERROR(S58/S$20,0) -> 0 | U58: 0 | V58: =IFERROR(U58/U$20,0) -> 0 | W58: 0 | X58: =IFERROR(W58/W$20,0) -> 0 | Y58: 0 | Z58: =IFERROR(Y58/Y$20,0) -> 0 | AB58: =SUM(C58,E58,G58,I58,K58,M58,O58,Q58,S58,U58,W58,Y58) -> 0 | AC58: =IFERROR(AB58/AB$20,0) -> 0
A59: Business Taxes | C59: 0 | D59: =IFERROR(C59/C$20,0) -> 0 | E59: 0 | F59: =IFERROR(E59/E$20,0) -> 0 | G59: 0 | H59: =IFERROR(G59/G$20,0) -> 0 | I59: 0 | J59: =IFERROR(I59/I$20,0) -> 0 | K59: 0 | L59: =IFERROR(K59/K$20,0) -> 0 | M59: 0 | N59: =IFERROR(M59/M$20,0) -> 0 | O59: 0 | P59: =IFERROR(O59/O$20,0) -> 0 | Q59: 0 | R59: =IFERROR(Q59/Q$20,0) -> 0 | S59: 0 | T59: =IFERROR(S59/S$20,0) -> 0 | U59: 0 | V59: =IFERROR(U59/U$20,0) -> 0 | W59: 0 | X59: =IFERROR(W59/W$20,0) -> 0 | Y59: 0 | Z59: =IFERROR(Y59/Y$20,0) -> 0 | AB59: =SUM(C59,E59,G59,I59,K59,M59,O59,Q59,S59,U59,W59,Y59) -> 0 | AC59: =IFERROR(AB59/AB$20,0) -> 0
A60: Total Uncontrollable Expenses | C60: =SUM(C53:C59) -> 2799.238 | D60: =IFERROR(C60/C$20,0) -> 0.064946237 | E60: =SUM(E53:E59) -> 861.304 | F60: =IFERROR(E60/E$20,0) -> 0.064946237 | G60: =SUM(G53:G59) -> 2799.238 | H60: =IFERROR(G60/G$20,0) -> 0.064946237 | I60: =SUM(I53:I59) -> 861.304 | J60: =IFERROR(I60/I$20,0) -> 0.064946237 | K60: =SUM(K53:K59) -> 2153.26 | L60: =IFERROR(K60/K$20,0) -> 0.064946237 | M60: =SUM(M53:M59) -> 1894.8688 | N60: =IFERROR(M60/M$20,0) -> 0.064946237 | O60: =SUM(O53:O59) -> 1894.8688 | P60: =IFERROR(O60/O$20,0) -> 0.064946237 | Q60: =SUM(Q53:Q59) -> 1894.8688 | R60: =IFERROR(Q60/Q$20,0) -> 0.064946237 | S60: =SUM(S53:S59) -> 1894.8688 | T60: =IFERROR(S60/S$20,0) -> 0.064946237 | U60: =SUM(U53:U59) -> 1894.8688 | V60: =IFERROR(U60/U$20,0) -> 0.064946237 | W60: =SUM(W53:W59) -> 1894.8688 | X60: =IFERROR(W60/W$20,0) -> 0.064946237 | Y60: =SUM(Y53:Y59) -> 1894.8688 | Z60: =IFERROR(Y60/Y$20,0) -> 0.064946237 | AB60: =SUM(AB53:AB59) -> 22738.426 | AC60: =IFERROR(AB60/AB$20,0) -> 0.064946237
A62: Net Operating Profit Before Debt Service | C62: =C41-C50-C60 -> 10724.233 | D62: =IFERROR(C62/C$20,0) -> 0.2488172 | E62: =E41-E50-E60 -> 3299.764 | F62: =IFERROR(E62/E$20,0) -> 0.2488172 | G62: =G41-G50-G60 -> 10724.233 | H62: =IFERROR(G62/G$20,0) -> 0.2488172 | I62: =I41-I50-I60 -> 3299.764 | J62: =IFERROR(I62/I$20,0) -> 0.2488172 | K62: =K41-K50-K60 -> 8249.41 | L62: =IFERROR(K62/K$20,0) -> 0.2488172 | M62: =M41-M50-M60 -> 7259.4808 | N62: =IFERROR(M62/M$20,0) -> 0.2488172 | O62: =O41-O50-O60 -> 7259.4808 | P62: =IFERROR(O62/O$20,0) -> 0.2488172 | Q62: =Q41-Q50-Q60 -> 7259.4808 | R62: =IFERROR(Q62/Q$20,0) -> 0.2488172 | S62: =S41-S50-S60 -> 7259.4808 | T62: =IFERROR(S62/S$20,0) -> 0.2488172 | U62: =U41-U50-U60 -> 7259.4808 | V62: =IFERROR(U62/U$20,0) -> 0.2488172 | W62: =W41-W50-W60 -> 7259.4808 | X62: =IFERROR(W62/W$20,0) -> 0.2488172 | Y62: =Y41-Y50-Y60 -> 7259.4808 | Z62: =IFERROR(Y62/Y$20,0) -> 0.2488172 | AB62: =AB41-AB50-AB60 -> 87113.77 | AC62: =IFERROR(AB62/AB$20,0) -> 0.2488172
A64: Debt Service | C64: 0 | D64: =IFERROR(C64/C$20,0) -> 0 | E64: 0 | F64: =IFERROR(E64/E$20,0) -> 0 | G64: 0 | H64: =IFERROR(G64/G$20,0) -> 0 | I64: 0 | J64: =IFERROR(I64/I$20,0) -> 0 | K64: 0 | L64: =IFERROR(K64/K$20,0) -> 0 | M64: 0 | N64: =IFERROR(M64/M$20,0) -> 0 | O64: 0 | P64: =IFERROR(O64/O$20,0) -> 0 | Q64: 0 | R64: =IFERROR(Q64/Q$20,0) -> 0 | S64: 0 | T64: =IFERROR(S64/S$20,0) -> 0 | U64: 0 | V64: =IFERROR(U64/U$20,0) -> 0 | W64: 0 | X64: =IFERROR(W64/W$20,0) -> 0 | Y64: 0 | Z64: =IFERROR(Y64/Y$20,0) -> 0 | AB64: =SUM(C64,E64,G64,I64,K64,M64,O64,Q64,S64,U64,W64,Y64) -> 0 | AC64: =IFERROR(AB64/AB$20,0) -> 0
A66: Net Operating Profit After Debt Service | C66: =C62-C64 -> 10724.233 | D66: =IFERROR(C66/C$20,0) -> 0.2488172 | E66: =E62-E64 -> 3299.764 | F66: =IFERROR(E66/E$20,0) -> 0.2488172 | G66: =G62-G64 -> 10724.233 | H66: =IFERROR(G66/G$20,0) -> 0.2488172 | I66: =I62-I64 -> 3299.764 | J66: =IFERROR(I66/I$20,0) -> 0.2488172 | K66: =K62-K64 -> 8249.41 | L66: =IFERROR(K66/K$20,0) -> 0.2488172 | M66: =M62-M64 -> 7259.4808 | N66: =IFERROR(M66/M$20,0) -> 0.2488172 | O66: =O62-O64 -> 7259.4808 | P66: =IFERROR(O66/O$20,0) -> 0.2488172 | Q66: =Q62-Q64 -> 7259.4808 | R66: =IFERROR(Q66/Q$20,0) -> 0.2488172 | S66: =S62-S64 -> 7259.4808 | T66: =IFERROR(S66/S$20,0) -> 0.2488172 | U66: =U62-U64 -> 7259.4808 | V66: =IFERROR(U66/U$20,0) -> 0.2488172 | W66: =W62-W64 -> 7259.4808 | X66: =IFERROR(W66/W$20,0) -> 0.2488172 | Y66: =Y62-Y64 -> 7259.4808 | Z66: =IFERROR(Y66/Y$20,0) -> 0.2488172 | AB66: =AB62-AB64 -> 87113.77 | AC66: =IFERROR(AB66/AB$20,0) -> 0.2488172
A68: Other (Income) Expense | C68: 0 | D68: =IFERROR(C68/C$20,0) -> 0 | E68: 0 | F68: =IFERROR(E68/E$20,0) -> 0 | G68: 0 | H68: =IFERROR(G68/G$20,0) -> 0 | I68: 0 | J68: =IFERROR(I68/I$20,0) -> 0 | K68: 0 | L68: =IFERROR(K68/K$20,0) -> 0 | M68: 0 | N68: =IFERROR(M68/M$20,0) -> 0 | O68: 0 | P68: =IFERROR(O68/O$20,0) -> 0 | Q68: 0 | R68: =IFERROR(Q68/Q$20,0) -> 0 | S68: 0 | T68: =IFERROR(S68/S$20,0) -> 0 | U68: 0 | V68: =IFERROR(U68/U$20,0) -> 0 | W68: 0 | X68: =IFERROR(W68/W$20,0) -> 0 | Y68: 0 | Z68: =IFERROR(Y68/Y$20,0) -> 0 | AB68: =SUM(C68,E68,G68,I68,K68,M68,O68,Q68,S68,U68,W68,Y68) -> 0 | AC68: =IFERROR(AB68/AB$20,0) -> 0
A69: Reserve / CapEx | C69: 0 | D69: =IFERROR(C69/C$20,0) -> 0 | E69: 0 | F69: =IFERROR(E69/E$20,0) -> 0 | G69: 0 | H69: =IFERROR(G69/G$20,0) -> 0 | I69: 0 | J69: =IFERROR(I69/I$20,0) -> 0 | K69: 0 | L69: =IFERROR(K69/K$20,0) -> 0 | M69: 0 | N69: =IFERROR(M69/M$20,0) -> 0 | O69: 0 | P69: =IFERROR(O69/O$20,0) -> 0 | Q69: 0 | R69: =IFERROR(Q69/Q$20,0) -> 0 | S69: 0 | T69: =IFERROR(S69/S$20,0) -> 0 | U69: 0 | V69: =IFERROR(U69/U$20,0) -> 0 | W69: 0 | X69: =IFERROR(W69/W$20,0) -> 0 | Y69: 0 | Z69: =IFERROR(Y69/Y$20,0) -> 0 | AB69: =SUM(C69,E69,G69,I69,K69,M69,O69,Q69,S69,U69,W69,Y69) -> 0 | AC69: =IFERROR(AB69/AB$20,0) -> 0
A70: Net Cash Flow | C70: =C66-C68-C69 -> 10724.233 | D70: =IFERROR(C70/C$20,0) -> 0.2488172 | E70: =E66-E68-E69 -> 3299.764 | F70: =IFERROR(E70/E$20,0) -> 0.2488172 | G70: =G66-G68-G69 -> 10724.233 | H70: =IFERROR(G70/G$20,0) -> 0.2488172 | I70: =I66-I68-I69 -> 3299.764 | J70: =IFERROR(I70/I$20,0) -> 0.2488172 | K70: =K66-K68-K69 -> 8249.41 | L70: =IFERROR(K70/K$20,0) -> 0.2488172 | M70: =M66-M68-M69 -> 7259.4808 | N70: =IFERROR(M70/M$20,0) -> 0.2488172 | O70: =O66-O68-O69 -> 7259.4808 | P70: =IFERROR(O70/O$20,0) -> 0.2488172 | Q70: =Q66-Q68-Q69 -> 7259.4808 | R70: =IFERROR(Q70/Q$20,0) -> 0.2488172 | S70: =S66-S68-S69 -> 7259.4808 | T70: =IFERROR(S70/S$20,0) -> 0.2488172 | U70: =U66-U68-U69 -> 7259.4808 | V70: =IFERROR(U70/U$20,0) -> 0.2488172 | W70: =W66-W68-W69 -> 7259.4808 | X70: =IFERROR(W70/W$20,0) -> 0.2488172 | Y70: =Y66-Y68-Y69 -> 7259.4808 | Z70: =IFERROR(Y70/Y$20,0) -> 0.2488172 | AB70: =AB66-AB68-AB69 -> 87113.77 | AC70: =IFERROR(AB70/AB$20,0) -> 0.2488172
A72: 2027 rebuilt on the per-event unit-economics card: $4,650 revenue/event (F&B $3,720 + 20% service fee + 5% admin fee), COGS $1,810, loaded labor $806 (hourly $525 + manager $55 + bonus $112 + PT&B), controllable 12.4%, uncontrollable 2.5%, mgmt fee 4% → NOP $1,157/event × 83 events.

Sheet Vessel Roadmap
A1: Vessel
A2: Roadmap at ~25% NOP — 2027 (Immediate) grown by the two rate inputs below
A4: GROWTH INPUTS (per year)
A5: Events added per year | B5: 10 | C5: volume build: +10 events each year toward the ~125–130 stabilized calendar
A6: Avg revenue / event growth %/yr | B6: 0.06 | C6: the driver: larger average events (minimums, upsells), not volume
B8: 2027 · IMMEDIATE | C8: 2028 · BUILDING | D8: 2029 · STABILIZED
A9: Annual events | B9: ='Vessel Budget'!$AB$9 -> 75.2928 | C9: =B9+$B$5 -> 85.2928 | D9: =C9+$B$5 -> 95.2928
A10: Avg. revenue / event | B10: ='Vessel Budget'!$AB$20/'Vessel Budget'!$AB$9 -> 4650 | C10: =B10*(1+$B$6) -> 4929 | D10: =C10*(1+$B$6) -> 5224.74
A11: Annual revenue | B11: =B9*B10 -> 350111.52 | C11: =C9*C10 -> 420408.21 | D11: =D9*D10 -> 497880.1
A12: NOI margin (per-event card) | B12: ='Vessel Budget'!$AB$62/'Vessel Budget'!$AB$20 -> 0.2488172 | C12: =$B$12 -> 0.2488172 | D12: =$B$12 -> 0.2488172
A13: Annual NOP | B13: =B11*B12 -> 87113.77 | C13: =C11*C12 -> 104604.8 | D13: =D11*D12 -> 123881.14
A15: 2027 links live to the Vessel Budget (per-event card: $4,650 revenue · $1,157 NOP · 24.9% margin — margin holds at any volume). Roadmap: +10 events per year and +6%/yr average event revenue → stabilized in year 3 (2029): ~95 events, ~$498K revenue, ~$124K NOP at 25%. Growth comes from both a fuller calendar and larger average events, generating incremental ROOST room sales.

Sheet Vessel GL Basis
A1: VESSEL — GL COST BASIS
A2: Cost basis now linked to Vessel 2026 P&L (Act/For) · controllable vs non-controllable (CC fees excluded)
B4: Expense group | C4: Annual | D4: Monthly
B6: LABOR (in model)
B8: Management labor – FOH mgmt (610300) | C8: ='Vessel 2026 P&L'!$AB$28 -> 17230 | D8: =C8/12 -> 1435.8333
B10: CONTROLLABLE (excl credit card fees)
B11: Direct operating (supplies, linen, equip) | C11: 18543 | D11: =C11/12 -> 1545.25
B12: G&A / accounting / bank | C12: 30300 | D12: =C12/12 -> 2525
B13: Marketing | C13: 13917 | D13: =C13/12 -> 1159.75
B14: Music & entertainment | C14: 6750 | D14: =C14/12 -> 562.5
B15: Repairs & maintenance | C15: 5748 | D15: =C15/12 -> 479
B16: Utilities | C16: 5602 | D16: =C16/12 -> 466.83333
B17: Total controllable (excl CC) | C17: =SUM(C11:C16) -> 80860 | D17: =C17/12 -> 6738.3333
B18: → Controllable / month feed | C18: ='Vessel 2026 P&L'!$AB$44 -> 80624 | D18: =C18/12 -> 6718.6667
B20: NON-CONTROLLABLE (in model)
B21: Insurance – liability | C21: 2106 | D21: =C21/12 -> 175.5
B22: Legal & accounting | C22: 1800 | D22: =C22/12 -> 150
B23: Replacement reserves | C23: 4855 | D23: =C23/12 -> 404.58333
B24: Total non-controllable | C24: ='Vessel 2026 P&L'!$AB$47+'Vessel 2026 P&L'!$AB$49+'Vessel 2026 P&L'!$AB$51+'Vessel 2026 P&L'!$AB$52 -> 12545 | D24: =C24/12 -> 1045.4167
B26: VARIABLE / EXCLUDED
B27: Credit card fees (actual GL → now variable 2.5%) | C27: 2745 | D27: =C27/12 -> 228.75
B28: Management fee (→ profit split) | C28: 48000 | D28: =C28/12 -> 4000
B29: Rent / RE tax (owner) | C29: ='Vessel 2026 P&L'!$AB$48 -> 21341 | D29: =C29/12 -> 1778.4167

Sheet Vessel 2026 P&L
A1: Vessel
A2: Profit & Loss Summary
A3: 2026
C5: January | E5: February | G5: March | I5: April | K5: May | M5: June | O5: July | Q5: August | S5: September | U5: October | W5: November | Y5: December | AB5: 2026
C6: Actual | E6: Actual | G6: Actual | I6: Actual | K6: Actual | M6: Actual | O6: Forecast | Q6: Forecast | S6: Forecast | U6: Forecast | W6: Forecast | Y6: Forecast | AB6: Act/For/Bud
C7: Amount $ | D7: % | E7: Amount $ | F7: % | G7: Amount $ | H7: % | I7: Amount $ | J7: % | K7: Amount $ | L7: % | M7: Amount $ | N7: % | O7: Amount $ | P7: % | Q7: Amount $ | R7: % | S7: Amount $ | T7: % | U7: Amount $ | V7: % | W7: Amount $ | X7: % | Y7: Amount $ | Z7: % | AB7: Amount $ | AC7: %
A8: Income
A9: Food Sales | C9: 28343 | D9: =IFERROR(C9/C$16,0) -> 0.74355947 | E9: 9119 | F9: =IFERROR(E9/E$16,0) -> 0.54630961 | G9: 21950 | H9: =IFERROR(G9/G$16,0) -> 0.55143826 | I9: 4645 | J9: =IFERROR(I9/I$16,0) -> 0.37079907 | K9: 14241 | L9: =IFERROR(K9/K$16,0) -> 0.34785901 | M9: 15390 | N9: =IFERROR(M9/M$16,0) -> 0.33585754 | O9: 11504 | P9: =IFERROR(O9/O$16,0) -> 0.34786816 | Q9: 8697 | R9: =IFERROR(Q9/Q$16,0) -> 0.34786609 | S9: 8697 | T9: =IFERROR(S9/S$16,0) -> 0.34786609 | U9: 6957 | V9: =IFERROR(U9/U$16,0) -> 0.34785 | W9: 6957 | X9: =IFERROR(W9/W$16,0) -> 0.34785 | Y9: 12175 | Z9: =IFERROR(Y9/Y$16,0) -> 0.34786708 | AB9: =SUM(C9,E9,G9,I9,K9,M9,O9,Q9,S9,U9,W9,Y9) -> 148675 | AC9: =IFERROR(AB9/AB$16,0) -> 0.42240216
A10: Non-Alcoholic Beverage Sales | C10: 5992 | D10: =IFERROR(C10/C$16,0) -> 0.15719608 | E10: 4542 | F10: =IFERROR(E10/E$16,0) -> 0.2721064 | G10: 3907 | H10: =IFERROR(G10/G$16,0) -> 0.098153498 | I10: 1012 | J10: =IFERROR(I10/I$16,0) -> 0.080785503 | K10: 2090 | L10: =IFERROR(K10/K$16,0) -> 0.051051565 | M10: 2193 | N10: =IFERROR(M10/M$16,0) -> 0.047858063 | O10: 1688 | P10: =IFERROR(O10/O$16,0) -> 0.051043242 | Q10: 1276 | R10: =IFERROR(Q10/Q$16,0) -> 0.051037958 | S10: 1276 | T10: =IFERROR(S10/S$16,0) -> 0.051037958 | U10: 1021 | V10: =IFERROR(U10/U$16,0) -> 0.05105 | W10: 1021 | X10: =IFERROR(W10/W$16,0) -> 0.05105 | Y10: 1786 | Z10: =IFERROR(Y10/Y$16,0) -> 0.051030029 | AB10: =SUM(C10,E10,G10,I10,K10,M10,O10,Q10,S10,U10,W10,Y10) -> 27804 | AC10: =IFERROR(AB10/AB$16,0) -> 0.078994247
A11: Liquor Sales | C11: 1351 | D11: =IFERROR(C11/C$16,0) -> 0.035442573 | E11: 2141 | F11: =IFERROR(E11/E$16,0) -> 0.12826504 | G11: 10278 | H11: =IFERROR(G11/G$16,0) -> 0.25820877 | I11: 1836 | J11: =IFERROR(I11/I$16,0) -> 0.14656342 | K11: 5557 | L11: =IFERROR(K11/K$16,0) -> 0.13573854 | M11: 4142 | N11: =IFERROR(M11/M$16,0) -> 0.090391288 | O11: 4489 | P11: =IFERROR(O11/O$16,0) -> 0.13574236 | Q11: 3394 | R11: =IFERROR(Q11/Q$16,0) -> 0.13575457 | S11: 3394 | T11: =IFERROR(S11/S$16,0) -> 0.13575457 | U11: 2715 | V11: =IFERROR(U11/U$16,0) -> 0.13575 | W11: 2715 | X11: =IFERROR(W11/W$16,0) -> 0.13575 | Y11: 4751 | Z11: =IFERROR(Y11/Y$16,0) -> 0.13574674 | AB11: =SUM(C11,E11,G11,I11,K11,M11,O11,Q11,S11,U11,W11,Y11) -> 46763 | AC11: =IFERROR(AB11/AB$16,0) -> 0.13285887
A12: Beer Sales | C12: 40 | D12: =IFERROR(C12/C$16,0) -> 0.001049373 | E12: 0 | F12: =IFERROR(E12/E$16,0) -> 0 | G12: 187 | H12: =IFERROR(G12/G$16,0) -> 0.0046979023 | I12: 34 | J12: =IFERROR(I12/I$16,0) -> 0.0027141375 | K12: 193 | L12: =IFERROR(K12/K$16,0) -> 0.0047143311 | M12: 525 | N12: =IFERROR(M12/M$16,0) -> 0.011457129 | O12: 156 | P12: =IFERROR(O12/O$16,0) -> 0.0047172664 | Q12: 118 | R12: =IFERROR(Q12/Q$16,0) -> 0.0047198112 | S12: 118 | T12: =IFERROR(S12/S$16,0) -> 0.0047198112 | U12: 94 | V12: =IFERROR(U12/U$16,0) -> 0.0047 | W12: 94 | X12: =IFERROR(W12/W$16,0) -> 0.0047 | Y12: 165 | Z12: =IFERROR(Y12/Y$16,0) -> 0.0047144204 | AB12: =SUM(C12,E12,G12,I12,K12,M12,O12,Q12,S12,U12,W12,Y12) -> 1724 | AC12: =IFERROR(AB12/AB$16,0) -> 0.0048980751
A13: Wine Sales | C13: 758 | D13: =IFERROR(C13/C$16,0) -> 0.019885618 | E13: 471 | F13: =IFERROR(E13/E$16,0) -> 0.02821711 | G13: 729 | H13: =IFERROR(G13/G$16,0) -> 0.018314282 | I13: 426 | J13: =IFERROR(I13/I$16,0) -> 0.034006546 | K13: 770 | L13: =IFERROR(K13/K$16,0) -> 0.018808471 | M13: 434 | N13: =IFERROR(M13/M$16,0) -> 0.0094712262 | O13: 622 | P13: =IFERROR(O13/O$16,0) -> 0.018808588 | Q13: 470 | R13: =IFERROR(Q13/Q$16,0) -> 0.018799248 | S13: 470 | T13: =IFERROR(S13/S$16,0) -> 0.018799248 | U13: 376 | V13: =IFERROR(U13/U$16,0) -> 0.0188 | W13: 376 | X13: =IFERROR(W13/W$16,0) -> 0.0188 | Y13: 658 | Z13: =IFERROR(Y13/Y$16,0) -> 0.018800537 | AB13: =SUM(C13,E13,G13,I13,K13,M13,O13,Q13,S13,U13,W13,Y13) -> 6560 | AC13: =IFERROR(AB13/AB$16,0) -> 0.018637687
A14: Other Operating Income | C14: 3280 | D14: =IFERROR(C14/C$16,0) -> 0.086048586 | E14: 419 | F14: =IFERROR(E14/E$16,0) -> 0.025101845 | G14: 2754 | H14: =IFERROR(G14/G$16,0) -> 0.069187288 | I14: 4574 | J14: =IFERROR(I14/I$16,0) -> 0.36513132 | K14: 18088 | L14: =IFERROR(K14/K$16,0) -> 0.44182809 | M14: 23139 | N14: =IFERROR(M14/M$16,0) -> 0.50496476 | O14: 14611 | P14: =IFERROR(O14/O$16,0) -> 0.44182038 | Q14: 11046 | R14: =IFERROR(Q14/Q$16,0) -> 0.44182233 | S14: 11046 | T14: =IFERROR(S14/S$16,0) -> 0.44182233 | U14: 8837 | V14: =IFERROR(U14/U$16,0) -> 0.44185 | W14: 8837 | X14: =IFERROR(W14/W$16,0) -> 0.44185 | Y14: 15464 | Z14: =IFERROR(Y14/Y$16,0) -> 0.4418412 | AB14: =SUM(C14,E14,G14,I14,K14,M14,O14,Q14,S14,U14,W14,Y14) -> 122095 | AC14: =IFERROR(AB14/AB$16,0) -> 0.34688543
A15: Discounts & Comps | C15: -1646 | D15: =IFERROR(C15/C$16,0) -> -0.043181699 | E15: 0 | F15: =IFERROR(E15/E$16,0) -> 0 | G15: 0 | H15: =IFERROR(G15/G$16,0) -> 0 | I15: 0 | J15: =IFERROR(I15/I$16,0) -> 0 | K15: 0 | L15: =IFERROR(K15/K$16,0) -> 0 | M15: 0 | N15: =IFERROR(M15/M$16,0) -> 0 | O15: 0 | P15: =IFERROR(O15/O$16,0) -> 0 | Q15: 0 | R15: =IFERROR(Q15/Q$16,0) -> 0 | S15: 0 | T15: =IFERROR(S15/S$16,0) -> 0 | U15: 0 | V15: =IFERROR(U15/U$16,0) -> 0 | W15: 0 | X15: =IFERROR(W15/W$16,0) -> 0 | Y15: 0 | Z15: =IFERROR(Y15/Y$16,0) -> 0 | AB15: =SUM(C15,E15,G15,I15,K15,M15,O15,Q15,S15,U15,W15,Y15) -> -1646 | AC15: =IFERROR(AB15/AB$16,0) -> -0.0046764685
A16: Total Income | C16: =SUM(C9:C15) -> 38118 | D16: =IFERROR(C16/C$16,0) -> 1 | E16: =SUM(E9:E15) -> 16692 | F16: =IFERROR(E16/E$16,0) -> 1 | G16: =SUM(G9:G15) -> 39805 | H16: =IFERROR(G16/G$16,0) -> 1 | I16: =SUM(I9:I15) -> 12527 | J16: =IFERROR(I16/I$16,0) -> 1 | K16: =SUM(K9:K15) -> 40939 | L16: =IFERROR(K16/K$16,0) -> 1 | M16: =SUM(M9:M15) -> 45823 | N16: =IFERROR(M16/M$16,0) -> 1 | O16: =SUM(O9:O15) -> 33070 | P16: =IFERROR(O16/O$16,0) -> 1 | Q16: =SUM(Q9:Q15) -> 25001 | R16: =IFERROR(Q16/Q$16,0) -> 1 | S16: =SUM(S9:S15) -> 25001 | T16: =IFERROR(S16/S$16,0) -> 1 | U16: =SUM(U9:U15) -> 20000 | V16: =IFERROR(U16/U$16,0) -> 1 | W16: =SUM(W9:W15) -> 20000 | X16: =IFERROR(W16/W$16,0) -> 1 | Y16: =SUM(Y9:Y15) -> 34999 | Z16: =IFERROR(Y16/Y$16,0) -> 1 | AB16: =SUM(AB9:AB15) -> 351975 | AC16: =IFERROR(AB16/AB$16,0) -> 1
A18: Cost of Goods Sold
A19: Food Cost | C19: 18631 | D19: =IFERROR(C19/C$9,0) -> 0.65734044 | E19: 8386 | F19: =IFERROR(E19/E$9,0) -> 0.91961838 | G19: 14740 | H19: =IFERROR(G19/G$9,0) -> 0.6715262 | I19: 4280 | J19: =IFERROR(I19/I$9,0) -> 0.92142088 | K19: 11232 | L19: =IFERROR(K19/K$9,0) -> 0.78870866 | M19: 10735 | N19: =IFERROR(M19/M$9,0) -> 0.69753086 | O19: 7478 | P19: =IFERROR(O19/O$9,0) -> 0.65003477 | Q19: 5653 | R19: =IFERROR(Q19/Q$9,0) -> 0.64999425 | S19: 5653 | T19: =IFERROR(S19/S$9,0) -> 0.64999425 | U19: 4522 | V19: =IFERROR(U19/U$9,0) -> 0.64999281 | W19: 4522 | X19: =IFERROR(W19/W$9,0) -> 0.64999281 | Y19: 7914 | Z19: =IFERROR(Y19/Y$9,0) -> 0.65002053 | AB19: =SUM(C19,E19,G19,I19,K19,M19,O19,Q19,S19,U19,W19,Y19) -> 103746 | AC19: =IFERROR(AB19/AB$9,0) -> 0.69780393
A20: Non-Alcoholic Beverage Cost | C20: 1198 | D20: =IFERROR(C20/C$10,0) -> 0.19993324 | E20: 895 | F20: =IFERROR(E20/E$10,0) -> 0.19704976 | G20: 1888 | H20: =IFERROR(G20/G$10,0) -> 0.48323522 | I20: 0 | J20: =IFERROR(I20/I$10,0) -> 0 | K20: 0 | L20: =IFERROR(K20/K$10,0) -> 0 | M20: 0 | N20: =IFERROR(M20/M$10,0) -> 0 | O20: 506 | P20: =IFERROR(O20/O$10,0) -> 0.29976303 | Q20: 383 | R20: =IFERROR(Q20/Q$10,0) -> 0.30015674 | S20: 383 | T20: =IFERROR(S20/S$10,0) -> 0.30015674 | U20: 306 | V20: =IFERROR(U20/U$10,0) -> 0.29970617 | W20: 306 | X20: =IFERROR(W20/W$10,0) -> 0.29970617 | Y20: 536 | Z20: =IFERROR(Y20/Y$10,0) -> 0.30011198 | AB20: =SUM(C20,E20,G20,I20,K20,M20,O20,Q20,S20,U20,W20,Y20) -> 6401 | AC20: =IFERROR(AB20/AB$10,0) -> 0.23021867
A21: Liquor Cost | C21: 243 | D21: =IFERROR(C21/C$11,0) -> 0.17986677 | E21: 931 | F21: =IFERROR(E21/E$11,0) -> 0.43484353 | G21: 723 | H21: =IFERROR(G21/G$11,0) -> 0.070344425 | I21: 0 | J21: =IFERROR(I21/I$11,0) -> 0 | K21: 1308 | L21: =IFERROR(K21/K$11,0) -> 0.2353788 | M21: 5238 | N21: =IFERROR(M21/M$11,0) -> 1.2646065 | O21: 0 | P21: =IFERROR(O21/O$11,0) -> 0 | Q21: 0 | R21: =IFERROR(Q21/Q$11,0) -> 0 | S21: 0 | T21: =IFERROR(S21/S$11,0) -> 0 | U21: 0 | V21: =IFERROR(U21/U$11,0) -> 0 | W21: 0 | X21: =IFERROR(W21/W$11,0) -> 0 | Y21: 0 | Z21: =IFERROR(Y21/Y$11,0) -> 0 | AB21: =SUM(C21,E21,G21,I21,K21,M21,O21,Q21,S21,U21,W21,Y21) -> 8443 | AC21: =IFERROR(AB21/AB$11,0) -> 0.18054872
A22: Beer Cost | C22: 8 | D22: =IFERROR(C22/C$12,0) -> 0.2 | E22: 707 | F22: =IFERROR(E22/E$12,0) -> 0 | G22: 239 | H22: =IFERROR(G22/G$12,0) -> 1.2780749 | I22: 0 | J22: =IFERROR(I22/I$12,0) -> 0 | K22: 0 | L22: =IFERROR(K22/K$12,0) -> 0 | M22: 180 | N22: =IFERROR(M22/M$12,0) -> 0.34285714 | O22: 47 | P22: =IFERROR(O22/O$12,0) -> 0.30128205 | Q22: 35 | R22: =IFERROR(Q22/Q$12,0) -> 0.29661017 | S22: 35 | T22: =IFERROR(S22/S$12,0) -> 0.29661017 | U22: 29 | V22: =IFERROR(U22/U$12,0) -> 0.30851064 | W22: 29 | X22: =IFERROR(W22/W$12,0) -> 0.30851064 | Y22: 49 | Z22: =IFERROR(Y22/Y$12,0) -> 0.2969697 | AB22: =SUM(C22,E22,G22,I22,K22,M22,O22,Q22,S22,U22,W22,Y22) -> 1358 | AC22: =IFERROR(AB22/AB$12,0) -> 0.78770302
A23: Wine/Sake Cost | C23: 190 | D23: =IFERROR(C23/C$13,0) -> 0.25065963 | E23: 888 | F23: =IFERROR(E23/E$13,0) -> 1.8853503 | G23: 699 | H23: =IFERROR(G23/G$13,0) -> 0.95884774 | I23: 252 | J23: =IFERROR(I23/I$13,0) -> 0.5915493 | K23: 404 | L23: =IFERROR(K23/K$13,0) -> 0.52467532 | M23: 551 | N23: =IFERROR(M23/M$13,0) -> 1.2695853 | O23: 0 | P23: =IFERROR(O23/O$13,0) -> 0 | Q23: 0 | R23: =IFERROR(Q23/Q$13,0) -> 0 | S23: 0 | T23: =IFERROR(S23/S$13,0) -> 0 | U23: 0 | V23: =IFERROR(U23/U$13,0) -> 0 | W23: 0 | X23: =IFERROR(W23/W$13,0) -> 0 | Y23: 0 | Z23: =IFERROR(Y23/Y$13,0) -> 0 | AB23: =SUM(C23,E23,G23,I23,K23,M23,O23,Q23,S23,U23,W23,Y23) -> 2984 | AC23: =IFERROR(AB23/AB$13,0) -> 0.45487805
A24: Total COGS | C24: =SUM(C19:C23) -> 20270 | D24: =IFERROR(C24/C$16,0) -> 0.53176977 | E24: =SUM(E19:E23) -> 11807 | F24: =IFERROR(E24/E$16,0) -> 0.70734484 | G24: =SUM(G19:G23) -> 18289 | H24: =IFERROR(G24/G$16,0) -> 0.45946489 | I24: =SUM(I19:I23) -> 4532 | J24: =IFERROR(I24/I$16,0) -> 0.36177856 | K24: =SUM(K19:K23) -> 12944 | L24: =IFERROR(K24/K$16,0) -> 0.31617773 | M24: =SUM(M19:M23) -> 16704 | N24: =IFERROR(M24/M$16,0) -> 0.36453309 | O24: =SUM(O19:O23) -> 8031 | P24: =IFERROR(O24/O$16,0) -> 0.2428485 | Q24: =SUM(Q19:Q23) -> 6071 | R24: =IFERROR(Q24/Q$16,0) -> 0.24283029 | S24: =SUM(S19:S23) -> 6071 | T24: =IFERROR(S24/S$16,0) -> 0.24283029 | U24: =SUM(U19:U23) -> 4857 | V24: =IFERROR(U24/U$16,0) -> 0.24285 | W24: =SUM(W19:W23) -> 4857 | X24: =IFERROR(W24/W$16,0) -> 0.24285 | Y24: =SUM(Y19:Y23) -> 8499 | Z24: =IFERROR(Y24/Y$16,0) -> 0.24283551 | AB24: =SUM(AB19:AB23) -> 122932 | AC24: =IFERROR(AB24/AB$16,0) -> 0.34926344
A25: Gross Profit | C25: =C16-C24 -> 17848 | D25: =IFERROR(C25/C$16,0) -> 0.46823023 | E25: =E16-E24 -> 4885 | F25: =IFERROR(E25/E$16,0) -> 0.29265516 | G25: =G16-G24 -> 21516 | H25: =IFERROR(G25/G$16,0) -> 0.54053511 | I25: =I16-I24 -> 7995 | J25: =IFERROR(I25/I$16,0) -> 0.63822144 | K25: =K16-K24 -> 27995 | L25: =IFERROR(K25/K$16,0) -> 0.68382227 | M25: =M16-M24 -> 29119 | N25: =IFERROR(M25/M$16,0) -> 0.63546691 | O25: =O16-O24 -> 25039 | P25: =IFERROR(O25/O$16,0) -> 0.7571515 | Q25: =Q16-Q24 -> 18930 | R25: =IFERROR(Q25/Q$16,0) -> 0.75716971 | S25: =S16-S24 -> 18930 | T25: =IFERROR(S25/S$16,0) -> 0.75716971 | U25: =U16-U24 -> 15143 | V25: =IFERROR(U25/U$16,0) -> 0.75715 | W25: =W16-W24 -> 15143 | X25: =IFERROR(W25/W$16,0) -> 0.75715 | Y25: =Y16-Y24 -> 26500 | Z25: =IFERROR(Y25/Y$16,0) -> 0.75716449 | AB25: =AB16-AB24 -> 229043 | AC25: =IFERROR(AB25/AB$16,0) -> 0.65073656
A27: Labor Cost
A28: Management Labor | C28: 1230 | D28: =IFERROR(C28/C$16,0) -> 0.03226822 | E28: 615 | F28: =IFERROR(E28/E$16,0) -> 0.036843997 | G28: 1277 | H28: =IFERROR(G28/G$16,0) -> 0.032081397 | I28: 1132 | J28: =IFERROR(I28/I$16,0) -> 0.090364812 | K28: 1657 | L28: =IFERROR(K28/K$16,0) -> 0.040474853 | M28: 1377 | N28: =IFERROR(M28/M$16,0) -> 0.030050411 | O28: 1657 | P28: =IFERROR(O28/O$16,0) -> 0.050105836 | Q28: 1657 | R28: =IFERROR(Q28/Q$16,0) -> 0.066277349 | S28: 1657 | T28: =IFERROR(S28/S$16,0) -> 0.066277349 | U28: 1657 | V28: =IFERROR(U28/U$16,0) -> 0.08285 | W28: 1657 | X28: =IFERROR(W28/W$16,0) -> 0.08285 | Y28: 1657 | Z28: =IFERROR(Y28/Y$16,0) -> 0.04734421 | AB28: =SUM(C28,E28,G28,I28,K28,M28,O28,Q28,S28,U28,W28,Y28) -> 17230 | AC28: =IFERROR(AB28/AB$16,0) -> 0.04895234
A29: Back of House Hourly Labor | C29: 1097 | D29: =IFERROR(C29/C$16,0) -> 0.028779055 | E29: 2016 | F29: =IFERROR(E29/E$16,0) -> 0.12077642 | G29: 1928 | H29: =IFERROR(G29/G$16,0) -> 0.048436126 | I29: 584 | J29: =IFERROR(I29/I$16,0) -> 0.046619302 | K29: 0 | L29: =IFERROR(K29/K$16,0) -> 0 | M29: -1 | N29: =IFERROR(M29/M$16,0) -> -2.1823102e-05 | O29: 0 | P29: =IFERROR(O29/O$16,0) -> 0 | Q29: 0 | R29: =IFERROR(Q29/Q$16,0) -> 0 | S29: 0 | T29: =IFERROR(S29/S$16,0) -> 0 | U29: 0 | V29: =IFERROR(U29/U$16,0) -> 0 | W29: 0 | X29: =IFERROR(W29/W$16,0) -> 0 | Y29: 0 | Z29: =IFERROR(Y29/Y$16,0) -> 0 | AB29: =SUM(C29,E29,G29,I29,K29,M29,O29,Q29,S29,U29,W29,Y29) -> 5624 | AC29: =IFERROR(AB29/AB$16,0) -> 0.015978408
A30: Front of House Hourly Labor | C30: 1384 | D30: =IFERROR(C30/C$16,0) -> 0.036308306 | E30: 1502 | F30: =IFERROR(E30/E$16,0) -> 0.089983225 | G30: 5284 | H30: =IFERROR(G30/G$16,0) -> 0.13274714 | I30: 0 | J30: =IFERROR(I30/I$16,0) -> 0 | K30: 8918 | L30: =IFERROR(K30/K$16,0) -> 0.21783629 | M30: 10928 | N30: =IFERROR(M30/M$16,0) -> 0.23848286 | O30: 5384 | P30: =IFERROR(O30/O$16,0) -> 0.16280617 | Q30: 2500 | R30: =IFERROR(Q30/Q$16,0) -> 0.099996 | S30: 2500 | T30: =IFERROR(S30/S$16,0) -> 0.099996 | U30: 2000 | V30: =IFERROR(U30/U$16,0) -> 0.1 | W30: 2000 | X30: =IFERROR(W30/W$16,0) -> 0.1 | Y30: 3500 | Z30: =IFERROR(Y30/Y$16,0) -> 0.10000286 | AB30: =SUM(C30,E30,G30,I30,K30,M30,O30,Q30,S30,U30,W30,Y30) -> 45900 | AC30: =IFERROR(AB30/AB$16,0) -> 0.13040699
A31: Payroll Taxes & Benefits | C31: 303 | D31: =IFERROR(C31/C$16,0) -> 0.0079490005 | E31: 1318 | F31: =IFERROR(E31/E$16,0) -> 0.078959981 | G31: 842 | H31: =IFERROR(G31/G$16,0) -> 0.021153121 | I31: 479 | J31: =IFERROR(I31/I$16,0) -> 0.038237407 | K31: 1667 | L31: =IFERROR(K31/K$16,0) -> 0.040719119 | M31: 1248 | N31: =IFERROR(M31/M$16,0) -> 0.027235231 | O31: 257 | P31: =IFERROR(O31/O$16,0) -> 0.007771394 | Q31: 257 | R31: =IFERROR(Q31/Q$16,0) -> 0.010279589 | S31: 257 | T31: =IFERROR(S31/S$16,0) -> 0.010279589 | U31: 257 | V31: =IFERROR(U31/U$16,0) -> 0.01285 | W31: 257 | X31: =IFERROR(W31/W$16,0) -> 0.01285 | Y31: 257 | Z31: =IFERROR(Y31/Y$16,0) -> 0.0073430669 | AB31: =SUM(C31,E31,G31,I31,K31,M31,O31,Q31,S31,U31,W31,Y31) -> 7399 | AC31: =IFERROR(AB31/AB$16,0) -> 0.021021379
A32: Bonus | C32: 313 | D32: =IFERROR(C32/C$16,0) -> 0.0082113437 | E32: 311 | F32: =IFERROR(E32/E$16,0) -> 0.01863168 | G32: 380 | H32: =IFERROR(G32/G$16,0) -> 0.0095465394 | I32: 380 | J32: =IFERROR(I32/I$16,0) -> 0.030334478 | K32: 551 | L32: =IFERROR(K32/K$16,0) -> 0.013459049 | M32: 1598 | N32: =IFERROR(M32/M$16,0) -> 0.034873317 | O32: 58 | P32: =IFERROR(O32/O$16,0) -> 0.0017538555 | Q32: 58 | R32: =IFERROR(Q32/Q$16,0) -> 0.0023199072 | S32: 58 | T32: =IFERROR(S32/S$16,0) -> 0.0023199072 | U32: 58 | V32: =IFERROR(U32/U$16,0) -> 0.0029 | W32: 58 | X32: =IFERROR(W32/W$16,0) -> 0.0029 | Y32: 58 | Z32: =IFERROR(Y32/Y$16,0) -> 0.0016571902 | AB32: =SUM(C32,E32,G32,I32,K32,M32,O32,Q32,S32,U32,W32,Y32) -> 3881 | AC32: =IFERROR(AB32/AB$16,0) -> 0.011026351
A33: Total Labor Cost | C33: =SUM(C28:C32) -> 4327 | D33: =IFERROR(C33/C$16,0) -> 0.11351592 | E33: =SUM(E28:E32) -> 5762 | F33: =IFERROR(E33/E$16,0) -> 0.3451953 | G33: =SUM(G28:G32) -> 9711 | H33: =IFERROR(G33/G$16,0) -> 0.24396433 | I33: =SUM(I28:I32) -> 2575 | J33: =IFERROR(I33/I$16,0) -> 0.205556 | K33: =SUM(K28:K32) -> 12793 | L33: =IFERROR(K33/K$16,0) -> 0.31248931 | M33: =SUM(M28:M32) -> 15150 | N33: =IFERROR(M33/M$16,0) -> 0.33061999 | O33: =SUM(O28:O32) -> 7356 | P33: =IFERROR(O33/O$16,0) -> 0.22243725 | Q33: =SUM(Q28:Q32) -> 4472 | R33: =IFERROR(Q33/Q$16,0) -> 0.17887285 | S33: =SUM(S28:S32) -> 4472 | T33: =IFERROR(S33/S$16,0) -> 0.17887285 | U33: =SUM(U28:U32) -> 3972 | V33: =IFERROR(U33/U$16,0) -> 0.1986 | W33: =SUM(W28:W32) -> 3972 | X33: =IFERROR(W33/W$16,0) -> 0.1986 | Y33: =SUM(Y28:Y32) -> 5472 | Z33: =IFERROR(Y33/Y$16,0) -> 0.15634732 | AB33: =SUM(AB28:AB32) -> 80034 | AC33: =IFERROR(AB33/AB$16,0) -> 0.22738547
A35: Prime Costs | C35: =C24+C33 -> 24597 | D35: =IFERROR(C35/C$16,0) -> 0.64528569 | E35: =E24+E33 -> 17569 | F35: =IFERROR(E35/E$16,0) -> 1.0525401 | G35: =G24+G33 -> 28000 | H35: =IFERROR(G35/G$16,0) -> 0.70342922 | I35: =I24+I33 -> 7107 | J35: =IFERROR(I35/I$16,0) -> 0.56733456 | K35: =K24+K33 -> 25737 | L35: =IFERROR(K35/K$16,0) -> 0.62866704 | M35: =M24+M33 -> 31854 | N35: =IFERROR(M35/M$16,0) -> 0.69515309 | O35: =O24+O33 -> 15387 | P35: =IFERROR(O35/O$16,0) -> 0.46528576 | Q35: =Q24+Q33 -> 10543 | R35: =IFERROR(Q35/Q$16,0) -> 0.42170313 | S35: =S24+S33 -> 10543 | T35: =IFERROR(S35/S$16,0) -> 0.42170313 | U35: =U24+U33 -> 8829 | V35: =IFERROR(U35/U$16,0) -> 0.44145 | W35: =W24+W33 -> 8829 | X35: =IFERROR(W35/W$16,0) -> 0.44145 | Y35: =Y24+Y33 -> 13971 | Z35: =IFERROR(Y35/Y$16,0) -> 0.39918283 | AB35: =AB24+AB33 -> 202966 | AC35: =IFERROR(AB35/AB$16,0) -> 0.57664891
A36: Operating Profit | C36: =C25-C33 -> 13521 | D36: =IFERROR(C36/C$16,0) -> 0.35471431 | E36: =E25-E33 -> -877 | F36: =IFERROR(E36/E$16,0) -> -0.052540139 | G36: =G25-G33 -> 11805 | H36: =IFERROR(G36/G$16,0) -> 0.29657078 | I36: =I25-I33 -> 5420 | J36: =IFERROR(I36/I$16,0) -> 0.43266544 | K36: =K25-K33 -> 15202 | L36: =IFERROR(K36/K$16,0) -> 0.37133296 | M36: =M25-M33 -> 13969 | N36: =IFERROR(M36/M$16,0) -> 0.30484691 | O36: =O25-O33 -> 17683 | P36: =IFERROR(O36/O$16,0) -> 0.53471424 | Q36: =Q25-Q33 -> 14458 | R36: =IFERROR(Q36/Q$16,0) -> 0.57829687 | S36: =S25-S33 -> 14458 | T36: =IFERROR(S36/S$16,0) -> 0.57829687 | U36: =U25-U33 -> 11171 | V36: =IFERROR(U36/U$16,0) -> 0.55855 | W36: =W25-W33 -> 11171 | X36: =IFERROR(W36/W$16,0) -> 0.55855 | Y36: =Y25-Y33 -> 21028 | Z36: =IFERROR(Y36/Y$16,0) -> 0.60081717 | AB36: =AB25-AB33 -> 149009 | AC36: =IFERROR(AB36/AB$16,0) -> 0.42335109
A38: Controllable Expenses
A39: Operating Expenses | C39: 1631 | D39: =IFERROR(C39/C$16,0) -> 0.042788184 | E39: 1306 | F39: =IFERROR(E39/E$16,0) -> 0.078241074 | G39: 3262 | H39: =IFERROR(G39/G$16,0) -> 0.081949504 | I39: 580 | J39: =IFERROR(I39/I$16,0) -> 0.046299992 | K39: 947 | L39: =IFERROR(K39/K$16,0) -> 0.023131977 | M39: 929 | N39: =IFERROR(M39/M$16,0) -> 0.020273662 | O39: 1262 | P39: =IFERROR(O39/O$16,0) -> 0.038161476 | Q39: 1262 | R39: =IFERROR(Q39/Q$16,0) -> 0.050477981 | S39: 1262 | T39: =IFERROR(S39/S$16,0) -> 0.050477981 | U39: 1262 | V39: =IFERROR(U39/U$16,0) -> 0.0631 | W39: 1262 | X39: =IFERROR(W39/W$16,0) -> 0.0631 | Y39: 1262 | Z39: =IFERROR(Y39/Y$16,0) -> 0.036058173 | AB39: =SUM(C39,E39,G39,I39,K39,M39,O39,Q39,S39,U39,W39,Y39) -> 16227 | AC39: =IFERROR(AB39/AB$16,0) -> 0.046102706
A40: Music & Entertainment | C40: 0 | D40: =IFERROR(C40/C$16,0) -> 0 | E40: 1112 | F40: =IFERROR(E40/E$16,0) -> 0.06661874 | G40: 256 | H40: =IFERROR(G40/G$16,0) -> 0.0064313528 | I40: 0 | J40: =IFERROR(I40/I$16,0) -> 0 | K40: 1445 | L40: =IFERROR(K40/K$16,0) -> 0.035296417 | M40: 0 | N40: =IFERROR(M40/M$16,0) -> 0 | O40: 1445 | P40: =IFERROR(O40/O$16,0) -> 0.043695192 | Q40: 1445 | R40: =IFERROR(Q40/Q$16,0) -> 0.057797688 | S40: 1445 | T40: =IFERROR(S40/S$16,0) -> 0.057797688 | U40: 1445 | V40: =IFERROR(U40/U$16,0) -> 0.07225 | W40: 1445 | X40: =IFERROR(W40/W$16,0) -> 0.07225 | Y40: 1445 | Z40: =IFERROR(Y40/Y$16,0) -> 0.041286894 | AB40: =SUM(C40,E40,G40,I40,K40,M40,O40,Q40,S40,U40,W40,Y40) -> 11483 | AC40: =IFERROR(AB40/AB$16,0) -> 0.032624476
A41: Marketing & Advertising | C41: 827 | D41: =IFERROR(C41/C$16,0) -> 0.021695787 | E41: 1090 | F41: =IFERROR(E41/E$16,0) -> 0.065300743 | G41: 1821 | H41: =IFERROR(G41/G$16,0) -> 0.045748022 | I41: 1386 | J41: =IFERROR(I41/I$16,0) -> 0.11064102 | K41: 674 | L41: =IFERROR(K41/K$16,0) -> 0.016463519 | M41: 697 | N41: =IFERROR(M41/M$16,0) -> 0.015210702 | O41: 674 | P41: =IFERROR(O41/O$16,0) -> 0.02038101 | Q41: 674 | R41: =IFERROR(Q41/Q$16,0) -> 0.026958922 | S41: 674 | T41: =IFERROR(S41/S$16,0) -> 0.026958922 | U41: 674 | V41: =IFERROR(U41/U$16,0) -> 0.0337 | W41: 674 | X41: =IFERROR(W41/W$16,0) -> 0.0337 | Y41: 674 | Z41: =IFERROR(Y41/Y$16,0) -> 0.019257693 | AB41: =SUM(C41,E41,G41,I41,K41,M41,O41,Q41,S41,U41,W41,Y41) -> 10539 | AC41: =IFERROR(AB41/AB$16,0) -> 0.029942468
A42: General & Administrative - Controllable | C42: 3621 | D42: =IFERROR(C42/C$16,0) -> 0.094994491 | E42: 3804 | F42: =IFERROR(E42/E$16,0) -> 0.2278936 | G42: 5208 | H42: =IFERROR(G42/G$16,0) -> 0.13083783 | I42: 2705 | J42: =IFERROR(I42/I$16,0) -> 0.21593358 | K42: 4709 | L42: =IFERROR(K42/K$16,0) -> 0.11502479 | M42: 2584 | N42: =IFERROR(M42/M$16,0) -> 0.056390895 | O42: 3340 | P42: =IFERROR(O42/O$16,0) -> 0.10099788 | Q42: 2979 | R42: =IFERROR(Q42/Q$16,0) -> 0.11915523 | S42: 2857 | T42: =IFERROR(S42/S$16,0) -> 0.11427543 | U42: 2748 | V42: =IFERROR(U42/U$16,0) -> 0.1374 | W42: 2707 | X42: =IFERROR(W42/W$16,0) -> 0.13535 | Y42: 2718 | Z42: =IFERROR(Y42/Y$16,0) -> 0.077659362 | AB42: =SUM(C42,E42,G42,I42,K42,M42,O42,Q42,S42,U42,W42,Y42) -> 39980 | AC42: =IFERROR(AB42/AB$16,0) -> 0.11358761
A43: Repairs & Maintenance | C43: 0 | D43: =IFERROR(C43/C$16,0) -> 0 | E43: 0 | F43: =IFERROR(E43/E$16,0) -> 0 | G43: 520 | H43: =IFERROR(G43/G$16,0) -> 0.013063685 | I43: 1875 | J43: =IFERROR(I43/I$16,0) -> 0.1496767 | K43: 0 | L43: =IFERROR(K43/K$16,0) -> 0 | M43: 0 | N43: =IFERROR(M43/M$16,0) -> 0 | O43: 0 | P43: =IFERROR(O43/O$16,0) -> 0 | Q43: 0 | R43: =IFERROR(Q43/Q$16,0) -> 0 | S43: 0 | T43: =IFERROR(S43/S$16,0) -> 0 | U43: 0 | V43: =IFERROR(U43/U$16,0) -> 0 | W43: 0 | X43: =IFERROR(W43/W$16,0) -> 0 | Y43: 0 | Z43: =IFERROR(Y43/Y$16,0) -> 0 | AB43: =SUM(C43,E43,G43,I43,K43,M43,O43,Q43,S43,U43,W43,Y43) -> 2395 | AC43: =IFERROR(AB43/AB$16,0) -> 0.0068044605
A44: Total Controllable Expenses | C44: =SUM(C39:C43) -> 6079 | D44: =IFERROR(C44/C$16,0) -> 0.15947846 | E44: =SUM(E39:E43) -> 7312 | F44: =IFERROR(E44/E$16,0) -> 0.43805416 | G44: =SUM(G39:G43) -> 11067 | H44: =IFERROR(G44/G$16,0) -> 0.2780304 | I44: =SUM(I39:I43) -> 6546 | J44: =IFERROR(I44/I$16,0) -> 0.52255129 | K44: =SUM(K39:K43) -> 7775 | L44: =IFERROR(K44/K$16,0) -> 0.18991671 | M44: =SUM(M39:M43) -> 4210 | N44: =IFERROR(M44/M$16,0) -> 0.091875259 | O44: =SUM(O39:O43) -> 6721 | P44: =IFERROR(O44/O$16,0) -> 0.20323556 | Q44: =SUM(Q39:Q43) -> 6360 | R44: =IFERROR(Q44/Q$16,0) -> 0.25438982 | S44: =SUM(S39:S43) -> 6238 | T44: =IFERROR(S44/S$16,0) -> 0.24951002 | U44: =SUM(U39:U43) -> 6129 | V44: =IFERROR(U44/U$16,0) -> 0.30645 | W44: =SUM(W39:W43) -> 6088 | X44: =IFERROR(W44/W$16,0) -> 0.3044 | Y44: =SUM(Y39:Y43) -> 6099 | Z44: =IFERROR(Y44/Y$16,0) -> 0.17426212 | AB44: =SUM(AB39:AB43) -> 80624 | AC44: =IFERROR(AB44/AB$16,0) -> 0.22906172
A46: Uncontrollable Expenses
A47: Utilities | C47: 479 | D47: =IFERROR(C47/C$16,0) -> 0.012566242 | E47: 433 | F47: =IFERROR(E47/E$16,0) -> 0.02594057 | G47: 479 | H47: =IFERROR(G47/G$16,0) -> 0.012033664 | I47: 464 | J47: =IFERROR(I47/I$16,0) -> 0.037039994 | K47: 479 | L47: =IFERROR(K47/K$16,0) -> 0.011700335 | M47: 479 | N47: =IFERROR(M47/M$16,0) -> 0.010453266 | O47: 479 | P47: =IFERROR(O47/O$16,0) -> 0.014484427 | Q47: 479 | R47: =IFERROR(Q47/Q$16,0) -> 0.019159234 | S47: 479 | T47: =IFERROR(S47/S$16,0) -> 0.019159234 | U47: 479 | V47: =IFERROR(U47/U$16,0) -> 0.02395 | W47: 479 | X47: =IFERROR(W47/W$16,0) -> 0.02395 | Y47: 479 | Z47: =IFERROR(Y47/Y$16,0) -> 0.013686105 | AB47: =SUM(C47,E47,G47,I47,K47,M47,O47,Q47,S47,U47,W47,Y47) -> 5687 | AC47: =IFERROR(AB47/AB$16,0) -> 0.016157398
A48: Occupancy Cost | C48: 2509 | D48: =IFERROR(C48/C$16,0) -> 0.065821921 | E48: 1020 | F48: =IFERROR(E48/E$16,0) -> 0.061107117 | G48: 2388 | H48: =IFERROR(G48/G$16,0) -> 0.059992463 | I48: 735 | J48: =IFERROR(I48/I$16,0) -> 0.058673266 | K48: 2456 | L48: =IFERROR(K48/K$16,0) -> 0.059991695 | M48: 2749 | N48: =IFERROR(M48/M$16,0) -> 0.059991707 | O48: 1984 | P48: =IFERROR(O48/O$16,0) -> 0.059993952 | Q48: 1500 | R48: =IFERROR(Q48/Q$16,0) -> 0.0599976 | S48: 1500 | T48: =IFERROR(S48/S$16,0) -> 0.0599976 | U48: 1200 | V48: =IFERROR(U48/U$16,0) -> 0.06 | W48: 1200 | X48: =IFERROR(W48/W$16,0) -> 0.06 | Y48: 2100 | Z48: =IFERROR(Y48/Y$16,0) -> 0.060001714 | AB48: =SUM(C48,E48,G48,I48,K48,M48,O48,Q48,S48,U48,W48,Y48) -> 21341 | AC48: =IFERROR(AB48/AB$16,0) -> 0.060632147
A49: General & Administrative - Uncon | C49: 1669 | D49: =IFERROR(C49/C$16,0) -> 0.043785088 | E49: 223 | F49: =IFERROR(E49/E$16,0) -> 0.013359693 | G49: 627 | H49: =IFERROR(G49/G$16,0) -> 0.01575179 | I49: -128 | J49: =IFERROR(I49/I$16,0) -> -0.010217929 | K49: 0 | L49: =IFERROR(K49/K$16,0) -> 0 | M49: 1306 | N49: =IFERROR(M49/M$16,0) -> 0.028500971 | O49: 661 | P49: =IFERROR(O49/O$16,0) -> 0.019987904 | Q49: 500 | R49: =IFERROR(Q49/Q$16,0) -> 0.0199992 | S49: 500 | T49: =IFERROR(S49/S$16,0) -> 0.0199992 | U49: 400 | V49: =IFERROR(U49/U$16,0) -> 0.02 | W49: 400 | X49: =IFERROR(W49/W$16,0) -> 0.02 | Y49: 700 | Z49: =IFERROR(Y49/Y$16,0) -> 0.020000571 | AB49: =SUM(C49,E49,G49,I49,K49,M49,O49,Q49,S49,U49,W49,Y49) -> 6858 | AC49: =IFERROR(AB49/AB$16,0) -> 0.019484338
A50: Management Fee | C50: 4000 | D50: =IFERROR(C50/C$16,0) -> 0.1049373 | E50: 4000 | F50: =IFERROR(E50/E$16,0) -> 0.23963575 | G50: 4000 | H50: =IFERROR(G50/G$16,0) -> 0.10048989 | I50: 4000 | J50: =IFERROR(I50/I$16,0) -> 0.31931029 | K50: 4000 | L50: =IFERROR(K50/K$16,0) -> 0.097706344 | M50: 4000 | N50: =IFERROR(M50/M$16,0) -> 0.087292408 | O50: 4000 | P50: =IFERROR(O50/O$16,0) -> 0.12095555 | Q50: 4000 | R50: =IFERROR(Q50/Q$16,0) -> 0.1599936 | S50: 4000 | T50: =IFERROR(S50/S$16,0) -> 0.1599936 | U50: 4000 | V50: =IFERROR(U50/U$16,0) -> 0.2 | W50: 4000 | X50: =IFERROR(W50/W$16,0) -> 0.2 | Y50: 4000 | Z50: =IFERROR(Y50/Y$16,0) -> 0.11428898 | AB50: =SUM(C50,E50,G50,I50,K50,M50,O50,Q50,S50,U50,W50,Y50) -> 48000 | AC50: =IFERROR(AB50/AB$16,0) -> 0.13637332
A51: Owner Fee | C51: 0 | D51: =IFERROR(C51/C$16,0) -> 0 | E51: 0 | F51: =IFERROR(E51/E$16,0) -> 0 | G51: 0 | H51: =IFERROR(G51/G$16,0) -> 0 | I51: 0 | J51: =IFERROR(I51/I$16,0) -> 0 | K51: 0 | L51: =IFERROR(K51/K$16,0) -> 0 | M51: 0 | N51: =IFERROR(M51/M$16,0) -> 0 | O51: 0 | P51: =IFERROR(O51/O$16,0) -> 0 | Q51: 0 | R51: =IFERROR(Q51/Q$16,0) -> 0 | S51: 0 | T51: =IFERROR(S51/S$16,0) -> 0 | U51: 0 | V51: =IFERROR(U51/U$16,0) -> 0 | W51: 0 | X51: =IFERROR(W51/W$16,0) -> 0 | Y51: 0 | Z51: =IFERROR(Y51/Y$16,0) -> 0 | AB51: =SUM(C51,E51,G51,I51,K51,M51,O51,Q51,S51,U51,W51,Y51) -> 0 | AC51: =IFERROR(AB51/AB$16,0) -> 0
A52: Business Taxes | C52: 0 | D52: =IFERROR(C52/C$16,0) -> 0 | E52: 0 | F52: =IFERROR(E52/E$16,0) -> 0 | G52: 0 | H52: =IFERROR(G52/G$16,0) -> 0 | I52: 0 | J52: =IFERROR(I52/I$16,0) -> 0 | K52: 0 | L52: =IFERROR(K52/K$16,0) -> 0 | M52: 0 | N52: =IFERROR(M52/M$16,0) -> 0 | O52: 0 | P52: =IFERROR(O52/O$16,0) -> 0 | Q52: 0 | R52: =IFERROR(Q52/Q$16,0) -> 0 | S52: 0 | T52: =IFERROR(S52/S$16,0) -> 0 | U52: 0 | V52: =IFERROR(U52/U$16,0) -> 0 | W52: 0 | X52: =IFERROR(W52/W$16,0) -> 0 | Y52: 0 | Z52: =IFERROR(Y52/Y$16,0) -> 0 | AB52: =SUM(C52,E52,G52,I52,K52,M52,O52,Q52,S52,U52,W52,Y52) -> 0 | AC52: =IFERROR(AB52/AB$16,0) -> 0
A53: Total Uncontrollable Expenses | C53: =SUM(C47:C52) -> 8657 | D53: =IFERROR(C53/C$16,0) -> 0.22711055 | E53: =SUM(E47:E52) -> 5676 | F53: =IFERROR(E53/E$16,0) -> 0.34004313 | G53: =SUM(G47:G52) -> 7494 | H53: =IFERROR(G53/G$16,0) -> 0.18826781 | I53: =SUM(I47:I52) -> 5071 | J53: =IFERROR(I53/I$16,0) -> 0.40480562 | K53: =SUM(K47:K52) -> 6935 | L53: =IFERROR(K53/K$16,0) -> 0.16939837 | M53: =SUM(M47:M52) -> 8534 | N53: =IFERROR(M53/M$16,0) -> 0.18623835 | O53: =SUM(O47:O52) -> 7124 | P53: =IFERROR(O53/O$16,0) -> 0.21542183 | Q53: =SUM(Q47:Q52) -> 6479 | R53: =IFERROR(Q53/Q$16,0) -> 0.25914963 | S53: =SUM(S47:S52) -> 6479 | T53: =IFERROR(S53/S$16,0) -> 0.25914963 | U53: =SUM(U47:U52) -> 6079 | V53: =IFERROR(U53/U$16,0) -> 0.30395 | W53: =SUM(W47:W52) -> 6079 | X53: =IFERROR(W53/W$16,0) -> 0.30395 | Y53: =SUM(Y47:Y52) -> 7279 | Z53: =IFERROR(Y53/Y$16,0) -> 0.20797737 | AB53: =SUM(AB47:AB52) -> 81886 | AC53: =IFERROR(AB53/AB$16,0) -> 0.23264721
A55: Net Operating Profit Before Debt Service | C55: =C36-C44-C53 -> -1215 | D55: =IFERROR(C55/C$16,0) -> -0.031874705 | E55: =E36-E44-E53 -> -13865 | F55: =IFERROR(E55/E$16,0) -> -0.83063743 | G55: =G36-G44-G53 -> -6756 | H55: =IFERROR(G55/G$16,0) -> -0.16972742 | I55: =I36-I44-I53 -> -6197 | J55: =IFERROR(I55/I$16,0) -> -0.49469147 | K55: =K36-K44-K53 -> 492 | L55: =IFERROR(K55/K$16,0) -> 0.01201788 | M55: =M36-M44-M53 -> 1225 | N55: =IFERROR(M55/M$16,0) -> 0.0267333 | O55: =O36-O44-O53 -> 3838 | P55: =IFERROR(O55/O$16,0) -> 0.11605685 | Q55: =Q36-Q44-Q53 -> 1619 | R55: =IFERROR(Q55/Q$16,0) -> 0.06475741 | S55: =S36-S44-S53 -> 1741 | T55: =IFERROR(S55/S$16,0) -> 0.069637215 | U55: =U36-U44-U53 -> -1037 | V55: =IFERROR(U55/U$16,0) -> -0.05185 | W55: =W36-W44-W53 -> -996 | X55: =IFERROR(W55/W$16,0) -> -0.0498 | Y55: =Y36-Y44-Y53 -> 7650 | Z55: =IFERROR(Y55/Y$16,0) -> 0.21857767 | AB55: =AB36-AB44-AB53 -> -13501 | AC55: =IFERROR(AB55/AB$16,0) -> -0.038357838
A57: Debt Service | C57: 0 | D57: =IFERROR(C57/C$16,0) -> 0 | E57: 0 | F57: =IFERROR(E57/E$16,0) -> 0 | G57: 0 | H57: =IFERROR(G57/G$16,0) -> 0 | I57: 0 | J57: =IFERROR(I57/I$16,0) -> 0 | K57: 0 | L57: =IFERROR(K57/K$16,0) -> 0 | M57: 0 | N57: =IFERROR(M57/M$16,0) -> 0 | O57: 0 | P57: =IFERROR(O57/O$16,0) -> 0 | Q57: 0 | R57: =IFERROR(Q57/Q$16,0) -> 0 | S57: 0 | T57: =IFERROR(S57/S$16,0) -> 0 | U57: 0 | V57: =IFERROR(U57/U$16,0) -> 0 | W57: 0 | X57: =IFERROR(W57/W$16,0) -> 0 | Y57: 0 | Z57: =IFERROR(Y57/Y$16,0) -> 0 | AB57: =SUM(C57,E57,G57,I57,K57,M57,O57,Q57,S57,U57,W57,Y57) -> 0 | AC57: =IFERROR(AB57/AB$16,0) -> 0
A59: Net Operating Profit After Debt Service | C59: =C55-C57 -> -1215 | D59: =IFERROR(C59/C$16,0) -> -0.031874705 | E59: =E55-E57 -> -13865 | F59: =IFERROR(E59/E$16,0) -> -0.83063743 | G59: =G55-G57 -> -6756 | H59: =IFERROR(G59/G$16,0) -> -0.16972742 | I59: =I55-I57 -> -6197 | J59: =IFERROR(I59/I$16,0) -> -0.49469147 | K59: =K55-K57 -> 492 | L59: =IFERROR(K59/K$16,0) -> 0.01201788 | M59: =M55-M57 -> 1225 | N59: =IFERROR(M59/M$16,0) -> 0.0267333 | O59: =O55-O57 -> 3838 | P59: =IFERROR(O59/O$16,0) -> 0.11605685 | Q59: =Q55-Q57 -> 1619 | R59: =IFERROR(Q59/Q$16,0) -> 0.06475741 | S59: =S55-S57 -> 1741 | T59: =IFERROR(S59/S$16,0) -> 0.069637215 | U59: =U55-U57 -> -1037 | V59: =IFERROR(U59/U$16,0) -> -0.05185 | W59: =W55-W57 -> -996 | X59: =IFERROR(W59/W$16,0) -> -0.0498 | Y59: =Y55-Y57 -> 7650 | Z59: =IFERROR(Y59/Y$16,0) -> 0.21857767 | AB59: =AB55-AB57 -> -13501 | AC59: =IFERROR(AB59/AB$16,0) -> -0.038357838
A61: Other (Income) Expense | C61: 0 | D61: =IFERROR(C61/C$16,0) -> 0 | E61: 0 | F61: =IFERROR(E61/E$16,0) -> 0 | G61: 0 | H61: =IFERROR(G61/G$16,0) -> 0 | I61: 0 | J61: =IFERROR(I61/I$16,0) -> 0 | K61: 0 | L61: =IFERROR(K61/K$16,0) -> 0 | M61: 0 | N61: =IFERROR(M61/M$16,0) -> 0 | O61: 0 | P61: =IFERROR(O61/O$16,0) -> 0 | Q61: 0 | R61: =IFERROR(Q61/Q$16,0) -> 0 | S61: 0 | T61: =IFERROR(S61/S$16,0) -> 0 | U61: 0 | V61: =IFERROR(U61/U$16,0) -> 0 | W61: 0 | X61: =IFERROR(W61/W$16,0) -> 0 | Y61: 0 | Z61: =IFERROR(Y61/Y$16,0) -> 0 | AB61: =SUM(C61,E61,G61,I61,K61,M61,O61,Q61,S61,U61,W61,Y61) -> 0 | AC61: =IFERROR(AB61/AB$16,0) -> 0
A62: Reserve / CapEx | C62: 239 | D62: =IFERROR(C62/C$16,0) -> 0.0062700037 | E62: 375 | F62: =IFERROR(E62/E$16,0) -> 0.022465852 | G62: 500 | H62: =IFERROR(G62/G$16,0) -> 0.012561236 | I62: 500 | J62: =IFERROR(I62/I$16,0) -> 0.039913786 | K62: 409 | L62: =IFERROR(K62/K$16,0) -> 0.0099904736 | M62: 458 | N62: =IFERROR(M62/M$16,0) -> 0.0099949807 | O62: 409 | P62: =IFERROR(O62/O$16,0) -> 0.012367705 | Q62: 409 | R62: =IFERROR(Q62/Q$16,0) -> 0.016359346 | S62: 409 | T62: =IFERROR(S62/S$16,0) -> 0.016359346 | U62: 409 | V62: =IFERROR(U62/U$16,0) -> 0.02045 | W62: 409 | X62: =IFERROR(W62/W$16,0) -> 0.02045 | Y62: 409 | Z62: =IFERROR(Y62/Y$16,0) -> 0.011686048 | AB62: =SUM(C62,E62,G62,I62,K62,M62,O62,Q62,S62,U62,W62,Y62) -> 4935 | AC62: =IFERROR(AB62/AB$16,0) -> 0.014020882
A63: Net Cash Flow | C63: =C59-C61-C62 -> -1454 | D63: =IFERROR(C63/C$16,0) -> -0.038144709 | E63: =E59-E61-E62 -> -14240 | F63: =IFERROR(E63/E$16,0) -> -0.85310328 | G63: =G59-G61-G62 -> -7256 | H63: =IFERROR(G63/G$16,0) -> -0.18228866 | I63: =I59-I61-I62 -> -6697 | J63: =IFERROR(I63/I$16,0) -> -0.53460525 | K63: =K59-K61-K62 -> 83 | L63: =IFERROR(K63/K$16,0) -> 0.0020274066 | M63: =M59-M61-M62 -> 767 | N63: =IFERROR(M63/M$16,0) -> 0.016738319 | O63: =O59-O61-O62 -> 3429 | P63: =IFERROR(O63/O$16,0) -> 0.10368914 | Q63: =Q59-Q61-Q62 -> 1210 | R63: =IFERROR(Q63/Q$16,0) -> 0.048398064 | S63: =S59-S61-S62 -> 1332 | T63: =IFERROR(S63/S$16,0) -> 0.053277869 | U63: =U59-U61-U62 -> -1446 | V63: =IFERROR(U63/U$16,0) -> -0.0723 | W63: =W59-W61-W62 -> -1405 | X63: =IFERROR(W63/W$16,0) -> -0.07025 | Y63: =Y59-Y61-Y62 -> 7241 | Z63: =IFERROR(Y63/Y$16,0) -> 0.20689163 | AB63: =AB59-AB61-AB62 -> -18436 | AC63: =IFERROR(AB63/AB$16,0) -> -0.05237872

Sheet LW 2026 P&L
A1: Little Wing Coffee & Goods
A2: Profit & Loss Summary
A3: 2026
C5: January | E5: February | G5: March | I5: April | K5: May | M5: June | O5: July | Q5: August | S5: September | U5: October | W5: November | Y5: December | AB5: 2026
C6: Actual | E6: Actual | G6: Actual | I6: Actual | K6: Actual | M6: Actual | O6: Forecast | Q6: Forecast | S6: Forecast | U6: Forecast | W6: Forecast | Y6: Forecast | AB6: Act/For/Bud
C7: Amount $ | D7: % | E7: Amount $ | F7: % | G7: Amount $ | H7: % | I7: Amount $ | J7: % | K7: Amount $ | L7: % | M7: Amount $ | N7: % | O7: Amount $ | P7: % | Q7: Amount $ | R7: % | S7: Amount $ | T7: % | U7: Amount $ | V7: % | W7: Amount $ | X7: % | Y7: Amount $ | Z7: % | AB7: Amount $ | AC7: %
A8: Income
A9: Food Sales | C9: 7659 | D9: =IFERROR(C9/C$16,0) -> 0.42854745 | E9: 9205 | F9: =IFERROR(E9/E$16,0) -> 0.51606212 | G9: 12511 | H9: =IFERROR(G9/G$16,0) -> 0.47296991 | I9: 9497 | J9: =IFERROR(I9/I$16,0) -> 0.46144502 | K9: 10762 | L9: =IFERROR(K9/K$16,0) -> 0.43260843 | M9: 10511 | N9: =IFERROR(M9/M$16,0) -> 0.38844747 | O9: 11085 | P9: =IFERROR(O9/O$16,0) -> 0.43184386 | Q9: 11085 | R9: =IFERROR(Q9/Q$16,0) -> 0.43184386 | S9: 11085 | T9: =IFERROR(S9/S$16,0) -> 0.43184386 | U9: 11085 | V9: =IFERROR(U9/U$16,0) -> 0.43184386 | W9: 11085 | X9: =IFERROR(W9/W$16,0) -> 0.43184386 | Y9: 11085 | Z9: =IFERROR(Y9/Y$16,0) -> 0.43184386 | AB9: =SUM(C9,E9,G9,I9,K9,M9,O9,Q9,S9,U9,W9,Y9) -> 126655 | AC9: =IFERROR(AB9/AB$16,0) -> 0.43872016
A10: Non-Alcoholic Beverage Sales | C10: 9236 | D10: =IFERROR(C10/C$16,0) -> 0.51678603 | E10: 9081 | F10: =IFERROR(E10/E$16,0) -> 0.50911028 | G10: 13436 | H10: =IFERROR(G10/G$16,0) -> 0.50793891 | I10: 10789 | J10: =IFERROR(I10/I$16,0) -> 0.52422137 | K10: 13103 | L10: =IFERROR(K10/K$16,0) -> 0.52671142 | M10: 14448 | N10: =IFERROR(M10/M$16,0) -> 0.53394434 | O10: 13496 | P10: =IFERROR(O10/O$16,0) -> 0.52577038 | Q10: 13496 | R10: =IFERROR(Q10/Q$16,0) -> 0.52577038 | S10: 13496 | T10: =IFERROR(S10/S$16,0) -> 0.52577038 | U10: 13496 | V10: =IFERROR(U10/U$16,0) -> 0.52577038 | W10: 13496 | X10: =IFERROR(W10/W$16,0) -> 0.52577038 | Y10: 13496 | Z10: =IFERROR(Y10/Y$16,0) -> 0.52577038 | AB10: =SUM(C10,E10,G10,I10,K10,M10,O10,Q10,S10,U10,W10,Y10) -> 151069 | AC10: =IFERROR(AB10/AB$16,0) -> 0.52328779
A11: Liquor Sales | C11: 800 | D11: =IFERROR(C11/C$16,0) -> 0.044762757 | E11: 295 | F11: =IFERROR(E11/E$16,0) -> 0.016538656 | G11: 1354 | H11: =IFERROR(G11/G$16,0) -> 0.051187056 | I11: 1490 | J11: =IFERROR(I11/I$16,0) -> 0.072396871 | K11: 591 | L11: =IFERROR(K11/K$16,0) -> 0.023756884 | M11: 984 | N11: =IFERROR(M11/M$16,0) -> 0.03636498 | O11: 609 | P11: =IFERROR(O11/O$16,0) -> 0.023725116 | Q11: 609 | R11: =IFERROR(Q11/Q$16,0) -> 0.023725116 | S11: 609 | T11: =IFERROR(S11/S$16,0) -> 0.023725116 | U11: 609 | V11: =IFERROR(U11/U$16,0) -> 0.023725116 | W11: 609 | X11: =IFERROR(W11/W$16,0) -> 0.023725116 | Y11: 609 | Z11: =IFERROR(Y11/Y$16,0) -> 0.023725116 | AB11: =SUM(C11,E11,G11,I11,K11,M11,O11,Q11,S11,U11,W11,Y11) -> 9168 | AC11: =IFERROR(AB11/AB$16,0) -> 0.031757028
A12: Beer Sales | C12: 54 | D12: =IFERROR(C12/C$16,0) -> 0.0030214861 | E12: 240 | F12: =IFERROR(E12/E$16,0) -> 0.013455177 | G12: 174 | H12: =IFERROR(G12/G$16,0) -> 0.0065779525 | I12: 333 | J12: =IFERROR(I12/I$16,0) -> 0.016179972 | K12: 597 | L12: =IFERROR(K12/K$16,0) -> 0.023998071 | M12: 743 | N12: =IFERROR(M12/M$16,0) -> 0.027458517 | O12: 615 | P12: =IFERROR(O12/O$16,0) -> 0.023958861 | Q12: 615 | R12: =IFERROR(Q12/Q$16,0) -> 0.023958861 | S12: 615 | T12: =IFERROR(S12/S$16,0) -> 0.023958861 | U12: 615 | V12: =IFERROR(U12/U$16,0) -> 0.023958861 | W12: 615 | X12: =IFERROR(W12/W$16,0) -> 0.023958861 | Y12: 615 | Z12: =IFERROR(Y12/Y$16,0) -> 0.023958861 | AB12: =SUM(C12,E12,G12,I12,K12,M12,O12,Q12,S12,U12,W12,Y12) -> 5831 | AC12: =IFERROR(AB12/AB$16,0) -> 0.020197996
A13: Wine Sales | C13: 0 | D13: =IFERROR(C13/C$16,0) -> 0 | E13: 12 | F13: =IFERROR(E13/E$16,0) -> 0.00067275887 | G13: 1 | H13: =IFERROR(G13/G$16,0) -> 3.7804325e-05 | I13: 496 | J13: =IFERROR(I13/I$16,0) -> 0.024099898 | K13: 1015 | L13: =IFERROR(K13/K$16,0) -> 0.04080074 | M13: 1101 | N13: =IFERROR(M13/M$16,0) -> 0.040688865 | O13: 1045 | P13: =IFERROR(O13/O$16,0) -> 0.040710585 | Q13: 1045 | R13: =IFERROR(Q13/Q$16,0) -> 0.040710585 | S13: 1045 | T13: =IFERROR(S13/S$16,0) -> 0.040710585 | U13: 1045 | V13: =IFERROR(U13/U$16,0) -> 0.040710585 | W13: 1045 | X13: =IFERROR(W13/W$16,0) -> 0.040710585 | Y13: 1045 | Z13: =IFERROR(Y13/Y$16,0) -> 0.040710585 | AB13: =SUM(C13,E13,G13,I13,K13,M13,O13,Q13,S13,U13,W13,Y13) -> 8895 | AC13: =IFERROR(AB13/AB$16,0) -> 0.030811384
A14: Other Operating Income | C14: 854 | D14: =IFERROR(C14/C$16,0) -> 0.047784244 | E14: 28 | F14: =IFERROR(E14/E$16,0) -> 0.0015697707 | G14: 1473 | H14: =IFERROR(G14/G$16,0) -> 0.05568577 | I14: 664 | J14: =IFERROR(I14/I$16,0) -> 0.032262767 | K14: 330 | L14: =IFERROR(K14/K$16,0) -> 0.013265265 | M14: 259 | N14: =IFERROR(M14/M$16,0) -> 0.0095716767 | O14: 340 | P14: =IFERROR(O14/O$16,0) -> 0.013245549 | Q14: 340 | R14: =IFERROR(Q14/Q$16,0) -> 0.013245549 | S14: 340 | T14: =IFERROR(S14/S$16,0) -> 0.013245549 | U14: 340 | V14: =IFERROR(U14/U$16,0) -> 0.013245549 | W14: 340 | X14: =IFERROR(W14/W$16,0) -> 0.013245549 | Y14: 340 | Z14: =IFERROR(Y14/Y$16,0) -> 0.013245549 | AB14: =SUM(C14,E14,G14,I14,K14,M14,O14,Q14,S14,U14,W14,Y14) -> 5648 | AC14: =IFERROR(AB14/AB$16,0) -> 0.019564103
A15: Discounts & Comps | C15: -731 | D15: =IFERROR(C15/C$16,0) -> -0.04090197 | E15: -1024 | F15: =IFERROR(E15/E$16,0) -> -0.057408757 | G15: -2497 | H15: =IFERROR(G15/G$16,0) -> -0.094397399 | I15: -2688 | J15: =IFERROR(I15/I$16,0) -> -0.1306059 | K15: -1521 | L15: =IFERROR(K15/K$16,0) -> -0.061140813 | M15: -987 | N15: =IFERROR(M15/M$16,0) -> -0.036475849 | O15: -1521 | P15: =IFERROR(O15/O$16,0) -> -0.059254354 | Q15: -1521 | R15: =IFERROR(Q15/Q$16,0) -> -0.059254354 | S15: -1521 | T15: =IFERROR(S15/S$16,0) -> -0.059254354 | U15: -1521 | V15: =IFERROR(U15/U$16,0) -> -0.059254354 | W15: -1521 | X15: =IFERROR(W15/W$16,0) -> -0.059254354 | Y15: -1521 | Z15: =IFERROR(Y15/Y$16,0) -> -0.059254354 | AB15: =SUM(C15,E15,G15,I15,K15,M15,O15,Q15,S15,U15,W15,Y15) -> -18574 | AC15: =IFERROR(AB15/AB$16,0) -> -0.064338465
A16: Total Income | C16: =SUM(C9:C15) -> 17872 | D16: =IFERROR(C16/C$16,0) -> 1 | E16: =SUM(E9:E15) -> 17837 | F16: =IFERROR(E16/E$16,0) -> 1 | G16: =SUM(G9:G15) -> 26452 | H16: =IFERROR(G16/G$16,0) -> 1 | I16: =SUM(I9:I15) -> 20581 | J16: =IFERROR(I16/I$16,0) -> 1 | K16: =SUM(K9:K15) -> 24877 | L16: =IFERROR(K16/K$16,0) -> 1 | M16: =SUM(M9:M15) -> 27059 | N16: =IFERROR(M16/M$16,0) -> 1 | O16: =SUM(O9:O15) -> 25669 | P16: =IFERROR(O16/O$16,0) -> 1 | Q16: =SUM(Q9:Q15) -> 25669 | R16: =IFERROR(Q16/Q$16,0) -> 1 | S16: =SUM(S9:S15) -> 25669 | T16: =IFERROR(S16/S$16,0) -> 1 | U16: =SUM(U9:U15) -> 25669 | V16: =IFERROR(U16/U$16,0) -> 1 | W16: =SUM(W9:W15) -> 25669 | X16: =IFERROR(W16/W$16,0) -> 1 | Y16: =SUM(Y9:Y15) -> 25669 | Z16: =IFERROR(Y16/Y$16,0) -> 1 | AB16: =SUM(AB9:AB15) -> 288692 | AC16: =IFERROR(AB16/AB$16,0) -> 1
A18: Cost of Goods Sold
A19: Food Cost | C19: 1608 | D19: =IFERROR(C19/C$9,0) -> 0.20994908 | E19: 2865 | F19: =IFERROR(E19/E$9,0) -> 0.31124389 | G19: 4719 | H19: =IFERROR(G19/G$9,0) -> 0.37718807 | I19: 3179 | J19: =IFERROR(I19/I$9,0) -> 0.33473729 | K19: 7902 | L19: =IFERROR(K19/K$9,0) -> 0.73425014 | M19: 7534 | N19: =IFERROR(M19/M$9,0) -> 0.7167729 | O19: 5809 | P19: =IFERROR(O19/O$9,0) -> 0.5240415 | Q19: 6414 | R19: =IFERROR(Q19/Q$9,0) -> 0.57861976 | S19: 5856 | T19: =IFERROR(S19/S$9,0) -> 0.52828146 | U19: 6026 | V19: =IFERROR(U19/U$9,0) -> 0.5436175 | W19: 6099 | X19: =IFERROR(W19/W$9,0) -> 0.55020298 | Y19: 5994 | Z19: =IFERROR(Y19/Y$9,0) -> 0.54073072 | AB19: =SUM(C19,E19,G19,I19,K19,M19,O19,Q19,S19,U19,W19,Y19) -> 64005 | AC19: =IFERROR(AB19/AB$9,0) -> 0.50534918
A20: Non-Alcoholic Beverage Cost | C20: 1549 | D20: =IFERROR(C20/C$10,0) -> 0.1677133 | E20: 2446 | F20: =IFERROR(E20/E$10,0) -> 0.2693536 | G20: 2186 | H20: =IFERROR(G20/G$10,0) -> 0.16269723 | I20: 2267 | J20: =IFERROR(I20/I$10,0) -> 0.21012142 | K20: 2981 | L20: =IFERROR(K20/K$10,0) -> 0.22750515 | M20: 3628 | N20: =IFERROR(M20/M$10,0) -> 0.25110742 | O20: 2865 | P20: =IFERROR(O20/O$10,0) -> 0.21228512 | Q20: 2873 | R20: =IFERROR(Q20/Q$10,0) -> 0.21287789 | S20: 2808 | T20: =IFERROR(S20/S$10,0) -> 0.20806165 | U20: 2849 | V20: =IFERROR(U20/U$10,0) -> 0.21109959 | W20: 2843 | X20: =IFERROR(W20/W$10,0) -> 0.21065501 | Y20: 2833 | Z20: =IFERROR(Y20/Y$10,0) -> 0.20991405 | AB20: =SUM(C20,E20,G20,I20,K20,M20,O20,Q20,S20,U20,W20,Y20) -> 32128 | AC20: =IFERROR(AB20/AB$10,0) -> 0.21267103
A21: Liquor Cost | C21: 294 | D21: =IFERROR(C21/C$11,0) -> 0.3675 | E21: 111 | F21: =IFERROR(E21/E$11,0) -> 0.37627119 | G21: 235 | H21: =IFERROR(G21/G$11,0) -> 0.17355982 | I21: 238 | J21: =IFERROR(I21/I$11,0) -> 0.15973154 | K21: 22 | L21: =IFERROR(K21/K$11,0) -> 0.037225042 | M21: 1711 | N21: =IFERROR(M21/M$11,0) -> 1.7388211 | O21: 91 | P21: =IFERROR(O21/O$11,0) -> 0.14942529 | Q21: 67 | R21: =IFERROR(Q21/Q$11,0) -> 0.11001642 | S21: 82 | T21: =IFERROR(S21/S$11,0) -> 0.13464696 | U21: 80 | V21: =IFERROR(U21/U$11,0) -> 0.13136289 | W21: 76 | X21: =IFERROR(W21/W$11,0) -> 0.12479475 | Y21: 79 | Z21: =IFERROR(Y21/Y$11,0) -> 0.12972085 | AB21: =SUM(C21,E21,G21,I21,K21,M21,O21,Q21,S21,U21,W21,Y21) -> 3086 | AC21: =IFERROR(AB21/AB$11,0) -> 0.33660558
A22: Beer Cost | C22: 82 | D22: =IFERROR(C22/C$12,0) -> 1.5185185 | E22: 153 | F22: =IFERROR(E22/E$12,0) -> 0.6375 | G22: 43 | H22: =IFERROR(G22/G$12,0) -> 0.24712644 | I22: 86 | J22: =IFERROR(I22/I$12,0) -> 0.25825826 | K22: 176 | L22: =IFERROR(K22/K$12,0) -> 0.29480737 | M22: 146 | N22: =IFERROR(M22/M$12,0) -> 0.19650067 | O22: 172 | P22: =IFERROR(O22/O$12,0) -> 0.2796748 | Q22: 174 | R22: =IFERROR(Q22/Q$12,0) -> 0.28292683 | S22: 172 | T22: =IFERROR(S22/S$12,0) -> 0.2796748 | U22: 172 | V22: =IFERROR(U22/U$12,0) -> 0.2796748 | W22: 173 | X22: =IFERROR(W22/W$12,0) -> 0.28130081 | Y22: 172 | Z22: =IFERROR(Y22/Y$12,0) -> 0.2796748 | AB22: =SUM(C22,E22,G22,I22,K22,M22,O22,Q22,S22,U22,W22,Y22) -> 1721 | AC22: =IFERROR(AB22/AB$12,0) -> 0.29514663
A23: Wine/Sake Cost | C23: 301 | D23: =IFERROR(C23/C$13,0) -> 0 | E23: 0 | F23: =IFERROR(E23/E$13,0) -> 0 | G23: 0 | H23: =IFERROR(G23/G$13,0) -> 0 | I23: 268 | J23: =IFERROR(I23/I$13,0) -> 0.54032258 | K23: 290 | L23: =IFERROR(K23/K$13,0) -> 0.28571429 | M23: 595 | N23: =IFERROR(M23/M$13,0) -> 0.5404178 | O23: 386 | P23: =IFERROR(O23/O$13,0) -> 0.36937799 | Q23: 358 | R23: =IFERROR(Q23/Q$13,0) -> 0.34258373 | S23: 377 | T23: =IFERROR(S23/S$13,0) -> 0.36076555 | U23: 373 | V23: =IFERROR(U23/U$13,0) -> 0.3569378 | W23: 369 | X23: =IFERROR(W23/W$13,0) -> 0.35311005 | Y23: 373 | Z23: =IFERROR(Y23/Y$13,0) -> 0.3569378 | AB23: =SUM(C23,E23,G23,I23,K23,M23,O23,Q23,S23,U23,W23,Y23) -> 3690 | AC23: =IFERROR(AB23/AB$13,0) -> 0.4148398
A24: Total COGS | C24: =SUM(C19:C23) -> 3834 | D24: =IFERROR(C24/C$16,0) -> 0.21452551 | E24: =SUM(E19:E23) -> 5575 | F24: =IFERROR(E24/E$16,0) -> 0.31255256 | G24: =SUM(G19:G23) -> 7183 | H24: =IFERROR(G24/G$16,0) -> 0.27154847 | I24: =SUM(I19:I23) -> 6038 | J24: =IFERROR(I24/I$16,0) -> 0.29337739 | K24: =SUM(K19:K23) -> 11371 | L24: =IFERROR(K24/K$16,0) -> 0.45708888 | M24: =SUM(M19:M23) -> 13614 | N24: =IFERROR(M24/M$16,0) -> 0.50312281 | O24: =SUM(O19:O23) -> 9323 | P24: =IFERROR(O24/O$16,0) -> 0.36320075 | Q24: =SUM(Q19:Q23) -> 9886 | R24: =IFERROR(Q24/Q$16,0) -> 0.38513382 | S24: =SUM(S19:S23) -> 9295 | T24: =IFERROR(S24/S$16,0) -> 0.36210994 | U24: =SUM(U19:U23) -> 9500 | V24: =IFERROR(U24/U$16,0) -> 0.37009623 | W24: =SUM(W19:W23) -> 9560 | X24: =IFERROR(W24/W$16,0) -> 0.37243367 | Y24: =SUM(Y19:Y23) -> 9451 | Z24: =IFERROR(Y24/Y$16,0) -> 0.36818731 | AB24: =SUM(AB19:AB23) -> 104630 | AC24: =IFERROR(AB24/AB$16,0) -> 0.36242778
A25: Gross Profit | C25: =C16-C24 -> 14038 | D25: =IFERROR(C25/C$16,0) -> 0.78547449 | E25: =E16-E24 -> 12262 | F25: =IFERROR(E25/E$16,0) -> 0.68744744 | G25: =G16-G24 -> 19269 | H25: =IFERROR(G25/G$16,0) -> 0.72845153 | I25: =I16-I24 -> 14543 | J25: =IFERROR(I25/I$16,0) -> 0.70662261 | K25: =K16-K24 -> 13506 | L25: =IFERROR(K25/K$16,0) -> 0.54291112 | M25: =M16-M24 -> 13445 | N25: =IFERROR(M25/M$16,0) -> 0.49687719 | O25: =O16-O24 -> 16346 | P25: =IFERROR(O25/O$16,0) -> 0.63679925 | Q25: =Q16-Q24 -> 15783 | R25: =IFERROR(Q25/Q$16,0) -> 0.61486618 | S25: =S16-S24 -> 16374 | T25: =IFERROR(S25/S$16,0) -> 0.63789006 | U25: =U16-U24 -> 16169 | V25: =IFERROR(U25/U$16,0) -> 0.62990377 | W25: =W16-W24 -> 16109 | X25: =IFERROR(W25/W$16,0) -> 0.62756633 | Y25: =Y16-Y24 -> 16218 | Z25: =IFERROR(Y25/Y$16,0) -> 0.63181269 | AB25: =AB16-AB24 -> 184062 | AC25: =IFERROR(AB25/AB$16,0) -> 0.63757222
A27: Labor Cost
A28: Management Labor | C28: 1230 | D28: =IFERROR(C28/C$16,0) -> 0.068822739 | E28: 479 | F28: =IFERROR(E28/E$16,0) -> 0.026854292 | G28: 868 | H28: =IFERROR(G28/G$16,0) -> 0.032814154 | I28: 1132 | J28: =IFERROR(I28/I$16,0) -> 0.055002186 | K28: 1657 | L28: =IFERROR(K28/K$16,0) -> 0.06660771 | M28: 1377 | N28: =IFERROR(M28/M$16,0) -> 0.050888799 | O28: 1657 | P28: =IFERROR(O28/O$16,0) -> 0.064552573 | Q28: 1657 | R28: =IFERROR(Q28/Q$16,0) -> 0.064552573 | S28: 1657 | T28: =IFERROR(S28/S$16,0) -> 0.064552573 | U28: 1657 | V28: =IFERROR(U28/U$16,0) -> 0.064552573 | W28: 1657 | X28: =IFERROR(W28/W$16,0) -> 0.064552573 | Y28: 1657 | Z28: =IFERROR(Y28/Y$16,0) -> 0.064552573 | AB28: =SUM(C28,E28,G28,I28,K28,M28,O28,Q28,S28,U28,W28,Y28) -> 16685 | AC28: =IFERROR(AB28/AB$16,0) -> 0.057795159
A29: Back of House Hourly Labor | C29: 2558 | D29: =IFERROR(C29/C$16,0) -> 0.14312892 | E29: 2016 | F29: =IFERROR(E29/E$16,0) -> 0.11302349 | G29: 2550 | H29: =IFERROR(G29/G$16,0) -> 0.096401028 | I29: 3413 | J29: =IFERROR(I29/I$16,0) -> 0.16583256 | K29: 2266 | L29: =IFERROR(K29/K$16,0) -> 0.091088154 | M29: 2637 | N29: =IFERROR(M29/M$16,0) -> 0.097453712 | O29: 2266 | P29: =IFERROR(O29/O$16,0) -> 0.088277689 | Q29: 2266 | R29: =IFERROR(Q29/Q$16,0) -> 0.088277689 | S29: 2266 | T29: =IFERROR(S29/S$16,0) -> 0.088277689 | U29: 2266 | V29: =IFERROR(U29/U$16,0) -> 0.088277689 | W29: 2266 | X29: =IFERROR(W29/W$16,0) -> 0.088277689 | Y29: 2266 | Z29: =IFERROR(Y29/Y$16,0) -> 0.088277689 | AB29: =SUM(C29,E29,G29,I29,K29,M29,O29,Q29,S29,U29,W29,Y29) -> 29036 | AC29: =IFERROR(AB29/AB$16,0) -> 0.10057778
A30: Front of House Hourly Labor | C30: 10115 | D30: =IFERROR(C30/C$16,0) -> 0.56596911 | E30: 8428 | F30: =IFERROR(E30/E$16,0) -> 0.47250098 | G30: 7366 | H30: =IFERROR(G30/G$16,0) -> 0.27846666 | I30: 6693 | J30: =IFERROR(I30/I$16,0) -> 0.32520286 | K30: 8447 | L30: =IFERROR(K30/K$16,0) -> 0.33955059 | M30: 9291 | N30: =IFERROR(M30/M$16,0) -> 0.3433608 | O30: 8447 | P30: =IFERROR(O30/O$16,0) -> 0.32907398 | Q30: 8447 | R30: =IFERROR(Q30/Q$16,0) -> 0.32907398 | S30: 8447 | T30: =IFERROR(S30/S$16,0) -> 0.32907398 | U30: 8447 | V30: =IFERROR(U30/U$16,0) -> 0.32907398 | W30: 8447 | X30: =IFERROR(W30/W$16,0) -> 0.32907398 | Y30: 8447 | Z30: =IFERROR(Y30/Y$16,0) -> 0.32907398 | AB30: =SUM(C30,E30,G30,I30,K30,M30,O30,Q30,S30,U30,W30,Y30) -> 101022 | AC30: =IFERROR(AB30/AB$16,0) -> 0.34993003
A31: Payroll Taxes & Benefits | C31: 3006 | D31: =IFERROR(C31/C$16,0) -> 0.16819606 | E31: 650 | F31: =IFERROR(E31/E$16,0) -> 0.036441106 | G31: 2488 | H31: =IFERROR(G31/G$16,0) -> 0.09405716 | I31: 1488 | J31: =IFERROR(I31/I$16,0) -> 0.072299694 | K31: 1840 | L31: =IFERROR(K31/K$16,0) -> 0.073963902 | M31: 3015 | N31: =IFERROR(M31/M$16,0) -> 0.11142319 | O31: 1840 | P31: =IFERROR(O31/O$16,0) -> 0.071681795 | Q31: 1840 | R31: =IFERROR(Q31/Q$16,0) -> 0.071681795 | S31: 1840 | T31: =IFERROR(S31/S$16,0) -> 0.071681795 | U31: 1840 | V31: =IFERROR(U31/U$16,0) -> 0.071681795 | W31: 1840 | X31: =IFERROR(W31/W$16,0) -> 0.071681795 | Y31: 1840 | Z31: =IFERROR(Y31/Y$16,0) -> 0.071681795 | AB31: =SUM(C31,E31,G31,I31,K31,M31,O31,Q31,S31,U31,W31,Y31) -> 23527 | AC31: =IFERROR(AB31/AB$16,0) -> 0.081495157
A32: Bonus | C32: 0 | D32: =IFERROR(C32/C$16,0) -> 0 | E32: 0 | F32: =IFERROR(E32/E$16,0) -> 0 | G32: 0 | H32: =IFERROR(G32/G$16,0) -> 0 | I32: 0 | J32: =IFERROR(I32/I$16,0) -> 0 | K32: 0 | L32: =IFERROR(K32/K$16,0) -> 0 | M32: 0 | N32: =IFERROR(M32/M$16,0) -> 0 | O32: 0 | P32: =IFERROR(O32/O$16,0) -> 0 | Q32: 0 | R32: =IFERROR(Q32/Q$16,0) -> 0 | S32: 0 | T32: =IFERROR(S32/S$16,0) -> 0 | U32: 0 | V32: =IFERROR(U32/U$16,0) -> 0 | W32: 0 | X32: =IFERROR(W32/W$16,0) -> 0 | Y32: 0 | Z32: =IFERROR(Y32/Y$16,0) -> 0 | AB32: =SUM(C32,E32,G32,I32,K32,M32,O32,Q32,S32,U32,W32,Y32) -> 0 | AC32: =IFERROR(AB32/AB$16,0) -> 0
A33: Total Labor Cost | C33: =SUM(C28:C32) -> 16909 | D33: =IFERROR(C33/C$16,0) -> 0.94611683 | E33: =SUM(E28:E32) -> 11573 | F33: =IFERROR(E33/E$16,0) -> 0.64881987 | G33: =SUM(G28:G32) -> 13272 | H33: =IFERROR(G33/G$16,0) -> 0.501739 | I33: =SUM(I28:I32) -> 12726 | J33: =IFERROR(I33/I$16,0) -> 0.6183373 | K33: =SUM(K28:K32) -> 14210 | L33: =IFERROR(K33/K$16,0) -> 0.57121035 | M33: =SUM(M28:M32) -> 16320 | N33: =IFERROR(M33/M$16,0) -> 0.6031265 | O33: =SUM(O28:O32) -> 14210 | P33: =IFERROR(O33/O$16,0) -> 0.55358604 | Q33: =SUM(Q28:Q32) -> 14210 | R33: =IFERROR(Q33/Q$16,0) -> 0.55358604 | S33: =SUM(S28:S32) -> 14210 | T33: =IFERROR(S33/S$16,0) -> 0.55358604 | U33: =SUM(U28:U32) -> 14210 | V33: =IFERROR(U33/U$16,0) -> 0.55358604 | W33: =SUM(W28:W32) -> 14210 | X33: =IFERROR(W33/W$16,0) -> 0.55358604 | Y33: =SUM(Y28:Y32) -> 14210 | Z33: =IFERROR(Y33/Y$16,0) -> 0.55358604 | AB33: =SUM(AB28:AB32) -> 170270 | AC33: =IFERROR(AB33/AB$16,0) -> 0.58979812
A35: Prime Costs | C35: =C24+C33 -> 20743 | D35: =IFERROR(C35/C$16,0) -> 1.1606423 | E35: =E24+E33 -> 17148 | F35: =IFERROR(E35/E$16,0) -> 0.96137243 | G35: =G24+G33 -> 20455 | H35: =IFERROR(G35/G$16,0) -> 0.77328746 | I35: =I24+I33 -> 18764 | J35: =IFERROR(I35/I$16,0) -> 0.91171469 | K35: =K24+K33 -> 25581 | L35: =IFERROR(K35/K$16,0) -> 1.0282992 | M35: =M24+M33 -> 29934 | N35: =IFERROR(M35/M$16,0) -> 1.1062493 | O35: =O24+O33 -> 23533 | P35: =IFERROR(O35/O$16,0) -> 0.91678679 | Q35: =Q24+Q33 -> 24096 | R35: =IFERROR(Q35/Q$16,0) -> 0.93871986 | S35: =S24+S33 -> 23505 | T35: =IFERROR(S35/S$16,0) -> 0.91569598 | U35: =U24+U33 -> 23710 | V35: =IFERROR(U35/U$16,0) -> 0.92368226 | W35: =W24+W33 -> 23770 | X35: =IFERROR(W35/W$16,0) -> 0.92601971 | Y35: =Y24+Y33 -> 23661 | Z35: =IFERROR(Y35/Y$16,0) -> 0.92177335 | AB35: =AB24+AB33 -> 274900 | AC35: =IFERROR(AB35/AB$16,0) -> 0.9522259
A36: Operating Profit | C36: =C25-C33 -> -2871 | D36: =IFERROR(C36/C$16,0) -> -0.16064235 | E36: =E25-E33 -> 689 | F36: =IFERROR(E36/E$16,0) -> 0.038627572 | G36: =G25-G33 -> 5997 | H36: =IFERROR(G36/G$16,0) -> 0.22671254 | I36: =I25-I33 -> 1817 | J36: =IFERROR(I36/I$16,0) -> 0.088285312 | K36: =K25-K33 -> -704 | L36: =IFERROR(K36/K$16,0) -> -0.028299232 | M36: =M25-M33 -> -2875 | N36: =IFERROR(M36/M$16,0) -> -0.10624931 | O36: =O25-O33 -> 2136 | P36: =IFERROR(O36/O$16,0) -> 0.083213214 | Q36: =Q25-Q33 -> 1573 | R36: =IFERROR(Q36/Q$16,0) -> 0.061280143 | S36: =S25-S33 -> 2164 | T36: =IFERROR(S36/S$16,0) -> 0.084304024 | U36: =U25-U33 -> 1959 | V36: =IFERROR(U36/U$16,0) -> 0.076317737 | W36: =W25-W33 -> 1899 | X36: =IFERROR(W36/W$16,0) -> 0.073980288 | Y36: =Y25-Y33 -> 2008 | Z36: =IFERROR(Y36/Y$16,0) -> 0.078226655 | AB36: =AB25-AB33 -> 13792 | AC36: =IFERROR(AB36/AB$16,0) -> 0.047774098
A38: Controllable Expenses
A39: Operating Expenses | C39: 3310 | D39: =IFERROR(C39/C$16,0) -> 0.18520591 | E39: 5119 | F39: =IFERROR(E39/E$16,0) -> 0.28698772 | G39: 1987 | H39: =IFERROR(G39/G$16,0) -> 0.075117193 | I39: 4160 | J39: =IFERROR(I39/I$16,0) -> 0.20212818 | K39: 3982 | L39: =IFERROR(K39/K$16,0) -> 0.16006753 | M39: 3744 | N39: =IFERROR(M39/M$16,0) -> 0.13836432 | O39: 3982 | P39: =IFERROR(O39/O$16,0) -> 0.15512875 | Q39: 3982 | R39: =IFERROR(Q39/Q$16,0) -> 0.15512875 | S39: 3982 | T39: =IFERROR(S39/S$16,0) -> 0.15512875 | U39: 3982 | V39: =IFERROR(U39/U$16,0) -> 0.15512875 | W39: 3982 | X39: =IFERROR(W39/W$16,0) -> 0.15512875 | Y39: 3982 | Z39: =IFERROR(Y39/Y$16,0) -> 0.15512875 | AB39: =SUM(C39,E39,G39,I39,K39,M39,O39,Q39,S39,U39,W39,Y39) -> 46194 | AC39: =IFERROR(AB39/AB$16,0) -> 0.16001136
