Workbook

Sheet Scenario Summary
A1: METHOD TERRAPIN — SCENARIO SUMMARY
A2: T12 (GL actual) · 2026 Forecast (status quo) · 2026 Modified (changes from Aug 1 go-live, see 2026 Bridge) · 2027 Plan · blue = external actuals
A4: LITTLE WING
B5: T12 (GL actual) | C5: 2026 Forecast | D5: 2026 Modified | E5: 2027 Plan
A6: Revenue | B6: 258287 | C6: 287305 | D6: =287305+'2026 Bridge'!$D$7*'LW Assumptions'!$C$43+'2026 Bridge'!$D$8*'LW Assumptions'!$C$47+'2026 Bridge'!$D$13*'LW Assumptions'!$C$36 -> 300862.55 | E6: ='LW Budget'!$Z$11 -> 298740.15
A7: Cost of goods sold | B7: 81599 | C7: 99691 | D7: =99691+'2026 Bridge'!$D$13*'LW Assumptions'!$C$36*'LW Assumptions'!$C$37 -> 102191 | E7: ='LW Budget'!$Z$18 -> 86932.346
A8: GROSS PROFIT | B8: =B6-B7 -> 176688 | C8: =C6-C7 -> 187614 | D8: =D6-D7 -> 198671.55 | E8: =E6-E7 -> 211807.8
A9: Labor | B9: 164857 | C9: 168162 | D9: =168162-'2026 Bridge'!$D$6*(168162-'LW Assumptions'!$C$25) -> 144741.97 | E9: ='LW Budget'!$Z$21 -> 111953.92
A10: Operating expenses (excl fees & rent) | B10: 105344 | C10: 112209 | D10: =112209+'LW Assumptions'!$C$31*('2026 Bridge'!$D$7*'LW Assumptions'!$C$43+'2026 Bridge'!$D$8*'LW Assumptions'!$C$47+'2026 Bridge'!$D$13*'LW Assumptions'!$C$36) -> 112547.94 | E10: ='LW Budget'!$Z$22+'LW Budget'!$Z$23+'LW Budget'!$Z$24 -> 102800.5
A11: Management fee | B11: 48000 | C11: 48000 | D11: =48000-'2026 Bridge'!$D$9*(48000-'LW Assumptions'!$C$40*(287305+'LW Assumptions'!$C$43+'LW Assumptions'!$C$47+'LW Assumptions'!$C$36)) -> 33330.719 | E11: ='LW Budget'!$Z$25 -> 11949.606
A12: Admin fee (Vessel 5% of F&B) | B12: 0 | C12: 0 | D12: =0 -> 0 | E12: =0 -> 0
A13: Rent / occupancy | B13: 15642 | C13: 17299 | D13: ='LW Assumptions'!$C$41*(287305+'2026 Bridge'!$D$7*'LW Assumptions'!$C$43+'2026 Bridge'!$D$8*'LW Assumptions'!$C$47+'2026 Bridge'!$D$13*'LW Assumptions'!$C$36) -> 18051.753 | E13: ='LW Budget'!$Z$26 -> 17924.409
A14: NET OPERATING INCOME | B14: =B6-B7-B9-B10-B11-B12-B13 -> -157155 | C14: =C6-C7-C9-C10-C11-C12-C13 -> -158056 | D14: =D6-D7-D9-D10-D11-D12-D13 -> -110000.82 | E14: =E6-E7-E9-E10-E11-E12-E13 -> -32820.635
A15: NOI margin | B15: =B14/B6 -> -0.60845106 | C15: =C14/C6 -> -0.55013313 | D15: =D14/D6 -> -0.36561819 | E15: =E14/E6 -> -0.10986349
A17: VESSEL
B18: T12 (GL actual) | C18: 2026 Forecast | D18: 2026 Modified | E18: 2027 Plan
A19: Revenue | B19: ='Vessel 2026 P&L'!$AB$16 -> 351975 | C19: ='Vessel 2026 P&L'!$AB$16 -> 351975 | D19: =C19 -> 351975 | E19: ='Vessel Budget'!$Z$10 -> 398400
A20: Cost of goods sold | B20: ='Vessel 2026 P&L'!$AB$24 -> 122932 | C20: ='Vessel 2026 P&L'!$AB$24 -> 122932 | D20: =C20 -> 122932 | E20: ='Vessel Budget'!$Z$14 -> 170033.8
A21: GROSS PROFIT | B21: =B19-B20 -> 229043 | C21: =C19-C20 -> 229043 | D21: =D19-D20 -> 229043 | E21: =E19-E20 -> 228366.2
A22: Labor | B22: ='Vessel 2026 P&L'!$AB$33 -> 77956 | C22: ='Vessel 2026 P&L'!$AB$33 -> 77956 | D22: =C22 -> 77956 | E22: ='Vessel Budget'!$Z$20 -> 75489.381
A23: Operating expenses (excl fees & rent) | B23: ='Vessel 2026 P&L'!$AB$44+'Vessel 2026 P&L'!$AB$53-'Vessel 2026 P&L'!$AB$50-'Vessel 2026 P&L'!$AB$48 -> 91608 | C23: ='Vessel 2026 P&L'!$AB$44+'Vessel 2026 P&L'!$AB$53-'Vessel 2026 P&L'!$AB$50-'Vessel 2026 P&L'!$AB$48 -> 91608 | D23: =C23 -> 91608 | E23: ='Vessel Budget'!$Z$24+'Vessel Budget'!$Z$23+'Vessel Budget'!$Z$25 -> 101568
A24: Management fee | B24: ='Vessel 2026 P&L'!$AB$50 -> 48000 | C24: ='Vessel 2026 P&L'!$AB$50 -> 48000 | D24: ='Vessel 2026 P&L'!$AB$50-'2026 Bridge'!$D$10*('Vessel 2026 P&L'!$AB$50-'Vessel Assumptions'!$C$30*'Vessel 2026 P&L'!$AB$16) -> 33866.25 | E24: ='Vessel Budget'!$Z$26 -> 15936
A25: Admin fee (Vessel 5% of F&B) | B25: 0 | C25: 0 | D25: ='2026 Bridge'!$D$12*'Vessel Assumptions'!$C$32*SUM('Vessel 2026 P&L'!$AB$9:$AB$13) -> 4823.4583 | E25: ='Vessel Budget'!$Z$27 -> 16600
A26: Rent / occupancy | B26: ='Vessel 2026 P&L'!$AB$48 -> 21342 | C26: ='Vessel 2026 P&L'!$AB$48 -> 21342 | D26: ='Vessel 2026 P&L'!$AB$48-'2026 Bridge'!$D$11*('Vessel 2026 P&L'!$AB$48-0) -> 12449.5 | E26: ='Vessel Budget'!$Z$28 -> 0
A27: NET OPERATING INCOME | B27: =B19-B20-B22-B23-B24-B25-B26 -> -9863 | C27: =C19-C20-C22-C23-C24-C25-C26 -> -9863 | D27: =D19-D20-D22-D23-D24-D25-D26 -> 8339.7917 | E27: =E19-E20-E22-E23-E24-E25-E26 -> 18772.819
A28: NOI margin | B28: =B27/B19 -> -0.028021877 | C28: =C27/C19 -> -0.028021877 | D28: =D27/D19 -> 0.023694273 | E28: =E27/E19 -> 0.04712053
A30: COMBINED
B31: T12 (GL actual) | C31: 2026 Forecast | D31: 2026 Modified | E31: 2027 Plan
A32: Revenue | B32: =B6+B19 -> 610262 | C32: =C6+C19 -> 639280 | D32: =D6+D19 -> 652837.55 | E32: =E6+E19 -> 697140.15
A33: Cost of goods sold | B33: =B7+B20 -> 204531 | C33: =C7+C20 -> 222623 | D33: =D7+D20 -> 225123 | E33: =E7+E20 -> 256966.15
A34: GROSS PROFIT | B34: =B32-B33 -> 405731 | C34: =C32-C33 -> 416657 | D34: =D32-D33 -> 427714.55 | E34: =E32-E33 -> 440174
A35: Labor | B35: =B9+B22 -> 242813 | C35: =C9+C22 -> 246118 | D35: =D9+D22 -> 222697.97 | E35: =E9+E22 -> 187443.3
A36: Operating expenses (excl fees & rent) | B36: =B10+B23 -> 196952 | C36: =C10+C23 -> 203817 | D36: =D10+D23 -> 204155.94 | E36: =E10+E23 -> 204368.5
A37: Management fee | B37: =B11+B24 -> 96000 | C37: =C11+C24 -> 96000 | D37: =D11+D24 -> 67196.969 | E37: =E11+E24 -> 27885.606
A38: Admin fee (Vessel 5% of F&B) | B38: =B12+B25 -> 0 | C38: =C12+C25 -> 0 | D38: =D12+D25 -> 4823.4583 | E38: =E12+E25 -> 16600
A39: Rent / occupancy | B39: =B13+B26 -> 36984 | C39: =C13+C26 -> 38641 | D39: =D13+D26 -> 30501.253 | E39: =E13+E26 -> 17924.409
A40: NET OPERATING INCOME | B40: =B32-B33-B35-B36-B37-B38-B39 -> -167018 | C40: =C32-C33-C35-C36-C37-C38-C39 -> -167919 | D40: =D32-D33-D35-D36-D37-D38-D39 -> -101661.03 | E40: =E32-E33-E35-E36-E37-E38-E39 -> -14047.816
A41: NOI margin | B41: =B40/B32 -> -0.27368245 | C41: =C40/C32 -> -0.26266894 | D41: =D40/D32 -> -0.15572179 | E41: =E40/E32 -> -0.020150634
A43: Vessel T12 seeded with 2026 actual/forecast. Admin fee = 5% of F&B (food+bev); did not exist in T12/Forecast. 2026 Modified = changes live from Aug 1, 2026 (edit dates on 2026 Bridge).

Sheet 2026 Bridge
A1: 2026 MODIFIED — TIME-STAMPED CHANGE BRIDGE
A2: Each change has an effective date (blue = editable). 2026 impact = full-year Δ × months live in 2026 ÷ 12. Base = 2026 status-quo forecast.
A5: Change | B5: Effective date | C5: Months live 2026 | D5: Proration | E5: Full-year Δ NOI | F5: 2026 Δ NOI
A6: Little Wing — Labor restructure (6a–4p, wknd 4h 2nd barista) | B6: 46235 | C6: =MAX(0,13-MONTH(B6)) -> 5 | D6: =C6/12 -> 0.41666667 | E6: =168162-'LW Assumptions'!$C$25 -> 56208.08 | F6: =E6*D6 -> 23420.033
A7: Little Wing — Menu pricing uplift (PMIX) | B7: 46235 | C7: =MAX(0,13-MONTH(B7)) -> 5 | D7: =C7/12 -> 0.41666667 | E7: ='LW Assumptions'!$C$43*(1-'LW Assumptions'!$C$31-'LW Assumptions'!$C$41) -> 16117.13 | F7: =E7*D7 -> 6715.4709
A8: Little Wing — Retail improvement uplift | B8: 46235 | C8: =MAX(0,13-MONTH(B8)) -> 5 | D8: =C8/12 -> 0.41666667 | E8: ='LW Assumptions'!$C$47*(1-'LW Assumptions'!$C$31-'LW Assumptions'!$C$41) -> 2675.2587 | F8: =E8*D8 -> 1114.6911
A9: Little Wing — Management fee: $48K flat → 4% of rev | B9: 46235 | C9: =MAX(0,13-MONTH(B9)) -> 5 | D9: =C9/12 -> 0.41666667 | E9: =48000-'LW Assumptions'!$C$40*(287305+'LW Assumptions'!$C$43+'LW Assumptions'!$C$47+'LW Assumptions'!$C$36) -> 35206.275 | F9: =E9*D9 -> 14669.281
A10: Vessel — Management fee: $48K flat → 4% of rev | B10: 46235 | C10: =MAX(0,13-MONTH(B10)) -> 5 | D10: =C10/12 -> 0.41666667 | E10: ='Vessel 2026 P&L'!$AB$50-'Vessel Assumptions'!$C$30*'Vessel 2026 P&L'!$AB$16 -> 33921 | F10: =E10*D10 -> 14133.75
A11: Vessel — Rent → $0 (waived) | B11: 46235 | C11: =MAX(0,13-MONTH(B11)) -> 5 | D11: =C11/12 -> 0.41666667 | E11: ='Vessel 2026 P&L'!$AB$48-0 -> 21342 | F11: =E11*D11 -> 8892.5
A12: Vessel — Admin fee: +5% of F&B revenue (new charge) | B12: 46235 | C12: =MAX(0,13-MONTH(B12)) -> 5 | D12: =C12/12 -> 0.41666667 | E12: =-'Vessel Assumptions'!$C$32*SUM('Vessel 2026 P&L'!$AB$9:$AB$13) -> -11576.3 | F12: =E12*D12 -> -4823.4583
A13: Little Wing — Retail programming expansion (new merch/goods) | B13: 46235 | C13: =MAX(0,13-MONTH(B13)) -> 5 | D13: =C13/12 -> 0.41666667 | E13: ='LW Assumptions'!$C$36*(1-'LW Assumptions'!$C$37-'LW Assumptions'!$C$31-'LW Assumptions'!$C$41) -> 4980 | F13: =E13*D13 -> 2075
A14: Little Wing — interaction / rounding (4% fee & 6% rent on added revenue) | F14: ='Scenario Summary'!$D$14-'Scenario Summary'!$C$14-(F6+F7+F8+F9+F13) -> 60.7
A17: RECONCILIATION — 2026 NOI
A18: Little Wing — 2026 Forecast (status quo) | F18: ='Scenario Summary'!$C$14 -> -158056
A19: + Little Wing changes (2026 Δ, time-stamped) | F19: =F6+F7+F8+F9+F13+F14 -> 48055.177
A20: Little Wing — 2026 MODIFIED | F20: ='Scenario Summary'!$D$14 -> -110000.82
A22: Vessel — 2026 Forecast (status quo) | F22: ='Scenario Summary'!$C$27 -> -9863
A23: + Vessel changes (2026 Δ, time-stamped) | F23: =F10+F11+F12 -> 18202.792
A24: Vessel — 2026 MODIFIED | F24: ='Scenario Summary'!$D$27 -> 8339.7917
A26: COMBINED — 2026 MODIFIED NOI | F26: ='Scenario Summary'!$D$40 -> -101661.03

Sheet Consolidated P&L
A1: METHOD TERRAPIN — CONSOLIDATED P&L 2027
A2: Vessel (events) + Little Wing (coffee) · FY roll-up · management fee (4%) & rent above NOI · $ and % of revenue
A4: FY 2027 | B4: Vessel | D4: Little Wing | F4: Consolidated
B5: $ | C5: % rev | D5: $ | E5: % rev | F5: $ | G5: % rev
A6: Revenue | B6: ='Vessel Budget'!$Z$10 -> 398400 | C6: =B6/$B$6 -> 1 | D6: ='LW Budget'!$Z$11 -> 298740.15 | E6: =D6/$D$6 -> 1 | F6: =B6+D6 -> 697140.15 | G6: =F6/$F$6 -> 1
A7: Cost of goods sold | B7: ='Vessel Budget'!$Z$14 -> 170033.8 | C7: =B7/$B$6 -> 0.42679167 | D7: ='LW Budget'!$Z$18 -> 86932.346 | E7: =D7/$D$6 -> 0.29099653 | F7: =B7+D7 -> 256966.15 | G7: =F7/$F$6 -> 0.36860041
A8: GROSS PROFIT | B8: =B6-B7 -> 228366.2 | C8: =B8/$B$6 -> 0.57320833 | D8: =D6-D7 -> 211807.8 | E8: =D8/$D$6 -> 0.70900347 | F8: =B8+D8 -> 440174 | G8: =F8/$F$6 -> 0.63139959
A10: Labor | B10: ='Vessel Budget'!$Z$20 -> 75489.381 | C10: =B10/$B$6 -> 0.18948138 | D10: ='LW Budget'!$Z$21 -> 111953.92 | E10: =D10/$D$6 -> 0.37475351 | F10: =B10+D10 -> 187443.3 | G10: =F10/$F$6 -> 0.26887463
A11: Credit card fees | B11: ='Vessel Budget'!$Z$24 -> 9960 | C11: =B11/$B$6 -> 0.025 | D11: ='LW Budget'!$Z$22 -> 7468.5037 | E11: =D11/$D$6 -> 0.025 | F11: =B11+D11 -> 17428.504 | G11: =F11/$F$6 -> 0.025
A12: Controllable expenses | B12: ='Vessel Budget'!$Z$23 -> 80848 | C12: =B12/$B$6 -> 0.20293173 | D12: ='LW Budget'!$Z$23 -> 89675 | E12: =D12/$D$6 -> 0.30017726 | F12: =B12+D12 -> 170523 | G12: =F12/$F$6 -> 0.24460361
A13: Non-controllable expenses | B13: ='Vessel Budget'!$Z$25 -> 10760 | C13: =B13/$B$6 -> 0.027008032 | D13: ='LW Budget'!$Z$24 -> 5657 | E13: =D13/$D$6 -> 0.018936189 | F13: =B13+D13 -> 16417 | G13: =F13/$F$6 -> 0.023549067
A14: Management fee (4% of revenue) | B14: ='Vessel Budget'!$Z$26 -> 15936 | C14: =B14/$B$6 -> 0.04 | D14: ='LW Budget'!$Z$25 -> 11949.606 | E14: =D14/$D$6 -> 0.04 | F14: =B14+D14 -> 27885.606 | G14: =F14/$F$6 -> 0.04
A15: Admin fee (Vessel 5% of F&B) | B15: ='Vessel Budget'!$Z$27 -> 16600 | C15: =B15/$B$6 -> 0.041666667 | D15: =0 -> 0 | E15: =D15/$D$6 -> 0 | F15: =B15+D15 -> 16600 | G15: =F15/$F$6 -> 0.023811568
A16: Rent (Vessel $0 / LW 6%) | B16: ='Vessel Budget'!$Z$28 -> 0 | C16: =B16/$B$6 -> 0 | D16: ='LW Budget'!$Z$26 -> 17924.409 | E16: =D16/$D$6 -> 0.06 | F16: =B16+D16 -> 17924.409 | G16: =F16/$F$6 -> 0.025711342
A17: Total operating expenses | B17: =B10+B11+B12+B13+B14+B15+B16 -> 209593.38 | C17: =B17/$B$6 -> 0.5260878 | D17: =D10+D11+D12+D13+D14+D15+D16 -> 244628.44 | E17: =D17/$D$6 -> 0.81886696 | F17: =B17+D17 -> 454221.82 | G17: =F17/$F$6 -> 0.65155022
A19: NET OPERATING INCOME (after mgmt fee, admin fee & rent) | B19: =B8-B17 -> 18772.819 | C19: =B19/$B$6 -> 0.04712053 | D19: =D8-D17 -> -32820.635 | E19: =D19/$D$6 -> -0.10986349 | F19: =B19+D19 -> -14047.816 | G19: =F19/$F$6 -> -0.020150634
A26: CONSOLIDATED NOI BY MONTH (after mgmt fee & rent)
A27: Month | B27: Vessel | C27: Little Wing | D27: Consolidated | E27: Cumulative
A28: Jan | B28: ='Vessel Budget'!B29 -> 6589.8495 | C28: ='LW Budget'!B27 -> -7042.8916 | D28: =B28+C28 -> -453.04209 | E28: =D28 -> -453.04209
A29: Feb | B29: ='Vessel Budget'!D29 -> -4819.2755 | C29: ='LW Budget'!D27 -> -5497.4199 | D29: =B29+C29 -> -10316.695 | E29: =E28+D29 -> -10769.738
A30: Mar | B30: ='Vessel Budget'!F29 -> 6589.8495 | C30: ='LW Budget'!F27 -> 257.02671 | D30: =B30+C30 -> 6846.8762 | E30: =E29+D30 -> -3922.8613
A31: Apr | B31: ='Vessel Budget'!H29 -> -4819.2755 | C31: ='LW Budget'!H27 -> -3745.4977 | D31: =B31+C31 -> -8564.7732 | E31: =E30+D31 -> -12487.635
A32: May | B32: ='Vessel Budget'!J29 -> 3330.0995 | C32: ='LW Budget'!J27 -> -946.78376 | D32: =B32+C32 -> 2383.3157 | E32: =E31+D32 -> -10104.319
A33: Jun | B33: ='Vessel Budget'!L29 -> 1700.2245 | C33: ='LW Budget'!L27 -> 565.24871 | D33: =B33+C33 -> 2265.4732 | E33: =E32+D33 -> -7838.8456
A34: Jul | B34: ='Vessel Budget'!N29 -> 1700.2245 | C34: ='LW Budget'!N27 -> -2735.0529 | D34: =B34+C34 -> -1034.8284 | E34: =E33+D34 -> -8873.674
A35: Aug | B35: ='Vessel Budget'!P29 -> 1700.2245 | C35: ='LW Budget'!P27 -> -2735.0529 | D35: =B35+C35 -> -1034.8284 | E35: =E34+D35 -> -9908.5024
A36: Sep | B36: ='Vessel Budget'!R29 -> 1700.2245 | C36: ='LW Budget'!R27 -> -2735.0529 | D36: =B36+C36 -> -1034.8284 | E36: =E35+D36 -> -10943.331
A37: Oct | B37: ='Vessel Budget'!T29 -> 1700.2245 | C37: ='LW Budget'!T27 -> -2735.0529 | D37: =B37+C37 -> -1034.8284 | E37: =E36+D37 -> -11978.159
A38: Nov | B38: ='Vessel Budget'!V29 -> 1700.2245 | C38: ='LW Budget'!V27 -> -2735.0529 | D38: =B38+C38 -> -1034.8284 | E38: =E37+D38 -> -13012.988
A39: Dec | B39: ='Vessel Budget'!X29 -> 1700.2245 | C39: ='LW Budget'!X27 -> -2735.0529 | D39: =B39+C39 -> -1034.8284 | E39: =E38+D39 -> -14047.816
A40: FY 2027 | B40: ='Vessel Budget'!$Z$29 -> 18772.819 | C40: ='LW Budget'!$Z$27 -> -32820.635 | D40: =B40+C40 -> -14047.816

Sheet Combined 12-Mo P&L
A1: METHOD TERRAPIN — COMBINED 12-MONTH P&L (2027 PLAN)
A2: Vessel + Little Wing · monthly · mgmt fee (4%), admin fee (Vessel 5% F&B) & rent above NOI
A4: ($) | B4: Jan | C4: Feb | D4: Mar | E4: Apr | F4: May | G4: Jun | H4: Jul | I4: Aug | J4: Sep | K4: Oct | L4: Nov | M4: Dec | N4: FY 2027
A6: Revenue | B6: ='Vessel Budget'!B10+'LW Budget'!B11 -> 65518.62 | C6: ='Vessel Budget'!D10+'LW Budget'!D11 -> 34564.96 | D6: ='Vessel Budget'!F10+'LW Budget'!F11 -> 78018.406 | E6: ='Vessel Budget'!H10+'LW Budget'!H11 -> 37564.809 | F6: ='Vessel Budget'!J10+'LW Budget'!J11 -> 66357.099 | G6: ='Vessel Budget'!L10+'LW Budget'!L11 -> 64146.18 | H6: ='Vessel Budget'!N10+'LW Budget'!N11 -> 58495.012 | I6: ='Vessel Budget'!P10+'LW Budget'!P11 -> 58495.012 | J6: ='Vessel Budget'!R10+'LW Budget'!R11 -> 58495.012 | K6: ='Vessel Budget'!T10+'LW Budget'!T11 -> 58495.012 | L6: ='Vessel Budget'!V10+'LW Budget'!V11 -> 58495.012 | M6: ='Vessel Budget'!X10+'LW Budget'!X11 -> 58495.012 | N6: ='Vessel Budget'!Z10+'LW Budget'!Z11 -> 697140.15
A7: Cost of goods sold | B7: ='Vessel Budget'!B14+'LW Budget'!B18 -> 25583.858 | C7: ='Vessel Budget'!D14+'LW Budget'!D18 -> 12013.733 | D7: ='Vessel Budget'!F14+'LW Budget'!F18 -> 29221.252 | E7: ='Vessel Budget'!H14+'LW Budget'!H18 -> 12886.679 | F7: ='Vessel Budget'!J14+'LW Budget'!J18 -> 24524.219 | G7: ='Vessel Budget'!L14+'LW Budget'!L18 -> 23229.032 | H7: ='Vessel Budget'!N14+'LW Budget'!N18 -> 21584.562 | I7: ='Vessel Budget'!P14+'LW Budget'!P18 -> 21584.562 | J7: ='Vessel Budget'!R14+'LW Budget'!R18 -> 21584.562 | K7: ='Vessel Budget'!T14+'LW Budget'!T18 -> 21584.562 | L7: ='Vessel Budget'!V14+'LW Budget'!V18 -> 21584.562 | M7: ='Vessel Budget'!X14+'LW Budget'!X18 -> 21584.562 | N7: ='Vessel Budget'!Z14+'LW Budget'!Z18 -> 256966.15
A8: GROSS PROFIT | B8: =B6-B7 -> 39934.763 | C8: =C6-C7 -> 22551.227 | D8: =D6-D7 -> 48797.154 | E8: =E6-E7 -> 24678.13 | F8: =F6-F7 -> 41832.88 | G8: =G6-G7 -> 40917.148 | H8: =H6-H7 -> 36910.45 | I8: =I6-I7 -> 36910.45 | ... N8: =N6-N7 -> 440174
A10: Labor | B10: ='Vessel Budget'!B20+'LW Budget'!B21 -> 17499.644 | C10: ='Vessel Budget'!D20+'LW Budget'!D21 -> 13232.969 | D10: ='Vessel Budget'!F20+'LW Budget'!F21 -> 17499.644 | E10: ='Vessel Budget'!H20+'LW Budget'!H21 -> 13232.969 | F10: ='Vessel Budget'!J20+'LW Budget'!J21 -> 16280.594 | G10: ='Vessel Budget'!L20+'LW Budget'!L21 -> 15671.069 | H10: ='Vessel Budget'!N20+'LW Budget'!N21 -> 15671.069 | I10: ='Vessel Budget'!P20+'LW Budget'!P21 -> 15671.069 | J10: ='Vessel Budget'!R20+'LW Budget'!R21 -> 15671.069 | K10: ='Vessel Budget'!T20+'LW Budget'!T21 -> 15671.069 | L10: ='Vessel Budget'!V20+'LW Budget'!V21 -> 15671.069 | M10: ='Vessel Budget'!X20+'LW Budget'!X21 -> 15671.069 | N10: ='Vessel Budget'!Z20+'LW Budget'!Z21 -> 187443.3
A11: Credit card fees | B11: ='Vessel Budget'!B24+'LW Budget'!B22 -> 1637.9655 | C11: ='Vessel Budget'!D24+'LW Budget'!D22 -> 864.124 | D11: ='Vessel Budget'!F24+'LW Budget'!F22 -> 1950.4602 | E11: ='Vessel Budget'!H24+'LW Budget'!H22 -> 939.12023 | F11: ='Vessel Budget'!J24+'LW Budget'!J22 -> 1658.9275 | G11: ='Vessel Budget'!L24+'LW Budget'!L22 -> 1603.6545 | H11: ='Vessel Budget'!N24+'LW Budget'!N22 -> 1462.3753 | I11: ='Vessel Budget'!P24+'LW Budget'!P22 -> 1462.3753 | J11: ='Vessel Budget'!R24+'LW Budget'!R22 -> 1462.3753 | K11: ='Vessel Budget'!T24+'LW Budget'!T22 -> 1462.3753 | L11: ='Vessel Budget'!V24+'LW Budget'!V22 -> 1462.3753 | M11: ='Vessel Budget'!X24+'LW Budget'!X22 -> 1462.3753 | N11: ='Vessel Budget'!Z24+'LW Budget'!Z22 -> 17428.504
A12: Controllable expenses | B12: ='Vessel Budget'!B23+'LW Budget'!B23 -> 14210.25 | C12: ='Vessel Budget'!D23+'LW Budget'!D23 -> 14210.25 | D12: ='Vessel Budget'!F23+'LW Budget'!F23 -> 14210.25 | E12: ='Vessel Budget'!H23+'LW Budget'!H23 -> 14210.25 | F12: ='Vessel Budget'!J23+'LW Budget'!J23 -> 14210.25 | G12: ='Vessel Budget'!L23+'LW Budget'!L23 -> 14210.25 | H12: ='Vessel Budget'!N23+'LW Budget'!N23 -> 14210.25 | I12: ='Vessel Budget'!P23+'LW Budget'!P23 -> 14210.25 | J12: ='Vessel Budget'!R23+'LW Budget'!R23 -> 14210.25 | K12: ='Vessel Budget'!T23+'LW Budget'!T23 -> 14210.25 | L12: ='Vessel Budget'!V23+'LW Budget'!V23 -> 14210.25 | M12: ='Vessel Budget'!X23+'LW Budget'!X23 -> 14210.25 | N12: ='Vessel Budget'!Z23+'LW Budget'!Z23 -> 170523
A13: Non-controllable expenses | B13: ='Vessel Budget'!B25+'LW Budget'!B24 -> 1368.0833 | C13: ='Vessel Budget'!D25+'LW Budget'!D24 -> 1368.0833 | D13: ='Vessel Budget'!F25+'LW Budget'!F24 -> 1368.0833 | E13: ='Vessel Budget'!H25+'LW Budget'!H24 -> 1368.0833 | F13: ='Vessel Budget'!J25+'LW Budget'!J24 -> 1368.0833 | G13: ='Vessel Budget'!L25+'LW Budget'!L24 -> 1368.0833 | H13: ='Vessel Budget'!N25+'LW Budget'!N24 -> 1368.0833 | I13: ='Vessel Budget'!P25+'LW Budget'!P24 -> 1368.0833 | J13: ='Vessel Budget'!R25+'LW Budget'!R24 -> 1368.0833 | K13: ='Vessel Budget'!T25+'LW Budget'!T24 -> 1368.0833 | L13: ='Vessel Budget'!V25+'LW Budget'!V24 -> 1368.0833 | M13: ='Vessel Budget'!X25+'LW Budget'!X24 -> 1368.0833 | N13: ='Vessel Budget'!Z25+'LW Budget'!Z24 -> 16417
A14: Management fee (4% of revenue) | B14: ='Vessel Budget'!B26+'LW Budget'!B25 -> 2620.7448 | C14: ='Vessel Budget'!D26+'LW Budget'!D25 -> 1382.5984 | D14: ='Vessel Budget'!F26+'LW Budget'!F25 -> 3120.7362 | E14: ='Vessel Budget'!H26+'LW Budget'!H25 -> 1502.5924 | F14: ='Vessel Budget'!J26+'LW Budget'!J25 -> 2654.284 | G14: ='Vessel Budget'!L26+'LW Budget'!L25 -> 2565.8472 | H14: ='Vessel Budget'!N26+'LW Budget'!N25 -> 2339.8005 | I14: ='Vessel Budget'!P26+'LW Budget'!P25 -> 2339.8005 | J14: ='Vessel Budget'!R26+'LW Budget'!R25 -> 2339.8005 | K14: ='Vessel Budget'!T26+'LW Budget'!T25 -> 2339.8005 | L14: ='Vessel Budget'!V26+'LW Budget'!V25 -> 2339.8005 | M14: ='Vessel Budget'!X26+'LW Budget'!X25 -> 2339.8005 | N14: ='Vessel Budget'!Z26+'LW Budget'!Z25 -> 27885.606
A15: Admin fee (Vessel 5% of F&B) | B15: ='Vessel Budget'!B27 -> 2000 | C15: ='Vessel Budget'!D27 -> 600 | D15: ='Vessel Budget'!F27 -> 2000 | E15: ='Vessel Budget'!H27 -> 600 | F15: ='Vessel Budget'!J27 -> 1600 | G15: ='Vessel Budget'!L27 -> 1400 | H15: ='Vessel Budget'!N27 -> 1400 | I15: ='Vessel Budget'!P27 -> 1400 | J15: ='Vessel Budget'!R27 -> 1400 | K15: ='Vessel Budget'!T27 -> 1400 | L15: ='Vessel Budget'!V27 -> 1400 | M15: ='Vessel Budget'!X27 -> 1400 | N15: ='Vessel Budget'!Z27 -> 16600
A16: Rent (Vessel $0 / LW 6%) | B16: ='Vessel Budget'!B28+'LW Budget'!B26 -> 1051.1172 | C16: ='Vessel Budget'!D28+'LW Budget'!D26 -> 1209.8976 | D16: ='Vessel Budget'!F28+'LW Budget'!F26 -> 1801.1044 | E16: ='Vessel Budget'!H28+'LW Budget'!H26 -> 1389.8885 | F16: ='Vessel Budget'!J28+'LW Budget'!J26 -> 1677.4259 | G16: ='Vessel Budget'!L28+'LW Budget'!L26 -> 1832.7708 | H16: ='Vessel Budget'!N28+'LW Budget'!N26 -> 1493.7007 | I16: ='Vessel Budget'!P28+'LW Budget'!P26 -> 1493.7007 | J16: ='Vessel Budget'!R28+'LW Budget'!R26 -> 1493.7007 | K16: ='Vessel Budget'!T28+'LW Budget'!T26 -> 1493.7007 | L16: ='Vessel Budget'!V28+'LW Budget'!V26 -> 1493.7007 | M16: ='Vessel Budget'!X28+'LW Budget'!X26 -> 1493.7007 | N16: ='Vessel Budget'!Z28+'LW Budget'!Z26 -> 17924.409
A18: NET OPERATING INCOME | B18: =B8-(B10+B11+B12+B13+B14+B15+B16) -> -453.04209 | C18: =C8-(C10+C11+C12+C13+C14+C15+C16) -> -10316.695 | D18: =D8-(D10+D11+D12+D13+D14+D15+D16) -> 6846.8762 | E18: =E8-(E10+E11+E12+E13+E14+E15+E16) -> -8564.7732 | F18: =F8-(F10+F11+F12+F13+F14+F15+F16) -> 2383.3157 | G18: =G8-(G10+G11+G12+G13+G14+G15+G16) -> 2265.4732 | H18: =H8-(H10+H11+H12+H13+H14+H15+H16) -> -1034.8284 | I18: =I8-(I10+I11+I12+I13+I14+I15+I16) -> -1034.8284 | ... N18: =N8-(N10+N11+N12+N13+N14+N15+N16) -> -14047.816

Sheet Vessel Summary
B2: VESSEL EVENTS — 2027 OPERATING SUMMARY
B3: ="$"&TEXT('Vessel Assumptions'!$C$6,"#,##0")&" F&B min · "&TEXT('Vessel Assumptions'!$C$7,"0%")&" volume · "&TEXT('Vessel Assumptions'!$C$30,"0%")&" mgmt fee" -> $4,000 F&B min · 80% volume · 4% mgmt fee
B5: ANNUAL P&L | C5: $ | D5: % rev | F5: KEY METRICS
B6: Total revenue | C6: ='Vessel Budget'!Z10 -> 398400 | D6: =C6/C6 -> 1 | F6: Net operating margin | G6: ='Vessel Budget'!Z28/'Vessel Budget'!Z10 -> 0
B7: Total COGS | C7: ='Vessel Budget'!Z14 -> 170033.8 | D7: =C7/C6 -> 0.42679167 | F7: Prime cost % | G7: ='Vessel Budget'!Z21/'Vessel Budget'!Z10 -> 0.61627304
B8: Gross profit | C8: ='Vessel Budget'!Z15 -> 228366.2 | D8: =C8/C6 -> 0.57320833 | F8: COGS % | G8: ='Vessel Budget'!Z14/'Vessel Budget'!Z10 -> 0.42679167
B9: Total labor (incl. mgmt) | C9: ='Vessel Budget'!Z20 -> 75489.381 | D9: =C9/C6 -> 0.18948138 | F9: Total events / year | G9: ='Vessel Budget'!Z6 -> 83
B10: Prime cost | C10: ='Vessel Budget'!Z21 -> 245523.18 | D10: =C10/C6 -> 0.61627304 | F10: Avg F&B / event | G10: ='Vessel Assumptions'!C6 -> 4000
B11: Controllable (excl CC) | C11: ='Vessel Budget'!Z23 -> 80848 | D11: =C11/C6 -> 0.20293173 | F11: Revenue / event | G11: ='Vessel Budget'!Z10/'Vessel Budget'!Z6 -> 4800
B12: Credit card fees (2.5%) | C12: ='Vessel Budget'!Z24 -> 9960 | D12: =C12/C6 -> 0.025
B13: Non-controllable | C13: ='Vessel Budget'!Z25 -> 10760 | D13: =C13/C6 -> 0.027008032
B14: Management fee (4% of revenue) | C14: ='Vessel Budget'!Z26 -> 15936 | D14: =C14/C6 -> 0.04
B15: Admin fee (5% of F&B) | C15: ='Vessel Budget'!Z27 -> 16600 | D15: =C15/C6 -> 0.041666667
B16: Rent / occupancy (none) | C16: ='Vessel Budget'!Z28 -> 0 | D16: =C16/C6 -> 0
B17: NET OPERATING INCOME | C17: ='Vessel Budget'!Z29 -> 18772.819 | D17: =C17/C6 -> 0.04712053
B20: Adjust inputs on the Vessel Assumptions tab — every figure recalculates. Management fee = 4% of revenue; no separate rent.

Sheet Vessel Assumptions
B2: VESSEL · EVENT OPERATING MODEL
B3: Model drivers — adjust any input and the 2027 budget recalculates
B5: REVENUE DRIVERS
B6: F&B minimum per event | C6: 4000 | D6: the recommended minimum
B7: Event volume (% of run-rate) | C7: 0.8 | D7: =TEXT($C$7,"0%")&" of Jan–May run-rate" -> 80% of Jan–May run-rate
B8: Food share of F&B | C8: 0.749 | D8: balance is beverage
B9: Service charge (% of F&B) | C9: 0.2 | D9: revenue, not billed labor
B11: COST OF SALES (% of that category's sales)
B12: Food cost % (of food sales) | C12: 0.6 | D12: =TEXT(1-$C$12,"0%")&" margin target" -> 40% margin target
B13: Beverage cost % (of bev sales) | C13: 0.25 | D13: =TEXT(1-$C$13,"0%")&" margin" -> 75% margin
B15: LABOR
B16: Bartenders per event | C16: 1
B17: Servers per event | C17: 2
B18: Hourly rate | C18: 35
B19: Shift hours | C19: 5
B20: Hourly labor per event (calc) | C20: =(C16+C17)*C18*C19 -> 525
B21: Management labor / month | C21: ='Vessel GL Basis'!D8 -> 1787.1667 | D21: linked ← Vessel GL Basis
B22: Payroll taxes & benefits % | C22: 0.161 | D22: on all wages (hourly + mgmt)
B24: OVERHEAD & VARIABLE
B25: Controllable exp / month (excl CC) | C25: ='Vessel GL Basis'!D18 -> 6737.3333 | D25: linked ← Vessel GL Basis
B26: Non-controllable / month | C26: ='Vessel GL Basis'!D24 -> 896.66667 | D26: linked ← Vessel GL Basis
B27: Credit card fee (% of revenue) | C27: 0.025 | D27: variable — own line
B29: OWNER CHARGES (above NOI)
B30: Management fee (% of revenue) | C30: 0.04 | D30: 4% of gross revenue → Method (replaces profit split)
B31: Rent (% of revenue) | C31: 0 | D31: Vessel carries no separate rent (owner)
B32: Admin fee (% of F&B revenue) | C32: 0.05 | D32: 5% of food + beverage sales → Method admin (above NOI)

Sheet Vessel Budget
A1: 2027 BUDGET
A2: $ per month · management fee (4% of revenue) & rent shown above NOI · driven by Vessel Assumptions
A4: ($ / % of revenue) | B4: Jan | D4: Feb | F4: Mar | H4: Apr | J4: May | L4: Jun | N4: Jul | P4: Aug | R4: Sep | T4: Oct | V4: Nov | X4: Dec | Z4: FY 2027
A5: Events (2026 run-rate) | B5: 13 | D5: 4 | F5: 13 | H5: 4 | J5: 10 | L5: =AVERAGE($B5,$D5,$F5,$H5,$J5) -> 8.8 | N5: =AVERAGE($B5,$D5,$F5,$H5,$J5) -> 8.8 | P5: =AVERAGE($B5,$D5,$F5,$H5,$J5) -> 8.8 | R5: =AVERAGE($B5,$D5,$F5,$H5,$J5) -> 8.8 | T5: =AVERAGE($B5,$D5,$F5,$H5,$J5) -> 8.8 | V5: =AVERAGE($B5,$D5,$F5,$H5,$J5) -> 8.8 | X5: =AVERAGE($B5,$D5,$F5,$H5,$J5) -> 8.8 | Z5: =B5+D5+F5+H5+J5+L5+N5+P5+R5+T5+V5+X5 -> 105.6
A6: Events (budgeted, whole) | B6: =ROUND(B5*'Vessel Assumptions'!$C$7,0) -> 10 | D6: =ROUND(D5*'Vessel Assumptions'!$C$7,0) -> 3 | F6: =ROUND(F5*'Vessel Assumptions'!$C$7,0) -> 10 | H6: =ROUND(H5*'Vessel Assumptions'!$C$7,0) -> 3 | J6: =ROUND(J5*'Vessel Assumptions'!$C$7,0) -> 8 | L6: =ROUND(L5*'Vessel Assumptions'!$C$7,0) -> 7 | N6: =ROUND(N5*'Vessel Assumptions'!$C$7,0) -> 7 | P6: =ROUND(P5*'Vessel Assumptions'!$C$7,0) -> 7 | R6: =ROUND(R5*'Vessel Assumptions'!$C$7,0) -> 7 | T6: =ROUND(T5*'Vessel Assumptions'!$C$7,0) -> 7 | V6: =ROUND(V5*'Vessel Assumptions'!$C$7,0) -> 7 | X6: =ROUND(X5*'Vessel Assumptions'!$C$7,0) -> 7 | Z6: =B6+D6+F6+H6+J6+L6+N6+P6+R6+T6+V6+X6 -> 83
A7: Food revenue | B7: =B6*'Vessel Assumptions'!$C$6*'Vessel Assumptions'!$C$8 -> 29960 | C7: =B7/B10 -> 0.62416667 | D7: =D6*'Vessel Assumptions'!$C$6*'Vessel Assumptions'!$C$8 -> 8988 | E7: =D7/D10 -> 0.62416667 | F7: =F6*'Vessel Assumptions'!$C$6*'Vessel Assumptions'!$C$8 -> 29960 | G7: =F7/F10 -> 0.62416667 | H7: =H6*'Vessel Assumptions'!$C$6*'Vessel Assumptions'!$C$8 -> 8988 | I7: =H7/H10 -> 0.62416667 | J7: =J6*'Vessel Assumptions'!$C$6*'Vessel Assumptions'!$C$8 -> 23968 | K7: =J7/J10 -> 0.62416667 | L7: =L6*'Vessel Assumptions'!$C$6*'Vessel Assumptions'!$C$8 -> 20972 | M7: =L7/L10 -> 0.62416667 | N7: =N6*'Vessel Assumptions'!$C$6*'Vessel Assumptions'!$C$8 -> 20972 | O7: =N7/N10 -> 0.62416667 | P7: =P6*'Vessel Assumptions'!$C$6*'Vessel Assumptions'!$C$8 -> 20972 | Q7: =P7/P10 -> 0.62416667 | R7: =R6*'Vessel Assumptions'!$C$6*'Vessel Assumptions'!$C$8 -> 20972 | S7: =R7/R10 -> 0.62416667 | T7: =T6*'Vessel Assumptions'!$C$6*'Vessel Assumptions'!$C$8 -> 20972 | U7: =T7/T10 -> 0.62416667 | V7: =V6*'Vessel Assumptions'!$C$6*'Vessel Assumptions'!$C$8 -> 20972 | W7: =V7/V10 -> 0.62416667 | X7: =X6*'Vessel Assumptions'!$C$6*'Vessel Assumptions'!$C$8 -> 20972 | Y7: =X7/X10 -> 0.62416667 | Z7: =B7+D7+F7+H7+J7+L7+N7+P7+R7+T7+V7+X7 -> 248668 | AA7: =Z7/Z10 -> 0.62416667
A8: Beverage revenue | B8: =B6*'Vessel Assumptions'!$C$6*(1-'Vessel Assumptions'!$C$8) -> 10040 | C8: =B8/B10 -> 0.20916667 | D8: =D6*'Vessel Assumptions'!$C$6*(1-'Vessel Assumptions'!$C$8) -> 3012 | E8: =D8/D10 -> 0.20916667 | F8: =F6*'Vessel Assumptions'!$C$6*(1-'Vessel Assumptions'!$C$8) -> 10040 | G8: =F8/F10 -> 0.20916667 | H8: =H6*'Vessel Assumptions'!$C$6*(1-'Vessel Assumptions'!$C$8) -> 3012 | I8: =H8/H10 -> 0.20916667 | J8: =J6*'Vessel Assumptions'!$C$6*(1-'Vessel Assumptions'!$C$8) -> 8032 | K8: =J8/J10 -> 0.20916667 | L8: =L6*'Vessel Assumptions'!$C$6*(1-'Vessel Assumptions'!$C$8) -> 7028 | M8: =L8/L10 -> 0.20916667 | N8: =N6*'Vessel Assumptions'!$C$6*(1-'Vessel Assumptions'!$C$8) -> 7028 | O8: =N8/N10 -> 0.20916667 | P8: =P6*'Vessel Assumptions'!$C$6*(1-'Vessel Assumptions'!$C$8) -> 7028 | Q8: =P8/P10 -> 0.20916667 | R8: =R6*'Vessel Assumptions'!$C$6*(1-'Vessel Assumptions'!$C$8) -> 7028 | S8: =R8/R10 -> 0.20916667 | T8: =T6*'Vessel Assumptions'!$C$6*(1-'Vessel Assumptions'!$C$8) -> 7028 | U8: =T8/T10 -> 0.20916667 | V8: =V6*'Vessel Assumptions'!$C$6*(1-'Vessel Assumptions'!$C$8) -> 7028 | W8: =V8/V10 -> 0.20916667 | X8: =X6*'Vessel Assumptions'!$C$6*(1-'Vessel Assumptions'!$C$8) -> 7028 | Y8: =X8/X10 -> 0.20916667 | Z8: =B8+D8+F8+H8+J8+L8+N8+P8+R8+T8+V8+X8 -> 83332 | AA8: =Z8/Z10 -> 0.20916667
A9: Service charge | B9: =B6*'Vessel Assumptions'!$C$6*'Vessel Assumptions'!$C$9 -> 8000 | C9: =B9/B10 -> 0.16666667 | D9: =D6*'Vessel Assumptions'!$C$6*'Vessel Assumptions'!$C$9 -> 2400 | E9: =D9/D10 -> 0.16666667 | F9: =F6*'Vessel Assumptions'!$C$6*'Vessel Assumptions'!$C$9 -> 8000 | G9: =F9/F10 -> 0.16666667 | H9: =H6*'Vessel Assumptions'!$C$6*'Vessel Assumptions'!$C$9 -> 2400 | I9: =H9/H10 -> 0.16666667 | J9: =J6*'Vessel Assumptions'!$C$6*'Vessel Assumptions'!$C$9 -> 6400 | K9: =J9/J10 -> 0.16666667 | L9: =L6*'Vessel Assumptions'!$C$6*'Vessel Assumptions'!$C$9 -> 5600 | M9: =L9/L10 -> 0.16666667 | N9: =N6*'Vessel Assumptions'!$C$6*'Vessel Assumptions'!$C$9 -> 5600 | O9: =N9/N10 -> 0.16666667 | P9: =P6*'Vessel Assumptions'!$C$6*'Vessel Assumptions'!$C$9 -> 5600 | Q9: =P9/P10 -> 0.16666667 | R9: =R6*'Vessel Assumptions'!$C$6*'Vessel Assumptions'!$C$9 -> 5600 | S9: =R9/R10 -> 0.16666667 | T9: =T6*'Vessel Assumptions'!$C$6*'Vessel Assumptions'!$C$9 -> 5600 | U9: =T9/T10 -> 0.16666667 | V9: =V6*'Vessel Assumptions'!$C$6*'Vessel Assumptions'!$C$9 -> 5600 | W9: =V9/V10 -> 0.16666667 | X9: =X6*'Vessel Assumptions'!$C$6*'Vessel Assumptions'!$C$9 -> 5600 | Y9: =X9/X10 -> 0.16666667 | Z9: =B9+D9+F9+H9+J9+L9+N9+P9+R9+T9+V9+X9 -> 66400 | AA9: =Z9/Z10 -> 0.16666667
A10: TOTAL REVENUE | B10: =SUM(B7:B9) -> 48000 | C10: =B10/B10 -> 1 | D10: =SUM(D7:D9) -> 14400 | E10: =D10/D10 -> 1 | F10: =SUM(F7:F9) -> 48000 | G10: =F10/F10 -> 1 | H10: =SUM(H7:H9) -> 14400 | I10: =H10/H10 -> 1 | J10: =SUM(J7:J9) -> 38400 | K10: =J10/J10 -> 1 | L10: =SUM(L7:L9) -> 33600 | M10: =L10/L10 -> 1 | N10: =SUM(N7:N9) -> 33600 | O10: =N10/N10 -> 1 | P10: =SUM(P7:P9) -> 33600 | Q10: =P10/P10 -> 1 | R10: =SUM(R7:R9) -> 33600 | S10: =R10/R10 -> 1 | T10: =SUM(T7:T9) -> 33600 | U10: =T10/T10 -> 1 | V10: =SUM(V7:V9) -> 33600 | W10: =V10/V10 -> 1 | X10: =SUM(X7:X9) -> 33600 | Y10: =X10/X10 -> 1 | Z10: =B10+D10+F10+H10+J10+L10+N10+P10+R10+T10+V10+X10 -> 398400 | AA10: =Z10/Z10 -> 1
A12: Food COGS (% of food sales) | B12: =B7*'Vessel Assumptions'!$C$12 -> 17976 | C12: =B12/B7 -> 0.6 | D12: =D7*'Vessel Assumptions'!$C$12 -> 5392.8 | E12: =D12/D7 -> 0.6 | F12: =F7*'Vessel Assumptions'!$C$12 -> 17976 | G12: =F12/F7 -> 0.6 | H12: =H7*'Vessel Assumptions'!$C$12 -> 5392.8 | I12: =H12/H7 -> 0.6 | J12: =J7*'Vessel Assumptions'!$C$12 -> 14380.8 | K12: =J12/J7 -> 0.6 | L12: =L7*'Vessel Assumptions'!$C$12 -> 12583.2 | M12: =L12/L7 -> 0.6 | N12: =N7*'Vessel Assumptions'!$C$12 -> 12583.2 | O12: =N12/N7 -> 0.6 | P12: =P7*'Vessel Assumptions'!$C$12 -> 12583.2 | Q12: =P12/P7 -> 0.6 | R12: =R7*'Vessel Assumptions'!$C$12 -> 12583.2 | S12: =R12/R7 -> 0.6 | T12: =T7*'Vessel Assumptions'!$C$12 -> 12583.2 | U12: =T12/T7 -> 0.6 | V12: =V7*'Vessel Assumptions'!$C$12 -> 12583.2 | W12: =V12/V7 -> 0.6 | X12: =X7*'Vessel Assumptions'!$C$12 -> 12583.2 | Y12: =X12/X7 -> 0.6 | Z12: =B12+D12+F12+H12+J12+L12+N12+P12+R12+T12+V12+X12 -> 149200.8 | AA12: =Z12/Z7 -> 0.6
A13: Beverage COGS (% of bev sales) | B13: =B8*'Vessel Assumptions'!$C$13 -> 2510 | C13: =B13/B8 -> 0.25 | D13: =D8*'Vessel Assumptions'!$C$13 -> 753 | E13: =D13/D8 -> 0.25 | F13: =F8*'Vessel Assumptions'!$C$13 -> 2510 | G13: =F13/F8 -> 0.25 | H13: =H8*'Vessel Assumptions'!$C$13 -> 753 | I13: =H13/H8 -> 0.25 | J13: =J8*'Vessel Assumptions'!$C$13 -> 2008 | K13: =J13/J8 -> 0.25 | L13: =L8*'Vessel Assumptions'!$C$13 -> 1757 | M13: =L13/L8 -> 0.25 | N13: =N8*'Vessel Assumptions'!$C$13 -> 1757 | O13: =N13/N8 -> 0.25 | P13: =P8*'Vessel Assumptions'!$C$13 -> 1757 | Q13: =P13/P8 -> 0.25 | R13: =R8*'Vessel Assumptions'!$C$13 -> 1757 | S13: =R13/R8 -> 0.25 | T13: =T8*'Vessel Assumptions'!$C$13 -> 1757 | U13: =T13/T8 -> 0.25 | V13: =V8*'Vessel Assumptions'!$C$13 -> 1757 | W13: =V13/V8 -> 0.25 | X13: =X8*'Vessel Assumptions'!$C$13 -> 1757 | Y13: =X13/X8 -> 0.25 | Z13: =B13+D13+F13+H13+J13+L13+N13+P13+R13+T13+V13+X13 -> 20833 | AA13: =Z13/Z8 -> 0.25
A14: TOTAL COGS | B14: =B12+B13 -> 20486 | C14: =B14/B10 -> 0.42679167 | D14: =D12+D13 -> 6145.8 | E14: =D14/D10 -> 0.42679167 | F14: =F12+F13 -> 20486 | G14: =F14/F10 -> 0.42679167 | H14: =H12+H13 -> 6145.8 | I14: =H14/H10 -> 0.42679167 | J14: =J12+J13 -> 16388.8 | K14: =J14/J10 -> 0.42679167 | L14: =L12+L13 -> 14340.2 | M14: =L14/L10 -> 0.42679167 | N14: =N12+N13 -> 14340.2 | O14: =N14/N10 -> 0.42679167 | P14: =P12+P13 -> 14340.2 | Q14: =P14/P10 -> 0.42679167 | R14: =R12+R13 -> 14340.2 | S14: =R14/R10 -> 0.42679167 | T14: =T12+T13 -> 14340.2 | U14: =T14/T10 -> 0.42679167 | V14: =V12+V13 -> 14340.2 | W14: =V14/V10 -> 0.42679167 | X14: =X12+X13 -> 14340.2 | Y14: =X14/X10 -> 0.42679167 | Z14: =B14+D14+F14+H14+J14+L14+N14+P14+R14+T14+V14+X14 -> 170033.8 | AA14: =Z14/Z10 -> 0.42679167
A15: GROSS PROFIT | B15: =B10-B14 -> 27514 | C15: =B15/B10 -> 0.57320833 | D15: =D10-D14 -> 8254.2 | E15: =D15/D10 -> 0.57320833 | F15: =F10-F14 -> 27514 | G15: =F15/F10 -> 0.57320833 | H15: =H10-H14 -> 8254.2 | I15: =H15/H10 -> 0.57320833 | J15: =J10-J14 -> 22011.2 | K15: =J15/J10 -> 0.57320833 | L15: =L10-L14 -> 19259.8 | M15: =L15/L10 -> 0.57320833 | N15: =N10-N14 -> 19259.8 | O15: =N15/N10 -> 0.57320833 | P15: =P10-P14 -> 19259.8 | Q15: =P15/P10 -> 0.57320833 | R15: =R10-R14 -> 19259.8 | S15: =R15/R10 -> 0.57320833 | T15: =T10-T14 -> 19259.8 | U15: =T15/T10 -> 0.57320833 | V15: =V10-V14 -> 19259.8 | W15: =V15/V10 -> 0.57320833 | X15: =X10-X14 -> 19259.8 | Y15: =X15/X10 -> 0.57320833 | Z15: =B15+D15+F15+H15+J15+L15+N15+P15+R15+T15+V15+X15 -> 228366.2 | AA15: =Z15/Z10 -> 0.57320833
A17: ="Hourly labor ("&'Vessel Assumptions'!$C$16&" bartender"&IF('Vessel Assumptions'!$C$16=1,"","s")&" + "&'Vessel Assumptions'!$C$17&" server"&IF('Vessel Assumptions'!$C$17=1,"","s")&")" -> Hourly labor (1 bartender + 2 servers) | B17: =B6*'Vessel Assumptions'!$C$20 -> 5250 | C17: =B17/B10 -> 0.109375 | D17: =D6*'Vessel Assumptions'!$C$20 -> 1575 | E17: =D17/D10 -> 0.109375 | F17: =F6*'Vessel Assumptions'!$C$20 -> 5250 | G17: =F17/F10 -> 0.109375 | H17: =H6*'Vessel Assumptions'!$C$20 -> 1575 | I17: =H17/H10 -> 0.109375 | J17: =J6*'Vessel Assumptions'!$C$20 -> 4200 | K17: =J17/J10 -> 0.109375 | L17: =L6*'Vessel Assumptions'!$C$20 -> 3675 | M17: =L17/L10 -> 0.109375 | N17: =N6*'Vessel Assumptions'!$C$20 -> 3675 | O17: =N17/N10 -> 0.109375 | P17: =P6*'Vessel Assumptions'!$C$20 -> 3675 | Q17: =P17/P10 -> 0.109375 | R17: =R6*'Vessel Assumptions'!$C$20 -> 3675 | S17: =R17/R10 -> 0.109375 | T17: =T6*'Vessel Assumptions'!$C$20 -> 3675 | U17: =T17/T10 -> 0.109375 | V17: =V6*'Vessel Assumptions'!$C$20 -> 3675 | W17: =V17/V10 -> 0.109375 | X17: =X6*'Vessel Assumptions'!$C$20 -> 3675 | Y17: =X17/X10 -> 0.109375 | Z17: =B17+D17+F17+H17+J17+L17+N17+P17+R17+T17+V17+X17 -> 43575 | AA17: =Z17/Z10 -> 0.109375
A18: Management labor (GL FOH mgmt) | B18: ='Vessel Assumptions'!$C$21 -> 1787.1667 | C18: =B18/B10 -> 0.037232639 | D18: ='Vessel Assumptions'!$C$21 -> 1787.1667 | E18: =D18/D10 -> 0.1241088 | F18: ='Vessel Assumptions'!$C$21 -> 1787.1667 | G18: =F18/F10 -> 0.037232639 | H18: ='Vessel Assumptions'!$C$21 -> 1787.1667 | I18: =H18/H10 -> 0.1241088 | J18: ='Vessel Assumptions'!$C$21 -> 1787.1667 | K18: =J18/J10 -> 0.046540799 | L18: ='Vessel Assumptions'!$C$21 -> 1787.1667 | M18: =L18/L10 -> 0.053189484 | N18: ='Vessel Assumptions'!$C$21 -> 1787.1667 | O18: =N18/N10 -> 0.053189484 | P18: ='Vessel Assumptions'!$C$21 -> 1787.1667 | Q18: =P18/P10 -> 0.053189484 | R18: ='Vessel Assumptions'!$C$21 -> 1787.1667 | S18: =R18/R10 -> 0.053189484 | T18: ='Vessel Assumptions'!$C$21 -> 1787.1667 | U18: =T18/T10 -> 0.053189484 | V18: ='Vessel Assumptions'!$C$21 -> 1787.1667 | W18: =V18/V10 -> 0.053189484 | X18: ='Vessel Assumptions'!$C$21 -> 1787.1667 | Y18: =X18/X10 -> 0.053189484 | Z18: =B18+D18+F18+H18+J18+L18+N18+P18+R18+T18+V18+X18 -> 21446 | AA18: =Z18/Z10 -> 0.053830321
A19: Payroll taxes & benefits | B19: =(B17+B18)*'Vessel Assumptions'!$C$22 -> 1132.9838 | C19: =B19/B10 -> 0.02360383 | D19: =(D17+D18)*'Vessel Assumptions'!$C$22 -> 541.30883 | E19: =D19/D10 -> 0.037590891 | F19: =(F17+F18)*'Vessel Assumptions'!$C$22 -> 1132.9838 | G19: =F19/F10 -> 0.02360383 | H19: =(H17+H18)*'Vessel Assumptions'!$C$22 -> 541.30883 | I19: =H19/H10 -> 0.037590891 | J19: =(J17+J18)*'Vessel Assumptions'!$C$22 -> 963.93383 | K19: =J19/J10 -> 0.025102444 | L19: =(L17+L18)*'Vessel Assumptions'!$C$22 -> 879.40883 | M19: =L19/L10 -> 0.026172882 | N19: =(N17+N18)*'Vessel Assumptions'!$C$22 -> 879.40883 | O19: =N19/N10 -> 0.026172882 | P19: =(P17+P18)*'Vessel Assumptions'!$C$22 -> 879.40883 | Q19: =P19/P10 -> 0.026172882 | R19: =(R17+R18)*'Vessel Assumptions'!$C$22 -> 879.40883 | S19: =R19/R10 -> 0.026172882 | T19: =(T17+T18)*'Vessel Assumptions'!$C$22 -> 879.40883 | U19: =T19/T10 -> 0.026172882 | V19: =(V17+V18)*'Vessel Assumptions'!$C$22 -> 879.40883 | W19: =V19/V10 -> 0.026172882 | X19: =(X17+X18)*'Vessel Assumptions'!$C$22 -> 879.40883 | Y19: =X19/X10 -> 0.026172882 | Z19: =B19+D19+F19+H19+J19+L19+N19+P19+R19+T19+V19+X19 -> 10468.381 | AA19: =Z19/Z10 -> 0.026276057
A20: TOTAL LABOR | B20: =B17+B18+B19 -> 8170.1505 | C20: =B20/B10 -> 0.17021147 | D20: =D17+D18+D19 -> 3903.4755 | E20: =D20/D10 -> 0.27107469 | F20: =F17+F18+F19 -> 8170.1505 | G20: =F20/F10 -> 0.17021147 | H20: =H17+H18+H19 -> 3903.4755 | I20: =H20/H10 -> 0.27107469 | J20: =J17+J18+J19 -> 6951.1005 | K20: =J20/J10 -> 0.18101824 | L20: =L17+L18+L19 -> 6341.5755 | M20: =L20/L10 -> 0.18873737 | N20: =N17+N18+N19 -> 6341.5755 | O20: =N20/N10 -> 0.18873737 | P20: =P17+P18+P19 -> 6341.5755 | Q20: =P20/P10 -> 0.18873737 | R20: =R17+R18+R19 -> 6341.5755 | S20: =R20/R10 -> 0.18873737 | T20: =T17+T18+T19 -> 6341.5755 | U20: =T20/T10 -> 0.18873737 | V20: =V17+V18+V19 -> 6341.5755 | W20: =V20/V10 -> 0.18873737 | X20: =X17+X18+X19 -> 6341.5755 | Y20: =X20/X10 -> 0.18873737 | Z20: =B20+D20+F20+H20+J20+L20+N20+P20+R20+T20+V20+X20 -> 75489.381 | AA20: =Z20/Z10 -> 0.18948138
A21: PRIME COST | B21: =B14+B20 -> 28656.15 | C21: =B21/B10 -> 0.59700314 | D21: =D14+D20 -> 10049.275 | E21: =D21/D10 -> 0.69786635 | F21: =F14+F20 -> 28656.15 | G21: =F21/F10 -> 0.59700314 | H21: =H14+H20 -> 10049.275 | I21: =H21/H10 -> 0.69786635 | J21: =J14+J20 -> 23339.9 | K21: =J21/J10 -> 0.60780991 | L21: =L14+L20 -> 20681.775 | M21: =L21/L10 -> 0.61552903 | N21: =N14+N20 -> 20681.775 | O21: =N21/N10 -> 0.61552903 | P21: =P14+P20 -> 20681.775 | Q21: =P21/P10 -> 0.61552903 | R21: =R14+R20 -> 20681.775 | S21: =R21/R10 -> 0.61552903 | T21: =T14+T20 -> 20681.775 | U21: =T21/T10 -> 0.61552903 | V21: =V14+V20 -> 20681.775 | W21: =V21/V10 -> 0.61552903 | X21: =X14+X20 -> 20681.775 | Y21: =X21/X10 -> 0.61552903 | Z21: =B21+D21+F21+H21+J21+L21+N21+P21+R21+T21+V21+X21 -> 245523.18 | AA21: =Z21/Z10 -> 0.61627304
A23: Controllable expenses (excl CC) | B23: ='Vessel Assumptions'!$C$25 -> 6737.3333 | C23: =B23/B10 -> 0.14036111 | D23: ='Vessel Assumptions'!$C$25 -> 6737.3333 | E23: =D23/D10 -> 0.46787037 | F23: ='Vessel Assumptions'!$C$25 -> 6737.3333 | G23: =F23/F10 -> 0.14036111 | H23: ='Vessel Assumptions'!$C$25 -> 6737.3333 | I23: =H23/H10 -> 0.46787037 | J23: ='Vessel Assumptions'!$C$25 -> 6737.3333 | K23: =J23/J10 -> 0.17545139 | L23: ='Vessel Assumptions'!$C$25 -> 6737.3333 | M23: =L23/L10 -> 0.20051587 | N23: ='Vessel Assumptions'!$C$25 -> 6737.3333 | O23: =N23/N10 -> 0.20051587 | P23: ='Vessel Assumptions'!$C$25 -> 6737.3333 | Q23: =P23/P10 -> 0.20051587 | R23: ='Vessel Assumptions'!$C$25 -> 6737.3333 | S23: =R23/R10 -> 0.20051587 | T23: ='Vessel Assumptions'!$C$25 -> 6737.3333 | U23: =T23/T10 -> 0.20051587 | V23: ='Vessel Assumptions'!$C$25 -> 6737.3333 | W23: =V23/V10 -> 0.20051587 | X23: ='Vessel Assumptions'!$C$25 -> 6737.3333 | Y23: =X23/X10 -> 0.20051587 | Z23: =B23+D23+F23+H23+J23+L23+N23+P23+R23+T23+V23+X23 -> 80848 | AA23: =Z23/Z10 -> 0.20293173
A24: Credit card fees (2.5% of revenue) | B24: =B10*'Vessel Assumptions'!$C$27 -> 1200 | C24: =B24/B10 -> 0.025 | D24: =D10*'Vessel Assumptions'!$C$27 -> 360 | E24: =D24/D10 -> 0.025 | F24: =F10*'Vessel Assumptions'!$C$27 -> 1200 | G24: =F24/F10 -> 0.025 | H24: =H10*'Vessel Assumptions'!$C$27 -> 360 | I24: =H24/H10 -> 0.025 | J24: =J10*'Vessel Assumptions'!$C$27 -> 960 | K24: =J24/J10 -> 0.025 | L24: =L10*'Vessel Assumptions'!$C$27 -> 840 | M24: =L24/L10 -> 0.025 | N24: =N10*'Vessel Assumptions'!$C$27 -> 840 | O24: =N24/N10 -> 0.025 | P24: =P10*'Vessel Assumptions'!$C$27 -> 840 | Q24: =P24/P10 -> 0.025 | R24: =R10*'Vessel Assumptions'!$C$27 -> 840 | S24: =R24/R10 -> 0.025 | T24: =T10*'Vessel Assumptions'!$C$27 -> 840 | U24: =T24/T10 -> 0.025 | V24: =V10*'Vessel Assumptions'!$C$27 -> 840 | W24: =V24/V10 -> 0.025 | X24: =X10*'Vessel Assumptions'!$C$27 -> 840 | Y24: =X24/X10 -> 0.025 | Z24: =B24+D24+F24+H24+J24+L24+N24+P24+R24+T24+V24+X24 -> 9960 | AA24: =Z24/Z10 -> 0.025
A25: Non-controllable (insurance, legal, reserves) | B25: ='Vessel Assumptions'!$C$26 -> 896.66667 | C25: =B25/B10 -> 0.018680556 | D25: ='Vessel Assumptions'!$C$26 -> 896.66667 | E25: =D25/D10 -> 0.062268519 | F25: ='Vessel Assumptions'!$C$26 -> 896.66667 | G25: =F25/F10 -> 0.018680556 | H25: ='Vessel Assumptions'!$C$26 -> 896.66667 | I25: =H25/H10 -> 0.062268519 | J25: ='Vessel Assumptions'!$C$26 -> 896.66667 | K25: =J25/J10 -> 0.023350694 | L25: ='Vessel Assumptions'!$C$26 -> 896.66667 | M25: =L25/L10 -> 0.026686508 | N25: ='Vessel Assumptions'!$C$26 -> 896.66667 | O25: =N25/N10 -> 0.026686508 | P25: ='Vessel Assumptions'!$C$26 -> 896.66667 | Q25: =P25/P10 -> 0.026686508 | R25: ='Vessel Assumptions'!$C$26 -> 896.66667 | S25: =R25/R10 -> 0.026686508 | T25: ='Vessel Assumptions'!$C$26 -> 896.66667 | U25: =T25/T10 -> 0.026686508 | V25: ='Vessel Assumptions'!$C$26 -> 896.66667 | W25: =V25/V10 -> 0.026686508 | X25: ='Vessel Assumptions'!$C$26 -> 896.66667 | Y25: =X25/X10 -> 0.026686508 | Z25: =B25+D25+F25+H25+J25+L25+N25+P25+R25+T25+V25+X25 -> 10760 | AA25: =Z25/Z10 -> 0.027008032
A26: Management fee (4% of revenue → Method) | B26: =B10*'Vessel Assumptions'!$C$30 -> 1920 | C26: =B26/B10 -> 0.04 | D26: =D10*'Vessel Assumptions'!$C$30 -> 576 | E26: =D26/D10 -> 0.04 | F26: =F10*'Vessel Assumptions'!$C$30 -> 1920 | G26: =F26/F10 -> 0.04 | H26: =H10*'Vessel Assumptions'!$C$30 -> 576 | I26: =H26/H10 -> 0.04 | J26: =J10*'Vessel Assumptions'!$C$30 -> 1536 | K26: =J26/J10 -> 0.04 | L26: =L10*'Vessel Assumptions'!$C$30 -> 1344 | M26: =L26/L10 -> 0.04 | N26: =N10*'Vessel Assumptions'!$C$30 -> 1344 | O26: =N26/N10 -> 0.04 | P26: =P10*'Vessel Assumptions'!$C$30 -> 1344 | Q26: =P26/P10 -> 0.04 | R26: =R10*'Vessel Assumptions'!$C$30 -> 1344 | S26: =R26/R10 -> 0.04 | T26: =T10*'Vessel Assumptions'!$C$30 -> 1344 | U26: =T26/T10 -> 0.04 | V26: =V10*'Vessel Assumptions'!$C$30 -> 1344 | W26: =V26/V10 -> 0.04 | X26: =X10*'Vessel Assumptions'!$C$30 -> 1344 | Y26: =X26/X10 -> 0.04 | Z26: =B26+D26+F26+H26+J26+L26+N26+P26+R26+T26+V26+X26 -> 15936 | AA26: =Z26/Z10 -> 0.04
A27: Admin fee (5% of F&B revenue → Method) | B27: =(B7+B8)*'Vessel Assumptions'!$C$32 -> 2000 | D27: =(D7+D8)*'Vessel Assumptions'!$C$32 -> 600 | F27: =(F7+F8)*'Vessel Assumptions'!$C$32 -> 2000 | H27: =(H7+H8)*'Vessel Assumptions'!$C$32 -> 600 | J27: =(J7+J8)*'Vessel Assumptions'!$C$32 -> 1600 | L27: =(L7+L8)*'Vessel Assumptions'!$C$32 -> 1400 | N27: =(N7+N8)*'Vessel Assumptions'!$C$32 -> 1400 | P27: =(P7+P8)*'Vessel Assumptions'!$C$32 -> 1400 | R27: =(R7+R8)*'Vessel Assumptions'!$C$32 -> 1400 | T27: =(T7+T8)*'Vessel Assumptions'!$C$32 -> 1400 | V27: =(V7+V8)*'Vessel Assumptions'!$C$32 -> 1400 | X27: =(X7+X8)*'Vessel Assumptions'!$C$32 -> 1400 | Z27: =B27+D27+F27+H27+J27+L27+N27+P27+R27+T27+V27+X27 -> 16600
A28: Rent / occupancy (Vessel: none) | B28: =B10*'Vessel Assumptions'!$C$31 -> 0 | C28: =B28/B10 -> 0 | D28: =D10*'Vessel Assumptions'!$C$31 -> 0 | E28: =D28/D10 -> 0 | F28: =F10*'Vessel Assumptions'!$C$31 -> 0 | G28: =F28/F10 -> 0 | H28: =H10*'Vessel Assumptions'!$C$31 -> 0 | I28: =H28/H10 -> 0 | J28: =J10*'Vessel Assumptions'!$C$31 -> 0 | K28: =J28/J10 -> 0 | L28: =L10*'Vessel Assumptions'!$C$31 -> 0 | M28: =L28/L10 -> 0 | N28: =N10*'Vessel Assumptions'!$C$31 -> 0 | O28: =N28/N10 -> 0 | P28: =P10*'Vessel Assumptions'!$C$31 -> 0 | Q28: =P28/P10 -> 0 | R28: =R10*'Vessel Assumptions'!$C$31 -> 0 | S28: =R28/R10 -> 0 | T28: =T10*'Vessel Assumptions'!$C$31 -> 0 | U28: =T28/T10 -> 0 | V28: =V10*'Vessel Assumptions'!$C$31 -> 0 | W28: =V28/V10 -> 0 | X28: =X10*'Vessel Assumptions'!$C$31 -> 0 | Y28: =X28/X10 -> 0 | Z28: =B28+D28+F28+H28+J28+L28+N28+P28+R28+T28+V28+X28 -> 0 | AA28: =Z28/Z10 -> 0
A29: NET OPERATING INCOME (after mgmt fee, admin fee & rent) | B29: =B15-B20-(B23+B24+B25+B26+B27+B28) -> 6589.8495 | D29: =D15-D20-(D23+D24+D25+D26+D27+D28) -> -4819.2755 | F29: =F15-F20-(F23+F24+F25+F26+F27+F28) -> 6589.8495 | H29: =H15-H20-(H23+H24+H25+H26+H27+H28) -> -4819.2755 | J29: =J15-J20-(J23+J24+J25+J26+J27+J28) -> 3330.0995 | L29: =L15-L20-(L23+L24+L25+L26+L27+L28) -> 1700.2245 | N29: =N15-N20-(N23+N24+N25+N26+N27+N28) -> 1700.2245 | P29: =P15-P20-(P23+P24+P25+P26+P27+P28) -> 1700.2245 | R29: =R15-R20-(R23+R24+R25+R26+R27+R28) -> 1700.2245 | T29: =T15-T20-(T23+T24+T25+T26+T27+T28) -> 1700.2245 | V29: =V15-V20-(V23+V24+V25+V26+V27+V28) -> 1700.2245 | X29: =X15-X20-(X23+X24+X25+X26+X27+X28) -> 1700.2245 | Z29: =Z15-Z20-(Z23+Z24+Z25+Z26+Z27+Z28) -> 18772.819
C30: =B30/B10 -> 0 | E30: =D30/D10 -> 0 | G30: =F30/F10 -> 0 | I30: =H30/H10 -> 0 | K30: =J30/J10 -> 0 | M30: =L30/L10 -> 0 | O30: =N30/N10 -> 0 | Q30: =P30/P10 -> 0 | S30: =R30/R10 -> 0 | U30: =T30/T10 -> 0 | W30: =V30/V10 -> 0 | Y30: =X30/X10 -> 0 | AA30: =Z30/Z10 -> 0
C31: =B31/B10 -> 0 | E31: =D31/D10 -> 0 | G31: =F31/F10 -> 0 | I31: =H31/H10 -> 0 | K31: =J31/J10 -> 0 | M31: =L31/L10 -> 0 | O31: =N31/N10 -> 0 | Q31: =P31/P10 -> 0 | S31: =R31/R10 -> 0 | U31: =T31/T10 -> 0 | W31: =V31/V10 -> 0 | Y31: =X31/X10 -> 0 | AA31: =Z31/Z10 -> 0
A33: Management fee = 4% of revenue; admin fee = 5% of food+beverage; Vessel has no separate rent. NOI is the bottom line.

Sheet Vessel GL Basis
A1: VESSEL — GL COST BASIS
A2: Cost basis now linked to Vessel 2026 P&L (Act/For) · controllable vs non-controllable (CC fees excluded)
B4: Expense group | C4: Annual | D4: Monthly
B6: LABOR (in model)
B8: Management labor – FOH mgmt (610300) | C8: ='Vessel 2026 P&L'!$AB$28 -> 21446 | D8: =C8/12 -> 1787.1667
B10: CONTROLLABLE (excl credit card fees)
B11: Direct operating (supplies, linen, equip) | C11: 18543 | D11: =C11/12 -> 1545.25
B12: G&A / accounting / bank | C12: 30300 | D12: =C12/12 -> 2525
B13: Marketing | C13: 13917 | D13: =C13/12 -> 1159.75
B14: Music & entertainment | C14: 6750 | D14: =C14/12 -> 562.5
B15: Repairs & maintenance | C15: 5748 | D15: =C15/12 -> 479
B16: Utilities | C16: 5602 | D16: =C16/12 -> 466.83333
B17: Total controllable (excl CC) | C17: =SUM(C11:C16) -> 80860 | D17: =C17/12 -> 6738.3333
B18: → Controllable / month feed | C18: ='Vessel 2026 P&L'!$AB$44 -> 80848 | D18: =C18/12 -> 6737.3333
B20: NON-CONTROLLABLE (in model)
B21: Insurance – liability | C21: 2106 | D21: =C21/12 -> 175.5
B22: Legal & accounting | C22: 1800 | D22: =C22/12 -> 150
B23: Replacement reserves | C23: 4855 | D23: =C23/12 -> 404.58333
B24: Total non-controllable | C24: ='Vessel 2026 P&L'!$AB$47+'Vessel 2026 P&L'!$AB$49+'Vessel 2026 P&L'!$AB$51+'Vessel 2026 P&L'!$AB$52 -> 10760 | D24: =C24/12 -> 896.66667
B26: VARIABLE / EXCLUDED
B27: Credit card fees (actual GL → now variable 2.5%) | C27: 2745 | D27: =C27/12 -> 228.75
B28: Management fee (→ profit split) | C28: 48000 | D28: =C28/12 -> 4000
B29: Rent / RE tax (owner) | C29: ='Vessel 2026 P&L'!$AB$48 -> 21342 | D29: =C29/12 -> 1778.5

Sheet Vessel 2026 P&L
A1: Vessel
A2: Profit & Loss Summary
A3: 2026
C5: January | E5: February | G5: March | I5: April | K5: May | M5: June | O5: July | Q5: August | S5: September | U5: October | W5: November | Y5: December | AB5: 2026
C6: Actual | E6: Actual | G6: Actual | I6: Actual | K6: Actual | M6: Actual | O6: Forecast | Q6: Forecast | S6: Forecast | U6: Forecast | W6: Forecast | Y6: Forecast | AB6: Act/For/Bud
C7: Amount $ | D7: % | E7: Amount $ | F7: % | G7: Amount $ | H7: % | I7: Amount $ | J7: % | K7: Amount $ | L7: % | M7: Amount $ | N7: % | O7: Amount $ | P7: % | Q7: Amount $ | R7: % | S7: Amount $ | T7: % | U7: Amount $ | V7: % | W7: Amount $ | X7: % | Y7: Amount $ | Z7: % | AB7: Amount $ | AC7: %
A8: Income
A9: Food Sales | C9: 28343 | D9: =IFERROR(C9/C$16,0) -> 0.74355947 | E9: 9119 | F9: =IFERROR(E9/E$16,0) -> 0.54630961 | G9: 21950 | H9: =IFERROR(G9/G$16,0) -> 0.55143826 | I9: 4645 | J9: =IFERROR(I9/I$16,0) -> 0.37079907 | K9: 14241 | L9: =IFERROR(K9/K$16,0) -> 0.34785901 | M9: 15390 | N9: =IFERROR(M9/M$16,0) -> 0.33585754 | O9: 11504 | P9: =IFERROR(O9/O$16,0) -> 0.34786816 | Q9: 8697 | R9: =IFERROR(Q9/Q$16,0) -> 0.34786609 | S9: 8697 | T9: =IFERROR(S9/S$16,0) -> 0.34786609 | U9: 6957 | V9: =IFERROR(U9/U$16,0) -> 0.34785 | W9: 6957 | X9: =IFERROR(W9/W$16,0) -> 0.34785 | Y9: 12175 | Z9: =IFERROR(Y9/Y$16,0) -> 0.34786708 | AB9: =SUM(C9,E9,G9,I9,K9,M9,O9,Q9,S9,U9,W9,Y9) -> 148675 | AC9: =IFERROR(AB9/AB$16,0) -> 0.42240216
A10: Non-Alcoholic Beverage Sales | C10: 5992 | D10: =IFERROR(C10/C$16,0) -> 0.15719608 | E10: 4542 | F10: =IFERROR(E10/E$16,0) -> 0.2721064 | G10: 3907 | H10: =IFERROR(G10/G$16,0) -> 0.098153498 | I10: 1012 | J10: =IFERROR(I10/I$16,0) -> 0.080785503 | K10: 2090 | L10: =IFERROR(K10/K$16,0) -> 0.051051565 | M10: 2193 | N10: =IFERROR(M10/M$16,0) -> 0.047858063 | O10: 1688 | P10: =IFERROR(O10/O$16,0) -> 0.051043242 | Q10: 1276 | R10: =IFERROR(Q10/Q$16,0) -> 0.051037958 | S10: 1276 | T10: =IFERROR(S10/S$16,0) -> 0.051037958 | U10: 1021 | V10: =IFERROR(U10/U$16,0) -> 0.05105 | W10: 1021 | X10: =IFERROR(W10/W$16,0) -> 0.05105 | Y10: 1786 | Z10: =IFERROR(Y10/Y$16,0) -> 0.051030029 | AB10: =SUM(C10,E10,G10,I10,K10,M10,O10,Q10,S10,U10,W10,Y10) -> 27804 | AC10: =IFERROR(AB10/AB$16,0) -> 0.078994247
A11: Liquor Sales | C11: 1351 | D11: =IFERROR(C11/C$16,0) -> 0.035442573 | E11: 2141 | F11: =IFERROR(E11/E$16,0) -> 0.12826504 | G11: 10278 | H11: =IFERROR(G11/G$16,0) -> 0.25820877 | I11: 1836 | J11: =IFERROR(I11/I$16,0) -> 0.14656342 | K11: 5557 | L11: =IFERROR(K11/K$16,0) -> 0.13573854 | M11: 4142 | N11: =IFERROR(M11/M$16,0) -> 0.090391288 | O11: 4489 | P11: =IFERROR(O11/O$16,0) -> 0.13574236 | Q11: 3394 | R11: =IFERROR(Q11/Q$16,0) -> 0.13575457 | S11: 3394 | T11: =IFERROR(S11/S$16,0) -> 0.13575457 | U11: 2715 | V11: =IFERROR(U11/U$16,0) -> 0.13575 | W11: 2715 | X11: =IFERROR(W11/W$16,0) -> 0.13575 | Y11: 4751 | Z11: =IFERROR(Y11/Y$16,0) -> 0.13574674 | AB11: =SUM(C11,E11,G11,I11,K11,M11,O11,Q11,S11,U11,W11,Y11) -> 46763 | AC11: =IFERROR(AB11/AB$16,0) -> 0.13285887
A12: Beer Sales | C12: 40 | D12: =IFERROR(C12/C$16,0) -> 0.001049373 | E12: 0 | F12: =IFERROR(E12/E$16,0) -> 0 | G12: 187 | H12: =IFERROR(G12/G$16,0) -> 0.0046979023 | I12: 34 | J12: =IFERROR(I12/I$16,0) -> 0.0027141375 | K12: 193 | L12: =IFERROR(K12/K$16,0) -> 0.0047143311 | M12: 525 | N12: =IFERROR(M12/M$16,0) -> 0.011457129 | O12: 156 | P12: =IFERROR(O12/O$16,0) -> 0.0047172664 | Q12: 118 | R12: =IFERROR(Q12/Q$16,0) -> 0.0047198112 | S12: 118 | T12: =IFERROR(S12/S$16,0) -> 0.0047198112 | U12: 94 | V12: =IFERROR(U12/U$16,0) -> 0.0047 | W12: 94 | X12: =IFERROR(W12/W$16,0) -> 0.0047 | Y12: 165 | Z12: =IFERROR(Y12/Y$16,0) -> 0.0047144204 | AB12: =SUM(C12,E12,G12,I12,K12,M12,O12,Q12,S12,U12,W12,Y12) -> 1724 | AC12: =IFERROR(AB12/AB$16,0) -> 0.0048980751
A13: Wine Sales | C13: 758 | D13: =IFERROR(C13/C$16,0) -> 0.019885618 | E13: 471 | F13: =IFERROR(E13/E$16,0) -> 0.02821711 | G13: 729 | H13: =IFERROR(G13/G$16,0) -> 0.018314282 | I13: 426 | J13: =IFERROR(I13/I$16,0) -> 0.034006546 | K13: 770 | L13: =IFERROR(K13/K$16,0) -> 0.018808471 | M13: 434 | N13: =IFERROR(M13/M$16,0) -> 0.0094712262 | O13: 622 | P13: =IFERROR(O13/O$16,0) -> 0.018808588 | Q13: 470 | R13: =IFERROR(Q13/Q$16,0) -> 0.018799248 | S13: 470 | T13: =IFERROR(S13/S$16,0) -> 0.018799248 | U13: 376 | V13: =IFERROR(U13/U$16,0) -> 0.0188 | W13: 376 | X13: =IFERROR(W13/W$16,0) -> 0.0188 | Y13: 658 | Z13: =IFERROR(Y13/Y$16,0) -> 0.018800537 | AB13: =SUM(C13,E13,G13,I13,K13,M13,O13,Q13,S13,U13,W13,Y13) -> 6560 | AC13: =IFERROR(AB13/AB$16,0) -> 0.018637687
A14: Other Operating Income | C14: 3280 | D14: =IFERROR(C14/C$16,0) -> 0.086048586 | E14: 419 | F14: =IFERROR(E14/E$16,0) -> 0.025101845 | G14: 2754 | H14: =IFERROR(G14/G$16,0) -> 0.069187288 | I14: 4574 | J14: =IFERROR(I14/I$16,0) -> 0.36513132 | K14: 18088 | L14: =IFERROR(K14/K$16,0) -> 0.44182809 | M14: 23139 | N14: =IFERROR(M14/M$16,0) -> 0.50496476 | O14: 14611 | P14: =IFERROR(O14/O$16,0) -> 0.44182038 | Q14: 11046 | R14: =IFERROR(Q14/Q$16,0) -> 0.44182233 | S14: 11046 | T14: =IFERROR(S14/S$16,0) -> 0.44182233 | U14: 8837 | V14: =IFERROR(U14/U$16,0) -> 0.44185 | W14: 8837 | X14: =IFERROR(W14/W$16,0) -> 0.44185 | Y14: 15464 | Z14: =IFERROR(Y14/Y$16,0) -> 0.4418412 | AB14: =SUM(C14,E14,G14,I14,K14,M14,O14,Q14,S14,U14,W14,Y14) -> 122095 | AC14: =IFERROR(AB14/AB$16,0) -> 0.34688543
A15: Discounts & Comps | C15: -1646 | D15: =IFERROR(C15/C$16,0) -> -0.043181699 | E15: 0 | F15: =IFERROR(E15/E$16,0) -> 0 | G15: 0 | H15: =IFERROR(G15/G$16,0) -> 0 | I15: 0 | J15: =IFERROR(I15/I$16,0) -> 0 | K15: 0 | L15: =IFERROR(K15/K$16,0) -> 0 | M15: 0 | N15: =IFERROR(M15/M$16,0) -> 0 | O15: 0 | P15: =IFERROR(O15/O$16,0) -> 0 | Q15: 0 | R15: =IFERROR(Q15/Q$16,0) -> 0 | S15: 0 | T15: =IFERROR(S15/S$16,0) -> 0 | U15: 0 | V15: =IFERROR(U15/U$16,0) -> 0 | W15: 0 | X15: =IFERROR(W15/W$16,0) -> 0 | Y15: 0 | Z15: =IFERROR(Y15/Y$16,0) -> 0 | AB15: =SUM(C15,E15,G15,I15,K15,M15,O15,Q15,S15,U15,W15,Y15) -> -1646 | AC15: =IFERROR(AB15/AB$16,0) -> -0.0046764685
A16: Total Income | C16: =SUM(C9:C15) -> 38118 | D16: =IFERROR(C16/C$16,0) -> 1 | E16: =SUM(E9:E15) -> 16692 | F16: =IFERROR(E16/E$16,0) -> 1 | G16: =SUM(G9:G15) -> 39805 | H16: =IFERROR(G16/G$16,0) -> 1 | I16: =SUM(I9:I15) -> 12527 | J16: =IFERROR(I16/I$16,0) -> 1 | K16: =SUM(K9:K15) -> 40939 | L16: =IFERROR(K16/K$16,0) -> 1 | M16: =SUM(M9:M15) -> 45823 | N16: =IFERROR(M16/M$16,0) -> 1 | O16: =SUM(O9:O15) -> 33070 | P16: =IFERROR(O16/O$16,0) -> 1 | Q16: =SUM(Q9:Q15) -> 25001 | R16: =IFERROR(Q16/Q$16,0) -> 1 | S16: =SUM(S9:S15) -> 25001 | T16: =IFERROR(S16/S$16,0) -> 1 | U16: =SUM(U9:U15) -> 20000 | V16: =IFERROR(U16/U$16,0) -> 1 | W16: =SUM(W9:W15) -> 20000 | X16: =IFERROR(W16/W$16,0) -> 1 | Y16: =SUM(Y9:Y15) -> 34999 | Z16: =IFERROR(Y16/Y$16,0) -> 1 | AB16: =SUM(AB9:AB15) -> 351975 | AC16: =IFERROR(AB16/AB$16,0) -> 1
A18: Cost of Goods Sold
A19: Food Cost | C19: 18631 | D19: =IFERROR(C19/C$9,0) -> 0.65734044 | E19: 8386 | F19: =IFERROR(E19/E$9,0) -> 0.91961838 | G19: 14740 | H19: =IFERROR(G19/G$9,0) -> 0.6715262 | I19: 4280 | J19: =IFERROR(I19/I$9,0) -> 0.92142088 | K19: 11232 | L19: =IFERROR(K19/K$9,0) -> 0.78870866 | M19: 10735 | N19: =IFERROR(M19/M$9,0) -> 0.69753086 | O19: 7478 | P19: =IFERROR(O19/O$9,0) -> 0.65003477 | Q19: 5653 | R19: =IFERROR(Q19/Q$9,0) -> 0.64999425 | S19: 5653 | T19: =IFERROR(S19/S$9,0) -> 0.64999425 | U19: 4522 | V19: =IFERROR(U19/U$9,0) -> 0.64999281 | W19: 4522 | X19: =IFERROR(W19/W$9,0) -> 0.64999281 | Y19: 7914 | Z19: =IFERROR(Y19/Y$9,0) -> 0.65002053 | AB19: =SUM(C19,E19,G19,I19,K19,M19,O19,Q19,S19,U19,W19,Y19) -> 103746 | AC19: =IFERROR(AB19/AB$9,0) -> 0.69780393
A20: Non-Alcoholic Beverage Cost | C20: 1198 | D20: =IFERROR(C20/C$10,0) -> 0.19993324 | E20: 895 | F20: =IFERROR(E20/E$10,0) -> 0.19704976 | G20: 1888 | H20: =IFERROR(G20/G$10,0) -> 0.48323522 | I20: 0 | J20: =IFERROR(I20/I$10,0) -> 0 | K20: 0 | L20: =IFERROR(K20/K$10,0) -> 0 | M20: 0 | N20: =IFERROR(M20/M$10,0) -> 0 | O20: 506 | P20: =IFERROR(O20/O$10,0) -> 0.29976303 | Q20: 383 | R20: =IFERROR(Q20/Q$10,0) -> 0.30015674 | S20: 383 | T20: =IFERROR(S20/S$10,0) -> 0.30015674 | U20: 306 | V20: =IFERROR(U20/U$10,0) -> 0.29970617 | W20: 306 | X20: =IFERROR(W20/W$10,0) -> 0.29970617 | Y20: 536 | Z20: =IFERROR(Y20/Y$10,0) -> 0.30011198 | AB20: =SUM(C20,E20,G20,I20,K20,M20,O20,Q20,S20,U20,W20,Y20) -> 6401 | AC20: =IFERROR(AB20/AB$10,0) -> 0.23021867
A21: Liquor Cost | C21: 243 | D21: =IFERROR(C21/C$11,0) -> 0.17986677 | E21: 931 | F21: =IFERROR(E21/E$11,0) -> 0.43484353 | G21: 723 | H21: =IFERROR(G21/G$11,0) -> 0.070344425 | I21: 0 | J21: =IFERROR(I21/I$11,0) -> 0 | K21: 1308 | L21: =IFERROR(K21/K$11,0) -> 0.2353788 | M21: 5238 | N21: =IFERROR(M21/M$11,0) -> 1.2646065 | O21: 0 | P21: =IFERROR(O21/O$11,0) -> 0 | Q21: 0 | R21: =IFERROR(Q21/Q$11,0) -> 0 | S21: 0 | T21: =IFERROR(S21/S$11,0) -> 0 | U21: 0 | V21: =IFERROR(U21/U$11,0) -> 0 | W21: 0 | X21: =IFERROR(W21/W$11,0) -> 0 | Y21: 0 | Z21: =IFERROR(Y21/Y$11,0) -> 0 | AB21: =SUM(C21,E21,G21,I21,K21,M21,O21,Q21,S21,U21,W21,Y21) -> 8443 | AC21: =IFERROR(AB21/AB$11,0) -> 0.18054872
A22: Beer Cost | C22: 8 | D22: =IFERROR(C22/C$12,0) -> 0.2 | E22: 707 | F22: =IFERROR(E22/E$12,0) -> 0 | G22: 239 | H22: =IFERROR(G22/G$12,0) -> 1.2780749 | I22: 0 | J22: =IFERROR(I22/I$12,0) -> 0 | K22: 0 | L22: =IFERROR(K22/K$12,0) -> 0 | M22: 180 | N22: =IFERROR(M22/M$12,0) -> 0.34285714 | O22: 47 | P22: =IFERROR(O22/O$12,0) -> 0.30128205 | Q22: 35 | R22: =IFERROR(Q22/Q$12,0) -> 0.29661017 | S22: 35 | T22: =IFERROR(S22/S$12,0) -> 0.29661017 | U22: 29 | V22: =IFERROR(U22/U$12,0) -> 0.30851064 | W22: 29 | X22: =IFERROR(W22/W$12,0) -> 0.30851064 | Y22: 49 | Z22: =IFERROR(Y22/Y$12,0) -> 0.2969697 | AB22: =SUM(C22,E22,G22,I22,K22,M22,O22,Q22,S22,U22,W22,Y22) -> 1358 | AC22: =IFERROR(AB22/AB$12,0) -> 0.78770302
A23: Wine/Sake Cost | C23: 190 | D23: =IFERROR(C23/C$13,0) -> 0.25065963 | E23: 888 | F23: =IFERROR(E23/E$13,0) -> 1.8853503 | G23: 699 | H23: =IFERROR(G23/G$13,0) -> 0.95884774 | I23: 252 | J23: =IFERROR(I23/I$13,0) -> 0.5915493 | K23: 404 | L23: =IFERROR(K23/K$13,0) -> 0.52467532 | M23: 551 | N23: =IFERROR(M23/M$13,0) -> 1.2695853 | O23: 0 | P23: =IFERROR(O23/O$13,0) -> 0 | Q23: 0 | R23: =IFERROR(Q23/Q$13,0) -> 0 | S23: 0 | T23: =IFERROR(S23/S$13,0) -> 0 | U23: 0 | V23: =IFERROR(U23/U$13,0) -> 0 | W23: 0 | X23: =IFERROR(W23/W$13,0) -> 0 | Y23: 0 | Z23: =IFERROR(Y23/Y$13,0) -> 0 | AB23: =SUM(C23,E23,G23,I23,K23,M23,O23,Q23,S23,U23,W23,Y23) -> 2984 | AC23: =IFERROR(AB23/AB$13,0) -> 0.45487805
A24: Total COGS | C24: =SUM(C19:C23) -> 20270 | D24: =IFERROR(C24/C$16,0) -> 0.53176977 | E24: =SUM(E19:E23) -> 11807 | F24: =IFERROR(E24/E$16,0) -> 0.70734484 | G24: =SUM(G19:G23) -> 18289 | H24: =IFERROR(G24/G$16,0) -> 0.45946489 | I24: =SUM(I19:I23) -> 4532 | J24: =IFERROR(I24/I$16,0) -> 0.36177856 | K24: =SUM(K19:K23) -> 12944 | L24: =IFERROR(K24/K$16,0) -> 0.31617773 | M24: =SUM(M19:M23) -> 16704 | N24: =IFERROR(M24/M$16,0) -> 0.36453309 | O24: =SUM(O19:O23) -> 8031 | P24: =IFERROR(O24/O$16,0) -> 0.2428485 | Q24: =SUM(Q19:Q23) -> 6071 | R24: =IFERROR(Q24/Q$16,0) -> 0.24283029 | S24: =SUM(S19:S23) -> 6071 | T24: =IFERROR(S24/S$16,0) -> 0.24283029 | U24: =SUM(U19:U23) -> 4857 | V24: =IFERROR(U24/U$16,0) -> 0.24285 | W24: =SUM(W19:W23) -> 4857 | X24: =IFERROR(W24/W$16,0) -> 0.24285 | Y24: =SUM(Y19:Y23) -> 8499 | Z24: =IFERROR(Y24/Y$16,0) -> 0.24283551 | AB24: =SUM(AB19:AB23) -> 122932 | AC24: =IFERROR(AB24/AB$16,0) -> 0.34926344
A25: Gross Profit | C25: =C16-C24 -> 17848 | D25: =IFERROR(C25/C$16,0) -> 0.46823023 | E25: =E16-E24 -> 4885 | F25: =IFERROR(E25/E$16,0) -> 0.29265516 | G25: =G16-G24 -> 21516 | H25: =IFERROR(G25/G$16,0) -> 0.54053511 | I25: =I16-I24 -> 7995 | J25: =IFERROR(I25/I$16,0) -> 0.63822144 | K25: =K16-K24 -> 27995 | L25: =IFERROR(K25/K$16,0) -> 0.68382227 | M25: =M16-M24 -> 29119 | N25: =IFERROR(M25/M$16,0) -> 0.63546691 | O25: =O16-O24 -> 25039 | P25: =IFERROR(O25/O$16,0) -> 0.7571515 | Q25: =Q16-Q24 -> 18930 | R25: =IFERROR(Q25/Q$16,0) -> 0.75716971 | S25: =S16-S24 -> 18930 | T25: =IFERROR(S25/S$16,0) -> 0.75716971 | U25: =U16-U24 -> 15143 | V25: =IFERROR(U25/U$16,0) -> 0.75715 | W25: =W16-W24 -> 15143 | X25: =IFERROR(W25/W$16,0) -> 0.75715 | Y25: =Y16-Y24 -> 26500 | Z25: =IFERROR(Y25/Y$16,0) -> 0.75716449 | AB25: =AB16-AB24 -> 229043 | AC25: =IFERROR(AB25/AB$16,0) -> 0.65073656
A27: Labor Cost
A28: Management Labor | C28: 1230 | D28: =IFERROR(C28/C$16,0) -> 0.03226822 | E28: 615 | F28: =IFERROR(E28/E$16,0) -> 0.036843997 | G28: 1277 | H28: =IFERROR(G28/G$16,0) -> 0.032081397 | I28: 1132 | J28: =IFERROR(I28/I$16,0) -> 0.090364812 | K28: 1657 | L28: =IFERROR(K28/K$16,0) -> 0.040474853 | M28: 5593 | N28: =IFERROR(M28/M$16,0) -> 0.12205661 | O28: 1657 | P28: =IFERROR(O28/O$16,0) -> 0.050105836 | Q28: 1657 | R28: =IFERROR(Q28/Q$16,0) -> 0.066277349 | S28: 1657 | T28: =IFERROR(S28/S$16,0) -> 0.066277349 | U28: 1657 | V28: =IFERROR(U28/U$16,0) -> 0.08285 | W28: 1657 | X28: =IFERROR(W28/W$16,0) -> 0.08285 | Y28: 1657 | Z28: =IFERROR(Y28/Y$16,0) -> 0.04734421 | AB28: =SUM(C28,E28,G28,I28,K28,M28,O28,Q28,S28,U28,W28,Y28) -> 21446 | AC28: =IFERROR(AB28/AB$16,0) -> 0.060930464
A29: Back of House Hourly Labor | C29: 1097 | D29: =IFERROR(C29/C$16,0) -> 0.028779055 | E29: 2016 | F29: =IFERROR(E29/E$16,0) -> 0.12077642 | G29: 1928 | H29: =IFERROR(G29/G$16,0) -> 0.048436126 | I29: 584 | J29: =IFERROR(I29/I$16,0) -> 0.046619302 | K29: 0 | L29: =IFERROR(K29/K$16,0) -> 0 | M29: 1619 | N29: =IFERROR(M29/M$16,0) -> 0.035331602 | O29: 0 | P29: =IFERROR(O29/O$16,0) -> 0 | Q29: 0 | R29: =IFERROR(Q29/Q$16,0) -> 0 | S29: 0 | T29: =IFERROR(S29/S$16,0) -> 0 | U29: 0 | V29: =IFERROR(U29/U$16,0) -> 0 | W29: 0 | X29: =IFERROR(W29/W$16,0) -> 0 | Y29: 0 | Z29: =IFERROR(Y29/Y$16,0) -> 0 | AB29: =SUM(C29,E29,G29,I29,K29,M29,O29,Q29,S29,U29,W29,Y29) -> 7244 | AC29: =IFERROR(AB29/AB$16,0) -> 0.020581007
A30: Front of House Hourly Labor | C30: 1384 | D30: =IFERROR(C30/C$16,0) -> 0.036308306 | E30: 1502 | F30: =IFERROR(E30/E$16,0) -> 0.089983225 | G30: 5284 | H30: =IFERROR(G30/G$16,0) -> 0.13274714 | I30: 0 | J30: =IFERROR(I30/I$16,0) -> 0 | K30: 8918 | L30: =IFERROR(K30/K$16,0) -> 0.21783629 | M30: 4034 | N30: =IFERROR(M30/M$16,0) -> 0.088034393 | O30: 5384 | P30: =IFERROR(O30/O$16,0) -> 0.16280617 | Q30: 2500 | R30: =IFERROR(Q30/Q$16,0) -> 0.099996 | S30: 2500 | T30: =IFERROR(S30/S$16,0) -> 0.099996 | U30: 2000 | V30: =IFERROR(U30/U$16,0) -> 0.1 | W30: 2000 | X30: =IFERROR(W30/W$16,0) -> 0.1 | Y30: 3500 | Z30: =IFERROR(Y30/Y$16,0) -> 0.10000286 | AB30: =SUM(C30,E30,G30,I30,K30,M30,O30,Q30,S30,U30,W30,Y30) -> 39006 | AC30: =IFERROR(AB30/AB$16,0) -> 0.11082037
A31: Payroll Taxes & Benefits | C31: 303 | D31: =IFERROR(C31/C$16,0) -> 0.0079490005 | E31: 1318 | F31: =IFERROR(E31/E$16,0) -> 0.078959981 | G31: 842 | H31: =IFERROR(G31/G$16,0) -> 0.021153121 | I31: 479 | J31: =IFERROR(I31/I$16,0) -> 0.038237407 | K31: 1667 | L31: =IFERROR(K31/K$16,0) -> 0.040719119 | M31: 1310 | N31: =IFERROR(M31/M$16,0) -> 0.028588264 | O31: 257 | P31: =IFERROR(O31/O$16,0) -> 0.007771394 | Q31: 257 | R31: =IFERROR(Q31/Q$16,0) -> 0.010279589 | S31: 257 | T31: =IFERROR(S31/S$16,0) -> 0.010279589 | U31: 257 | V31: =IFERROR(U31/U$16,0) -> 0.01285 | W31: 257 | X31: =IFERROR(W31/W$16,0) -> 0.01285 | Y31: 257 | Z31: =IFERROR(Y31/Y$16,0) -> 0.0073430669 | AB31: =SUM(C31,E31,G31,I31,K31,M31,O31,Q31,S31,U31,W31,Y31) -> 7461 | AC31: =IFERROR(AB31/AB$16,0) -> 0.021197528
A32: Bonus | C32: 313 | D32: =IFERROR(C32/C$16,0) -> 0.0082113437 | E32: 311 | F32: =IFERROR(E32/E$16,0) -> 0.01863168 | G32: 380 | H32: =IFERROR(G32/G$16,0) -> 0.0095465394 | I32: 380 | J32: =IFERROR(I32/I$16,0) -> 0.030334478 | K32: 551 | L32: =IFERROR(K32/K$16,0) -> 0.013459049 | M32: 516 | N32: =IFERROR(M32/M$16,0) -> 0.011260721 | O32: 58 | P32: =IFERROR(O32/O$16,0) -> 0.0017538555 | Q32: 58 | R32: =IFERROR(Q32/Q$16,0) -> 0.0023199072 | S32: 58 | T32: =IFERROR(S32/S$16,0) -> 0.0023199072 | U32: 58 | V32: =IFERROR(U32/U$16,0) -> 0.0029 | W32: 58 | X32: =IFERROR(W32/W$16,0) -> 0.0029 | Y32: 58 | Z32: =IFERROR(Y32/Y$16,0) -> 0.0016571902 | AB32: =SUM(C32,E32,G32,I32,K32,M32,O32,Q32,S32,U32,W32,Y32) -> 2799 | AC32: =IFERROR(AB32/AB$16,0) -> 0.0079522693
A33: Total Labor Cost | C33: =SUM(C28:C32) -> 4327 | D33: =IFERROR(C33/C$16,0) -> 0.11351592 | E33: =SUM(E28:E32) -> 5762 | F33: =IFERROR(E33/E$16,0) -> 0.3451953 | G33: =SUM(G28:G32) -> 9711 | H33: =IFERROR(G33/G$16,0) -> 0.24396433 | I33: =SUM(I28:I32) -> 2575 | J33: =IFERROR(I33/I$16,0) -> 0.205556 | K33: =SUM(K28:K32) -> 12793 | L33: =IFERROR(K33/K$16,0) -> 0.31248931 | M33: =SUM(M28:M32) -> 13072 | N33: =IFERROR(M33/M$16,0) -> 0.28527159 | O33: =SUM(O28:O32) -> 7356 | P33: =IFERROR(O33/O$16,0) -> 0.22243725 | Q33: =SUM(Q28:Q32) -> 4472 | R33: =IFERROR(Q33/Q$16,0) -> 0.17887285 | S33: =SUM(S28:S32) -> 4472 | T33: =IFERROR(S33/S$16,0) -> 0.17887285 | U33: =SUM(U28:U32) -> 3972 | V33: =IFERROR(U33/U$16,0) -> 0.1986 | W33: =SUM(W28:W32) -> 3972 | X33: =IFERROR(W33/W$16,0) -> 0.1986 | Y33: =SUM(Y28:Y32) -> 5472 | Z33: =IFERROR(Y33/Y$16,0) -> 0.15634732 | AB33: =SUM(AB28:AB32) -> 77956 | AC33: =IFERROR(AB33/AB$16,0) -> 0.22148164
A35: Prime Costs | C35: =C24+C33 -> 24597 | D35: =IFERROR(C35/C$16,0) -> 0.64528569 | E35: =E24+E33 -> 17569 | F35: =IFERROR(E35/E$16,0) -> 1.0525401 | G35: =G24+G33 -> 28000 | H35: =IFERROR(G35/G$16,0) -> 0.70342922 | I35: =I24+I33 -> 7107 | J35: =IFERROR(I35/I$16,0) -> 0.56733456 | K35: =K24+K33 -> 25737 | L35: =IFERROR(K35/K$16,0) -> 0.62866704 | M35: =M24+M33 -> 29776 | N35: =IFERROR(M35/M$16,0) -> 0.64980468 | O35: =O24+O33 -> 15387 | P35: =IFERROR(O35/O$16,0) -> 0.46528576 | Q35: =Q24+Q33 -> 10543 | R35: =IFERROR(Q35/Q$16,0) -> 0.42170313 | S35: =S24+S33 -> 10543 | T35: =IFERROR(S35/S$16,0) -> 0.42170313 | U35: =U24+U33 -> 8829 | V35: =IFERROR(U35/U$16,0) -> 0.44145 | W35: =W24+W33 -> 8829 | X35: =IFERROR(W35/W$16,0) -> 0.44145 | Y35: =Y24+Y33 -> 13971 | Z35: =IFERROR(Y35/Y$16,0) -> 0.39918283 | AB35: =AB24+AB33 -> 200888 | AC35: =IFERROR(AB35/AB$16,0) -> 0.57074508
A36: Operating Profit | C36: =C25-C33 -> 13521 | D36: =IFERROR(C36/C$16,0) -> 0.35471431 | E36: =E25-E33 -> -877 | F36: =IFERROR(E36/E$16,0) -> -0.052540139 | G36: =G25-G33 -> 11805 | H36: =IFERROR(G36/G$16,0) -> 0.29657078 | I36: =I25-I33 -> 5420 | J36: =IFERROR(I36/I$16,0) -> 0.43266544 | K36: =K25-K33 -> 15202 | L36: =IFERROR(K36/K$16,0) -> 0.37133296 | M36: =M25-M33 -> 16047 | N36: =IFERROR(M36/M$16,0) -> 0.35019532 | O36: =O25-O33 -> 17683 | P36: =IFERROR(O36/O$16,0) -> 0.53471424 | Q36: =Q25-Q33 -> 14458 | R36: =IFERROR(Q36/Q$16,0) -> 0.57829687 | S36: =S25-S33 -> 14458 | T36: =IFERROR(S36/S$16,0) -> 0.57829687 | U36: =U25-U33 -> 11171 | V36: =IFERROR(U36/U$16,0) -> 0.55855 | W36: =W25-W33 -> 11171 | X36: =IFERROR(W36/W$16,0) -> 0.55855 | Y36: =Y25-Y33 -> 21028 | Z36: =IFERROR(Y36/Y$16,0) -> 0.60081717 | AB36: =AB25-AB33 -> 151087 | AC36: =IFERROR(AB36/AB$16,0) -> 0.42925492
A38: Controllable Expenses
A39: Operating Expenses | C39: 1631 | D39: =IFERROR(C39/C$16,0) -> 0.042788184 | E39: 1306 | F39: =IFERROR(E39/E$16,0) -> 0.078241074 | G39: 3262 | H39: =IFERROR(G39/G$16,0) -> 0.081949504 | I39: 580 | J39: =IFERROR(I39/I$16,0) -> 0.046299992 | K39: 947 | L39: =IFERROR(K39/K$16,0) -> 0.023131977 | M39: 929 | N39: =IFERROR(M39/M$16,0) -> 0.020273662 | O39: 1262 | P39: =IFERROR(O39/O$16,0) -> 0.038161476 | Q39: 1262 | R39: =IFERROR(Q39/Q$16,0) -> 0.050477981 | S39: 1262 | T39: =IFERROR(S39/S$16,0) -> 0.050477981 | U39: 1262 | V39: =IFERROR(U39/U$16,0) -> 0.0631 | W39: 1262 | X39: =IFERROR(W39/W$16,0) -> 0.0631 | Y39: 1262 | Z39: =IFERROR(Y39/Y$16,0) -> 0.036058173 | AB39: =SUM(C39,E39,G39,I39,K39,M39,O39,Q39,S39,U39,W39,Y39) -> 16227 | AC39: =IFERROR(AB39/AB$16,0) -> 0.046102706
A40: Music & Entertainment | C40: 0 | D40: =IFERROR(C40/C$16,0) -> 0 | E40: 1112 | F40: =IFERROR(E40/E$16,0) -> 0.06661874 | G40: 256 | H40: =IFERROR(G40/G$16,0) -> 0.0064313528 | I40: 0 | J40: =IFERROR(I40/I$16,0) -> 0 | K40: 1445 | L40: =IFERROR(K40/K$16,0) -> 0.035296417 | M40: 0 | N40: =IFERROR(M40/M$16,0) -> 0 | O40: 1445 | P40: =IFERROR(O40/O$16,0) -> 0.043695192 | Q40: 1445 | R40: =IFERROR(Q40/Q$16,0) -> 0.057797688 | S40: 1445 | T40: =IFERROR(S40/S$16,0) -> 0.057797688 | U40: 1445 | V40: =IFERROR(U40/U$16,0) -> 0.07225 | W40: 1445 | X40: =IFERROR(W40/W$16,0) -> 0.07225 | Y40: 1445 | Z40: =IFERROR(Y40/Y$16,0) -> 0.041286894 | AB40: =SUM(C40,E40,G40,I40,K40,M40,O40,Q40,S40,U40,W40,Y40) -> 11483 | AC40: =IFERROR(AB40/AB$16,0) -> 0.032624476
A41: Marketing & Advertising | C41: 827 | D41: =IFERROR(C41/C$16,0) -> 0.021695787 | E41: 1090 | F41: =IFERROR(E41/E$16,0) -> 0.065300743 | G41: 1821 | H41: =IFERROR(G41/G$16,0) -> 0.045748022 | I41: 1386 | J41: =IFERROR(I41/I$16,0) -> 0.11064102 | K41: 674 | L41: =IFERROR(K41/K$16,0) -> 0.016463519 | M41: 619 | N41: =IFERROR(M41/M$16,0) -> 0.0135085 | O41: 674 | P41: =IFERROR(O41/O$16,0) -> 0.02038101 | Q41: 674 | R41: =IFERROR(Q41/Q$16,0) -> 0.026958922 | S41: 674 | T41: =IFERROR(S41/S$16,0) -> 0.026958922 | U41: 674 | V41: =IFERROR(U41/U$16,0) -> 0.0337 | W41: 674 | X41: =IFERROR(W41/W$16,0) -> 0.0337 | Y41: 674 | Z41: =IFERROR(Y41/Y$16,0) -> 0.019257693 | AB41: =SUM(C41,E41,G41,I41,K41,M41,O41,Q41,S41,U41,W41,Y41) -> 10461 | AC41: =IFERROR(AB41/AB$16,0) -> 0.029720861
A42: General & Administrative - Controllable | C42: 3621 | D42: =IFERROR(C42/C$16,0) -> 0.094994491 | E42: 3804 | F42: =IFERROR(E42/E$16,0) -> 0.2278936 | G42: 5209 | H42: =IFERROR(G42/G$16,0) -> 0.13086296 | I42: 2705 | J42: =IFERROR(I42/I$16,0) -> 0.21593358 | K42: 4709 | L42: =IFERROR(K42/K$16,0) -> 0.11502479 | M42: 2885 | N42: =IFERROR(M42/M$16,0) -> 0.062959649 | O42: 3340 | P42: =IFERROR(O42/O$16,0) -> 0.10099788 | Q42: 2979 | R42: =IFERROR(Q42/Q$16,0) -> 0.11915523 | S42: 2857 | T42: =IFERROR(S42/S$16,0) -> 0.11427543 | U42: 2748 | V42: =IFERROR(U42/U$16,0) -> 0.1374 | W42: 2707 | X42: =IFERROR(W42/W$16,0) -> 0.13535 | Y42: 2718 | Z42: =IFERROR(Y42/Y$16,0) -> 0.077659362 | AB42: =SUM(C42,E42,G42,I42,K42,M42,O42,Q42,S42,U42,W42,Y42) -> 40282 | AC42: =IFERROR(AB42/AB$16,0) -> 0.11444563
A43: Repairs & Maintenance | C43: 0 | D43: =IFERROR(C43/C$16,0) -> 0 | E43: 0 | F43: =IFERROR(E43/E$16,0) -> 0 | G43: 520 | H43: =IFERROR(G43/G$16,0) -> 0.013063685 | I43: 1875 | J43: =IFERROR(I43/I$16,0) -> 0.1496767 | K43: 0 | L43: =IFERROR(K43/K$16,0) -> 0 | M43: 0 | N43: =IFERROR(M43/M$16,0) -> 0 | O43: 0 | P43: =IFERROR(O43/O$16,0) -> 0 | Q43: 0 | R43: =IFERROR(Q43/Q$16,0) -> 0 | S43: 0 | T43: =IFERROR(S43/S$16,0) -> 0 | U43: 0 | V43: =IFERROR(U43/U$16,0) -> 0 | W43: 0 | X43: =IFERROR(W43/W$16,0) -> 0 | Y43: 0 | Z43: =IFERROR(Y43/Y$16,0) -> 0 | AB43: =SUM(C43,E43,G43,I43,K43,M43,O43,Q43,S43,U43,W43,Y43) -> 2395 | AC43: =IFERROR(AB43/AB$16,0) -> 0.0068044605
A44: Total Controllable Expenses | C44: =SUM(C39:C43) -> 6079 | D44: =IFERROR(C44/C$16,0) -> 0.15947846 | E44: =SUM(E39:E43) -> 7312 | F44: =IFERROR(E44/E$16,0) -> 0.43805416 | G44: =SUM(G39:G43) -> 11068 | H44: =IFERROR(G44/G$16,0) -> 0.27805552 | I44: =SUM(I39:I43) -> 6546 | J44: =IFERROR(I44/I$16,0) -> 0.52255129 | K44: =SUM(K39:K43) -> 7775 | L44: =IFERROR(K44/K$16,0) -> 0.18991671 | M44: =SUM(M39:M43) -> 4433 | N44: =IFERROR(M44/M$16,0) -> 0.096741811 | O44: =SUM(O39:O43) -> 6721 | P44: =IFERROR(O44/O$16,0) -> 0.20323556 | Q44: =SUM(Q39:Q43) -> 6360 | R44: =IFERROR(Q44/Q$16,0) -> 0.25438982 | S44: =SUM(S39:S43) -> 6238 | T44: =IFERROR(S44/S$16,0) -> 0.24951002 | U44: =SUM(U39:U43) -> 6129 | V44: =IFERROR(U44/U$16,0) -> 0.30645 | W44: =SUM(W39:W43) -> 6088 | X44: =IFERROR(W44/W$16,0) -> 0.3044 | Y44: =SUM(Y39:Y43) -> 6099 | Z44: =IFERROR(Y44/Y$16,0) -> 0.17426212 | AB44: =SUM(AB39:AB43) -> 80848 | AC44: =IFERROR(AB44/AB$16,0) -> 0.22969813
A46: Uncontrollable Expenses
A47: Utilities | C47: 479 | D47: =IFERROR(C47/C$16,0) -> 0.012566242 | E47: 433 | F47: =IFERROR(E47/E$16,0) -> 0.02594057 | G47: 479 | H47: =IFERROR(G47/G$16,0) -> 0.012033664 | I47: 464 | J47: =IFERROR(I47/I$16,0) -> 0.037039994 | K47: 479 | L47: =IFERROR(K47/K$16,0) -> 0.011700335 | M47: 0 | N47: =IFERROR(M47/M$16,0) -> 0 | O47: 479 | P47: =IFERROR(O47/O$16,0) -> 0.014484427 | Q47: 479 | R47: =IFERROR(Q47/Q$16,0) -> 0.019159234 | S47: 479 | T47: =IFERROR(S47/S$16,0) -> 0.019159234 | U47: 479 | V47: =IFERROR(U47/U$16,0) -> 0.02395 | W47: 479 | X47: =IFERROR(W47/W$16,0) -> 0.02395 | Y47: 479 | Z47: =IFERROR(Y47/Y$16,0) -> 0.013686105 | AB47: =SUM(C47,E47,G47,I47,K47,M47,O47,Q47,S47,U47,W47,Y47) -> 5208 | AC47: =IFERROR(AB47/AB$16,0) -> 0.014796505
A48: Occupancy Cost | C48: 2509 | D48: =IFERROR(C48/C$16,0) -> 0.065821921 | E48: 1020 | F48: =IFERROR(E48/E$16,0) -> 0.061107117 | G48: 2388 | H48: =IFERROR(G48/G$16,0) -> 0.059992463 | I48: 736 | J48: =IFERROR(I48/I$16,0) -> 0.058753093 | K48: 2456 | L48: =IFERROR(K48/K$16,0) -> 0.059991695 | M48: 2749 | N48: =IFERROR(M48/M$16,0) -> 0.059991707 | O48: 1984 | P48: =IFERROR(O48/O$16,0) -> 0.059993952 | Q48: 1500 | R48: =IFERROR(Q48/Q$16,0) -> 0.0599976 | S48: 1500 | T48: =IFERROR(S48/S$16,0) -> 0.0599976 | U48: 1200 | V48: =IFERROR(U48/U$16,0) -> 0.06 | W48: 1200 | X48: =IFERROR(W48/W$16,0) -> 0.06 | Y48: 2100 | Z48: =IFERROR(Y48/Y$16,0) -> 0.060001714 | AB48: =SUM(C48,E48,G48,I48,K48,M48,O48,Q48,S48,U48,W48,Y48) -> 21342 | AC48: =IFERROR(AB48/AB$16,0) -> 0.060634988
A49: General & Administrative - Uncon | C49: 1669 | D49: =IFERROR(C49/C$16,0) -> 0.043785088 | E49: 223 | F49: =IFERROR(E49/E$16,0) -> 0.013359693 | G49: 627 | H49: =IFERROR(G49/G$16,0) -> 0.01575179 | I49: -128 | J49: =IFERROR(I49/I$16,0) -> -0.010217929 | K49: 0 | L49: =IFERROR(K49/K$16,0) -> 0 | M49: 0 | N49: =IFERROR(M49/M$16,0) -> 0 | O49: 661 | P49: =IFERROR(O49/O$16,0) -> 0.019987904 | Q49: 500 | R49: =IFERROR(Q49/Q$16,0) -> 0.0199992 | S49: 500 | T49: =IFERROR(S49/S$16,0) -> 0.0199992 | U49: 400 | V49: =IFERROR(U49/U$16,0) -> 0.02 | W49: 400 | X49: =IFERROR(W49/W$16,0) -> 0.02 | Y49: 700 | Z49: =IFERROR(Y49/Y$16,0) -> 0.020000571 | AB49: =SUM(C49,E49,G49,I49,K49,M49,O49,Q49,S49,U49,W49,Y49) -> 5552 | AC49: =IFERROR(AB49/AB$16,0) -> 0.015773848
A50: Management Fee | C50: 4000 | D50: =IFERROR(C50/C$16,0) -> 0.1049373 | E50: 4000 | F50: =IFERROR(E50/E$16,0) -> 0.23963575 | G50: 4000 | H50: =IFERROR(G50/G$16,0) -> 0.10048989 | I50: 4000 | J50: =IFERROR(I50/I$16,0) -> 0.31931029 | K50: 4000 | L50: =IFERROR(K50/K$16,0) -> 0.097706344 | M50: 4000 | N50: =IFERROR(M50/M$16,0) -> 0.087292408 | O50: 4000 | P50: =IFERROR(O50/O$16,0) -> 0.12095555 | Q50: 4000 | R50: =IFERROR(Q50/Q$16,0) -> 0.1599936 | S50: 4000 | T50: =IFERROR(S50/S$16,0) -> 0.1599936 | U50: 4000 | V50: =IFERROR(U50/U$16,0) -> 0.2 | W50: 4000 | X50: =IFERROR(W50/W$16,0) -> 0.2 | Y50: 4000 | Z50: =IFERROR(Y50/Y$16,0) -> 0.11428898 | AB50: =SUM(C50,E50,G50,I50,K50,M50,O50,Q50,S50,U50,W50,Y50) -> 48000 | AC50: =IFERROR(AB50/AB$16,0) -> 0.13637332
A51: Owner Fee | C51: 0 | D51: =IFERROR(C51/C$16,0) -> 0 | E51: 0 | F51: =IFERROR(E51/E$16,0) -> 0 | G51: 0 | H51: =IFERROR(G51/G$16,0) -> 0 | I51: 0 | J51: =IFERROR(I51/I$16,0) -> 0 | K51: 0 | L51: =IFERROR(K51/K$16,0) -> 0 | M51: 0 | N51: =IFERROR(M51/M$16,0) -> 0 | O51: 0 | P51: =IFERROR(O51/O$16,0) -> 0 | Q51: 0 | R51: =IFERROR(Q51/Q$16,0) -> 0 | S51: 0 | T51: =IFERROR(S51/S$16,0) -> 0 | U51: 0 | V51: =IFERROR(U51/U$16,0) -> 0 | W51: 0 | X51: =IFERROR(W51/W$16,0) -> 0 | Y51: 0 | Z51: =IFERROR(Y51/Y$16,0) -> 0 | AB51: =SUM(C51,E51,G51,I51,K51,M51,O51,Q51,S51,U51,W51,Y51) -> 0 | AC51: =IFERROR(AB51/AB$16,0) -> 0
A52: Business Taxes | C52: 0 | D52: =IFERROR(C52/C$16,0) -> 0 | E52: 0 | F52: =IFERROR(E52/E$16,0) -> 0 | G52: 0 | H52: =IFERROR(G52/G$16,0) -> 0 | I52: 0 | J52: =IFERROR(I52/I$16,0) -> 0 | K52: 0 | L52: =IFERROR(K52/K$16,0) -> 0 | M52: 0 | N52: =IFERROR(M52/M$16,0) -> 0 | O52: 0 | P52: =IFERROR(O52/O$16,0) -> 0 | Q52: 0 | R52: =IFERROR(Q52/Q$16,0) -> 0 | S52: 0 | T52: =IFERROR(S52/S$16,0) -> 0 | U52: 0 | V52: =IFERROR(U52/U$16,0) -> 0 | W52: 0 | X52: =IFERROR(W52/W$16,0) -> 0 | Y52: 0 | Z52: =IFERROR(Y52/Y$16,0) -> 0 | AB52: =SUM(C52,E52,G52,I52,K52,M52,O52,Q52,S52,U52,W52,Y52) -> 0 | AC52: =IFERROR(AB52/AB$16,0) -> 0
A53: Total Uncontrollable Expenses | C53: =SUM(C47:C52) -> 8657 | D53: =IFERROR(C53/C$16,0) -> 0.22711055 | E53: =SUM(E47:E52) -> 5676 | F53: =IFERROR(E53/E$16,0) -> 0.34004313 | G53: =SUM(G47:G52) -> 7494 | H53: =IFERROR(G53/G$16,0) -> 0.18826781 | I53: =SUM(I47:I52) -> 5072 | J53: =IFERROR(I53/I$16,0) -> 0.40488545 | K53: =SUM(K47:K52) -> 6935 | L53: =IFERROR(K53/K$16,0) -> 0.16939837 | M53: =SUM(M47:M52) -> 6749 | N53: =IFERROR(M53/M$16,0) -> 0.14728411 | O53: =SUM(O47:O52) -> 7124 | P53: =IFERROR(O53/O$16,0) -> 0.21542183 | Q53: =SUM(Q47:Q52) -> 6479 | R53: =IFERROR(Q53/Q$16,0) -> 0.25914963 | S53: =SUM(S47:S52) -> 6479 | T53: =IFERROR(S53/S$16,0) -> 0.25914963 | U53: =SUM(U47:U52) -> 6079 | V53: =IFERROR(U53/U$16,0) -> 0.30395 | W53: =SUM(W47:W52) -> 6079 | X53: =IFERROR(W53/W$16,0) -> 0.30395 | Y53: =SUM(Y47:Y52) -> 7279 | Z53: =IFERROR(Y53/Y$16,0) -> 0.20797737 | AB53: =SUM(AB47:AB52) -> 80102 | AC53: =IFERROR(AB53/AB$16,0) -> 0.22757866
A55: Net Operating Profit Before Debt Service | C55: =C36-C44-C53 -> -1215 | D55: =IFERROR(C55/C$16,0) -> -0.031874705 | E55: =E36-E44-E53 -> -13865 | F55: =IFERROR(E55/E$16,0) -> -0.83063743 | G55: =G36-G44-G53 -> -6757 | H55: =IFERROR(G55/G$16,0) -> -0.16975254 | I55: =I36-I44-I53 -> -6198 | J55: =IFERROR(I55/I$16,0) -> -0.49477129 | K55: =K36-K44-K53 -> 492 | L55: =IFERROR(K55/K$16,0) -> 0.01201788 | M55: =M36-M44-M53 -> 4865 | N55: =IFERROR(M55/M$16,0) -> 0.10616939 | O55: =O36-O44-O53 -> 3838 | P55: =IFERROR(O55/O$16,0) -> 0.11605685 | Q55: =Q36-Q44-Q53 -> 1619 | R55: =IFERROR(Q55/Q$16,0) -> 0.06475741 | S55: =S36-S44-S53 -> 1741 | T55: =IFERROR(S55/S$16,0) -> 0.069637215 | U55: =U36-U44-U53 -> -1037 | V55: =IFERROR(U55/U$16,0) -> -0.05185 | W55: =W36-W44-W53 -> -996 | X55: =IFERROR(W55/W$16,0) -> -0.0498 | Y55: =Y36-Y44-Y53 -> 7650 | Z55: =IFERROR(Y55/Y$16,0) -> 0.21857767 | AB55: =AB36-AB44-AB53 -> -9863 | AC55: =IFERROR(AB55/AB$16,0) -> -0.028021877
A57: Debt Service | C57: 0 | D57: =IFERROR(C57/C$16,0) -> 0 | E57: 0 | F57: =IFERROR(E57/E$16,0) -> 0 | G57: 0 | H57: =IFERROR(G57/G$16,0) -> 0 | I57: 0 | J57: =IFERROR(I57/I$16,0) -> 0 | K57: 0 | L57: =IFERROR(K57/K$16,0) -> 0 | M57: 0 | N57: =IFERROR(M57/M$16,0) -> 0 | O57: 0 | P57: =IFERROR(O57/O$16,0) -> 0 | Q57: 0 | R57: =IFERROR(Q57/Q$16,0) -> 0 | S57: 0 | T57: =IFERROR(S57/S$16,0) -> 0 | U57: 0 | V57: =IFERROR(U57/U$16,0) -> 0 | W57: 0 | X57: =IFERROR(W57/W$16,0) -> 0 | Y57: 0 | Z57: =IFERROR(Y57/Y$16,0) -> 0 | AB57: =SUM(C57,E57,G57,I57,K57,M57,O57,Q57,S57,U57,W57,Y57) -> 0 | AC57: =IFERROR(AB57/AB$16,0) -> 0
A59: Net Operating Profit After Debt Service | C59: =C55-C57 -> -1215 | D59: =IFERROR(C59/C$16,0) -> -0.031874705 | E59: =E55-E57 -> -13865 | F59: =IFERROR(E59/E$16,0) -> -0.83063743 | G59: =G55-G57 -> -6757 | H59: =IFERROR(G59/G$16,0) -> -0.16975254 | I59: =I55-I57 -> -6198 | J59: =IFERROR(I59/I$16,0) -> -0.49477129 | K59: =K55-K57 -> 492 | L59: =IFERROR(K59/K$16,0) -> 0.01201788 | M59: =M55-M57 -> 4865 | N59: =IFERROR(M59/M$16,0) -> 0.10616939 | O59: =O55-O57 -> 3838 | P59: =IFERROR(O59/O$16,0) -> 0.11605685 | Q59: =Q55-Q57 -> 1619 | R59: =IFERROR(Q59/Q$16,0) -> 0.06475741 | S59: =S55-S57 -> 1741 | T59: =IFERROR(S59/S$16,0) -> 0.069637215 | U59: =U55-U57 -> -1037 | V59: =IFERROR(U59/U$16,0) -> -0.05185 | W59: =W55-W57 -> -996 | X59: =IFERROR(W59/W$16,0) -> -0.0498 | Y59: =Y55-Y57 -> 7650 | Z59: =IFERROR(Y59/Y$16,0) -> 0.21857767 | AB59: =AB55-AB57 -> -9863 | AC59: =IFERROR(AB59/AB$16,0) -> -0.028021877
A61: Other (Income) Expense | C61: 0 | D61: =IFERROR(C61/C$16,0) -> 0 | E61: 0 | F61: =IFERROR(E61/E$16,0) -> 0 | G61: 0 | H61: =IFERROR(G61/G$16,0) -> 0 | I61: 0 | J61: =IFERROR(I61/I$16,0) -> 0 | K61: 0 | L61: =IFERROR(K61/K$16,0) -> 0 | M61: 0 | N61: =IFERROR(M61/M$16,0) -> 0 | O61: 0 | P61: =IFERROR(O61/O$16,0) -> 0 | Q61: 0 | R61: =IFERROR(Q61/Q$16,0) -> 0 | S61: 0 | T61: =IFERROR(S61/S$16,0) -> 0 | U61: 0 | V61: =IFERROR(U61/U$16,0) -> 0 | W61: 0 | X61: =IFERROR(W61/W$16,0) -> 0 | Y61: 0 | Z61: =IFERROR(Y61/Y$16,0) -> 0 | AB61: =SUM(C61,E61,G61,I61,K61,M61,O61,Q61,S61,U61,W61,Y61) -> 0 | AC61: =IFERROR(AB61/AB$16,0) -> 0
A62: Reserve / CapEx | C62: 239 | D62: =IFERROR(C62/C$16,0) -> 0.0062700037 | E62: 375 | F62: =IFERROR(E62/E$16,0) -> 0.022465852 | G62: 500 | H62: =IFERROR(G62/G$16,0) -> 0.012561236 | I62: 500 | J62: =IFERROR(I62/I$16,0) -> 0.039913786 | K62: 409 | L62: =IFERROR(K62/K$16,0) -> 0.0099904736 | M62: 458 | N62: =IFERROR(M62/M$16,0) -> 0.0099949807 | O62: 409 | P62: =IFERROR(O62/O$16,0) -> 0.012367705 | Q62: 409 | R62: =IFERROR(Q62/Q$16,0) -> 0.016359346 | S62: 409 | T62: =IFERROR(S62/S$16,0) -> 0.016359346 | U62: 409 | V62: =IFERROR(U62/U$16,0) -> 0.02045 | W62: 409 | X62: =IFERROR(W62/W$16,0) -> 0.02045 | Y62: 409 | Z62: =IFERROR(Y62/Y$16,0) -> 0.011686048 | AB62: =SUM(C62,E62,G62,I62,K62,M62,O62,Q62,S62,U62,W62,Y62) -> 4935 | AC62: =IFERROR(AB62/AB$16,0) -> 0.014020882
A63: Net Cash Flow | C63: =C59-C61-C62 -> -1454 | D63: =IFERROR(C63/C$16,0) -> -0.038144709 | E63: =E59-E61-E62 -> -14240 | F63: =IFERROR(E63/E$16,0) -> -0.85310328 | G63: =G59-G61-G62 -> -7257 | H63: =IFERROR(G63/G$16,0) -> -0.18231378 | I63: =I59-I61-I62 -> -6698 | J63: =IFERROR(I63/I$16,0) -> -0.53468508 | K63: =K59-K61-K62 -> 83 | L63: =IFERROR(K63/K$16,0) -> 0.0020274066 | M63: =M59-M61-M62 -> 4407 | N63: =IFERROR(M63/M$16,0) -> 0.09617441 | O63: =O59-O61-O62 -> 3429 | P63: =IFERROR(O63/O$16,0) -> 0.10368914 | Q63: =Q59-Q61-Q62 -> 1210 | R63: =IFERROR(Q63/Q$16,0) -> 0.048398064 | S63: =S59-S61-S62 -> 1332 | T63: =IFERROR(S63/S$16,0) -> 0.053277869 | U63: =U59-U61-U62 -> -1446 | V63: =IFERROR(U63/U$16,0) -> -0.0723 | W63: =W59-W61-W62 -> -1405 | X63: =IFERROR(W63/W$16,0) -> -0.07025 | Y63: =Y59-Y61-Y62 -> 7241 | Z63: =IFERROR(Y63/Y$16,0) -> 0.20689163 | AB63: =AB59-AB61-AB62 -> -14798 | AC63: =IFERROR(AB63/AB$16,0) -> -0.042042759

Sheet LW Assumptions
A1: LITTLE WING · COFFEE SHOP MODEL
A2: Single-shift efficiency model — 6am–4pm staffed (2nd barista Sat/Sun) + BOH cook kept, self-serve/retail after 4pm (front desk, no FOH labor)
B4: REVENUE (Toast H1 2026 actuals ×2 — Jan–Jun item detail, reconciled to Sales Summary)
B5: Food | C5: 106838.2
B6: NA / Coffee | C6: 131727.36 | D6: the margin engine — 22.2% cost
B7: Alcohol | C7: 13996.3
B8: Retail / merch | C8: 5847.56
B9: Other | C9: 7792.6 | D9: gift cards, open items, uncategorized rings
B10: TOTAL REVENUE | C10: =SUM(C5:C9) -> 266202.02
B12: COST OF SALES (% of each category · GL actual)
B13: Food cost % | C13: 0.4407 | D13: GL cost ÷ net sales
B14: NA / Coffee cost % | C14: 0.2216
B15: Alcohol cost % | C15: 0.3328
B16: Retail cost % | C16: 0 | D16: no COGS booked in GL for retail
B17: Other cost % | C17: 0 | D17: no COGS booked in GL for other
B19: ADJUSTED LABOR (single 6am–4pm shift + 2nd barista on peak days)
B20: Opener/supervisor hours/day | C20: 10 | D20: 6am–4pm · one barista/supervisor
B21: 2nd barista avg hrs/day | C21: =2*4/7 -> 1.1428571 | D21: Sat & Sun opener/closer overlap, 4 hrs/day ×2 days ÷7 — covers the 8–11a weekend rush
B22: Days per week | C22: 7
B23: Blended wage $/hr | C23: 20 | D23: Dolce actual blended FOH rate ~$20/hr
B24: Payroll taxes & benefits % | C24: 0.16
B25: Adjusted labor / year | C25: =(C20+C21)*C22*52*C23*(1+C24)+C26*52*(1+C24) -> 111953.92 | D25: servers eliminated (self-serve); BOH cook KEPT at $296/wk
B26: BOH cook labor — kept ($/wk base) | C26: 296 | D26: current cook schedule held (~13.3 hrs/wk) — food program stays in-house
B27: CURRENT LABOR (GL actual, for comparison)
B28: Current labor / year (incl burden) | C28: 164857 | D28: GL T12 actual: wages+taxes+benefits
B30: VARIABLE & OVERHEAD (annual)
B31: Credit card fee (% of revenue) | C31: 0.025 | D31: go-forward target (Current column uses GL actual → C42)
B32: Controllable exp (excl CC) | C32: 89675 | D32: paper/plastics, accounting, linen…
B33: Non-controllable | C33: 5657 | D33: insurance, legal, reserves
B35: RETAIL PROGRAMMING (expanded merch/goods — new lever)
B36: Retail programming — incremental revenue ($/yr) | C36: 12000 | D36: INPUT (placeholder ~$1K/mo) — new goods program layered on top of the existing-base uplift below
B37: Retail programming COGS % | C37: 0.5 | D37: new merch carries real product cost (GL retail COGS was $0)
B39: BELOW NOI (owner / occupancy)
B40: Management fee (% of revenue) | C40: 0.04 | D40: 4% of gross revenue → Method (replaces $48K flat fee)
B41: Rent (% of revenue) | C41: 0.06 | D41: occupancy — GL actual ~6% of sales
B42: Credit card fee — GL actual (T12 $) | C42: 10012 | D42: 3.9% of rev — used for Current column; go-forward uses 2.5% target
B43: Menu price uplift ($/yr, pure margin) | C43: ='LW Menu Pricing'!$C$53 -> 17614.35 | D43: from LW Menu Pricing tab · held volume
B44: Apply price increase? (1=yes,0=no) | C44: 1 | D44: toggle the 2027 pricing scenario on/off
B45: Management labor — GL 610300 ($/yr) | C45: 12880 | D45: FOH Management wage, annualized ×12/5 — separate from hourly schedule
B46: Retail improvement uplift % (INPUT) | C46: 0.5 | D46: incremental retail rev from expanded inventory — % of current retail base
B47: → incremental retail $ / yr | C47: ='LW Assumptions'!$C$8*'LW Assumptions'!$C$46 -> 2923.78

Sheet LW P&L
A1: LITTLE WING — 2027 P&L
A2: Current staffing vs adjusted single-shift (6am–4pm, wknd 2nd barista) · annual · the gap is almost entirely labor
B4: Current | C4: % rev | D4: Adjusted | E4: % rev | F4: Change
A5: Food revenue | B5: ='LW Assumptions'!C5 -> 106838.2 | C5: =B5/B10 -> 0.40134256 | D5: ='LW Assumptions'!C5 -> 106838.2 | E5: =D5/D10 -> 0.40134256 | F5: =D5-B5 -> 0
A6: NA / Coffee revenue | B6: ='LW Assumptions'!C6 -> 131727.36 | C6: =B6/B10 -> 0.49483982 | D6: ='LW Assumptions'!C6 -> 131727.36 | E6: =D6/D10 -> 0.49483982 | F6: =D6-B6 -> 0
A7: Alcohol revenue | B7: ='LW Assumptions'!C7 -> 13996.3 | C7: =B7/B10 -> 0.052577738 | D7: ='LW Assumptions'!C7 -> 13996.3 | E7: =D7/D10 -> 0.052577738 | F7: =D7-B7 -> 0
A8: Retail / merch revenue | B8: ='LW Assumptions'!C8 -> 5847.56 | C8: =B8/B10 -> 0.021966625 | D8: ='LW Assumptions'!C8 -> 5847.56 | E8: =D8/D10 -> 0.021966625 | F8: =D8-B8 -> 0
A9: Other revenue | B9: ='LW Assumptions'!C9 -> 7792.6 | C9: =B9/B10 -> 0.029273256 | D9: ='LW Assumptions'!C9 -> 7792.6 | E9: =D9/D10 -> 0.029273256 | F9: =D9-B9 -> 0
A10: TOTAL REVENUE | B10: =SUM(B5:B9) -> 266202.02 | C10: =B10/B10 -> 1 | D10: =SUM(D5:D9) -> 266202.02 | E10: =D10/D10 -> 1 | F10: =D10-B10 -> 0
A12: Food COGS | B12: =B5*'LW Assumptions'!C13 -> 47083.595 | C12: =B12/B5 -> 0.4407 | D12: =D5*'LW Assumptions'!C13 -> 47083.595 | E12: =D12/D5 -> 0.4407 | F12: =D12-B12 -> 0
A13: NA / Coffee COGS | B13: =B6*'LW Assumptions'!C14 -> 29190.783 | C13: =B13/B6 -> 0.2216 | D13: =D6*'LW Assumptions'!C14 -> 29190.783 | E13: =D13/D6 -> 0.2216 | F13: =D13-B13 -> 0
A14: Alcohol COGS | B14: =B7*'LW Assumptions'!C15 -> 4657.9686 | C14: =B14/B7 -> 0.3328 | D14: =D7*'LW Assumptions'!C15 -> 4657.9686 | E14: =D14/D7 -> 0.3328 | F14: =D14-B14 -> 0
A15: Retail COGS | B15: =B8*'LW Assumptions'!C16 -> 0 | C15: =B15/B8 -> 0 | D15: =D8*'LW Assumptions'!C16 -> 0 | E15: =D15/D8 -> 0 | F15: =D15-B15 -> 0
A16: Other COGS | B16: =B9*'LW Assumptions'!C17 -> 0 | C16: =B16/B9 -> 0 | D16: =D9*'LW Assumptions'!C17 -> 0 | E16: =D16/D9 -> 0 | F16: =D16-B16 -> 0
A17: TOTAL COGS | B17: =SUM(B12:B16) -> 80932.346 | C17: =B17/B10 -> 0.30402604 | D17: =SUM(D12:D16) -> 80932.346 | E17: =D17/D10 -> 0.30402604 | F17: =D17-B17 -> 0
A18: GROSS PROFIT | B18: =B10-B17 -> 185269.67 | C18: =B18/B10 -> 0.69597396 | D18: =D10-D17 -> 185269.67 | E18: =D18/D10 -> 0.69597396 | F18: =D18-B18 -> 0
A20: Labor | B20: ='LW Assumptions'!C28 -> 164857 | C20: =B20/B10 -> 0.61929282 | D20: ='LW Assumptions'!C25 -> 111953.92 | E20: =D20/D10 -> 0.42055999 | F20: =D20-B20 -> -52903.08
A21: Credit card fees | B21: ='LW Assumptions'!$C$42 -> 10012 | C21: =B21/B10 -> 0.037610534 | D21: =D10*'LW Assumptions'!C31 -> 6655.0505 | E21: =D21/D10 -> 0.025 | F21: =D21-B21 -> -3356.9495
A22: Controllable (excl CC) | B22: ='LW Assumptions'!C32 -> 89675 | C22: =B22/B10 -> 0.33686822 | D22: ='LW Assumptions'!C32 -> 89675 | E22: =D22/D10 -> 0.33686822 | F22: =D22-B22 -> 0
A23: Non-controllable | B23: ='LW Assumptions'!C33 -> 5657 | C23: =B23/B10 -> 0.021250778 | D23: ='LW Assumptions'!C33 -> 5657 | E23: =D23/D10 -> 0.021250778 | F23: =D23-B23 -> 0
A24: Management fee (4% of revenue) | B24: =B10*'LW Assumptions'!$C$40 -> 10648.081 | C24: =B24/B10 -> 0.04 | D24: =D10*'LW Assumptions'!$C$40 -> 10648.081 | E24: =D24/D10 -> 0.04 | F24: =D24-B24 -> 0
A25: Rent (6% of revenue) | B25: =B10*'LW Assumptions'!$C$41 -> 15972.121 | C25: =B25/B10 -> 0.06 | D25: =D10*'LW Assumptions'!$C$41 -> 15972.121 | E25: =D25/D10 -> 0.06 | F25: =D25-B25 -> 0
A26: TOTAL COSTS BELOW GROSS | B26: =SUM(B20:B25) -> 296821.2 | C26: =B26/B10 -> 1.1150224 | D26: =SUM(D20:D25) -> 240561.17 | E26: =D26/D10 -> 0.90367899 | F26: =D26-B26 -> -56260.029
A28: NET OPERATING INCOME (after mgmt fee & rent) | B28: =B18-B26 -> -111551.53 | C28: =B28/B10 -> -0.41904839 | D28: =D18-D26 -> -55291.499 | E28: =D28/D10 -> -0.20770503 | F28: =D28-B28 -> 56260.029
A34: Labor savings from the single-shift model: | F34: =B20-D20 -> 52903.08
A35: Both columns use go-forward owner terms (4% mgmt fee + 6% rent) so the gap is purely the labor model. Management fee now scales with revenue (replaces the $48K flat fee).

Sheet LW Budget
A1: LITTLE WING — 2027 BUDGET
A2: Adjusted single-shift model (6am–4pm) · $ and % of revenue each month · driven by LW Assumptions
A4: ($ / % of revenue) | B4: Jan | D4: Feb | F4: Mar | H4: Apr | J4: May | L4: Jun | N4: Jul | P4: Aug | R4: Sep | T4: Oct | V4: Nov | X4: Dec | Z4: FY 2027
A5: Revenue index (Jan–Jun = actual Toast · avg = 1.00) | B5: 0.7037 | D5: 0.81 | F5: 1.2058 | H5: 0.9305 | J5: 1.123 | L5: 1.227 | N5: =AVERAGE($B5,$D5,$F5,$H5,$J5,$L5) -> 1 | P5: =AVERAGE($B5,$D5,$F5,$H5,$J5,$L5) -> 1 | R5: =AVERAGE($B5,$D5,$F5,$H5,$J5,$L5) -> 1 | T5: =AVERAGE($B5,$D5,$F5,$H5,$J5,$L5) -> 1 | V5: =AVERAGE($B5,$D5,$F5,$H5,$J5,$L5) -> 1 | X5: =AVERAGE($B5,$D5,$F5,$H5,$J5,$L5) -> 1 | Z5: =AVERAGE(B5,D5,F5,H5,J5,L5,N5,P5,R5,T5,V5,X5) -> 1
A6: Food revenue | B6: =('LW Assumptions'!$C$5/12)*B5 -> 6265.1701 | C6: =B6/B11 -> 0.3576292 | D6: =('LW Assumptions'!$C$5/12)*D5 -> 7211.5785 | E6: =D6/D11 -> 0.3576292 | F6: =('LW Assumptions'!$C$5/12)*F5 -> 10735.458 | G6: =F6/F11 -> 0.3576292 | H6: =('LW Assumptions'!$C$5/12)*H5 -> 8284.4121 | I6: =H6/H11 -> 0.3576292 | J6: =('LW Assumptions'!$C$5/12)*J5 -> 9998.2749 | K6: =J6/J11 -> 0.3576292 | L6: =('LW Assumptions'!$C$5/12)*L5 -> 10924.206 | M6: =L6/L11 -> 0.3576292 | N6: =('LW Assumptions'!$C$5/12)*N5 -> 8903.1833 | O6: =N6/N11 -> 0.3576292 | P6: =('LW Assumptions'!$C$5/12)*P5 -> 8903.1833 | Q6: =P6/P11 -> 0.3576292 | R6: =('LW Assumptions'!$C$5/12)*R5 -> 8903.1833 | S6: =R6/R11 -> 0.3576292 | T6: =('LW Assumptions'!$C$5/12)*T5 -> 8903.1833 | U6: =T6/T11 -> 0.3576292 | V6: =('LW Assumptions'!$C$5/12)*V5 -> 8903.1833 | W6: =V6/V11 -> 0.3576292 | X6: =('LW Assumptions'!$C$5/12)*X5 -> 8903.1833 | Y6: =X6/X11 -> 0.3576292 | Z6: =B6+D6+F6+H6+J6+L6+N6+P6+R6+T6+V6+X6 -> 106838.2 | AA6: =Z6/Z11 -> 0.3576292
A7: NA / Coffee revenue | B7: =('LW Assumptions'!$C$6/12)*B5 -> 7724.7119 | C7: =B7/B11 -> 0.44094294 | D7: =('LW Assumptions'!$C$6/12)*D5 -> 8891.5968 | E7: =D7/D11 -> 0.44094294 | F7: =('LW Assumptions'!$C$6/12)*F5 -> 13236.404 | G7: =F7/F11 -> 0.44094294 | H7: =('LW Assumptions'!$C$6/12)*H5 -> 10214.359 | I7: =H7/H11 -> 0.44094294 | J7: =('LW Assumptions'!$C$6/12)*J5 -> 12327.485 | K7: =J7/J11 -> 0.44094294 | L7: =('LW Assumptions'!$C$6/12)*L5 -> 13469.123 | M7: =L7/L11 -> 0.44094294 | N7: =('LW Assumptions'!$C$6/12)*N5 -> 10977.28 | O7: =N7/N11 -> 0.44094294 | P7: =('LW Assumptions'!$C$6/12)*P5 -> 10977.28 | Q7: =P7/P11 -> 0.44094294 | R7: =('LW Assumptions'!$C$6/12)*R5 -> 10977.28 | S7: =R7/R11 -> 0.44094294 | T7: =('LW Assumptions'!$C$6/12)*T5 -> 10977.28 | U7: =T7/T11 -> 0.44094294 | V7: =('LW Assumptions'!$C$6/12)*V5 -> 10977.28 | W7: =V7/V11 -> 0.44094294 | X7: =('LW Assumptions'!$C$6/12)*X5 -> 10977.28 | Y7: =X7/X11 -> 0.44094294 | Z7: =B7+D7+F7+H7+J7+L7+N7+P7+R7+T7+V7+X7 -> 131727.36 | AA7: =Z7/Z11 -> 0.44094294
A8: Alcohol revenue | B8: =('LW Assumptions'!$C$7/12)*B5 -> 820.76636 | C8: =B8/B11 -> 0.046851084 | D8: =('LW Assumptions'!$C$7/12)*D5 -> 944.75025 | E8: =D8/D11 -> 0.046851084 | F8: =('LW Assumptions'!$C$7/12)*F5 -> 1406.3949 | G8: =F8/F11 -> 0.046851084 | H8: =('LW Assumptions'!$C$7/12)*H5 -> 1085.2964 | I8: =H8/H11 -> 0.046851084 | J8: =('LW Assumptions'!$C$7/12)*J5 -> 1309.8204 | K8: =J8/J11 -> 0.046851084 | L8: =('LW Assumptions'!$C$7/12)*L5 -> 1431.1217 | M8: =L8/L11 -> 0.046851084 | N8: =('LW Assumptions'!$C$7/12)*N5 -> 1166.3583 | O8: =N8/N11 -> 0.046851084 | P8: =('LW Assumptions'!$C$7/12)*P5 -> 1166.3583 | Q8: =P8/P11 -> 0.046851084 | R8: =('LW Assumptions'!$C$7/12)*R5 -> 1166.3583 | S8: =R8/R11 -> 0.046851084 | T8: =('LW Assumptions'!$C$7/12)*T5 -> 1166.3583 | U8: =T8/T11 -> 0.046851084 | V8: =('LW Assumptions'!$C$7/12)*V5 -> 1166.3583 | W8: =V8/V11 -> 0.046851084 | X8: =('LW Assumptions'!$C$7/12)*X5 -> 1166.3583 | Y8: =X8/X11 -> 0.046851084 | Z8: =B8+D8+F8+H8+J8+L8+N8+P8+R8+T8+V8+X8 -> 13996.3 | AA8: =Z8/Z11 -> 0.046851084
A9: Retail / merch revenue (incl. uplift + programming) | B9: =('LW Assumptions'!$C$8/12)*B5*(1+'LW Assumptions'!$C$46)+('LW Assumptions'!$C$36/12)*B5 -> 1218.066 | C9: =B9/B11 -> 0.06952979 | D9: =('LW Assumptions'!$C$8/12)*D5*(1+'LW Assumptions'!$C$46)+('LW Assumptions'!$C$36/12)*D5 -> 1402.0655 | E9: =D9/D11 -> 0.06952979 | F9: =('LW Assumptions'!$C$8/12)*F5*(1+'LW Assumptions'!$C$46)+('LW Assumptions'!$C$36/12)*F5 -> 2087.1735 | G9: =F9/F11 -> 0.06952979 | H9: =('LW Assumptions'!$C$8/12)*H5*(1+'LW Assumptions'!$C$46)+('LW Assumptions'!$C$36/12)*H5 -> 1610.6443 | I9: =H9/H11 -> 0.06952979 | J9: =('LW Assumptions'!$C$8/12)*J5*(1+'LW Assumptions'!$C$46)+('LW Assumptions'!$C$36/12)*J5 -> 1943.8512 | K9: =J9/J11 -> 0.06952979 | L9: =('LW Assumptions'!$C$8/12)*L5*(1+'LW Assumptions'!$C$46)+('LW Assumptions'!$C$36/12)*L5 -> 2123.8695 | M9: =L9/L11 -> 0.06952979 | N9: =('LW Assumptions'!$C$8/12)*N5*(1+'LW Assumptions'!$C$46)+('LW Assumptions'!$C$36/12)*N5 -> 1730.945 | O9: =N9/N11 -> 0.06952979 | P9: =('LW Assumptions'!$C$8/12)*P5*(1+'LW Assumptions'!$C$46)+('LW Assumptions'!$C$36/12)*P5 -> 1730.945 | Q9: =P9/P11 -> 0.06952979 | R9: =('LW Assumptions'!$C$8/12)*R5*(1+'LW Assumptions'!$C$46)+('LW Assumptions'!$C$36/12)*R5 -> 1730.945 | S9: =R9/R11 -> 0.06952979 | T9: =('LW Assumptions'!$C$8/12)*T5*(1+'LW Assumptions'!$C$46)+('LW Assumptions'!$C$36/12)*T5 -> 1730.945 | U9: =T9/T11 -> 0.06952979 | V9: =('LW Assumptions'!$C$8/12)*V5*(1+'LW Assumptions'!$C$46)+('LW Assumptions'!$C$36/12)*V5 -> 1730.945 | W9: =V9/V11 -> 0.06952979 | X9: =('LW Assumptions'!$C$8/12)*X5*(1+'LW Assumptions'!$C$46)+('LW Assumptions'!$C$36/12)*X5 -> 1730.945 | Y9: =X9/X11 -> 0.06952979 | Z9: =B9+D9+F9+H9+J9+L9+N9+P9+R9+T9+V9+X9 -> 20771.34 | AA9: =Z9/Z11 -> 0.06952979
A10: Other revenue | B10: =('LW Assumptions'!$C$9/12)*B5 -> 456.97105 | C10: =B10/B11 -> 0.026084877 | D10: =('LW Assumptions'!$C$9/12)*D5 -> 526.0005 | E10: =D10/D11 -> 0.026084877 | F10: =('LW Assumptions'!$C$9/12)*F5 -> 783.02642 | G10: =F10/F11 -> 0.026084877 | H10: =('LW Assumptions'!$C$9/12)*H5 -> 604.25119 | I10: =H10/H11 -> 0.026084877 | J10: =('LW Assumptions'!$C$9/12)*J5 -> 729.25748 | K10: =J10/J11 -> 0.026084877 | L10: =('LW Assumptions'!$C$9/12)*L5 -> 796.79335 | M10: =L10/L11 -> 0.026084877 | N10: =('LW Assumptions'!$C$9/12)*N5 -> 649.38333 | O10: =N10/N11 -> 0.026084877 | P10: =('LW Assumptions'!$C$9/12)*P5 -> 649.38333 | Q10: =P10/P11 -> 0.026084877 | R10: =('LW Assumptions'!$C$9/12)*R5 -> 649.38333 | S10: =R10/R11 -> 0.026084877 | T10: =('LW Assumptions'!$C$9/12)*T5 -> 649.38333 | U10: =T10/T11 -> 0.026084877 | V10: =('LW Assumptions'!$C$9/12)*V5 -> 649.38333 | W10: =V10/V11 -> 0.026084877 | X10: =('LW Assumptions'!$C$9/12)*X5 -> 649.38333 | Y10: =X10/X11 -> 0.026084877 | Z10: =B10+D10+F10+H10+J10+L10+N10+P10+R10+T10+V10+X10 -> 7792.6 | AA10: =Z10/Z11 -> 0.026084877
A11: TOTAL REVENUE (incl. price increase) | B11: =SUM(B6:B10)+('LW Assumptions'!$C$43*'LW Assumptions'!$C$44/12)*B5 -> 17518.62 | C11: =B11/B11 -> 1 | D11: =SUM(D6:D10)+('LW Assumptions'!$C$43*'LW Assumptions'!$C$44/12)*D5 -> 20164.96 | E11: =D11/D11 -> 1 | F11: =SUM(F6:F10)+('LW Assumptions'!$C$43*'LW Assumptions'!$C$44/12)*F5 -> 30018.406 | G11: =F11/F11 -> 1 | H11: =SUM(H6:H10)+('LW Assumptions'!$C$43*'LW Assumptions'!$C$44/12)*H5 -> 23164.809 | I11: =H11/H11 -> 1 | J11: =SUM(J6:J10)+('LW Assumptions'!$C$43*'LW Assumptions'!$C$44/12)*J5 -> 27957.099 | K11: =J11/J11 -> 1 | L11: =SUM(L6:L10)+('LW Assumptions'!$C$43*'LW Assumptions'!$C$44/12)*L5 -> 30546.18 | M11: =L11/L11 -> 1 | N11: =SUM(N6:N10)+('LW Assumptions'!$C$43*'LW Assumptions'!$C$44/12)*N5 -> 24895.013 | O11: =N11/N11 -> 1 | P11: =SUM(P6:P10)+('LW Assumptions'!$C$43*'LW Assumptions'!$C$44/12)*P5 -> 24895.013 | Q11: =P11/P11 -> 1 | R11: =SUM(R6:R10)+('LW Assumptions'!$C$43*'LW Assumptions'!$C$44/12)*R5 -> 24895.013 | S11: =R11/R11 -> 1 | T11: =SUM(T6:T10)+('LW Assumptions'!$C$43*'LW Assumptions'!$C$44/12)*T5 -> 24895.013 | U11: =T11/T11 -> 1 | V11: =SUM(V6:V10)+('LW Assumptions'!$C$43*'LW Assumptions'!$C$44/12)*V5 -> 24895.013 | W11: =V11/V11 -> 1 | X11: =SUM(X6:X10)+('LW Assumptions'!$C$43*'LW Assumptions'!$C$44/12)*X5 -> 24895.013 | Y11: =X11/X11 -> 1 | Z11: =B11+D11+F11+H11+J11+L11+N11+P11+R11+T11+V11+X11 -> 298740.15 | AA11: =Z11/Z11 -> 1
A13: Food COGS (% of food sales) | B13: =B6*'LW Assumptions'!$C$13 -> 2761.0605 | C13: =B13/B6 -> 0.4407 | D13: =D6*'LW Assumptions'!$C$13 -> 3178.1426 | E13: =D13/D6 -> 0.4407 | F13: =F6*'LW Assumptions'!$C$13 -> 4731.1165 | G13: =F13/F6 -> 0.4407 | H13: =H6*'LW Assumptions'!$C$13 -> 3650.9404 | I13: =H13/H6 -> 0.4407 | J13: =J6*'LW Assumptions'!$C$13 -> 4406.2397 | K13: =J13/J6 -> 0.4407 | L13: =L6*'LW Assumptions'!$C$13 -> 4814.2976 | M13: =L13/L6 -> 0.4407 | N13: =N6*'LW Assumptions'!$C$13 -> 3923.6329 | O13: =N13/N6 -> 0.4407 | P13: =P6*'LW Assumptions'!$C$13 -> 3923.6329 | Q13: =P13/P6 -> 0.4407 | R13: =R6*'LW Assumptions'!$C$13 -> 3923.6329 | S13: =R13/R6 -> 0.4407 | T13: =T6*'LW Assumptions'!$C$13 -> 3923.6329 | U13: =T13/T6 -> 0.4407 | V13: =V6*'LW Assumptions'!$C$13 -> 3923.6329 | W13: =V13/V6 -> 0.4407 | X13: =X6*'LW Assumptions'!$C$13 -> 3923.6329 | Y13: =X13/X6 -> 0.4407 | Z13: =B13+D13+F13+H13+J13+L13+N13+P13+R13+T13+V13+X13 -> 47083.595 | AA13: =Z13/Z6 -> 0.4407
A14: NA / Coffee COGS (% of NA sales) | B14: =B7*'LW Assumptions'!$C$14 -> 1711.7962 | C14: =B14/B7 -> 0.2216 | D14: =D7*'LW Assumptions'!$C$14 -> 1970.3779 | E14: =D14/D7 -> 0.2216 | F14: =F7*'LW Assumptions'!$C$14 -> 2933.1872 | G14: =F14/F7 -> 0.2216 | H14: =H7*'LW Assumptions'!$C$14 -> 2263.502 | I14: =H14/H7 -> 0.2216 | J14: =J7*'LW Assumptions'!$C$14 -> 2731.7708 | K14: =J14/J7 -> 0.2216 | L14: =L7*'LW Assumptions'!$C$14 -> 2984.7576 | M14: =L14/L7 -> 0.2216 | N14: =N7*'LW Assumptions'!$C$14 -> 2432.5652 | O14: =N14/N7 -> 0.2216 | P14: =P7*'LW Assumptions'!$C$14 -> 2432.5652 | Q14: =P14/P7 -> 0.2216 | R14: =R7*'LW Assumptions'!$C$14 -> 2432.5652 | S14: =R14/R7 -> 0.2216 | T14: =T7*'LW Assumptions'!$C$14 -> 2432.5652 | U14: =T14/T7 -> 0.2216 | V14: =V7*'LW Assumptions'!$C$14 -> 2432.5652 | W14: =V14/V7 -> 0.2216 | X14: =X7*'LW Assumptions'!$C$14 -> 2432.5652 | Y14: =X14/X7 -> 0.2216 | Z14: =B14+D14+F14+H14+J14+L14+N14+P14+R14+T14+V14+X14 -> 29190.783 | AA14: =Z14/Z7 -> 0.2216
A15: Alcohol COGS (% of alc sales) | B15: =B8*'LW Assumptions'!$C$15 -> 273.15104 | C15: =B15/B8 -> 0.3328 | D15: =D8*'LW Assumptions'!$C$15 -> 314.41288 | E15: =D15/D8 -> 0.3328 | F15: =F8*'LW Assumptions'!$C$15 -> 468.04822 | G15: =F15/F8 -> 0.3328 | H15: =H8*'LW Assumptions'!$C$15 -> 361.18665 | I15: =H15/H8 -> 0.3328 | J15: =J8*'LW Assumptions'!$C$15 -> 435.90823 | K15: =J15/J8 -> 0.3328 | L15: =L8*'LW Assumptions'!$C$15 -> 476.27729 | M15: =L15/L8 -> 0.3328 | N15: =N8*'LW Assumptions'!$C$15 -> 388.16405 | O15: =N15/N8 -> 0.3328 | P15: =P8*'LW Assumptions'!$C$15 -> 388.16405 | Q15: =P15/P8 -> 0.3328 | R15: =R8*'LW Assumptions'!$C$15 -> 388.16405 | S15: =R15/R8 -> 0.3328 | T15: =T8*'LW Assumptions'!$C$15 -> 388.16405 | U15: =T15/T8 -> 0.3328 | V15: =V8*'LW Assumptions'!$C$15 -> 388.16405 | W15: =V15/V8 -> 0.3328 | X15: =X8*'LW Assumptions'!$C$15 -> 388.16405 | Y15: =X15/X8 -> 0.3328 | Z15: =B15+D15+F15+H15+J15+L15+N15+P15+R15+T15+V15+X15 -> 4657.9686 | AA15: =Z15/Z8 -> 0.3328
A16: Retail COGS (base % + programming COGS %) | B16: =B9*'LW Assumptions'!$C$16+('LW Assumptions'!$C$36/12)*B5*('LW Assumptions'!$C$37-'LW Assumptions'!$C$16) -> 351.85 | C16: =B16/B9 -> 0.28885955 | D16: =D9*'LW Assumptions'!$C$16+('LW Assumptions'!$C$36/12)*D5*('LW Assumptions'!$C$37-'LW Assumptions'!$C$16) -> 405 | E16: =D16/D9 -> 0.28885955 | F16: =F9*'LW Assumptions'!$C$16+('LW Assumptions'!$C$36/12)*F5*('LW Assumptions'!$C$37-'LW Assumptions'!$C$16) -> 602.9 | G16: =F16/F9 -> 0.28885955 | H16: =H9*'LW Assumptions'!$C$16+('LW Assumptions'!$C$36/12)*H5*('LW Assumptions'!$C$37-'LW Assumptions'!$C$16) -> 465.25 | I16: =H16/H9 -> 0.28885955 | J16: =J9*'LW Assumptions'!$C$16+('LW Assumptions'!$C$36/12)*J5*('LW Assumptions'!$C$37-'LW Assumptions'!$C$16) -> 561.5 | K16: =J16/J9 -> 0.28885955 | L16: =L9*'LW Assumptions'!$C$16+('LW Assumptions'!$C$36/12)*L5*('LW Assumptions'!$C$37-'LW Assumptions'!$C$16) -> 613.5 | M16: =L16/L9 -> 0.28885955 | N16: =N9*'LW Assumptions'!$C$16+('LW Assumptions'!$C$36/12)*N5*('LW Assumptions'!$C$37-'LW Assumptions'!$C$16) -> 500 | O16: =N16/N9 -> 0.28885955 | P16: =P9*'LW Assumptions'!$C$16+('LW Assumptions'!$C$36/12)*P5*('LW Assumptions'!$C$37-'LW Assumptions'!$C$16) -> 500 | Q16: =P16/P9 -> 0.28885955 | R16: =R9*'LW Assumptions'!$C$16+('LW Assumptions'!$C$36/12)*R5*('LW Assumptions'!$C$37-'LW Assumptions'!$C$16) -> 500 | S16: =R16/R9 -> 0.28885955 | T16: =T9*'LW Assumptions'!$C$16+('LW Assumptions'!$C$36/12)*T5*('LW Assumptions'!$C$37-'LW Assumptions'!$C$16) -> 500 | U16: =T16/T9 -> 0.28885955 | V16: =V9*'LW Assumptions'!$C$16+('LW Assumptions'!$C$36/12)*V5*('LW Assumptions'!$C$37-'LW Assumptions'!$C$16) -> 500 | W16: =V16/V9 -> 0.28885955 | X16: =X9*'LW Assumptions'!$C$16+('LW Assumptions'!$C$36/12)*X5*('LW Assumptions'!$C$37-'LW Assumptions'!$C$16) -> 500 | Y16: =X16/X9 -> 0.28885955 | Z16: =B16+D16+F16+H16+J16+L16+N16+P16+R16+T16+V16+X16 -> 6000 | AA16: =Z16/Z9 -> 0.28885955
A17: Other COGS (% of other sales) | B17: =B10*'LW Assumptions'!$C$17 -> 0 | C17: =B17/B10 -> 0 | D17: =D10*'LW Assumptions'!$C$17 -> 0 | E17: =D17/D10 -> 0 | F17: =F10*'LW Assumptions'!$C$17 -> 0 | G17: =F17/F10 -> 0 | H17: =H10*'LW Assumptions'!$C$17 -> 0 | I17: =H17/H10 -> 0 | J17: =J10*'LW Assumptions'!$C$17 -> 0 | K17: =J17/J10 -> 0 | L17: =L10*'LW Assumptions'!$C$17 -> 0 | M17: =L17/L10 -> 0 | N17: =N10*'LW Assumptions'!$C$17 -> 0 | O17: =N17/N10 -> 0 | P17: =P10*'LW Assumptions'!$C$17 -> 0 | Q17: =P17/P10 -> 0 | R17: =R10*'LW Assumptions'!$C$17 -> 0 | S17: =R17/R10 -> 0 | T17: =T10*'LW Assumptions'!$C$17 -> 0 | U17: =T17/T10 -> 0 | V17: =V10*'LW Assumptions'!$C$17 -> 0 | W17: =V17/V10 -> 0 | X17: =X10*'LW Assumptions'!$C$17 -> 0 | Y17: =X17/X10 -> 0 | Z17: =B17+D17+F17+H17+J17+L17+N17+P17+R17+T17+V17+X17 -> 0 | AA17: =Z17/Z10 -> 0
A18: TOTAL COGS | B18: =SUM(B13:B17) -> 5097.8577 | C18: =B18/B11 -> 0.29099653 | D18: =SUM(D13:D17) -> 5867.9334 | E18: =D18/D11 -> 0.29099653 | F18: =SUM(F13:F17) -> 8735.2519 | G18: =F18/F11 -> 0.29099653 | H18: =SUM(H13:H17) -> 6740.879 | I18: =H18/H11 -> 0.29099653 | J18: =SUM(J13:J17) -> 8135.4187 | K18: =J18/J11 -> 0.29099653 | L18: =SUM(L13:L17) -> 8888.8324 | M18: =L18/L11 -> 0.29099653 | N18: =SUM(N13:N17) -> 7244.3622 | O18: =N18/N11 -> 0.29099653 | P18: =SUM(P13:P17) -> 7244.3622 | Q18: =P18/P11 -> 0.29099653 | R18: =SUM(R13:R17) -> 7244.3622 | S18: =R18/R11 -> 0.29099653 | T18: =SUM(T13:T17) -> 7244.3622 | U18: =T18/T11 -> 0.29099653 | V18: =SUM(V13:V17) -> 7244.3622 | W18: =V18/V11 -> 0.29099653 | X18: =SUM(X13:X17) -> 7244.3622 | Y18: =X18/X11 -> 0.29099653 | Z18: =B18+D18+F18+H18+J18+L18+N18+P18+R18+T18+V18+X18 -> 86932.346 | AA18: =Z18/Z11 -> 0.29099653
A19: GROSS PROFIT | B19: =B11-B18 -> 12420.763 | C19: =B19/B11 -> 0.70900347 | D19: =D11-D18 -> 14297.027 | E19: =D19/D11 -> 0.70900347 | F19: =F11-F18 -> 21283.154 | G19: =F19/F11 -> 0.70900347 | H19: =H11-H18 -> 16423.93 | I19: =H19/H11 -> 0.70900347 | J19: =J11-J18 -> 19821.68 | K19: =J19/J11 -> 0.70900347 | L19: =L11-L18 -> 21657.348 | M19: =L19/L11 -> 0.70900347 | N19: =N11-N18 -> 17650.65 | O19: =N19/N11 -> 0.70900347 | P19: =P11-P18 -> 17650.65 | Q19: =P19/P11 -> 0.70900347 | R19: =R11-R18 -> 17650.65 | S19: =R19/R11 -> 0.70900347 | T19: =T11-T18 -> 17650.65 | U19: =T19/T11 -> 0.70900347 | V19: =V11-V18 -> 17650.65 | W19: =V19/V11 -> 0.70900347 | X19: =X11-X18 -> 17650.65 | Y19: =X19/X11 -> 0.70900347 | Z19: =Z11-Z18 -> 211807.8 | AA19: =Z19/Z11 -> 0.70900347
A21: Labor (single 6am–4pm shift + wknd 2nd barista) | B21: ='LW Assumptions'!$C$25/12 -> 9329.4933 | C21: =B21/B11 -> 0.53254727 | D21: ='LW Assumptions'!$C$25/12 -> 9329.4933 | E21: =D21/D11 -> 0.46265866 | F21: ='LW Assumptions'!$C$25/12 -> 9329.4933 | G21: =F21/F11 -> 0.31079243 | H21: ='LW Assumptions'!$C$25/12 -> 9329.4933 | I21: =H21/H11 -> 0.40274424 | J21: ='LW Assumptions'!$C$25/12 -> 9329.4933 | K21: =J21/J11 -> 0.33370749 | L21: ='LW Assumptions'!$C$25/12 -> 9329.4933 | M21: =L21/L11 -> 0.30542258 | N21: ='LW Assumptions'!$C$25/12 -> 9329.4933 | O21: =N21/N11 -> 0.37475351 | P21: ='LW Assumptions'!$C$25/12 -> 9329.4933 | Q21: =P21/P11 -> 0.37475351 | R21: ='LW Assumptions'!$C$25/12 -> 9329.4933 | S21: =R21/R11 -> 0.37475351 | T21: ='LW Assumptions'!$C$25/12 -> 9329.4933 | U21: =T21/T11 -> 0.37475351 | V21: ='LW Assumptions'!$C$25/12 -> 9329.4933 | W21: =V21/V11 -> 0.37475351 | X21: ='LW Assumptions'!$C$25/12 -> 9329.4933 | Y21: =X21/X11 -> 0.37475351 | Z21: =B21+D21+F21+H21+J21+L21+N21+P21+R21+T21+V21+X21 -> 111953.92 | AA21: =Z21/Z11 -> 0.37475351
A22: Credit card fees (2.5% of revenue) | B22: =B11*'LW Assumptions'!$C$31 -> 437.96551 | C22: =B22/B11 -> 0.025 | D22: =D11*'LW Assumptions'!$C$31 -> 504.124 | E22: =D22/D11 -> 0.025 | F22: =F11*'LW Assumptions'!$C$31 -> 750.46015 | G22: =F22/F11 -> 0.025 | H22: =H11*'LW Assumptions'!$C$31 -> 579.12023 | I22: =H22/H11 -> 0.025 | J22: =J11*'LW Assumptions'!$C$31 -> 698.92748 | K22: =J22/J11 -> 0.025 | L22: =L11*'LW Assumptions'!$C$31 -> 763.65451 | M22: =L22/L11 -> 0.025 | N22: =N11*'LW Assumptions'!$C$31 -> 622.37531 | O22: =N22/N11 -> 0.025 | P22: =P11*'LW Assumptions'!$C$31 -> 622.37531 | Q22: =P22/P11 -> 0.025 | R22: =R11*'LW Assumptions'!$C$31 -> 622.37531 | S22: =R22/R11 -> 0.025 | T22: =T11*'LW Assumptions'!$C$31 -> 622.37531 | U22: =T22/T11 -> 0.025 | V22: =V11*'LW Assumptions'!$C$31 -> 622.37531 | W22: =V22/V11 -> 0.025 | X22: =X11*'LW Assumptions'!$C$31 -> 622.37531 | Y22: =X22/X11 -> 0.025 | Z22: =B22+D22+F22+H22+J22+L22+N22+P22+R22+T22+V22+X22 -> 7468.5037 | AA22: =Z22/Z11 -> 0.025
A23: Controllable expenses (excl CC) | B23: ='LW Assumptions'!$C$32/12 -> 7472.9167 | C23: =B23/B11 -> 0.42656993 | D23: ='LW Assumptions'!$C$32/12 -> 7472.9167 | E23: =D23/D11 -> 0.37058921 | F23: ='LW Assumptions'!$C$32/12 -> 7472.9167 | G23: =F23/F11 -> 0.24894449 | H23: ='LW Assumptions'!$C$32/12 -> 7472.9167 | I23: =H23/H11 -> 0.32259781 | J23: ='LW Assumptions'!$C$32/12 -> 7472.9167 | K23: =J23/J11 -> 0.26729943 | L23: ='LW Assumptions'!$C$32/12 -> 7472.9167 | M23: =L23/L11 -> 0.24464324 | N23: ='LW Assumptions'!$C$32/12 -> 7472.9167 | O23: =N23/N11 -> 0.30017726 | P23: ='LW Assumptions'!$C$32/12 -> 7472.9167 | Q23: =P23/P11 -> 0.30017726 | R23: ='LW Assumptions'!$C$32/12 -> 7472.9167 | S23: =R23/R11 -> 0.30017726 | T23: ='LW Assumptions'!$C$32/12 -> 7472.9167 | U23: =T23/T11 -> 0.30017726 | V23: ='LW Assumptions'!$C$32/12 -> 7472.9167 | W23: =V23/V11 -> 0.30017726 | X23: ='LW Assumptions'!$C$32/12 -> 7472.9167 | Y23: =X23/X11 -> 0.30017726 | Z23: =B23+D23+F23+H23+J23+L23+N23+P23+R23+T23+V23+X23 -> 89675 | AA23: =Z23/Z11 -> 0.30017726
A24: Non-controllable (insurance, legal, reserves) | B24: ='LW Assumptions'!$C$33/12 -> 471.41667 | C24: =B24/B11 -> 0.026909463 | D24: ='LW Assumptions'!$C$33/12 -> 471.41667 | E24: =D24/D11 -> 0.023378011 | F24: ='LW Assumptions'!$C$33/12 -> 471.41667 | G24: =F24/F11 -> 0.015704254 | H24: ='LW Assumptions'!$C$33/12 -> 471.41667 | I24: =H24/H11 -> 0.020350553 | J24: ='LW Assumptions'!$C$33/12 -> 471.41667 | K24: =J24/J11 -> 0.016862145 | L24: ='LW Assumptions'!$C$33/12 -> 471.41667 | M24: =L24/L11 -> 0.015432917 | N24: ='LW Assumptions'!$C$33/12 -> 471.41667 | O24: =N24/N11 -> 0.018936189 | P24: ='LW Assumptions'!$C$33/12 -> 471.41667 | Q24: =P24/P11 -> 0.018936189 | R24: ='LW Assumptions'!$C$33/12 -> 471.41667 | S24: =R24/R11 -> 0.018936189 | T24: ='LW Assumptions'!$C$33/12 -> 471.41667 | U24: =T24/T11 -> 0.018936189 | V24: ='LW Assumptions'!$C$33/12 -> 471.41667 | W24: =V24/V11 -> 0.018936189 | X24: ='LW Assumptions'!$C$33/12 -> 471.41667 | Y24: =X24/X11 -> 0.018936189 | Z24: =B24+D24+F24+H24+J24+L24+N24+P24+R24+T24+V24+X24 -> 5657 | AA24: =Z24/Z11 -> 0.018936189
A25: Management fee (4% of revenue → Method) | B25: =B11*'LW Assumptions'!$C$40 -> 700.74481 | C25: =B25/B11 -> 0.04 | D25: =D11*'LW Assumptions'!$C$40 -> 806.5984 | E25: =D25/D11 -> 0.04 | F25: =F11*'LW Assumptions'!$C$40 -> 1200.7362 | G25: =F25/F11 -> 0.04 | H25: =H11*'LW Assumptions'!$C$40 -> 926.59237 | I25: =H25/H11 -> 0.04 | J25: =J11*'LW Assumptions'!$C$40 -> 1118.284 | K25: =J25/J11 -> 0.04 | L25: =L11*'LW Assumptions'!$C$40 -> 1221.8472 | M25: =L25/L11 -> 0.04 | N25: =N11*'LW Assumptions'!$C$40 -> 995.8005 | O25: =N25/N11 -> 0.04 | P25: =P11*'LW Assumptions'!$C$40 -> 995.8005 | Q25: =P25/P11 -> 0.04 | R25: =R11*'LW Assumptions'!$C$40 -> 995.8005 | S25: =R25/R11 -> 0.04 | T25: =T11*'LW Assumptions'!$C$40 -> 995.8005 | U25: =T25/T11 -> 0.04 | V25: =V11*'LW Assumptions'!$C$40 -> 995.8005 | W25: =V25/V11 -> 0.04 | X25: =X11*'LW Assumptions'!$C$40 -> 995.8005 | Y25: =X25/X11 -> 0.04 | Z25: =B25+D25+F25+H25+J25+L25+N25+P25+R25+T25+V25+X25 -> 11949.606 | AA25: =Z25/Z11 -> 0.04
A26: Rent (6% of revenue) | B26: =B11*'LW Assumptions'!$C$41 -> 1051.1172 | D26: =D11*'LW Assumptions'!$C$41 -> 1209.8976 | F26: =F11*'LW Assumptions'!$C$41 -> 1801.1044 | H26: =H11*'LW Assumptions'!$C$41 -> 1389.8885 | J26: =J11*'LW Assumptions'!$C$41 -> 1677.4259 | L26: =L11*'LW Assumptions'!$C$41 -> 1832.7708 | N26: =N11*'LW Assumptions'!$C$41 -> 1493.7007 | P26: =P11*'LW Assumptions'!$C$41 -> 1493.7007 | R26: =R11*'LW Assumptions'!$C$41 -> 1493.7007 | T26: =T11*'LW Assumptions'!$C$41 -> 1493.7007 | V26: =V11*'LW Assumptions'!$C$41 -> 1493.7007 | X26: =X11*'LW Assumptions'!$C$41 -> 1493.7007 | Z26: =B26+D26+F26+H26+J26+L26+N26+P26+R26+T26+V26+X26 -> 17924.409
A27: NET OPERATING INCOME (after mgmt fee & rent) | B27: =B19-(B21+B22+B23+B24+B25+B26) -> -7042.8916 | C27: =B27/B11 -> -0.40202319 | D27: =D19-(D21+D22+D23+D24+D25+D26) -> -5497.4199 | E27: =D27/D11 -> -0.27262241 | F27: =F19-(F21+F22+F23+F24+F25+F26) -> 257.02671 | G27: =F27/F11 -> 0.0085623037 | H27: =H19-(H21+H22+H23+H24+H25+H26) -> -3745.4977 | I27: =H27/H11 -> -0.16168912 | J27: =J19-(J21+J22+J23+J24+J25+J26) -> -946.78376 | K27: =J27/J11 -> -0.033865594 | L27: =L19-(L21+L22+L23+L24+L25+L26) -> 565.24871 | M27: =L27/L11 -> 0.018504727 | N27: =N19-(N21+N22+N23+N24+N25+N26) -> -2735.0529 | O27: =N27/N11 -> -0.10986349 | P27: =P19-(P21+P22+P23+P24+P25+P26) -> -2735.0529 | Q27: =P27/P11 -> -0.10986349 | R27: =R19-(R21+R22+R23+R24+R25+R26) -> -2735.0529 | S27: =R27/R11 -> -0.10986349 | T27: =T19-(T21+T22+T23+T24+T25+T26) -> -2735.0529 | U27: =T27/T11 -> -0.10986349 | V27: =V19-(V21+V22+V23+V24+V25+V26) -> -2735.0529 | W27: =V27/V11 -> -0.10986349 | X27: =X19-(X21+X22+X23+X24+X25+X26) -> -2735.0529 | Y27: =X27/X11 -> -0.10986349 | Z27: =Z19-(Z21+Z22+Z23+Z24+Z25+Z26) -> -32820.635 | AA27: =Z27/Z11 -> -0.10986349
C28: =B28/B11 -> 0 | E28: =D28/D11 -> 0 | G28: =F28/F11 -> 0 | I28: =H28/H11 -> 0 | K28: =J28/J11 -> 0 | M28: =L28/L11 -> 0 | O28: =N28/N11 -> 0 | Q28: =P28/P11 -> 0 | S28: =R28/R11 -> 0 | U28: =T28/T11 -> 0 | W28: =V28/V11 -> 0 | Y28: =X28/X11 -> 0 | AA28: =Z28/Z11 -> 0
C29: =B29/B11 -> 0 | E29: =D29/D11 -> 0 | G29: =F29/F11 -> 0 | I29: =H29/H11 -> 0 | K29: =J29/J11 -> 0 | M29: =L29/L11 -> 0 | O29: =N29/N11 -> 0 | Q29: =P29/P11 -> 0 | S29: =R29/R11 -> 0 | U29: =T29/T11 -> 0 | W29: =V29/V11 -> 0 | Y29: =X29/X11 -> 0 | AA29: =Z29/Z11 -> 0
C30: =B30/B11 -> 0 | E30: =D30/D11 -> 0 | G30: =F30/F11 -> 0 | I30: =H30/H11 -> 0 | K30: =J30/J11 -> 0 | M30: =L30/L11 -> 0 | O30: =N30/N11 -> 0 | Q30: =P30/P11 -> 0 | S30: =R30/R11 -> 0 | U30: =T30/T11 -> 0 | W30: =V30/V11 -> 0 | Y30: =X30/X11 -> 0 | AA30: =Z30/Z11 -> 0
C31: =B31/B11 -> 0 | E31: =D31/D11 -> 0 | G31: =F31/F11 -> 0 | I31: =H31/H11 -> 0 | K31: =J31/J11 -> 0 | M31: =L31/L11 -> 0 | O31: =N31/N11 -> 0 | Q31: =P31/P11 -> 0 | S31: =R31/R11 -> 0 | U31: =T31/T11 -> 0 | W31: =V31/V11 -> 0 | Y31: =X31/X11 -> 0 | AA31: =Z31/Z11 -> 0
C32: =B32/B11 -> 0 | E32: =D32/D11 -> 0 | G32: =F32/F11 -> 0 | I32: =H32/H11 -> 0 | K32: =J32/J11 -> 0 | M32: =L32/L11 -> 0 | O32: =N32/N11 -> 0 | Q32: =P32/P11 -> 0 | S32: =R32/R11 -> 0 | U32: =T32/T11 -> 0 | W32: =V32/V11 -> 0 | Y32: =X32/X11 -> 0 | AA32: =Z32/Z11 -> 0
A33: Monthly revenue index = actual Toast net sales ÷ 6-mo avg (Jan 0.70 · Feb 0.81 · Mar 1.21 · Apr 0.93 · May 1.12 · Jun 1.23); Jul–Dec = H1 average
A35: STAFFING SENSITIVITY — annual NOI by morning coverage (after mgmt fee & rent)
A36: Scenario (6am–4pm) | B36: Hrs/day | C36: Annual labor | D36: NOI | E36: NOI % | F36: Method 75%
A37: 1.36 barista-equiv (base: 10h + wknd overlap) | B37: ='LW Assumptions'!C20+'LW Assumptions'!C21 -> 11.142857 | C37: =B37*'LW Assumptions'!$C$22*52*'LW Assumptions'!$C$23*(1+'LW Assumptions'!$C$24) -> 94099.2 | D37: =$Z$19-C37-($Z$22+$Z$23+$Z$24) -> 14908.1 | E37: =D37/$Z$11 -> 0.049903235
A38: 1.25 (+2h afternoon help) | B38: 10 | C38: =B38*'LW Assumptions'!$C$22*52*'LW Assumptions'!$C$23*(1+'LW Assumptions'!$C$24) -> 84448 | D38: =$Z$19-C38-($Z$22+$Z$23+$Z$24) -> 24559.3 | E38: =D38/$Z$11 -> 0.082209572
A39: 1.5 (+4h afternoon help) | B39: 12 | C39: =B39*'LW Assumptions'!$C$22*52*'LW Assumptions'!$C$23*(1+'LW Assumptions'!$C$24) -> 101337.6 | D39: =$Z$19-C39-($Z$22+$Z$23+$Z$24) -> 7669.6999 | E39: =D39/$Z$11 -> 0.025673482
A40: 2.0 (two full shifts) | B40: 16 | C40: =B40*'LW Assumptions'!$C$22*52*'LW Assumptions'!$C$23*(1+'LW Assumptions'!$C$24) -> 135116.8 | D40: =$Z$19-C40-($Z$22+$Z$23+$Z$24) -> -26109.5 | E40: =D40/$Z$11 -> -0.087398698
A42: Labor = Hrs/day × days/wk × 52 × blended wage × (1+burden), all live from LW Assumptions. NOI holds revenue, COGS, CC fees and overhead constant — only morning staffing flexes. Base case = one barista covering the shift solo.

Sheet LW Labor Model
A1: LITTLE WING — LABOR MODEL
A2: Current roles (GL) vs adjusted single-shift schedule (6am–4pm) · sales-by-hour basis
B4: CURRENT LABOR (GL annualized) | F4: SALES BY DAYPART (Jan–May)
B5: Role | C5: Annual | D5: % of rev | F5: Window | G5: Net sales | H5: % of day
B6: Baristas | C6: 42998 | D6: =C6/'LW Assumptions'!C10 -> 0.16152394 | F6: 6am – 2pm (staffed) | G6: 72907 | H6: =G6/$G$8 -> 0.69235444
B7: Servers (eliminated → counter/self-serve) | C7: 54634 | D7: =C7/'LW Assumptions'!C10 -> 0.20523511 | F7: After 2pm (self-serve / front desk) | G7: 32396 | H7: =G7/$G$8 -> 0.30764556
B8: Line cooks (cook KEPT at $296/wk — see below) | C8: 30727 | D8: =C8/'LW Assumptions'!C10 -> 0.11542737 | F8: Total day | G8: =G6+G7 -> 105303 | H8: =G8/$G$8 -> 1
B9: FOH management (into supervisor) | C9: 12880 | D9: =C9/'LW Assumptions'!C10 -> 0.048384306
B10: Bartenders | C10: 886 | D10: =C10/'LW Assumptions'!C10 -> 0.0033282993 | F10: → 69% of sales fall in the staffed
B11: Payroll taxes & benefits | C11: 22733 | D11: =C11/'LW Assumptions'!C10 -> 0.085397549 | F11: 6am–2pm window; after 2pm shifts
B12: Total current labor | C12: =SUM(C6:C11) -> 164858 | D12: =C12/'LW Assumptions'!C10 -> 0.61929658 | F12: to no-cost self-serve service.
B14: ADJUSTED LABOR (single 6am–4pm shift + wknd 2nd barista)
B15: Staff-hours / day | C15: ='LW Assumptions'!C20+'LW Assumptions'!C21 -> 11.142857
B16: Staff-hours / year | C16: =('LW Assumptions'!C20+'LW Assumptions'!C21)*'LW Assumptions'!C22*52 -> 4056
B17: FOH wages / year | C17: =C16*'LW Assumptions'!C23 -> 81120
B18: BOH cook wages / year (kept · $296/wk) | C18: ='LW Assumptions'!C26*52 -> 15392
B19: + payroll taxes & benefits | C19: =(C17+C18)*'LW Assumptions'!C24 -> 15441.92
B20: Total adjusted labor | C20: =C17+C18+C19 -> 111953.92
B21: LABOR SAVINGS / YEAR | C21: =C12-C20 -> 52904.08
B23: Dolce Teamwork (131 pg, Jan-May): FOH blended ~$20/hr, BOH cook ~$25/hr. Current = 2 staggered FOH shifts (opener 6am-2pm + afternoon 12-8pm, ~15 hrs/day). Adjusted model collapses FOH to ONE 6am-4pm shift (+wknd 2nd barista) and KEEPS the BOH cook at the current schedule (~13.3 hrs/wk, $296/wk base — in-house food program retained). Sensitivity on FOH: 1 barista (8h) => NOI +$5.8K; 1+peak (10h) => -$11K; 1.5 avg (12h) => -$28K.

Sheet LW Weekly Compare
A1: LITTLE WING — WEEKLY LABOR: ACTUAL vs PROPOSED
A2: Week of Jun 1–7, 2026 · actual Dolce clock-ins + Toast sales vs the single-shift model (BOH cook kept) · incl. management labor & PT&B
B4: Current (actual wk) | C4: Proposed | D4: Δ
A5: SCHEDULE / COVERAGE
A6: FOH coverage hours/day | B6: ~16 (2 staggered shifts) | C6: =('LW Assumptions'!$C$20+'LW Assumptions'!$C$21)&" (6am–2pm)" -> 11.1428571428571 (6am–2pm)
A7: Days open / week | B7: 7 | C7: ='LW Assumptions'!$C$22 -> 7
A9: STAFF-HOURS (week · all hourly, incl. supervisor)
A10: FOH counter + supervisor | B10: 111.8 | C10: =('LW Assumptions'!$C$20+'LW Assumptions'!$C$21)*'LW Assumptions'!$C$22 -> 78
A11: BOH cook | B11: 13.3 | C11: =B11 -> 13.3
A12: Total hourly staff-hours | B12: 125.1 | C12: =('LW Assumptions'!$C$20+'LW Assumptions'!$C$21)*'LW Assumptions'!$C$22+C11 -> 91.3
A14: LABOR COST (week)
A15: FOH hourly (counter + supervisor) | B15: 2207 | C15: =('LW Assumptions'!$C$20+'LW Assumptions'!$C$21)*'LW Assumptions'!$C$22*'LW Assumptions'!$C$23 -> 1560
A16: BOH hourly (cook) | B16: 296 | C16: ='LW Assumptions'!$C$26 -> 296
A17: Hourly labor subtotal | B17: 2503 | C17: =C15+C16 -> 1856
A18: Management labor (GL 610300 actual) | B18: ='LW Assumptions'!$C$45/52 -> 247.69231 | C18: ='LW Assumptions'!$C$45/52 -> 247.69231
A19: Payroll taxes & benefits (16%) | B19: =(B17+B18)*'LW Assumptions'!$C$24 -> 440.11077 | C19: =(C17+C18)*'LW Assumptions'!$C$24 -> 336.59077
A20: TOTAL LOADED LABOR | B20: =B17+B18+B19 -> 3190.8031 | C20: =C17+C18+C19 -> 2440.2831 | D20: =C20-B20 -> -750.52
A22: Annualized (×52) | B22: =B20*52 -> 165921.76 | C22: =C20*52 -> 126894.72 | D22: =C22-B22 -> -39027.04
A24: vs SALES (actual week)
A25: Net sales (Toast) | B25: 5888.94 | C25: 5888.94
A26: Labor % of sales | B26: =B20/B25 -> 0.54182978 | C26: =C20/C25 -> 0.4143841 | D26: =C26-B26 -> -0.12744569
A28: WEEKLY SAVINGS = hourly reduction only (management held equal)
A29: Weekly savings | annualized → | C29: =B20-C20 -> 750.52 | D29: =C22-B22 -> -39027.04
A31: Supervisor = hourly
A32: The shift-manager/supervisor hours (Brennan, Marnie) are clock-in labor and sit in the FOH hourly line. Current week: 111.8 FOH hourly hrs — heavy because two supervisors staff staggered shifts. Proposal runs one supervisor/barista, 6am–2pm.
A35: Management labor = GL actual
A36: Separate salaried FOH management (GL acct 610300) = $5,366.59 over Jan–May → $12,880/yr → ~$248/wk. Held equal in both columns (management overhead persists). Hourly + this + 16% PT&B annualizes to ~$165K, tying to the GL run-rate.
A39: ⚠ After-2pm exposure
A40: 39% of this week's sales ($2,293) came after 2pm. The proposal assumes the front desk captures this via self-serve at no labor cost — the key risk to pressure-test.

Sheet LW Shift Detail
A1: LITTLE WING — SHIFT DETAIL (Week of Jun 1–7, 2026)
A2: By employee · by day · by shift — actual scheduled roster vs proposed single-shift
A4: Rates ($/hr): | B4: FOH | C4: ='LW Assumptions'!$C$23 -> 20 | D4: BOH | E4: 25
A6: DAILY LABOR COST BY EMPLOYEE (actual effective rates, derived from schedule $)
A7: Employee | B7: Role | C7: Rate/hr | D7: Mon | E7: Tue | F7: Wed | G7: Thu | H7: Fri | I7: Sat | J7: Sun | K7: Wk hrs | L7: Wk $
A8: Donte Johnson | B8: Barista | C8: 18.29 | D8: =6*$C8 -> 109.74 | E8: =7.75*$C8 -> 141.7475 | F8: 0 | G8: 0 | H8: 0 | I8: 0 | J8: 0 | K8: 13.75 | L8: =SUM(D8:J8) -> 251.4875
A9: Donte Johnson | B9: Cook (BOH) | C9: 21.03 | D9: =1.75*$C9 -> 36.8025 | E9: =1.75*$C9 -> 36.8025 | F9: =7.75*$C9 -> 162.9825 | G9: 0 | H9: 0 | I9: 0 | J9: 0 | K9: 11.25 | L9: =SUM(D9:J9) -> 236.5875 | M9: Mon no-show
A10: Santo Starkey Jr | B10: Barista | C10: 17.79 | D10: 0 | E10: 0 | F10: 0 | G10: 0 | H10: =8*$C10 -> 142.32 | I10: =8*$C10 -> 142.32 | J10: =8*$C10 -> 142.32 | K10: 24 | L10: =SUM(D10:J10) -> 426.96
A11: Brennan Stark | B11: Shift Manager | C11: 19.79 | D11: =8*$C11 -> 158.32 | E11: =8*$C11 -> 158.32 | F11: =8*$C11 -> 158.32 | G11: =8*$C11 -> 158.32 | H11: 0 | I11: 0 | J11: =3*$C11 -> 59.37 | K11: 35 | L11: =SUM(D11:J11) -> 692.65 | M11: Sun unscheduled
A12: Marnie Van Den Berg | B12: Shift Manager | C12: 21.21 | D12: 0 | E12: 0 | F12: =8*$C12 -> 169.68 | G12: =8*$C12 -> 169.68 | H12: =8*$C12 -> 169.68 | I12: =8*$C12 -> 169.68 | J12: =8*$C12 -> 169.68 | K12: 40 | L12: =SUM(D12:J12) -> 848.4
A13: Tyesha Tucker | B13: Chef (BOH) | C13: 25 | D13: 0 | E13: 0 | F13: 0 | G13: =8*$C13 -> 200 | H13: =8*$C13 -> 200 | I13: 0 | J13: 0 | K13: 16 | L13: =SUM(D13:J13) -> 400 | M13: Thu left early · Fri no-show
A14: Daily total (base) | D14: =SUM(D8:D13) -> 304.8625 | E14: =SUM(E8:E13) -> 336.87 | F14: =SUM(F8:F13) -> 490.9825 | G14: =SUM(G8:G13) -> 528 | H14: =SUM(H8:H13) -> 512 | I14: =SUM(I8:I13) -> 312 | J14: =SUM(J8:J13) -> 371.37 | K14: =SUM(K8:K13) -> 140 | L14: =SUM(L8:L13) -> 2856.085 | M14: scheduled; actual ~$2,503
A17: SHIFT STRUCTURE — CURRENT vs PROPOSED (hourly basis)
B18: Shift | D18: Hours | F18: Staff | G18: Daily hrs | H18: Daily $ (base) | J18: ×7 week
A19: CURRENT | B19: Opening | D19: 5:45a–1:45p | F19: 8h · 1 FOH | G19: 8 | H19: =8*$C$4 -> 160 | J19: =H19*7 -> 1120
B20: Closing | D20: 12:00p–8:00p | F20: 8h · 1 FOH | G20: 8 | H20: =8*$C$4 -> 160 | J20: =H20*7 -> 1120
B21: BOH (avg) | D21: varies | F21: ~4h · cook | G21: 4 | H21: =4*$E$4 -> 100 | J21: =H21*7 -> 700
A22: Current total / day | G22: =G19+G20+G21 -> 20 | H22: =H19+H20+H21 -> 420 | J22: =H22*7 -> 2940
A24: PROPOSED | B24: Single shift | D24: 6:00a–4:00p | F24: 10h · 1 barista | G24: 10 | H24: =10*$C$4 -> 200 | J24: =H24*7 -> 1400
B25: After 4:00p | D25: self-serve | F25: front desk · 0 | G25: 0 | H25: 0 | J25: =H25*7 -> 0
A26: Proposed total / day | G26: 10 | H26: =10*$C$4 -> 200 | J26: =H26*7 -> 1400
A28: Note: base labor only (before management labor & PT&B). Proposed = one 6am–4pm barista (10h) + BOH cook kept at current schedule (~13.3 hrs/wk, $296/wk); after 4pm FOH moves to self-serve / front desk. Rates: FOH $20 (C4), BOH $25 (E4).

Sheet LW GL Basis
A1: LITTLE WING — GL COST BASIS (T12)
A2: Jan–May GL actuals → annualized run-rate (×12/5) · source for the Current column
A4: Line | B4: Annual | C4: Monthly | D4: % net rev
A5: REVENUE (gross by category)
A6: Food | B6: 119121 | C6: =B6/12 -> 9926.75 | D6: =B6/258287 -> 0.46119627
A7: NA / Coffee | B7: 133545 | C7: =B7/12 -> 11128.75 | D7: =B7/258287 -> 0.51704112
A8: Alcohol (liquor+beer+wine) | B8: 17887 | C8: =B8/12 -> 1490.5833 | D8: =B8/258287 -> 0.069252421
A9: Retail / merch | B9: 6836 | C9: =B9/12 -> 569.66667 | D9: =B9/258287 -> 0.026466682
A10: Less: discounts & comps | B10: -20307 | C10: =B10/12 -> -1692.25 | D10: =B10/258287 -> -0.078621843
A11: Other income (net PDR/catering) | B11: 1204 | C11: =B11/12 -> 100.33333 | D11: =B11/258287 -> 0.0046614812
A12: NET REVENUE | B12: 258287 | C12: =B12/12 -> 21523.917 | D12: =B12/258287 -> 1
A14: COST OF SALES
A15: Food (44.1% of net food) | B15: 48655 | C15: =B15/12 -> 4054.5833 | D15: =B15/258287 -> 0.18837572
A16: NA / Coffee (22.2%) | B16: 27428 | C16: =B16/12 -> 2285.6667 | D16: =B16/258287 -> 0.10619195
A17: Alcohol (33.3%) | B17: 5516 | C17: =B17/12 -> 459.66667 | D17: =B17/258287 -> 0.021356088
A18: Retail / other (none booked in GL) | B18: 0 | C18: =B18/12 -> 0 | D18: =B18/258287 -> 0
A19: TOTAL COGS | B19: 81599 | C19: =B19/12 -> 6799.9167 | D19: =B19/258287 -> 0.31592376
A20: GROSS PROFIT | B20: 176688 | C20: =B20/12 -> 14724 | D20: =B20/258287 -> 0.68407624
A22: LABOR
A23: Wages (all roles) | B23: 142124 | C23: =B23/12 -> 11843.667 | D23: =B23/258287 -> 0.55025611
A24: Payroll taxes | B24: 16219 | C24: =B24/12 -> 1351.5833 | D24: =B24/258287 -> 0.062794488
A25: Benefits & insurance | B25: 6514 | C25: =B25/12 -> 542.83333 | D25: =B25/258287 -> 0.025220007
A26: TOTAL LABOR | B26: 164857 | C26: =B26/12 -> 13738.083 | D26: =B26/258287 -> 0.63827061
A28: CONTROLLABLE (excl CC)
A29: Operating supplies / paper / linen / equip | B29: 44540 | C29: =B29/12 -> 3711.6667 | D29: =B29/258287 -> 0.17244383
A30: Marketing | B30: 11918 | C30: =B30/12 -> 993.16667 | D30: =B30/258287 -> 0.046142469
A31: Utilities | B31: 2912 | C31: =B31/12 -> 242.66667 | D31: =B31/258287 -> 0.01127428
A32: G&A / acct / bank / computer / R&M | B32: 30305 | C32: =B32/12 -> 2525.4167 | D32: =B32/258287 -> 0.11733072
A33: TOTAL CONTROLLABLE | B33: 89675 | C33: =B33/12 -> 7472.9167 | D33: =B33/258287 -> 0.3471913
A34: Credit card fees (GL actual 3.9%) | B34: 10012 | C34: =B34/12 -> 834.33333 | D34: =B34/258287 -> 0.038763081
A35: NON-CONTROLLABLE (insurance, legal, reserves) | B35: 5657 | C35: =B35/12 -> 471.41667 | D35: =B35/258287 -> 0.021901993
A37: NET OPERATING INCOME | B37: -93513 | C37: =B37/12 -> -7792.75 | D37: =B37/258287 -> -0.36205074
A38: Less: management fee | B38: -48000 | C38: =B38/12 -> -4000
A39: Less: rent | B39: -15642 | C39: =B39/12 -> -1303.5
A40: NET INCOME | B40: -157155 | C40: =B40/12 -> -13096.25 | D40: =B40/258287 -> -0.60845106
A42: Note: State income tax accrual ($157K annualized) excluded — below-the-line entity tax, not operating. Retail/other show no COGS because none is booked in the GL (true merch cost likely sits in food/supplies).

Sheet LW Menu Pricing
A1: LITTLE WING — MENU PRICING & REVENUE STRATEGY
A2: Item-level pricing — raise price on the inelastic core (coffee, breakfast), hold the elastic · per-item Rec +$ inputs (blue) · pure margin
A4: Menu item | B4: Cat | C4: Annual qty | D4: Cur avg $ | E4: Cur revenue | F4: Rec +$ | G4: New avg $ | H4: New revenue | I4: Uplift $
A5: COFFEE & TEA DRINKS · +$0.50 across the board
A6: Latte | B6: NA | C6: =2441*12/5 -> 5858.4 | D6: =IF(C6=0,0,E6/C6) -> 5.5301106 | E6: =13499*12/5 -> 32397.6 | F6: 0.5 | G6: =D6+F6 -> 6.0301106 | H6: =E6+I6 -> 35326.8 | I6: =C6*F6 -> 2929.2
A7: Drip Coffee | B7: NA | C7: =1454*12/5 -> 3489.6 | D7: =IF(C7=0,0,E7/C7) -> 3.4594223 | E7: =5030*12/5 -> 12072 | F7: 0.5 | G7: =D7+F7 -> 3.9594223 | H7: =E7+I7 -> 13816.8 | I7: =C7*F7 -> 1744.8
A8: Coldbrew | B8: NA | C8: =823*12/5 -> 1975.2 | D8: =IF(C8=0,0,E8/C8) -> 5.2235723 | E8: =4299*12/5 -> 10317.6 | F8: 0.5 | G8: =D8+F8 -> 5.7235723 | H8: =E8+I8 -> 11305.2 | I8: =C8*F8 -> 987.6
A9: Cappuccino | B9: NA | C9: =512*12/5 -> 1228.8 | D9: =IF(C9=0,0,E9/C9) -> 4.375 | E9: =2240*12/5 -> 5376 | F9: 0.5 | G9: =D9+F9 -> 4.875 | H9: =E9+I9 -> 5990.4 | I9: =C9*F9 -> 614.4
A10: Americano | B10: NA | C10: =528*12/5 -> 1267.2 | D10: =IF(C10=0,0,E10/C10) -> 4.0113636 | E10: =2118*12/5 -> 5083.2 | F10: 0.5 | G10: =D10+F10 -> 4.5113636 | H10: =E10+I10 -> 5716.8 | I10: =C10*F10 -> 633.6
A11: Espresso | B11: NA | C11: =737*12/5 -> 1768.8 | D11: =IF(C11=0,0,E11/C11) -> 2.6919946 | E11: =1984*12/5 -> 4761.6 | F11: 0.5 | G11: =D11+F11 -> 3.1919946 | H11: =E11+I11 -> 5646 | I11: =C11*F11 -> 884.4
A12: Matcha Latte | B12: NA | C12: =348*12/5 -> 835.2 | D12: =IF(C12=0,0,E12/C12) -> 6.637931 | E12: =2310*12/5 -> 5544 | F12: 0.5 | G12: =D12+F12 -> 7.137931 | H12: =E12+I12 -> 5961.6 | I12: =C12*F12 -> 417.6
A13: All other coffee & tea drinks | B13: NA | C13: =20731-SUM(C6:C12) -> 4307.8 | D13: =IF(C13=0,0,E13/C13) -> 4.7597381 | E13: =96056-SUM(E6:E12) -> 20504 | F13: 0.5 | G13: =D13+F13 -> 5.2597381 | H13: =E13+I13 -> 22657.9 | I13: =C13*F13 -> 2153.9
A14: SANDWICHES · +$1.00
A15: Bacon, Egg, & Cheese | B15: Food | C15: =684*12/5 -> 1641.6 | D15: =IF(C15=0,0,E15/C15) -> 11.792398 | E15: =8066*12/5 -> 19358.4 | F15: 1 | G15: =D15+F15 -> 12.792398 | H15: =E15+I15 -> 21000 | I15: =C15*F15 -> 1641.6
A16: Egg & Cheese | B16: Food | C16: =261*12/5 -> 626.4 | D16: =IF(C16=0,0,E16/C16) -> 9.7586207 | E16: =2547*12/5 -> 6112.8 | F16: 1 | G16: =D16+F16 -> 10.758621 | H16: =E16+I16 -> 6739.2 | I16: =C16*F16 -> 626.4
A17: All other sandwiches | B17: Food | C17: =3386-SUM(C15:C16) -> 1118 | D17: =IF(C17=0,0,E17/C17) -> 12.150984 | E17: =39056-SUM(E15:E16) -> 13584.8 | F17: 1 | G17: =D17+F17 -> 13.150984 | H17: =E17+I17 -> 14702.8 | I17: =C17*F17 -> 1118
A18: NA BEVERAGES — JUICES · +$0.50
A19: Natalie's Juice | B19: NA | C19: =385*12/5 -> 924 | D19: =IF(C19=0,0,E19/C19) -> 5.7142857 | E19: =2200*12/5 -> 5280 | F19: 0.5 | G19: =D19+F19 -> 6.2142857 | H19: =E19+I19 -> 5742 | I19: =C19*F19 -> 462
A20: All other NA beverages | B20: NA | C20: =6022-C19 -> 5098 | D20: =IF(C20=0,0,E20/C20) -> 4.3962338 | E20: =27692-E19 -> 22412 | F20: 0.5 | G20: =D20+F20 -> 4.8962338 | H20: =E20+I20 -> 24961 | I20: =C20*F20 -> 2549
A21: GROUP LEVEL · +$0.50 (no item detail in Toast top sellers)
A22: Pastries (all items) | B22: Food | C22: 3775 | D22: =IF(C22=0,0,E22/C22) -> 4.541457 | E22: 17144 | F22: 0.5 | G22: =D22+F22 -> 5.041457 | H22: =E22+I22 -> 19031.5 | I22: =C22*F22 -> 1887.5
A23: Smoothies (all items) | B23: NA | C23: 806 | D23: =IF(C23=0,0,E23/C23) -> 6.7456576 | E23: 5437 | F23: 0.5 | G23: =D23+F23 -> 7.2456576 | H23: =E23+I23 -> 5840 | I23: =C23*F23 -> 403
A24: Specials Menu (all items) | B24: Food | C24: 1037 | D24: =IF(C24=0,0,E24/C24) -> 6.1311475 | E24: 6358 | F24: 0.5 | G24: =D24+F24 -> 6.6311475 | H24: =E24+I24 -> 6876.5 | I24: =C24*F24 -> 518.5
A25: HOLD · price-marked / market-referenced — more elastic
A26: Grab & Go (all items) | B26: Food | C26: 2210 | D26: =IF(C26=0,0,E26/C26) -> 6.5067873 | E26: 14380 | F26: 0 | G26: =D26+F26 -> 6.5067873 | H26: =E26+I26 -> 14380 | I26: =C26*F26 -> 0
A27: Snacks (all items) | B27: Food | C27: 3060 | D27: =IF(C27=0,0,E27/C27) -> 4.2781046 | E27: 13091 | F27: 0 | G27: =D27+F27 -> 4.2781046 | H27: =E27+I27 -> 13091 | I27: =C27*F27 -> 0
A28: Alcohol / Wine / Retail (all items) | B28: Alc | C28: 358 | D28: =IF(C28=0,0,E28/C28) -> 24.840782 | E28: 8893 | F28: 0 | G28: =D28+F28 -> 24.840782 | H28: =E28+I28 -> 8893 | I28: =C28*F28 -> 0
A29: TOTAL | C29: =SUM(C6:C28) -> 41385 | E29: =SUM(E6:E28) -> 228107 | H29: =SUM(H6:H28) -> 247678.5 | I29: =SUM(I6:I28) -> 19571.5
A30: Item qty & revenue = Toast Jan–May item detail ×12/5 (annualized). 'All other' rows = category total (H1 ×2) − listed items, so every group still ties to the LW Assumptions revenue base.
A32: REVENUE UPLIFT (held volume · pure margin)
A33: NA / Coffee uplift | C33: =SUMIF($B$6:$B$28,"NA",$I$6:$I$28) -> 13779.5
A34: Food uplift | C34: =SUMIF($B$6:$B$28,"Food",$I$6:$I$28) -> 5792
A35: TOTAL ANNUAL UPLIFT | C35: =I29 -> 19571.5
A36: as % of current revenue | C36: =I29/258287 -> 0.075774236
A38: Elasticity check — net uplift if some volume attrites:
A39: 100% capture (coffee is sticky) | C39: =I29*1 -> 19571.5
A40: 90% capture | C40: =I29*0.9 -> 17614.35
A41: 80% capture | C41: =I29*0.8 -> 15657.2
A43: RECOMMENDATIONS
A44: 1. Coffee & Tea (+$0.50 every item): the engine — ~20,700 drinks/yr. Latte $5.53→$6.03, Drip $3.49→$3.99, Coldbrew $5.25→$5.75, Cappuccino $4.38→$4.88, Americano $4.01→$4.51, Espresso $3.28→$3.78, Matcha $6.63→$7.13. All stay at/below specialty-market price; coffee demand is sticky (elasticity ~ -0.3). Biggest single lever: ~$10.4K/yr.
A45: 2. Breakfast sandwiches (+$1.00): captive AM/hotel crowd, hot prepared food. BEC $11.78→$12.78, Egg & Cheese $9.78→$10.78. ~$3.4K/yr.
A46: 3. Specialty NA + pastries + specials (+$0.50): Natalie's Juice $5.83→$6.33, smoothies, croissants. ~$5.8K/yr combined.
A47: 4. HOLD Grab & Go, Snacks, packaged retail & alcohol — price-marked / market-referenced, more elastic; raising these risks volume.
A48: Net: ~$19.6K/yr (+7.6% revenue) with ZERO added covers — pure margin. Each item now carries its own Rec +$ input, so the move can be tuned line by line (e.g. hold espresso, push latte). Revisit prices every 6–12 months; a $0.25 annual creep on coffee alone keeps pace with cost inflation.
A50: PRICING UPLIFT → MODEL (feeds LW Assumptions C43)
A51: Gross annual uplift (held volume) | C51: =I29 -> 19571.5
A52: Capture % (INPUT — coffee demand is sticky) | C52: 0.9
A53: NET UPLIFT applied in 2027 budget | C53: =C51*C52 -> 17614.35
